package com.google.android.gms.internal.measurement;

import java.io.IOException;
import java.lang.reflect.Field;
import java.util.Arrays;
import java.util.List;
import java.util.Map;
import java.util.Objects;
import sun.misc.Unsafe;

final class zzlo<T>
  implements zzlw<T>
{
  private static final int[] zza = new int[0];
  private static final Unsafe zzb = zzmx.zzg();
  private final int[] zzc;
  private final Object[] zzd;
  private final int zze;
  private final int zzf;
  private final zzll zzg;
  private final boolean zzh;
  private final boolean zzi;
  private final int[] zzj;
  private final int zzk;
  private final int zzl;
  private final zzkz zzm;
  private final zzmn zzn;
  private final zzjr zzo;
  private final zzlq zzp;
  private final zzlg zzq;
  
  private zzlo(int[] paramArrayOfInt1, Object[] paramArrayOfObject, int paramInt1, int paramInt2, zzll paramZzll, boolean paramBoolean1, boolean paramBoolean2, int[] paramArrayOfInt2, int paramInt3, int paramInt4, zzlq paramZzlq, zzkz paramZzkz, zzmn paramZzmn, zzjr paramZzjr, zzlg paramZzlg, byte[] paramArrayOfByte)
  {
    zzc = paramArrayOfInt1;
    zzd = paramArrayOfObject;
    zze = paramInt1;
    zzf = paramInt2;
    zzi = paramBoolean1;
    paramBoolean2 = false;
    paramBoolean1 = paramBoolean2;
    if (paramZzjr != null)
    {
      paramBoolean1 = paramBoolean2;
      if (paramZzjr.zzc(paramZzll)) {
        paramBoolean1 = true;
      }
    }
    zzh = paramBoolean1;
    zzj = paramArrayOfInt2;
    zzk = paramInt3;
    zzl = paramInt4;
    zzp = paramZzlq;
    zzm = paramZzkz;
    zzn = paramZzmn;
    zzo = paramZzjr;
    zzg = paramZzll;
    zzq = paramZzlg;
  }
  
  private static int zzA(int paramInt)
  {
    return paramInt >>> 20 & 0xFF;
  }
  
  private final int zzB(int paramInt)
  {
    return zzc[(paramInt + 1)];
  }
  
  private static long zzC(Object paramObject, long paramLong)
  {
    return ((Long)zzmx.zzf(paramObject, paramLong)).longValue();
  }
  
  private final zzki zzD(int paramInt)
  {
    paramInt /= 3;
    return (zzki)zzd[(paramInt + paramInt + 1)];
  }
  
  private final zzlw zzE(int paramInt)
  {
    paramInt /= 3;
    paramInt += paramInt;
    zzlw localZzlw = (zzlw)zzd[paramInt];
    if (localZzlw != null) {
      return localZzlw;
    }
    localZzlw = zzlt.zza().zzb((Class)zzd[(paramInt + 1)]);
    zzd[paramInt] = localZzlw;
    return localZzlw;
  }
  
  private final Object zzF(int paramInt)
  {
    paramInt /= 3;
    return zzd[(paramInt + paramInt)];
  }
  
  private static Field zzG(Class paramClass, String paramString)
  {
    try
    {
      localObject1 = paramClass.getDeclaredField(paramString);
      return localObject1;
    }
    catch (NoSuchFieldException localNoSuchFieldException)
    {
      Object localObject1;
      int j;
      int i;
      Object localObject2;
      for (;;) {}
    }
    localObject1 = paramClass.getDeclaredFields();
    j = localObject1.length;
    i = 0;
    while (i < j)
    {
      localObject2 = localObject1[i];
      if (paramString.equals(((Field)localObject2).getName())) {
        return localObject2;
      }
      i += 1;
    }
    paramClass = paramClass.getName();
    localObject1 = Arrays.toString((Object[])localObject1);
    localObject2 = new StringBuilder();
    ((StringBuilder)localObject2).append("Field ");
    ((StringBuilder)localObject2).append(paramString);
    ((StringBuilder)localObject2).append(" for ");
    ((StringBuilder)localObject2).append(paramClass);
    ((StringBuilder)localObject2).append(" not found. Known fields are ");
    ((StringBuilder)localObject2).append((String)localObject1);
    throw new RuntimeException(((StringBuilder)localObject2).toString());
  }
  
  private final void zzH(Object paramObject1, Object paramObject2, int paramInt)
  {
    long l = zzB(paramInt) & 0xFFFFF;
    if (!zzO(paramObject2, paramInt)) {
      return;
    }
    Object localObject = zzmx.zzf(paramObject1, l);
    paramObject2 = zzmx.zzf(paramObject2, l);
    if ((localObject != null) && (paramObject2 != null))
    {
      zzmx.zzs(paramObject1, l, zzkm.zzg(localObject, paramObject2));
      zzJ(paramObject1, paramInt);
      return;
    }
    if (paramObject2 != null)
    {
      zzmx.zzs(paramObject1, l, paramObject2);
      zzJ(paramObject1, paramInt);
    }
  }
  
  private final void zzI(Object paramObject1, Object paramObject2, int paramInt)
  {
    int i = zzB(paramInt);
    int j = zzc[paramInt];
    long l = i & 0xFFFFF;
    if (!zzR(paramObject2, j, paramInt)) {
      return;
    }
    Object localObject;
    if (zzR(paramObject1, j, paramInt)) {
      localObject = zzmx.zzf(paramObject1, l);
    } else {
      localObject = null;
    }
    paramObject2 = zzmx.zzf(paramObject2, l);
    if ((localObject != null) && (paramObject2 != null))
    {
      zzmx.zzs(paramObject1, l, zzkm.zzg(localObject, paramObject2));
      zzK(paramObject1, j, paramInt);
      return;
    }
    if (paramObject2 != null)
    {
      zzmx.zzs(paramObject1, l, paramObject2);
      zzK(paramObject1, j, paramInt);
    }
  }
  
  private final void zzJ(Object paramObject, int paramInt)
  {
    paramInt = zzy(paramInt);
    long l = 0xFFFFF & paramInt;
    if (l == 1048575L) {
      return;
    }
    zzmx.zzq(paramObject, l, 1 << (paramInt >>> 20) | zzmx.zzc(paramObject, l));
  }
  
  private final void zzK(Object paramObject, int paramInt1, int paramInt2)
  {
    zzmx.zzq(paramObject, zzy(paramInt2) & 0xFFFFF, paramInt1);
  }
  
  private final void zzL(Object paramObject, zznf paramZznf)
    throws IOException
  {
    if (!zzh)
    {
      int i1 = zzc.length;
      Object localObject = zzb;
      int i = 1048575;
      int m = 0;
      int k;
      for (int j = 0; m < i1; j = k)
      {
        int i2 = zzB(m);
        int[] arrayOfInt = zzc;
        int i3 = arrayOfInt[m];
        int i4 = zzA(i2);
        int n;
        if (i4 <= 17)
        {
          int i5 = arrayOfInt[(m + 2)];
          n = i5 & 0xFFFFF;
          k = j;
          j = i;
          if (n != i)
          {
            k = ((Unsafe)localObject).getInt(paramObject, n);
            j = n;
          }
          n = 1 << (i5 >>> 20);
          i = j;
        }
        else
        {
          n = 0;
          k = j;
        }
        long l = i2 & 0xFFFFF;
        switch (i4)
        {
        }
        for (;;)
        {
          break;
          if (zzR(paramObject, i3, m))
          {
            paramZznf.zzq(i3, ((Unsafe)localObject).getObject(paramObject, l), zzE(m));
            continue;
            if (zzR(paramObject, i3, m))
            {
              paramZznf.zzC(i3, zzC(paramObject, l));
              continue;
              if (zzR(paramObject, i3, m))
              {
                paramZznf.zzA(i3, zzr(paramObject, l));
                continue;
                if (zzR(paramObject, i3, m))
                {
                  paramZznf.zzy(i3, zzC(paramObject, l));
                  continue;
                  if (zzR(paramObject, i3, m))
                  {
                    paramZznf.zzw(i3, zzr(paramObject, l));
                    continue;
                    if (zzR(paramObject, i3, m))
                    {
                      paramZznf.zzi(i3, zzr(paramObject, l));
                      continue;
                      if (zzR(paramObject, i3, m))
                      {
                        paramZznf.zzH(i3, zzr(paramObject, l));
                        continue;
                        if (zzR(paramObject, i3, m))
                        {
                          paramZznf.zzd(i3, (zzjd)((Unsafe)localObject).getObject(paramObject, l));
                          continue;
                          if (zzR(paramObject, i3, m))
                          {
                            paramZznf.zzv(i3, ((Unsafe)localObject).getObject(paramObject, l), zzE(m));
                            continue;
                            if (zzR(paramObject, i3, m))
                            {
                              zzT(i3, ((Unsafe)localObject).getObject(paramObject, l), paramZznf);
                              continue;
                              if (zzR(paramObject, i3, m))
                              {
                                paramZznf.zzb(i3, zzS(paramObject, l));
                                continue;
                                if (zzR(paramObject, i3, m))
                                {
                                  paramZznf.zzk(i3, zzr(paramObject, l));
                                  continue;
                                  if (zzR(paramObject, i3, m))
                                  {
                                    paramZznf.zzm(i3, zzC(paramObject, l));
                                    continue;
                                    if (zzR(paramObject, i3, m))
                                    {
                                      paramZznf.zzr(i3, zzr(paramObject, l));
                                      continue;
                                      if (zzR(paramObject, i3, m))
                                      {
                                        paramZznf.zzJ(i3, zzC(paramObject, l));
                                        continue;
                                        if (zzR(paramObject, i3, m))
                                        {
                                          paramZznf.zzt(i3, zzC(paramObject, l));
                                          continue;
                                          if (zzR(paramObject, i3, m))
                                          {
                                            paramZznf.zzo(i3, zzo(paramObject, l));
                                            continue;
                                            if (zzR(paramObject, i3, m))
                                            {
                                              paramZznf.zzf(i3, zzn(paramObject, l));
                                              continue;
                                              zzM(paramZznf, i3, ((Unsafe)localObject).getObject(paramObject, l), m);
                                              continue;
                                              zzly.zzO(zzc[m], (List)((Unsafe)localObject).getObject(paramObject, l), paramZznf, zzE(m));
                                              continue;
                                              zzly.zzV(zzc[m], (List)((Unsafe)localObject).getObject(paramObject, l), paramZznf, true);
                                              continue;
                                              zzly.zzU(zzc[m], (List)((Unsafe)localObject).getObject(paramObject, l), paramZznf, true);
                                              continue;
                                              zzly.zzT(zzc[m], (List)((Unsafe)localObject).getObject(paramObject, l), paramZznf, true);
                                              continue;
                                              zzly.zzS(zzc[m], (List)((Unsafe)localObject).getObject(paramObject, l), paramZznf, true);
                                              continue;
                                              zzly.zzK(zzc[m], (List)((Unsafe)localObject).getObject(paramObject, l), paramZznf, true);
                                              continue;
                                              zzly.zzX(zzc[m], (List)((Unsafe)localObject).getObject(paramObject, l), paramZznf, true);
                                              continue;
                                              zzly.zzH(zzc[m], (List)((Unsafe)localObject).getObject(paramObject, l), paramZznf, true);
                                              continue;
                                              zzly.zzL(zzc[m], (List)((Unsafe)localObject).getObject(paramObject, l), paramZznf, true);
                                              continue;
                                              zzly.zzM(zzc[m], (List)((Unsafe)localObject).getObject(paramObject, l), paramZznf, true);
                                              continue;
                                              zzly.zzP(zzc[m], (List)((Unsafe)localObject).getObject(paramObject, l), paramZznf, true);
                                              continue;
                                              zzly.zzY(zzc[m], (List)((Unsafe)localObject).getObject(paramObject, l), paramZznf, true);
                                              continue;
                                              zzly.zzQ(zzc[m], (List)((Unsafe)localObject).getObject(paramObject, l), paramZznf, true);
                                              continue;
                                              zzly.zzN(zzc[m], (List)((Unsafe)localObject).getObject(paramObject, l), paramZznf, true);
                                              continue;
                                              zzly.zzJ(zzc[m], (List)((Unsafe)localObject).getObject(paramObject, l), paramZznf, true);
                                              continue;
                                              zzly.zzV(zzc[m], (List)((Unsafe)localObject).getObject(paramObject, l), paramZznf, false);
                                              break label1550;
                                              zzly.zzU(zzc[m], (List)((Unsafe)localObject).getObject(paramObject, l), paramZznf, false);
                                              break label1550;
                                              zzly.zzT(zzc[m], (List)((Unsafe)localObject).getObject(paramObject, l), paramZznf, false);
                                              break label1550;
                                              zzly.zzS(zzc[m], (List)((Unsafe)localObject).getObject(paramObject, l), paramZznf, false);
                                              break label1550;
                                              zzly.zzK(zzc[m], (List)((Unsafe)localObject).getObject(paramObject, l), paramZznf, false);
                                              break label1550;
                                              zzly.zzX(zzc[m], (List)((Unsafe)localObject).getObject(paramObject, l), paramZznf, false);
                                              label1550:
                                              break;
                                              zzly.zzI(zzc[m], (List)((Unsafe)localObject).getObject(paramObject, l), paramZznf);
                                              continue;
                                              zzly.zzR(zzc[m], (List)((Unsafe)localObject).getObject(paramObject, l), paramZznf, zzE(m));
                                              continue;
                                              zzly.zzW(zzc[m], (List)((Unsafe)localObject).getObject(paramObject, l), paramZznf);
                                              continue;
                                              zzly.zzH(zzc[m], (List)((Unsafe)localObject).getObject(paramObject, l), paramZznf, false);
                                              break;
                                              zzly.zzL(zzc[m], (List)((Unsafe)localObject).getObject(paramObject, l), paramZznf, false);
                                              break;
                                              zzly.zzM(zzc[m], (List)((Unsafe)localObject).getObject(paramObject, l), paramZznf, false);
                                              break;
                                              zzly.zzP(zzc[m], (List)((Unsafe)localObject).getObject(paramObject, l), paramZznf, false);
                                              break;
                                              zzly.zzY(zzc[m], (List)((Unsafe)localObject).getObject(paramObject, l), paramZznf, false);
                                              break;
                                              zzly.zzQ(zzc[m], (List)((Unsafe)localObject).getObject(paramObject, l), paramZznf, false);
                                              break;
                                              zzly.zzN(zzc[m], (List)((Unsafe)localObject).getObject(paramObject, l), paramZznf, false);
                                              break;
                                              zzly.zzJ(zzc[m], (List)((Unsafe)localObject).getObject(paramObject, l), paramZznf, false);
                                              break;
                                              if ((k & n) != 0)
                                              {
                                                paramZznf.zzq(i3, ((Unsafe)localObject).getObject(paramObject, l), zzE(m));
                                                break;
                                                if ((k & n) != 0)
                                                {
                                                  paramZznf.zzC(i3, ((Unsafe)localObject).getLong(paramObject, l));
                                                  break;
                                                  if ((k & n) != 0)
                                                  {
                                                    paramZznf.zzA(i3, ((Unsafe)localObject).getInt(paramObject, l));
                                                    break;
                                                    if ((k & n) != 0)
                                                    {
                                                      paramZznf.zzy(i3, ((Unsafe)localObject).getLong(paramObject, l));
                                                      break;
                                                      if ((k & n) != 0)
                                                      {
                                                        paramZznf.zzw(i3, ((Unsafe)localObject).getInt(paramObject, l));
                                                        break;
                                                        if ((k & n) != 0)
                                                        {
                                                          paramZznf.zzi(i3, ((Unsafe)localObject).getInt(paramObject, l));
                                                          break;
                                                          if ((k & n) != 0)
                                                          {
                                                            paramZznf.zzH(i3, ((Unsafe)localObject).getInt(paramObject, l));
                                                            break;
                                                            if ((k & n) != 0)
                                                            {
                                                              paramZznf.zzd(i3, (zzjd)((Unsafe)localObject).getObject(paramObject, l));
                                                              break;
                                                              if ((k & n) != 0)
                                                              {
                                                                paramZznf.zzv(i3, ((Unsafe)localObject).getObject(paramObject, l), zzE(m));
                                                                break;
                                                                if ((k & n) != 0)
                                                                {
                                                                  zzT(i3, ((Unsafe)localObject).getObject(paramObject, l), paramZznf);
                                                                  break;
                                                                  if ((k & n) != 0)
                                                                  {
                                                                    paramZznf.zzb(i3, zzmx.zzw(paramObject, l));
                                                                    break;
                                                                    if ((k & n) != 0)
                                                                    {
                                                                      paramZznf.zzk(i3, ((Unsafe)localObject).getInt(paramObject, l));
                                                                      break;
                                                                      if ((k & n) != 0)
                                                                      {
                                                                        paramZznf.zzm(i3, ((Unsafe)localObject).getLong(paramObject, l));
                                                                        break;
                                                                        if ((k & n) != 0)
                                                                        {
                                                                          paramZznf.zzr(i3, ((Unsafe)localObject).getInt(paramObject, l));
                                                                          break;
                                                                          if ((k & n) != 0)
                                                                          {
                                                                            paramZznf.zzJ(i3, ((Unsafe)localObject).getLong(paramObject, l));
                                                                            break;
                                                                            if ((k & n) != 0)
                                                                            {
                                                                              paramZznf.zzt(i3, ((Unsafe)localObject).getLong(paramObject, l));
                                                                              break;
                                                                              if ((k & n) != 0)
                                                                              {
                                                                                paramZznf.zzo(i3, zzmx.zzb(paramObject, l));
                                                                                break;
                                                                                if ((k & n) != 0) {
                                                                                  paramZznf.zzf(i3, zzmx.zza(paramObject, l));
                                                                                }
                                                                              }
                                                                            }
                                                                          }
                                                                        }
                                                                      }
                                                                    }
                                                                  }
                                                                }
                                                              }
                                                            }
                                                          }
                                                        }
                                                      }
                                                    }
                                                  }
                                                }
                                              }
                                            }
                                          }
                                        }
                                      }
                                    }
                                  }
                                }
                              }
                            }
                          }
                        }
                      }
                    }
                  }
                }
              }
            }
          }
        }
        m += 3;
      }
      localObject = zzn;
      ((zzmn)localObject).zzi(((zzmn)localObject).zzc(paramObject), paramZznf);
      return;
    }
    zzo.zza(paramObject);
    throw null;
  }
  
  private final void zzM(zznf paramZznf, int paramInt1, Object paramObject, int paramInt2)
    throws IOException
  {
    if (paramObject == null) {
      return;
    }
    paramZznf = (zzle)zzF(paramInt2);
    throw null;
  }
  
  private final boolean zzN(Object paramObject1, Object paramObject2, int paramInt)
  {
    return zzO(paramObject1, paramInt) == zzO(paramObject2, paramInt);
  }
  
  private final boolean zzO(Object paramObject, int paramInt)
  {
    int i = zzy(paramInt);
    long l = i & 0xFFFFF;
    if (l == 1048575L)
    {
      paramInt = zzB(paramInt);
      l = paramInt & 0xFFFFF;
      switch (zzA(paramInt))
      {
      default: 
        throw new IllegalArgumentException();
      case 17: 
        return zzmx.zzf(paramObject, l) != null;
      case 16: 
        return zzmx.zzd(paramObject, l) != 0L;
      case 15: 
        return zzmx.zzc(paramObject, l) != 0;
      case 14: 
        return zzmx.zzd(paramObject, l) != 0L;
      case 13: 
        return zzmx.zzc(paramObject, l) != 0;
      case 12: 
        return zzmx.zzc(paramObject, l) != 0;
      case 11: 
        return zzmx.zzc(paramObject, l) != 0;
      case 10: 
        return !zzjd.zzb.equals(zzmx.zzf(paramObject, l));
      case 9: 
        return zzmx.zzf(paramObject, l) != null;
      case 8: 
        paramObject = zzmx.zzf(paramObject, l);
        if ((paramObject instanceof String)) {
          return !((String)paramObject).isEmpty();
        }
        if ((paramObject instanceof zzjd)) {
          return !zzjd.zzb.equals(paramObject);
        }
        throw new IllegalArgumentException();
      case 7: 
        return zzmx.zzw(paramObject, l);
      case 6: 
        return zzmx.zzc(paramObject, l) != 0;
      case 5: 
        return zzmx.zzd(paramObject, l) != 0L;
      case 4: 
        return zzmx.zzc(paramObject, l) != 0;
      case 3: 
        return zzmx.zzd(paramObject, l) != 0L;
      case 2: 
        return zzmx.zzd(paramObject, l) != 0L;
      case 1: 
        return Float.floatToRawIntBits(zzmx.zzb(paramObject, l)) != 0;
      }
      return Double.doubleToRawLongBits(zzmx.zza(paramObject, l)) != 0L;
    }
    return (zzmx.zzc(paramObject, l) & 1 << (i >>> 20)) != 0;
  }
  
  private final boolean zzP(Object paramObject, int paramInt1, int paramInt2, int paramInt3, int paramInt4)
  {
    if (paramInt2 == 1048575) {
      return zzO(paramObject, paramInt1);
    }
    return (paramInt3 & paramInt4) != 0;
  }
  
  private static boolean zzQ(Object paramObject, int paramInt, zzlw paramZzlw)
  {
    return paramZzlw.zzk(zzmx.zzf(paramObject, paramInt & 0xFFFFF));
  }
  
  private final boolean zzR(Object paramObject, int paramInt1, int paramInt2)
  {
    return zzmx.zzc(paramObject, zzy(paramInt2) & 0xFFFFF) == paramInt1;
  }
  
  private static boolean zzS(Object paramObject, long paramLong)
  {
    return ((Boolean)zzmx.zzf(paramObject, paramLong)).booleanValue();
  }
  
  private static final void zzT(int paramInt, Object paramObject, zznf paramZznf)
    throws IOException
  {
    if ((paramObject instanceof String))
    {
      paramZznf.zzF(paramInt, (String)paramObject);
      return;
    }
    paramZznf.zzd(paramInt, (zzjd)paramObject);
  }
  
  static zzmo zzd(Object paramObject)
  {
    zzke localZzke = (zzke)paramObject;
    zzmo localZzmo = zzc;
    paramObject = localZzmo;
    if (localZzmo == zzmo.zzc())
    {
      paramObject = zzmo.zze();
      zzc = paramObject;
    }
    return paramObject;
  }
  
  static zzlo zzl(Class paramClass, zzli paramZzli, zzlq paramZzlq, zzkz paramZzkz, zzmn paramZzmn, zzjr paramZzjr, zzlg paramZzlg)
  {
    if ((paramZzli instanceof zzlv)) {
      return zzm((zzlv)paramZzli, paramZzlq, paramZzkz, paramZzmn, paramZzjr, paramZzlg);
    }
    paramClass = (zzmk)paramZzli;
    throw null;
  }
  
  static zzlo zzm(zzlv paramZzlv, zzlq paramZzlq, zzkz paramZzkz, zzmn paramZzmn, zzjr paramZzjr, zzlg paramZzlg)
  {
    boolean bool;
    if (paramZzlv.zzc() == 2) {
      bool = true;
    } else {
      bool = false;
    }
    String str = paramZzlv.zzd();
    int i8 = str.length();
    if (str.charAt(0) >= 55296) {
      for (i = 1;; i = k)
      {
        k = i + 1;
        j = k;
        if (str.charAt(i) < 55296) {
          break;
        }
      }
    }
    int j = 1;
    int i = j + 1;
    int m = str.charAt(j);
    int k = i;
    j = m;
    if (m >= 55296)
    {
      k = m & 0x1FFF;
      j = 13;
      for (m = i;; m = i)
      {
        i = m + 1;
        m = str.charAt(m);
        if (m < 55296) {
          break;
        }
        k |= (m & 0x1FFF) << j;
        j += 13;
      }
      j = k | m << j;
      k = i;
    }
    int[] arrayOfInt2;
    int i2;
    int n;
    int i4;
    if (j == 0)
    {
      arrayOfInt2 = zza;
      i1 = 0;
      m = i1;
      i = m;
      i2 = i;
      j = i2;
      n = j;
      i4 = n;
      i5 = i;
    }
    else
    {
      j = k + 1;
      m = str.charAt(k);
      i = m;
      k = j;
      if (m >= 55296)
      {
        k = m & 0x1FFF;
        i = 13;
        for (m = j;; m = j)
        {
          j = m + 1;
          m = str.charAt(m);
          if (m < 55296) {
            break;
          }
          k |= (m & 0x1FFF) << i;
          i += 13;
        }
        i = k | m << i;
        k = j;
      }
      j = k + 1;
      m = str.charAt(k);
      i3 = m;
      k = j;
      if (m >= 55296)
      {
        m &= 0x1FFF;
        k = 13;
        for (n = j;; n = j)
        {
          j = n + 1;
          n = str.charAt(n);
          if (n < 55296) {
            break;
          }
          m |= (n & 0x1FFF) << k;
          k += 13;
        }
        i3 = m | n << k;
        k = j;
      }
      j = k + 1;
      m = str.charAt(k);
      k = m;
      n = j;
      if (m >= 55296)
      {
        m &= 0x1FFF;
        k = 13;
        for (n = j;; n = j)
        {
          j = n + 1;
          n = str.charAt(n);
          if (n < 55296) {
            break;
          }
          m |= (n & 0x1FFF) << k;
          k += 13;
        }
        k = m | n << k;
        n = j;
      }
      m = n + 1;
      n = str.charAt(n);
      j = n;
      i1 = m;
      if (n >= 55296)
      {
        n &= 0x1FFF;
        j = 13;
        for (i1 = m;; i1 = m)
        {
          m = i1 + 1;
          i1 = str.charAt(i1);
          if (i1 < 55296) {
            break;
          }
          n |= (i1 & 0x1FFF) << j;
          j += 13;
        }
        j = n | i1 << j;
        i1 = m;
      }
      n = i1 + 1;
      i1 = str.charAt(i1);
      m = i1;
      i2 = n;
      if (i1 >= 55296)
      {
        i1 &= 0x1FFF;
        m = 13;
        for (i2 = n;; i2 = n)
        {
          n = i2 + 1;
          i2 = str.charAt(i2);
          if (i2 < 55296) {
            break;
          }
          i1 |= (i2 & 0x1FFF) << m;
          m += 13;
        }
        m = i1 | i2 << m;
        i2 = n;
      }
      i1 = i2 + 1;
      i4 = str.charAt(i2);
      n = i4;
      i2 = i1;
      if (i4 >= 55296)
      {
        i2 = i4 & 0x1FFF;
        n = 13;
        for (i4 = i1;; i4 = i1)
        {
          i1 = i4 + 1;
          i4 = str.charAt(i4);
          if (i4 < 55296) {
            break;
          }
          i2 |= (i4 & 0x1FFF) << n;
          n += 13;
        }
        n = i2 | i4 << n;
        i2 = i1;
      }
      i1 = i2 + 1;
      i5 = str.charAt(i2);
      i4 = i5;
      i2 = i1;
      if (i5 >= 55296)
      {
        i4 = i5 & 0x1FFF;
        i2 = 13;
        for (i5 = i1;; i5 = i1)
        {
          i1 = i5 + 1;
          i5 = str.charAt(i5);
          if (i5 < 55296) {
            break;
          }
          i4 |= (i5 & 0x1FFF) << i2;
          i2 += 13;
        }
        i4 |= i5 << i2;
        i2 = i1;
      }
      i5 = i2 + 1;
      i6 = str.charAt(i2);
      i1 = i6;
      i2 = i5;
      if (i6 >= 55296)
      {
        i2 = i6 & 0x1FFF;
        i1 = 13;
        i6 = i5;
        i5 = i2;
        for (;;)
        {
          i2 = i6 + 1;
          i6 = str.charAt(i6);
          if (i6 < 55296) {
            break;
          }
          i5 |= (i6 & 0x1FFF) << i1;
          i1 += 13;
          i6 = i2;
        }
        i1 = i5 | i6 << i1;
      }
      arrayOfInt2 = new int[i1 + n + i4];
      i5 = i + i + i3;
      i3 = i2;
      i2 = j;
      i4 = n;
      n = i5;
      j = i1;
      i5 = m;
      m = i4;
      i1 = k;
      i4 = i;
      k = i3;
    }
    Unsafe localUnsafe = zzb;
    Object[] arrayOfObject2 = paramZzlv.zze();
    Class localClass = paramZzlv.zza().getClass();
    int[] arrayOfInt1 = new int[i5 * 3];
    Object[] arrayOfObject1 = new Object[i5 + i5];
    int i14 = j + m;
    i = j;
    m = i14;
    int i7 = 0;
    int i3 = 0;
    int i5 = j;
    j = i2;
    int i6 = i1;
    int i1 = k;
    k = i8;
    while (i1 < k)
    {
      int i9 = i1 + 1;
      i8 = str.charAt(i1);
      if (i8 >= 55296)
      {
        i8 &= 0x1FFF;
        i1 = 13;
        for (;;)
        {
          i2 = i9 + 1;
          i9 = str.charAt(i9);
          if (i9 < 55296) {
            break;
          }
          i8 |= (i9 & 0x1FFF) << i1;
          i1 += 13;
          i9 = i2;
        }
        i8 |= i9 << i1;
      }
      else
      {
        i2 = i9;
      }
      i1 = i2 + 1;
      int i10 = str.charAt(i2);
      if (i10 >= 55296)
      {
        i2 = i10 & 0x1FFF;
        i10 = i1;
        i1 = 13;
        for (;;)
        {
          i9 = i10 + 1;
          i10 = str.charAt(i10);
          if (i10 < 55296) {
            break;
          }
          i2 |= (i10 & 0x1FFF) << i1;
          i1 += 13;
          i10 = i9;
        }
        i10 = i2 | i10 << i1;
        i1 = i9;
      }
      int i15 = i10 & 0xFF;
      i9 = i3;
      if ((i10 & 0x400) != 0)
      {
        arrayOfInt2[i3] = i7;
        i9 = i3 + 1;
      }
      int i11;
      label1765:
      Object localObject;
      int i13;
      int i12;
      if (i15 >= 51)
      {
        i2 = i1 + 1;
        i3 = str.charAt(i1);
        if (i3 >= 55296)
        {
          i3 &= 0x1FFF;
          i1 = 13;
          i11 = i2;
          i2 = i3;
          for (;;)
          {
            i3 = i11 + 1;
            i11 = str.charAt(i11);
            if (i11 < 55296) {
              break;
            }
            i2 |= (i11 & 0x1FFF) << i1;
            i1 += 13;
            i11 = i3;
          }
          i2 |= i11 << i1;
          i1 = i3;
          i3 = i2;
        }
        else
        {
          i1 = i2;
        }
        i11 = i15 - 51;
        i2 = i1;
        if ((i11 != 9) && (i11 != 17))
        {
          i1 = n;
          if (i11 != 12) {
            break label1765;
          }
          i1 = n;
          if (bool) {
            break label1765;
          }
          i11 = i7 / 3;
          i1 = n + 1;
          arrayOfObject1[(i11 + i11 + 1)] = arrayOfObject2[n];
          n = i1;
        }
        else
        {
          i11 = i7 / 3;
          i1 = n + 1;
          arrayOfObject1[(i11 + i11 + 1)] = arrayOfObject2[n];
          n = i1;
        }
        i1 = n;
        n = i3 + i3;
        localObject = arrayOfObject2[n];
        if ((localObject instanceof Field))
        {
          localObject = (Field)localObject;
        }
        else
        {
          localObject = zzG(localClass, (String)localObject);
          arrayOfObject2[n] = localObject;
        }
        i13 = (int)localUnsafe.objectFieldOffset((Field)localObject);
        n += 1;
        localObject = arrayOfObject2[n];
        if ((localObject instanceof Field))
        {
          localObject = (Field)localObject;
        }
        else
        {
          localObject = zzG(localClass, (String)localObject);
          arrayOfObject2[n] = localObject;
        }
        i3 = (int)localUnsafe.objectFieldOffset((Field)localObject);
        i12 = 0;
        n = i1;
        i11 = m;
        m = i2;
      }
      else
      {
        i11 = j;
        i2 = n + 1;
        localObject = zzG(localClass, (String)arrayOfObject2[n]);
        if ((i15 != 9) && (i15 != 17))
        {
          if ((i15 != 27) && (i15 != 49))
          {
            if ((i15 != 12) && (i15 != 30) && (i15 != 44))
            {
              n = i2;
              j = i;
              if (i15 == 50)
              {
                j = i + 1;
                arrayOfInt2[i] = i7;
                i = i7 / 3;
                i3 = i + i;
                n = i2 + 1;
                arrayOfObject1[i3] = arrayOfObject2[i2];
                if ((i10 & 0x800) == 0) {
                  break label2082;
                }
                i = n + 1;
                arrayOfObject1[(i3 + 1)] = arrayOfObject2[n];
                n = i;
              }
            }
            label2082:
            do
            {
              i = j;
              break;
              i = j;
              j = n;
              break label2195;
              n = i2;
              j = i;
            } while (bool);
            n = i7 / 3;
            j = i2 + 1;
            arrayOfObject1[(n + n + 1)] = arrayOfObject2[i2];
          }
          else
          {
            n = i7 / 3;
            j = i2 + 1;
            arrayOfObject1[(n + n + 1)] = arrayOfObject2[i2];
          }
        }
        else
        {
          j = i7 / 3;
          arrayOfObject1[(j + j + 1)] = ((Field)localObject).getType();
          n = i2;
          j = n;
        }
        label2195:
        i13 = (int)localUnsafe.objectFieldOffset((Field)localObject);
        if (((i10 & 0x1000) == 4096) && (i15 <= 17))
        {
          n = i1 + 1;
          i1 = str.charAt(i1);
          if (i1 >= 55296)
          {
            i2 = i1 & 0x1FFF;
            i1 = 13;
            for (i3 = n;; i3 = n)
            {
              n = i3 + 1;
              i3 = str.charAt(i3);
              if (i3 < 55296) {
                break;
              }
              i2 |= (i3 & 0x1FFF) << i1;
              i1 += 13;
            }
            i1 = i2 | i3 << i1;
          }
          i2 = i4 + i4 + i1 / 32;
          localObject = arrayOfObject2[i2];
          if ((localObject instanceof Field))
          {
            localObject = (Field)localObject;
          }
          else
          {
            localObject = zzG(localClass, (String)localObject);
            arrayOfObject2[i2] = localObject;
          }
          i2 = (int)localUnsafe.objectFieldOffset((Field)localObject);
          i3 = i1 % 32;
          i1 = i2;
          i2 = i3;
        }
        else
        {
          i3 = 1048575;
          n = i1;
          i2 = 0;
          i1 = i3;
        }
        i3 = m;
        if (i15 >= 18)
        {
          i3 = m;
          if (i15 <= 49)
          {
            arrayOfInt2[m] = i13;
            i3 = m + 1;
          }
        }
        i12 = j;
        j = i11;
        m = n;
        i11 = i3;
        n = i12;
        i12 = i2;
        i3 = i1;
      }
      int i16 = i7 + 1;
      arrayOfInt1[i7] = i8;
      i8 = i16 + 1;
      if ((i10 & 0x200) != 0) {
        i1 = 536870912;
      } else {
        i1 = 0;
      }
      if ((i10 & 0x100) != 0) {
        i2 = 268435456;
      } else {
        i2 = 0;
      }
      arrayOfInt1[i16] = (i2 | i1 | i15 << 20 | i13);
      i7 = i8 + 1;
      arrayOfInt1[i8] = (i3 | i12 << 20);
      i1 = m;
      i3 = i9;
      m = i11;
    }
    return new zzlo(arrayOfInt1, arrayOfObject1, i6, j, paramZzlv.zza(), bool, false, arrayOfInt2, i5, i14, paramZzlq, paramZzkz, paramZzmn, paramZzjr, paramZzlg, null);
  }
  
  private static double zzn(Object paramObject, long paramLong)
  {
    return ((Double)zzmx.zzf(paramObject, paramLong)).doubleValue();
  }
  
  private static float zzo(Object paramObject, long paramLong)
  {
    return ((Float)zzmx.zzf(paramObject, paramLong)).floatValue();
  }
  
  private final int zzp(Object paramObject)
  {
    Object localObject1 = zzb;
    int i = 1048575;
    int n = 0;
    int m = 0;
    int i1 = 0;
    while (n < zzc.length)
    {
      int i5 = zzB(n);
      Object localObject2 = zzc;
      int i4 = localObject2[n];
      int i6 = zzA(i5);
      int j;
      int k;
      int i3;
      int i2;
      if (i6 <= 17)
      {
        j = localObject2[(n + 2)];
        k = j & 0xFFFFF;
        i3 = 1 << (j >>> 20);
        i2 = i;
        j = i3;
        if (k != i)
        {
          i1 = ((Unsafe)localObject1).getInt(paramObject, k);
          i2 = k;
          j = i3;
        }
      }
      else
      {
        j = 0;
        i2 = i;
      }
      long l = i5 & 0xFFFFF;
      switch (i6)
      {
      default: 
        i = m;
        break;
      case 68: 
        i = m;
        if (zzR(paramObject, i4, n)) {
          i = zzjl.zzu(i4, (zzll)((Unsafe)localObject1).getObject(paramObject, l), zzE(n));
        }
        break;
      case 67: 
        i = m;
        if (zzR(paramObject, i4, n))
        {
          l = zzC(paramObject, l);
          i = m + (zzjl.zzA(i4 << 3) + zzjl.zzB(l >> 63 ^ l + l));
        }
        break;
      case 66: 
        i = m;
        if (zzR(paramObject, i4, n))
        {
          i = zzr(paramObject, l);
          j = zzjl.zzA(i4 << 3);
          i = zzjl.zzA(i >> 31 ^ i + i);
        }
        break;
      case 65: 
        i = m;
        if (zzR(paramObject, i4, n)) {
          i = zzjl.zzA(i4 << 3);
        }
        break;
      case 64: 
        i = m;
        if (zzR(paramObject, i4, n)) {
          i = zzjl.zzA(i4 << 3);
        }
        break;
      case 63: 
        i = m;
        if (zzR(paramObject, i4, n))
        {
          i = zzr(paramObject, l);
          j = zzjl.zzA(i4 << 3);
          i = zzjl.zzv(i);
        }
        break;
      case 62: 
        i = m;
        if (zzR(paramObject, i4, n))
        {
          i = zzr(paramObject, l);
          j = zzjl.zzA(i4 << 3);
          i = zzjl.zzA(i);
        }
        break;
      case 61: 
        i = m;
        if (zzR(paramObject, i4, n))
        {
          localObject2 = (zzjd)((Unsafe)localObject1).getObject(paramObject, l);
          j = zzjl.zzA(i4 << 3);
          i = ((zzjd)localObject2).zzd();
        }
      case 60: 
      case 59: 
        for (k = zzjl.zzA(i);; k = zzjl.zzA(i))
        {
          i = j + (k + i);
          break label1805;
          i = m;
          if (!zzR(paramObject, i4, n)) {
            break label2012;
          }
          i = zzly.zzo(i4, ((Unsafe)localObject1).getObject(paramObject, l), zzE(n));
          break label2007;
          i = m;
          if (!zzR(paramObject, i4, n)) {
            break label2012;
          }
          localObject2 = ((Unsafe)localObject1).getObject(paramObject, l);
          if (!(localObject2 instanceof zzjd)) {
            break;
          }
          localObject2 = (zzjd)localObject2;
          j = zzjl.zzA(i4 << 3);
          i = ((zzjd)localObject2).zzd();
        }
        localObject2 = (String)localObject2;
        j = zzjl.zzA(i4 << 3);
        i = zzjl.zzy((String)localObject2);
        break;
      case 58: 
        i = m;
        if (zzR(paramObject, i4, n)) {
          i = zzjl.zzA(i4 << 3) + 1;
        }
        break;
      case 57: 
        i = m;
        if (zzR(paramObject, i4, n)) {
          i = zzjl.zzA(i4 << 3);
        }
        break;
      case 56: 
        i = m;
        if (zzR(paramObject, i4, n)) {
          i = zzjl.zzA(i4 << 3);
        }
        break;
      case 55: 
        i = m;
        if (zzR(paramObject, i4, n))
        {
          i = zzr(paramObject, l);
          j = zzjl.zzA(i4 << 3);
          i = zzjl.zzv(i);
        }
        break;
      case 54: 
        i = m;
        if (zzR(paramObject, i4, n))
        {
          l = zzC(paramObject, l);
          j = zzjl.zzA(i4 << 3);
          i = zzjl.zzB(l);
        }
        break;
      case 53: 
        i = m;
        if (zzR(paramObject, i4, n))
        {
          l = zzC(paramObject, l);
          j = zzjl.zzA(i4 << 3);
          i = zzjl.zzB(l);
          i = m + (j + i);
        }
        break;
      case 52: 
        i = m;
        if (zzR(paramObject, i4, n))
        {
          i = zzjl.zzA(i4 << 3);
          i += 4;
        }
        break;
      case 51: 
        i = m;
        if (zzR(paramObject, i4, n))
        {
          i = zzjl.zzA(i4 << 3);
          i += 8;
        }
        break;
      case 50: 
        zzlg.zza(i4, ((Unsafe)localObject1).getObject(paramObject, l), zzF(n));
        i = m;
        break;
      case 49: 
        i = zzly.zzj(i4, (List)((Unsafe)localObject1).getObject(paramObject, l), zzE(n));
        break;
      case 48: 
        j = zzly.zzt((List)((Unsafe)localObject1).getObject(paramObject, l));
        i = m;
        if (j > 0)
        {
          i3 = zzjl.zzz(i4);
          k = zzjl.zzA(j);
          i = j;
          j = i3;
        }
        break;
      case 47: 
        j = zzly.zzr((List)((Unsafe)localObject1).getObject(paramObject, l));
        i = m;
        if (j > 0)
        {
          i3 = zzjl.zzz(i4);
          k = zzjl.zzA(j);
          i = j;
          j = i3;
        }
        break;
      case 46: 
        j = zzly.zzi((List)((Unsafe)localObject1).getObject(paramObject, l));
        i = m;
        if (j > 0)
        {
          i3 = zzjl.zzz(i4);
          k = zzjl.zzA(j);
          i = j;
          j = i3;
        }
        break;
      case 45: 
        j = zzly.zzg((List)((Unsafe)localObject1).getObject(paramObject, l));
        i = m;
        if (j > 0)
        {
          i3 = zzjl.zzz(i4);
          k = zzjl.zzA(j);
          i = j;
          j = i3;
        }
        break;
      case 44: 
        j = zzly.zze((List)((Unsafe)localObject1).getObject(paramObject, l));
        i = m;
        if (j > 0)
        {
          i3 = zzjl.zzz(i4);
          k = zzjl.zzA(j);
          i = j;
          j = i3;
        }
        break;
      case 43: 
        j = zzly.zzw((List)((Unsafe)localObject1).getObject(paramObject, l));
        i = m;
        if (j > 0)
        {
          i3 = zzjl.zzz(i4);
          k = zzjl.zzA(j);
          i = j;
          j = i3;
        }
        break;
      case 42: 
        j = zzly.zzb((List)((Unsafe)localObject1).getObject(paramObject, l));
        i = m;
        if (j > 0)
        {
          i3 = zzjl.zzz(i4);
          k = zzjl.zzA(j);
          i = j;
          j = i3;
        }
        break;
      case 41: 
        j = zzly.zzg((List)((Unsafe)localObject1).getObject(paramObject, l));
        i = m;
        if (j > 0)
        {
          i3 = zzjl.zzz(i4);
          k = zzjl.zzA(j);
          i = j;
          j = i3;
        }
        break;
      case 40: 
        j = zzly.zzi((List)((Unsafe)localObject1).getObject(paramObject, l));
        i = m;
        if (j > 0)
        {
          i3 = zzjl.zzz(i4);
          k = zzjl.zzA(j);
          i = j;
          j = i3;
        }
        break;
      case 39: 
        j = zzly.zzl((List)((Unsafe)localObject1).getObject(paramObject, l));
        i = m;
        if (j > 0)
        {
          i3 = zzjl.zzz(i4);
          k = zzjl.zzA(j);
          i = j;
          j = i3;
        }
        break;
      case 38: 
        j = zzly.zzy((List)((Unsafe)localObject1).getObject(paramObject, l));
        i = m;
        if (j > 0)
        {
          i3 = zzjl.zzz(i4);
          k = zzjl.zzA(j);
          i = j;
          j = i3;
        }
        break;
      case 37: 
        j = zzly.zzn((List)((Unsafe)localObject1).getObject(paramObject, l));
        i = m;
        if (j > 0)
        {
          i3 = zzjl.zzz(i4);
          k = zzjl.zzA(j);
          i = j;
          j = i3;
        }
        break;
      case 36: 
        j = zzly.zzg((List)((Unsafe)localObject1).getObject(paramObject, l));
        i = m;
        if (j > 0)
        {
          i3 = zzjl.zzz(i4);
          k = zzjl.zzA(j);
          i = j;
          j = i3;
        }
        break;
      case 35: 
        i3 = zzly.zzi((List)((Unsafe)localObject1).getObject(paramObject, l));
        i = m;
        if (i3 > 0)
        {
          j = zzjl.zzz(i4);
          k = zzjl.zzA(i3);
          i = i3;
          j += k;
          i = j + i;
          i = m + i;
        }
        break;
      case 34: 
        i = zzly.zzs(i4, (List)((Unsafe)localObject1).getObject(paramObject, l), false);
        break;
      case 33: 
        i = zzly.zzq(i4, (List)((Unsafe)localObject1).getObject(paramObject, l), false);
        break;
      case 32: 
        i = zzly.zzh(i4, (List)((Unsafe)localObject1).getObject(paramObject, l), false);
        break;
      case 31: 
        i = zzly.zzf(i4, (List)((Unsafe)localObject1).getObject(paramObject, l), false);
        break;
      case 30: 
        i = zzly.zzd(i4, (List)((Unsafe)localObject1).getObject(paramObject, l), false);
        i = m + i;
        break;
      case 29: 
        i = zzly.zzv(i4, (List)((Unsafe)localObject1).getObject(paramObject, l), false);
        break;
      case 28: 
        i = zzly.zzc(i4, (List)((Unsafe)localObject1).getObject(paramObject, l));
        break;
      case 27: 
        i = zzly.zzp(i4, (List)((Unsafe)localObject1).getObject(paramObject, l), zzE(n));
        break;
      case 26: 
        i = zzly.zzu(i4, (List)((Unsafe)localObject1).getObject(paramObject, l));
        i = m + i;
        break;
      case 25: 
        i = zzly.zza(i4, (List)((Unsafe)localObject1).getObject(paramObject, l), false);
        break;
      case 24: 
        i = zzly.zzf(i4, (List)((Unsafe)localObject1).getObject(paramObject, l), false);
        break;
      case 23: 
        i = zzly.zzh(i4, (List)((Unsafe)localObject1).getObject(paramObject, l), false);
        break;
      case 22: 
        i = zzly.zzk(i4, (List)((Unsafe)localObject1).getObject(paramObject, l), false);
        break;
      case 21: 
        i = zzly.zzx(i4, (List)((Unsafe)localObject1).getObject(paramObject, l), false);
        break;
      case 20: 
        i = zzly.zzm(i4, (List)((Unsafe)localObject1).getObject(paramObject, l), false);
        break;
      case 19: 
        i = zzly.zzf(i4, (List)((Unsafe)localObject1).getObject(paramObject, l), false);
        break;
      case 18: 
        label1805:
        label2007:
        label2012:
        i = zzly.zzh(i4, (List)((Unsafe)localObject1).getObject(paramObject, l), false);
      }
      for (;;)
      {
        i = m + i;
        break;
        i = m;
        if ((i1 & j) == 0) {
          break;
        }
        i = zzjl.zzu(i4, (zzll)((Unsafe)localObject1).getObject(paramObject, l), zzE(n));
        continue;
        i = m;
        if ((j & i1) == 0) {
          break;
        }
        l = ((Unsafe)localObject1).getLong(paramObject, l);
        i = m + (zzjl.zzA(i4 << 3) + zzjl.zzB(l >> 63 ^ l + l));
        break;
        i = m;
        if ((i1 & j) == 0) {
          break;
        }
        i = ((Unsafe)localObject1).getInt(paramObject, l);
        j = zzjl.zzA(i4 << 3);
        i = zzjl.zzA(i >> 31 ^ i + i);
        break label2692;
        i = m;
        if ((i1 & j) == 0) {
          break;
        }
        i = zzjl.zzA(i4 << 3);
        break label2828;
        i = m;
        if ((i1 & j) == 0) {
          break;
        }
        i = zzjl.zzA(i4 << 3);
        break label2803;
        i = m;
        if ((i1 & j) == 0) {
          break;
        }
        i = ((Unsafe)localObject1).getInt(paramObject, l);
        j = zzjl.zzA(i4 << 3);
        i = zzjl.zzv(i);
        break label2692;
        i = m;
        if ((i1 & j) == 0) {
          break;
        }
        i = ((Unsafe)localObject1).getInt(paramObject, l);
        j = zzjl.zzA(i4 << 3);
        i = zzjl.zzA(i);
        break label2692;
        i = m;
        if ((i1 & j) == 0) {
          break;
        }
        localObject2 = (zzjd)((Unsafe)localObject1).getObject(paramObject, l);
        j = zzjl.zzA(i4 << 3);
        i = ((zzjd)localObject2).zzd();
        for (k = zzjl.zzA(i);; k = zzjl.zzA(i))
        {
          i = j + (k + i);
          break label2696;
          i = m;
          if ((i1 & j) == 0) {
            break label2836;
          }
          i = zzly.zzo(i4, ((Unsafe)localObject1).getObject(paramObject, l), zzE(n));
          break;
          i = m;
          if ((i1 & j) == 0) {
            break label2836;
          }
          localObject2 = ((Unsafe)localObject1).getObject(paramObject, l);
          if (!(localObject2 instanceof zzjd)) {
            break label2571;
          }
          localObject2 = (zzjd)localObject2;
          j = zzjl.zzA(i4 << 3);
          i = ((zzjd)localObject2).zzd();
        }
        label2571:
        localObject2 = (String)localObject2;
        j = zzjl.zzA(i4 << 3);
        i = zzjl.zzy((String)localObject2);
        break label2692;
        i = m;
        if ((i1 & j) == 0) {
          break;
        }
        i = zzjl.zzA(i4 << 3) + 1;
        continue;
        i = m;
        if ((i1 & j) == 0) {
          break;
        }
        i = zzjl.zzA(i4 << 3);
        break label2803;
        i = m;
        if ((i1 & j) == 0) {
          break;
        }
        i = zzjl.zzA(i4 << 3);
        break label2828;
        i = m;
        if ((i1 & j) == 0) {
          break;
        }
        i = ((Unsafe)localObject1).getInt(paramObject, l);
        j = zzjl.zzA(i4 << 3);
        i = zzjl.zzv(i);
        label2692:
        i = j + i;
        label2696:
        i = m + i;
        break;
        i = m;
        if ((i1 & j) == 0) {
          break;
        }
        l = ((Unsafe)localObject1).getLong(paramObject, l);
        j = zzjl.zzA(i4 << 3);
        i = zzjl.zzB(l);
        break label2775;
        i = m;
        if ((i1 & j) == 0) {
          break;
        }
        l = ((Unsafe)localObject1).getLong(paramObject, l);
        j = zzjl.zzA(i4 << 3);
        i = zzjl.zzB(l);
        label2775:
        i = m + (j + i);
        break;
        i = m;
        if ((i1 & j) == 0) {
          break;
        }
        i = zzjl.zzA(i4 << 3);
        label2803:
        i += 4;
        continue;
        i = m;
        if ((i1 & j) == 0) {
          break;
        }
        i = zzjl.zzA(i4 << 3);
        label2828:
        i += 8;
      }
      label2836:
      n += 3;
      m = i;
      i = i2;
    }
    localObject1 = zzn;
    i = ((zzmn)localObject1).zza(((zzmn)localObject1).zzc(paramObject));
    if (!zzh) {
      return m + i;
    }
    zzo.zza(paramObject);
    throw null;
  }
  
  private final int zzq(Object paramObject)
  {
    Object localObject1 = zzb;
    int m = 0;
    int i;
    for (int n = m; m < zzc.length; n = i)
    {
      int j = zzB(m);
      i = zzA(j);
      int k = zzc[m];
      long l = j & 0xFFFFF;
      if ((i >= zzjw.zzJ.zza()) && (i <= zzjw.zzW.zza())) {
        j = zzc[(m + 2)];
      }
      Object localObject2;
      int i1;
      switch (i)
      {
      default: 
        i = n;
        break;
      case 68: 
        i = n;
        if (!zzR(paramObject, k, m)) {
          break label2722;
        }
        i = zzjl.zzu(k, (zzll)zzmx.zzf(paramObject, l), zzE(m));
        break;
      case 67: 
        i = n;
        if (!zzR(paramObject, k, m)) {
          break label2722;
        }
        l = zzC(paramObject, l);
        j = zzjl.zzA(k << 3);
        i = zzjl.zzB(l >> 63 ^ l + l);
        break;
      case 66: 
        i = n;
        if (!zzR(paramObject, k, m)) {
          break label2722;
        }
        i = zzr(paramObject, l);
        j = zzjl.zzA(k << 3);
        i = zzjl.zzA(i >> 31 ^ i + i);
        break;
      case 65: 
        i = n;
        if (!zzR(paramObject, k, m)) {
          break label2722;
        }
        i = zzjl.zzA(k << 3);
        break;
      case 64: 
        i = n;
        if (!zzR(paramObject, k, m)) {
          break label2722;
        }
        i = zzjl.zzA(k << 3);
        break;
      case 63: 
        i = n;
        if (!zzR(paramObject, k, m)) {
          break label2722;
        }
        i = zzr(paramObject, l);
        j = zzjl.zzA(k << 3);
        i = zzjl.zzv(i);
        break;
      case 62: 
        i = n;
        if (!zzR(paramObject, k, m)) {
          break label2722;
        }
        i = zzr(paramObject, l);
        j = zzjl.zzA(k << 3);
        i = zzjl.zzA(i);
        break;
      case 61: 
        i = n;
        if (!zzR(paramObject, k, m)) {
          break label2722;
        }
        localObject2 = (zzjd)zzmx.zzf(paramObject, l);
        j = zzjl.zzA(k << 3);
        i = ((zzjd)localObject2).zzd();
        k = zzjl.zzA(i);
        break;
      case 60: 
        i = n;
        if (!zzR(paramObject, k, m)) {
          break label2722;
        }
        i = zzly.zzo(k, zzmx.zzf(paramObject, l), zzE(m));
        break;
      case 59: 
        i = n;
        if (!zzR(paramObject, k, m)) {
          break label2722;
        }
        localObject2 = zzmx.zzf(paramObject, l);
        if ((localObject2 instanceof zzjd))
        {
          localObject2 = (zzjd)localObject2;
          j = zzjl.zzA(k << 3);
          i = ((zzjd)localObject2).zzd();
          k = zzjl.zzA(i);
        }
        else
        {
          localObject2 = (String)localObject2;
          j = zzjl.zzA(k << 3);
          i = zzjl.zzy((String)localObject2);
        }
        break;
      case 58: 
        i = n;
        if (!zzR(paramObject, k, m)) {
          break label2722;
        }
        i = zzjl.zzA(k << 3);
        break;
      case 57: 
        i = n;
        if (!zzR(paramObject, k, m)) {
          break label2722;
        }
        i = zzjl.zzA(k << 3);
        break;
      case 56: 
        i = n;
        if (!zzR(paramObject, k, m)) {
          break label2722;
        }
        i = zzjl.zzA(k << 3);
        break;
      case 55: 
        i = n;
        if (!zzR(paramObject, k, m)) {
          break label2722;
        }
        i = zzr(paramObject, l);
        j = zzjl.zzA(k << 3);
        i = zzjl.zzv(i);
        break;
      case 54: 
        i = n;
        if (!zzR(paramObject, k, m)) {
          break label2722;
        }
        l = zzC(paramObject, l);
        j = zzjl.zzA(k << 3);
        i = zzjl.zzB(l);
        break;
      case 53: 
        i = n;
        if (!zzR(paramObject, k, m)) {
          break label2722;
        }
        l = zzC(paramObject, l);
        j = zzjl.zzA(k << 3);
        i = zzjl.zzB(l);
        break;
      case 52: 
        i = n;
        if (!zzR(paramObject, k, m)) {
          break label2722;
        }
        i = zzjl.zzA(k << 3);
        break;
      case 51: 
        i = n;
        if (!zzR(paramObject, k, m)) {
          break label2722;
        }
        i = zzjl.zzA(k << 3);
        break;
      case 50: 
        zzlg.zza(k, zzmx.zzf(paramObject, l), zzF(m));
        i = n;
        break;
      case 49: 
        i = zzly.zzj(k, (List)zzmx.zzf(paramObject, l), zzE(m));
        break;
      case 48: 
        j = zzly.zzt((List)((Unsafe)localObject1).getObject(paramObject, l));
        i = n;
        if (j <= 0) {
          break label2722;
        }
        i1 = zzjl.zzz(k);
        k = zzjl.zzA(j);
        i = j;
        j = i1;
        break;
      case 47: 
        j = zzly.zzr((List)((Unsafe)localObject1).getObject(paramObject, l));
        i = n;
        if (j <= 0) {
          break label2722;
        }
        i1 = zzjl.zzz(k);
        k = zzjl.zzA(j);
        i = j;
        j = i1;
        break;
      case 46: 
        j = zzly.zzi((List)((Unsafe)localObject1).getObject(paramObject, l));
        i = n;
        if (j <= 0) {
          break label2722;
        }
        i1 = zzjl.zzz(k);
        k = zzjl.zzA(j);
        i = j;
        j = i1;
        break;
      case 45: 
        j = zzly.zzg((List)((Unsafe)localObject1).getObject(paramObject, l));
        i = n;
        if (j <= 0) {
          break label2722;
        }
        i1 = zzjl.zzz(k);
        k = zzjl.zzA(j);
        i = j;
        j = i1;
        break;
      case 44: 
        j = zzly.zze((List)((Unsafe)localObject1).getObject(paramObject, l));
        i = n;
        if (j <= 0) {
          break label2722;
        }
        i1 = zzjl.zzz(k);
        k = zzjl.zzA(j);
        i = j;
        j = i1;
        break;
      case 43: 
        j = zzly.zzw((List)((Unsafe)localObject1).getObject(paramObject, l));
        i = n;
        if (j <= 0) {
          break label2722;
        }
        i1 = zzjl.zzz(k);
        k = zzjl.zzA(j);
        i = j;
        j = i1;
        break;
      case 42: 
        j = zzly.zzb((List)((Unsafe)localObject1).getObject(paramObject, l));
        i = n;
        if (j <= 0) {
          break label2722;
        }
        i1 = zzjl.zzz(k);
        k = zzjl.zzA(j);
        i = j;
        j = i1;
        break;
      case 41: 
        j = zzly.zzg((List)((Unsafe)localObject1).getObject(paramObject, l));
        i = n;
        if (j <= 0) {
          break label2722;
        }
        i1 = zzjl.zzz(k);
        k = zzjl.zzA(j);
        i = j;
        j = i1;
        break;
      case 40: 
        j = zzly.zzi((List)((Unsafe)localObject1).getObject(paramObject, l));
        i = n;
        if (j <= 0) {
          break label2722;
        }
        i1 = zzjl.zzz(k);
        k = zzjl.zzA(j);
        i = j;
        j = i1;
        break;
      case 39: 
        j = zzly.zzl((List)((Unsafe)localObject1).getObject(paramObject, l));
        i = n;
        if (j <= 0) {
          break label2722;
        }
        i1 = zzjl.zzz(k);
        k = zzjl.zzA(j);
        i = j;
        j = i1;
        break;
      case 38: 
        j = zzly.zzy((List)((Unsafe)localObject1).getObject(paramObject, l));
        i = n;
        if (j <= 0) {
          break label2722;
        }
        i1 = zzjl.zzz(k);
        k = zzjl.zzA(j);
        i = j;
        j = i1;
        break;
      case 37: 
        j = zzly.zzn((List)((Unsafe)localObject1).getObject(paramObject, l));
        i = n;
        if (j <= 0) {
          break label2722;
        }
        i1 = zzjl.zzz(k);
        k = zzjl.zzA(j);
        i = j;
        j = i1;
        break;
      case 36: 
        j = zzly.zzg((List)((Unsafe)localObject1).getObject(paramObject, l));
        i = n;
        if (j <= 0) {
          break label2722;
        }
        i1 = zzjl.zzz(k);
        k = zzjl.zzA(j);
        i = j;
        j = i1;
        break;
      case 35: 
        i1 = zzly.zzi((List)((Unsafe)localObject1).getObject(paramObject, l));
        i = n;
        if (i1 <= 0) {
          break label2722;
        }
        j = zzjl.zzz(k);
        k = zzjl.zzA(i1);
        i = i1;
        j += k;
        break;
      case 34: 
        i = zzly.zzs(k, (List)zzmx.zzf(paramObject, l), false);
        break;
      case 33: 
        i = zzly.zzq(k, (List)zzmx.zzf(paramObject, l), false);
        break;
      case 32: 
        i = zzly.zzh(k, (List)zzmx.zzf(paramObject, l), false);
        break;
      case 31: 
        i = zzly.zzf(k, (List)zzmx.zzf(paramObject, l), false);
        break;
      case 30: 
        i = zzly.zzd(k, (List)zzmx.zzf(paramObject, l), false);
        break;
      case 29: 
        i = zzly.zzv(k, (List)zzmx.zzf(paramObject, l), false);
        break;
      case 28: 
        i = zzly.zzc(k, (List)zzmx.zzf(paramObject, l));
        break;
      case 27: 
        i = zzly.zzp(k, (List)zzmx.zzf(paramObject, l), zzE(m));
        break;
      case 26: 
        i = zzly.zzu(k, (List)zzmx.zzf(paramObject, l));
        break;
      case 25: 
        i = zzly.zza(k, (List)zzmx.zzf(paramObject, l), false);
        break;
      case 24: 
        i = zzly.zzf(k, (List)zzmx.zzf(paramObject, l), false);
        break;
      case 23: 
        i = zzly.zzh(k, (List)zzmx.zzf(paramObject, l), false);
        break;
      case 22: 
        i = zzly.zzk(k, (List)zzmx.zzf(paramObject, l), false);
        break;
      case 21: 
        i = zzly.zzx(k, (List)zzmx.zzf(paramObject, l), false);
        break;
      case 20: 
        i = zzly.zzm(k, (List)zzmx.zzf(paramObject, l), false);
        break;
      case 19: 
        i = zzly.zzf(k, (List)zzmx.zzf(paramObject, l), false);
        break;
      case 18: 
        i = zzly.zzh(k, (List)zzmx.zzf(paramObject, l), false);
      }
      for (;;)
      {
        i = n + i;
        break;
        i = n;
        if (!zzO(paramObject, m)) {
          break;
        }
        i = zzjl.zzu(k, (zzll)zzmx.zzf(paramObject, l), zzE(m));
        continue;
        i = n;
        if (!zzO(paramObject, m)) {
          break;
        }
        l = zzmx.zzd(paramObject, l);
        j = zzjl.zzA(k << 3);
        i = zzjl.zzB(l >> 63 ^ l + l);
        break label2570;
        i = n;
        if (!zzO(paramObject, m)) {
          break;
        }
        i = zzmx.zzc(paramObject, l);
        j = zzjl.zzA(k << 3);
        i = zzjl.zzA(i >> 31 ^ i + i);
        break label2570;
        i = n;
        if (!zzO(paramObject, m)) {
          break;
        }
        i = zzjl.zzA(k << 3);
        break label2714;
        i = n;
        if (!zzO(paramObject, m)) {
          break;
        }
        i = zzjl.zzA(k << 3);
        break label2686;
        i = n;
        if (!zzO(paramObject, m)) {
          break;
        }
        i = zzmx.zzc(paramObject, l);
        j = zzjl.zzA(k << 3);
        i = zzjl.zzv(i);
        break label2570;
        i = n;
        if (!zzO(paramObject, m)) {
          break;
        }
        i = zzmx.zzc(paramObject, l);
        j = zzjl.zzA(k << 3);
        i = zzjl.zzA(i);
        break label2570;
        i = n;
        if (!zzO(paramObject, m)) {
          break;
        }
        localObject2 = (zzjd)zzmx.zzf(paramObject, l);
        j = zzjl.zzA(k << 3);
        i = ((zzjd)localObject2).zzd();
        for (k = zzjl.zzA(i);; k = zzjl.zzA(i))
        {
          i = j + (k + i);
          break label2574;
          i = n;
          if (!zzO(paramObject, m)) {
            break label2722;
          }
          i = zzly.zzo(k, zzmx.zzf(paramObject, l), zzE(m));
          break;
          i = n;
          if (!zzO(paramObject, m)) {
            break label2722;
          }
          localObject2 = zzmx.zzf(paramObject, l);
          if (!(localObject2 instanceof zzjd)) {
            break label2437;
          }
          localObject2 = (zzjd)localObject2;
          j = zzjl.zzA(k << 3);
          i = ((zzjd)localObject2).zzd();
        }
        label2437:
        localObject2 = (String)localObject2;
        j = zzjl.zzA(k << 3);
        i = zzjl.zzy((String)localObject2);
        break label2570;
        i = n;
        if (!zzO(paramObject, m)) {
          break;
        }
        i = zzjl.zzA(k << 3);
        i += 1;
        continue;
        i = n;
        if (!zzO(paramObject, m)) {
          break;
        }
        i = zzjl.zzA(k << 3);
        break label2686;
        i = n;
        if (!zzO(paramObject, m)) {
          break;
        }
        i = zzjl.zzA(k << 3);
        break label2714;
        i = n;
        if (!zzO(paramObject, m)) {
          break;
        }
        i = zzmx.zzc(paramObject, l);
        j = zzjl.zzA(k << 3);
        i = zzjl.zzv(i);
        label2570:
        i = j + i;
        label2574:
        i = n + i;
        break;
        i = n;
        if (!zzO(paramObject, m)) {
          break;
        }
        l = zzmx.zzd(paramObject, l);
        j = zzjl.zzA(k << 3);
        i = zzjl.zzB(l);
        break label2655;
        i = n;
        if (!zzO(paramObject, m)) {
          break;
        }
        l = zzmx.zzd(paramObject, l);
        j = zzjl.zzA(k << 3);
        i = zzjl.zzB(l);
        label2655:
        i = n + (j + i);
        break;
        i = n;
        if (!zzO(paramObject, m)) {
          break;
        }
        i = zzjl.zzA(k << 3);
        label2686:
        i += 4;
        continue;
        i = n;
        if (!zzO(paramObject, m)) {
          break;
        }
        i = zzjl.zzA(k << 3);
        label2714:
        i += 8;
      }
      label2722:
      m += 3;
    }
    localObject1 = zzn;
    return n + ((zzmn)localObject1).zza(((zzmn)localObject1).zzc(paramObject));
  }
  
  private static int zzr(Object paramObject, long paramLong)
  {
    return ((Integer)zzmx.zzf(paramObject, paramLong)).intValue();
  }
  
  private final int zzs(Object paramObject, byte[] paramArrayOfByte, int paramInt1, int paramInt2, int paramInt3, long paramLong, zziq paramZziq)
    throws IOException
  {
    paramArrayOfByte = zzb;
    paramZziq = zzF(paramInt3);
    Object localObject = paramArrayOfByte.getObject(paramObject, paramLong);
    if (!((zzlf)localObject).zze())
    {
      zzlf localZzlf = zzlf.zza().zzb();
      zzlg.zzb(localZzlf, localObject);
      paramArrayOfByte.putObject(paramObject, paramLong, localZzlf);
    }
    paramObject = (zzle)paramZziq;
    throw null;
  }
  
  private final int zzt(Object paramObject, byte[] paramArrayOfByte, int paramInt1, int paramInt2, int paramInt3, int paramInt4, int paramInt5, int paramInt6, int paramInt7, long paramLong, int paramInt8, zziq paramZziq)
    throws IOException
  {
    Unsafe localUnsafe = zzb;
    long l = zzc[(paramInt8 + 2)] & 0xFFFFF;
    switch (paramInt7)
    {
    default: 
      break;
    case 68: 
      if (paramInt5 == 3)
      {
        paramInt1 = zzir.zzc(zzE(paramInt8), paramArrayOfByte, paramInt1, paramInt2, paramInt3 & 0xFFFFFFF8 | 0x4, paramZziq);
        if (localUnsafe.getInt(paramObject, l) == paramInt4) {
          paramArrayOfByte = localUnsafe.getObject(paramObject, paramLong);
        } else {
          paramArrayOfByte = null;
        }
        if (paramArrayOfByte == null) {
          localUnsafe.putObject(paramObject, paramLong, zzc);
        } else {
          localUnsafe.putObject(paramObject, paramLong, zzkm.zzg(paramArrayOfByte, zzc));
        }
        localUnsafe.putInt(paramObject, l, paramInt4);
        return paramInt1;
      }
      break;
    case 67: 
      if (paramInt5 == 0)
      {
        paramInt1 = zzir.zzm(paramArrayOfByte, paramInt1, paramZziq);
        localUnsafe.putObject(paramObject, paramLong, Long.valueOf(zzjh.zzc(zzb)));
        localUnsafe.putInt(paramObject, l, paramInt4);
        return paramInt1;
      }
      break;
    case 66: 
      if (paramInt5 == 0)
      {
        paramInt1 = zzir.zzj(paramArrayOfByte, paramInt1, paramZziq);
        localUnsafe.putObject(paramObject, paramLong, Integer.valueOf(zzjh.zzb(zza)));
        localUnsafe.putInt(paramObject, l, paramInt4);
        return paramInt1;
      }
      break;
    case 63: 
      if (paramInt5 == 0)
      {
        paramInt1 = zzir.zzj(paramArrayOfByte, paramInt1, paramZziq);
        paramInt2 = zza;
        paramArrayOfByte = zzD(paramInt8);
        if ((paramArrayOfByte != null) && (!paramArrayOfByte.zza(paramInt2)))
        {
          zzd(paramObject).zzh(paramInt3, Long.valueOf(paramInt2));
        }
        else
        {
          localUnsafe.putObject(paramObject, paramLong, Integer.valueOf(paramInt2));
          localUnsafe.putInt(paramObject, l, paramInt4);
        }
        return paramInt1;
      }
      break;
    case 61: 
      if (paramInt5 == 2)
      {
        paramInt1 = zzir.zza(paramArrayOfByte, paramInt1, paramZziq);
        localUnsafe.putObject(paramObject, paramLong, zzc);
        localUnsafe.putInt(paramObject, l, paramInt4);
        return paramInt1;
      }
      break;
    case 60: 
      if (paramInt5 == 2)
      {
        paramInt1 = zzir.zzd(zzE(paramInt8), paramArrayOfByte, paramInt1, paramInt2, paramZziq);
        if (localUnsafe.getInt(paramObject, l) == paramInt4) {
          paramArrayOfByte = localUnsafe.getObject(paramObject, paramLong);
        } else {
          paramArrayOfByte = null;
        }
        if (paramArrayOfByte == null) {
          localUnsafe.putObject(paramObject, paramLong, zzc);
        } else {
          localUnsafe.putObject(paramObject, paramLong, zzkm.zzg(paramArrayOfByte, zzc));
        }
        localUnsafe.putInt(paramObject, l, paramInt4);
        return paramInt1;
      }
      break;
    case 59: 
      if (paramInt5 == 2)
      {
        paramInt1 = zzir.zzj(paramArrayOfByte, paramInt1, paramZziq);
        paramInt2 = zza;
        if (paramInt2 == 0)
        {
          localUnsafe.putObject(paramObject, paramLong, "");
        }
        else
        {
          if (((paramInt6 & 0x20000000) != 0) && (!zznc.zzf(paramArrayOfByte, paramInt1, paramInt1 + paramInt2))) {
            throw zzko.zzc();
          }
          localUnsafe.putObject(paramObject, paramLong, new String(paramArrayOfByte, paramInt1, paramInt2, zzkm.zzb));
          paramInt1 += paramInt2;
        }
        localUnsafe.putInt(paramObject, l, paramInt4);
        return paramInt1;
      }
      break;
    case 58: 
      if (paramInt5 == 0)
      {
        paramInt1 = zzir.zzm(paramArrayOfByte, paramInt1, paramZziq);
        boolean bool;
        if (zzb != 0L) {
          bool = true;
        } else {
          bool = false;
        }
        localUnsafe.putObject(paramObject, paramLong, Boolean.valueOf(bool));
        localUnsafe.putInt(paramObject, l, paramInt4);
        return paramInt1;
      }
      break;
    case 57: 
    case 64: 
      if (paramInt5 == 5)
      {
        localUnsafe.putObject(paramObject, paramLong, Integer.valueOf(zzir.zzb(paramArrayOfByte, paramInt1)));
        localUnsafe.putInt(paramObject, l, paramInt4);
        return paramInt1 + 4;
      }
      break;
    case 56: 
    case 65: 
      if (paramInt5 == 1)
      {
        localUnsafe.putObject(paramObject, paramLong, Long.valueOf(zzir.zzn(paramArrayOfByte, paramInt1)));
        localUnsafe.putInt(paramObject, l, paramInt4);
        return paramInt1 + 8;
      }
      break;
    case 55: 
    case 62: 
      if (paramInt5 == 0)
      {
        paramInt1 = zzir.zzj(paramArrayOfByte, paramInt1, paramZziq);
        localUnsafe.putObject(paramObject, paramLong, Integer.valueOf(zza));
        localUnsafe.putInt(paramObject, l, paramInt4);
        return paramInt1;
      }
      break;
    case 53: 
    case 54: 
      if (paramInt5 == 0)
      {
        paramInt1 = zzir.zzm(paramArrayOfByte, paramInt1, paramZziq);
        localUnsafe.putObject(paramObject, paramLong, Long.valueOf(zzb));
        localUnsafe.putInt(paramObject, l, paramInt4);
        return paramInt1;
      }
      break;
    case 52: 
      if (paramInt5 == 5)
      {
        localUnsafe.putObject(paramObject, paramLong, Float.valueOf(Float.intBitsToFloat(zzir.zzb(paramArrayOfByte, paramInt1))));
        localUnsafe.putInt(paramObject, l, paramInt4);
        return paramInt1 + 4;
      }
      break;
    case 51: 
      if (paramInt5 == 1)
      {
        localUnsafe.putObject(paramObject, paramLong, Double.valueOf(Double.longBitsToDouble(zzir.zzn(paramArrayOfByte, paramInt1))));
        localUnsafe.putInt(paramObject, l, paramInt4);
        return paramInt1 + 8;
      }
      break;
    }
    return paramInt1;
  }
  
  private final int zzu(Object paramObject, byte[] paramArrayOfByte, int paramInt1, int paramInt2, zziq paramZziq)
    throws IOException
  {
    Object localObject1 = zzb;
    int m = -1;
    int i1 = 1048575;
    int j = paramInt1;
    int i = 1048575;
    int k = -1;
    int i2 = 0;
    paramInt1 = i2;
    for (;;)
    {
      Object localObject4 = this;
      Object localObject3 = paramObject;
      int i4 = paramInt2;
      byte[] arrayOfByte = paramArrayOfByte;
      Object localObject5 = paramZziq;
      if (j >= i4) {
        break;
      }
      int n = j + 1;
      int i3 = arrayOfByte[j];
      if (i3 < 0)
      {
        j = zzir.zzk(i3, arrayOfByte, n, (zziq)localObject5);
        i3 = zza;
      }
      else
      {
        j = n;
      }
      n = i3 >>> 3;
      int i5 = i3 & 0x7;
      if (n > k) {
        k = ((zzlo)localObject4).zzx(n, i2 / 3);
      } else {
        k = ((zzlo)localObject4).zzw(n);
      }
      if (k == m)
      {
        i1 = j;
        j = m;
        k = 0;
      }
      else
      {
        Object localObject2 = zzc;
        int i6 = localObject2[(k + 1)];
        int i7 = zzA(i6);
        long l = i6 & i1;
        if (i7 <= 17)
        {
          m = localObject2[(k + 2)];
          i1 = 1 << (m >>> 20);
          m &= 0xFFFFF;
          if (m != i)
          {
            if (i != 1048575) {
              ((Unsafe)localObject1).putInt(localObject3, i, paramInt1);
            }
            if (m != 1048575) {
              paramInt1 = ((Unsafe)localObject1).getInt(localObject3, m);
            }
            i = m;
            m = paramInt1;
          }
          else
          {
            m = paramInt1;
          }
          switch (i7)
          {
          }
          for (;;)
          {
            break;
            if (i5 == 0)
            {
              paramInt1 = zzir.zzm(arrayOfByte, j, (zziq)localObject5);
              ((Unsafe)localObject1).putLong(paramObject, l, zzjh.zzc(zzb));
              m |= i1;
              j = k;
              k = m;
            }
            else
            {
              break;
              if (i5 != 0) {
                continue;
              }
              paramInt1 = zzir.zzj(arrayOfByte, j, (zziq)localObject5);
              ((Unsafe)localObject1).putInt(localObject3, l, zzjh.zzb(zza));
              break label916;
              if (i5 != 0) {
                continue;
              }
              paramInt1 = zzir.zzj(arrayOfByte, j, (zziq)localObject5);
              ((Unsafe)localObject1).putInt(localObject3, l, zza);
              break label916;
              if (i5 != 2) {
                continue;
              }
              paramInt1 = zzir.zza(arrayOfByte, j, (zziq)localObject5);
              ((Unsafe)localObject1).putObject(localObject3, l, zzc);
              break label916;
              localObject2 = localObject1;
              if (i5 != 2) {
                continue;
              }
              paramInt1 = zzir.zzd(((zzlo)localObject4).zzE(k), arrayOfByte, j, i4, (zziq)localObject5);
              localObject4 = ((Unsafe)localObject2).getObject(localObject3, l);
              if (localObject4 == null)
              {
                ((Unsafe)localObject2).putObject(localObject3, l, zzc);
              }
              else
              {
                ((Unsafe)localObject2).putObject(localObject3, l, zzkm.zzg(localObject4, zzc));
                break label916;
                if (i5 != 2) {
                  continue;
                }
                if ((i6 & 0x20000000) == 0) {
                  paramInt1 = zzir.zzg(arrayOfByte, j, (zziq)localObject5);
                } else {
                  paramInt1 = zzir.zzh(arrayOfByte, j, (zziq)localObject5);
                }
                ((Unsafe)localObject1).putObject(localObject3, l, zzc);
                break label916;
                if (i5 != 0) {
                  continue;
                }
                paramInt1 = zzir.zzm(arrayOfByte, j, (zziq)localObject5);
                boolean bool;
                if (zzb != 0L) {
                  bool = true;
                } else {
                  bool = false;
                }
                zzmx.zzm(localObject3, l, bool);
                break label916;
                if (i5 != 5) {
                  continue;
                }
                ((Unsafe)localObject1).putInt(localObject3, l, zzir.zzb(arrayOfByte, j));
                paramInt1 = j + 4;
                break label916;
                if (i5 != 1) {
                  continue;
                }
                ((Unsafe)localObject1).putLong(paramObject, l, zzir.zzn(arrayOfByte, j));
                paramInt1 = j + 8;
                break label916;
                if (i5 != 0) {
                  break;
                }
                paramInt1 = zzir.zzj(arrayOfByte, j, (zziq)localObject5);
                ((Unsafe)localObject1).putInt(localObject3, l, zza);
                break label916;
                localObject2 = localObject1;
                if (i5 != 0) {
                  break;
                }
                paramInt1 = zzir.zzm(arrayOfByte, j, (zziq)localObject5);
                ((Unsafe)localObject2).putLong(paramObject, l, zzb);
                m |= i1;
                localObject1 = localObject2;
                j = k;
                k = m;
                break label931;
                paramInt1 = j;
                if (i5 != 5) {
                  break;
                }
                zzmx.zzp(localObject3, l, Float.intBitsToFloat(zzir.zzb(arrayOfByte, paramInt1)));
                paramInt1 += 4;
                break label916;
                paramInt1 = j;
                if (i5 != 1) {
                  break;
                }
                zzmx.zzo(localObject3, l, Double.longBitsToDouble(zzir.zzn(arrayOfByte, paramInt1)));
                paramInt1 += 8;
              }
              label916:
              m |= i1;
              j = k;
              k = m;
            }
            label931:
            m = n;
            n = paramInt1;
            i2 = j;
            paramInt1 = k;
            break label1091;
          }
          i2 = -1;
          i1 = j;
          paramInt1 = m;
          j = i2;
        }
        else
        {
          i1 = n;
          if (i7 == 27)
          {
            if (i5 == 2)
            {
              localObject5 = (zzkl)((Unsafe)localObject1).getObject(localObject3, l);
              localObject2 = localObject5;
              if (!((zzkl)localObject5).zzc())
              {
                m = ((List)localObject5).size();
                if (m == 0) {
                  m = 10;
                } else {
                  m += m;
                }
                localObject2 = ((zzkl)localObject5).zzd(m);
                ((Unsafe)localObject1).putObject(localObject3, l, localObject2);
              }
              n = zzir.zze(((zzlo)localObject4).zzE(k), i3, paramArrayOfByte, j, paramInt2, (zzkl)localObject2, paramZziq);
              m = i1;
              i2 = k;
              label1091:
              i1 = 1048575;
              i3 = -1;
              j = n;
              k = m;
              m = i3;
              continue;
            }
          }
          else
          {
            i2 = k;
            if (i7 <= 49)
            {
              i4 = zzv(paramObject, paramArrayOfByte, j, paramInt2, i3, i1, i5, i2, i6, i7, l, paramZziq);
              m = i4;
              if (i4 != j) {
                j = i4;
              }
            }
          }
          for (;;)
          {
            m = -1;
            k = i1;
            break label1323;
            label1241:
            label1247:
            do
            {
              do
              {
                i1 = m;
                break label1241;
                i4 = j;
                if (i7 != 50) {
                  break label1247;
                }
                if (i5 != 2) {
                  break;
                }
                j = zzs(paramObject, paramArrayOfByte, i4, paramInt2, i2, l, paramZziq);
                m = j;
              } while (j == i4);
              break;
              i1 = j;
              j = -1;
              break label1289;
              j = zzt(paramObject, paramArrayOfByte, i4, paramInt2, i3, i1, i5, i6, i7, l, i2, paramZziq);
              m = j;
            } while (j == i4);
          }
        }
      }
      label1289:
      i1 = zzir.zzi(i3, paramArrayOfByte, i1, paramInt2, zzd(paramObject), paramZziq);
      m = j;
      i2 = k;
      k = n;
      j = i1;
      label1323:
      i1 = 1048575;
    }
    if (i != i1) {
      ((Unsafe)localObject1).putInt(paramObject, i, paramInt1);
    }
    if (j == paramInt2) {
      return j;
    }
    throw zzko.zze();
  }
  
  private final int zzv(Object paramObject, byte[] paramArrayOfByte, int paramInt1, int paramInt2, int paramInt3, int paramInt4, int paramInt5, int paramInt6, long paramLong1, int paramInt7, long paramLong2, zziq paramZziq)
    throws IOException
  {
    int i = paramInt1;
    Unsafe localUnsafe = zzb;
    zzkl localZzkl2 = (zzkl)localUnsafe.getObject(paramObject, paramLong2);
    zzkl localZzkl1 = localZzkl2;
    if (!localZzkl2.zzc())
    {
      int j = localZzkl2.size();
      if (j == 0) {
        j = 10;
      } else {
        j += j;
      }
      localZzkl1 = localZzkl2.zzd(j);
      localUnsafe.putObject(paramObject, paramLong2, localZzkl1);
    }
    switch (paramInt7)
    {
    default: 
      if (paramInt5 != 3) {
        break label2292;
      }
      paramObject = zzE(paramInt6);
      paramInt4 = paramInt3 & 0xFFFFFFF8 | 0x4;
      paramInt1 = zzir.zzc(paramObject, paramArrayOfByte, paramInt1, paramInt2, paramInt4, paramZziq);
      localZzkl1.add(zzc);
      break;
    case 34: 
    case 48: 
      if (paramInt5 == 2)
      {
        paramObject = (zzla)localZzkl1;
        paramInt1 = zzir.zzj(paramArrayOfByte, i, paramZziq);
        paramInt2 = zza + paramInt1;
        while (paramInt1 < paramInt2)
        {
          paramInt1 = zzir.zzm(paramArrayOfByte, paramInt1, paramZziq);
          paramObject.zzg(zzjh.zzc(zzb));
        }
        if (paramInt1 == paramInt2) {
          return paramInt1;
        }
        throw zzko.zzf();
      }
      if (paramInt5 != 0) {
        break label2292;
      }
      paramObject = (zzla)localZzkl1;
      paramInt1 = zzir.zzm(paramArrayOfByte, i, paramZziq);
      paramObject.zzg(zzjh.zzc(zzb));
      while (paramInt1 < paramInt2)
      {
        paramInt4 = zzir.zzj(paramArrayOfByte, paramInt1, paramZziq);
        if (paramInt3 != zza) {
          return paramInt1;
        }
        paramInt1 = zzir.zzm(paramArrayOfByte, paramInt4, paramZziq);
        paramObject.zzg(zzjh.zzc(zzb));
      }
      return paramInt1;
    case 33: 
    case 47: 
      if (paramInt5 == 2)
      {
        paramObject = (zzkf)localZzkl1;
        paramInt1 = zzir.zzj(paramArrayOfByte, i, paramZziq);
        paramInt2 = zza + paramInt1;
        while (paramInt1 < paramInt2)
        {
          paramInt1 = zzir.zzj(paramArrayOfByte, paramInt1, paramZziq);
          paramObject.zzh(zzjh.zzb(zza));
        }
        if (paramInt1 == paramInt2) {
          return paramInt1;
        }
        throw zzko.zzf();
      }
      if (paramInt5 != 0) {
        break label2292;
      }
      paramObject = (zzkf)localZzkl1;
      paramInt1 = zzir.zzj(paramArrayOfByte, i, paramZziq);
      paramObject.zzh(zzjh.zzb(zza));
      while (paramInt1 < paramInt2)
      {
        paramInt4 = zzir.zzj(paramArrayOfByte, paramInt1, paramZziq);
        if (paramInt3 != zza) {
          return paramInt1;
        }
        paramInt1 = zzir.zzj(paramArrayOfByte, paramInt4, paramZziq);
        paramObject.zzh(zzjh.zzb(zza));
      }
      return paramInt1;
    case 30: 
    case 44: 
      if (paramInt5 == 2)
      {
        paramInt1 = zzir.zzf(paramArrayOfByte, i, localZzkl1, paramZziq);
      }
      else
      {
        if (paramInt5 != 0) {
          break label2292;
        }
        paramInt1 = zzir.zzl(paramInt3, paramArrayOfByte, paramInt1, paramInt2, localZzkl1, paramZziq);
      }
      paramZziq = (zzke)paramObject;
      paramArrayOfByte = zzc;
      paramObject = paramArrayOfByte;
      if (paramArrayOfByte == zzmo.zzc()) {
        paramObject = null;
      }
      paramObject = zzly.zzC(paramInt4, localZzkl1, zzD(paramInt6), paramObject, zzn);
      if (paramObject != null)
      {
        zzc = ((zzmo)paramObject);
        return paramInt1;
      }
    case 28: 
      if (paramInt5 != 2) {
        break label2292;
      }
      paramInt1 = zzir.zzj(paramArrayOfByte, i, paramZziq);
      paramInt4 = zza;
      if (paramInt4 >= 0)
      {
        if (paramInt4 <= paramArrayOfByte.length - paramInt1)
        {
          if (paramInt4 == 0) {
            localZzkl1.add(zzjd.zzb);
          } else {
            localZzkl1.add(zzjd.zzl(paramArrayOfByte, paramInt1, paramInt4));
          }
          for (;;)
          {
            paramInt1 += paramInt4;
            for (;;)
            {
              if (paramInt1 >= paramInt2) {
                break label863;
              }
              paramInt4 = zzir.zzj(paramArrayOfByte, paramInt1, paramZziq);
              if (paramInt3 != zza) {
                return paramInt1;
              }
              paramInt1 = zzir.zzj(paramArrayOfByte, paramInt4, paramZziq);
              paramInt4 = zza;
              if (paramInt4 < 0) {
                break label859;
              }
              if (paramInt4 > paramArrayOfByte.length - paramInt1) {
                break label855;
              }
              if (paramInt4 != 0) {
                break;
              }
              localZzkl1.add(zzjd.zzb);
            }
            localZzkl1.add(zzjd.zzl(paramArrayOfByte, paramInt1, paramInt4));
          }
          throw zzko.zzf();
          throw zzko.zzd();
          return paramInt1;
        }
        throw zzko.zzf();
      }
      throw zzko.zzd();
    case 27: 
      if (paramInt5 != 2) {
        break label2292;
      }
      return zzir.zze(zzE(paramInt6), paramInt3, paramArrayOfByte, paramInt1, paramInt2, localZzkl1, paramZziq);
    case 26: 
      if (paramInt5 != 2) {
        break label2292;
      }
      if ((paramLong1 & 0x20000000) == 0L)
      {
        paramInt1 = zzir.zzj(paramArrayOfByte, i, paramZziq);
        paramInt4 = zza;
        if (paramInt4 >= 0)
        {
          if (paramInt4 == 0) {
            localZzkl1.add("");
          } else {
            localZzkl1.add(new String(paramArrayOfByte, paramInt1, paramInt4, zzkm.zzb));
          }
          for (;;)
          {
            paramInt1 += paramInt4;
            for (;;)
            {
              paramInt4 = paramInt1;
              if (paramInt1 >= paramInt2) {
                break label2296;
              }
              paramInt5 = zzir.zzj(paramArrayOfByte, paramInt1, paramZziq);
              paramInt4 = paramInt1;
              if (paramInt3 != zza) {
                break label2296;
              }
              paramInt1 = zzir.zzj(paramArrayOfByte, paramInt5, paramZziq);
              paramInt4 = zza;
              if (paramInt4 < 0) {
                break label1082;
              }
              if (paramInt4 != 0) {
                break;
              }
              localZzkl1.add("");
            }
            localZzkl1.add(new String(paramArrayOfByte, paramInt1, paramInt4, zzkm.zzb));
          }
          throw zzko.zzd();
        }
        throw zzko.zzd();
      }
      paramInt1 = zzir.zzj(paramArrayOfByte, i, paramZziq);
      paramInt5 = zza;
      if (paramInt5 >= 0)
      {
        if (paramInt5 == 0)
        {
          localZzkl1.add("");
        }
        else
        {
          paramInt4 = paramInt1 + paramInt5;
          if (!zznc.zzf(paramArrayOfByte, paramInt1, paramInt4)) {
            break label1294;
          }
          localZzkl1.add(new String(paramArrayOfByte, paramInt1, paramInt5, zzkm.zzb));
          paramInt1 = paramInt4;
        }
        for (;;)
        {
          paramInt4 = paramInt1;
          if (paramInt1 >= paramInt2) {
            break label2296;
          }
          paramInt5 = zzir.zzj(paramArrayOfByte, paramInt1, paramZziq);
          paramInt4 = paramInt1;
          if (paramInt3 != zza) {
            break label2296;
          }
          paramInt1 = zzir.zzj(paramArrayOfByte, paramInt5, paramZziq);
          paramInt5 = zza;
          if (paramInt5 < 0) {
            break label1290;
          }
          if (paramInt5 == 0)
          {
            localZzkl1.add("");
          }
          else
          {
            paramInt4 = paramInt1 + paramInt5;
            if (!zznc.zzf(paramArrayOfByte, paramInt1, paramInt4)) {
              break;
            }
            localZzkl1.add(new String(paramArrayOfByte, paramInt1, paramInt5, zzkm.zzb));
            paramInt1 = paramInt4;
          }
        }
        throw zzko.zzc();
        throw zzko.zzd();
        throw zzko.zzc();
      }
      throw zzko.zzd();
    case 25: 
    case 42: 
      boolean bool;
      if (paramInt5 == 2)
      {
        paramObject = (zzis)localZzkl1;
        paramInt1 = zzir.zzj(paramArrayOfByte, i, paramZziq);
        paramInt2 = zza + paramInt1;
        while (paramInt1 < paramInt2)
        {
          paramInt1 = zzir.zzm(paramArrayOfByte, paramInt1, paramZziq);
          if (zzb != 0L) {
            bool = true;
          } else {
            bool = false;
          }
          paramObject.zze(bool);
        }
        if (paramInt1 == paramInt2) {
          return paramInt1;
        }
        throw zzko.zzf();
      }
      if (paramInt5 != 0) {
        break label2292;
      }
      paramObject = (zzis)localZzkl1;
      paramInt1 = zzir.zzm(paramArrayOfByte, i, paramZziq);
      if (zzb != 0L) {
        bool = true;
      } else {
        bool = false;
      }
      paramObject.zze(bool);
      while (paramInt1 < paramInt2)
      {
        paramInt4 = zzir.zzj(paramArrayOfByte, paramInt1, paramZziq);
        if (paramInt3 != zza) {
          return paramInt1;
        }
        paramInt1 = zzir.zzm(paramArrayOfByte, paramInt4, paramZziq);
        if (zzb != 0L) {
          bool = true;
        } else {
          bool = false;
        }
        paramObject.zze(bool);
      }
      return paramInt1;
    case 24: 
    case 31: 
    case 41: 
    case 45: 
      if (paramInt5 == 2)
      {
        paramObject = (zzkf)localZzkl1;
        paramInt1 = zzir.zzj(paramArrayOfByte, i, paramZziq);
        paramInt2 = zza + paramInt1;
        while (paramInt1 < paramInt2)
        {
          paramObject.zzh(zzir.zzb(paramArrayOfByte, paramInt1));
          paramInt1 += 4;
        }
        if (paramInt1 == paramInt2) {
          return paramInt1;
        }
        throw zzko.zzf();
      }
      if (paramInt5 != 5) {
        break label2292;
      }
      paramObject = (zzkf)localZzkl1;
      paramObject.zzh(zzir.zzb(paramArrayOfByte, paramInt1));
      for (;;)
      {
        paramInt1 = i + 4;
        if (paramInt1 >= paramInt2) {
          break;
        }
        i = zzir.zzj(paramArrayOfByte, paramInt1, paramZziq);
        if (paramInt3 != zza) {
          return paramInt1;
        }
        paramObject.zzh(zzir.zzb(paramArrayOfByte, i));
      }
      return paramInt1;
    case 23: 
    case 32: 
    case 40: 
    case 46: 
      if (paramInt5 == 2)
      {
        paramObject = (zzla)localZzkl1;
        paramInt1 = zzir.zzj(paramArrayOfByte, i, paramZziq);
        paramInt2 = zza + paramInt1;
        while (paramInt1 < paramInt2)
        {
          paramObject.zzg(zzir.zzn(paramArrayOfByte, paramInt1));
          paramInt1 += 8;
        }
        if (paramInt1 == paramInt2) {
          return paramInt1;
        }
        throw zzko.zzf();
      }
      if (paramInt5 != 1) {
        break label2292;
      }
      paramObject = (zzla)localZzkl1;
      paramObject.zzg(zzir.zzn(paramArrayOfByte, paramInt1));
      for (;;)
      {
        paramInt1 = i + 8;
        if (paramInt1 >= paramInt2) {
          break;
        }
        i = zzir.zzj(paramArrayOfByte, paramInt1, paramZziq);
        if (paramInt3 != zza) {
          return paramInt1;
        }
        paramObject.zzg(zzir.zzn(paramArrayOfByte, i));
      }
      return paramInt1;
    case 22: 
    case 29: 
    case 39: 
    case 43: 
      if (paramInt5 == 2) {
        return zzir.zzf(paramArrayOfByte, i, localZzkl1, paramZziq);
      }
      if (paramInt5 != 0) {
        break label2292;
      }
      return zzir.zzl(paramInt3, paramArrayOfByte, paramInt1, paramInt2, localZzkl1, paramZziq);
    case 20: 
    case 21: 
    case 37: 
    case 38: 
      if (paramInt5 == 2)
      {
        paramObject = (zzla)localZzkl1;
        paramInt1 = zzir.zzj(paramArrayOfByte, i, paramZziq);
        paramInt2 = zza + paramInt1;
        while (paramInt1 < paramInt2)
        {
          paramInt1 = zzir.zzm(paramArrayOfByte, paramInt1, paramZziq);
          paramObject.zzg(zzb);
        }
        if (paramInt1 == paramInt2) {
          return paramInt1;
        }
        throw zzko.zzf();
      }
      if (paramInt5 != 0) {
        break label2292;
      }
      paramObject = (zzla)localZzkl1;
      paramInt1 = zzir.zzm(paramArrayOfByte, i, paramZziq);
      paramObject.zzg(zzb);
      while (paramInt1 < paramInt2)
      {
        paramInt4 = zzir.zzj(paramArrayOfByte, paramInt1, paramZziq);
        if (paramInt3 != zza) {
          return paramInt1;
        }
        paramInt1 = zzir.zzm(paramArrayOfByte, paramInt4, paramZziq);
        paramObject.zzg(zzb);
      }
      return paramInt1;
    case 19: 
    case 36: 
      label855:
      label859:
      label863:
      label1082:
      label1290:
      label1294:
      if (paramInt5 == 2)
      {
        paramObject = (zzjx)localZzkl1;
        paramInt1 = zzir.zzj(paramArrayOfByte, i, paramZziq);
        paramInt2 = zza + paramInt1;
        while (paramInt1 < paramInt2)
        {
          paramObject.zze(Float.intBitsToFloat(zzir.zzb(paramArrayOfByte, paramInt1)));
          paramInt1 += 4;
        }
        if (paramInt1 == paramInt2) {
          return paramInt1;
        }
        throw zzko.zzf();
      }
      if (paramInt5 != 5) {
        break label2292;
      }
      paramObject = (zzjx)localZzkl1;
      paramObject.zze(Float.intBitsToFloat(zzir.zzb(paramArrayOfByte, paramInt1)));
      for (;;)
      {
        paramInt1 = i + 4;
        if (paramInt1 >= paramInt2) {
          break;
        }
        i = zzir.zzj(paramArrayOfByte, paramInt1, paramZziq);
        if (paramInt3 != zza) {
          return paramInt1;
        }
        paramObject.zze(Float.intBitsToFloat(zzir.zzb(paramArrayOfByte, i)));
      }
      return paramInt1;
    }
    if (paramInt5 == 2)
    {
      paramObject = (zzjn)localZzkl1;
      paramInt1 = zzir.zzj(paramArrayOfByte, i, paramZziq);
      paramInt2 = zza + paramInt1;
      while (paramInt1 < paramInt2)
      {
        paramObject.zze(Double.longBitsToDouble(zzir.zzn(paramArrayOfByte, paramInt1)));
        paramInt1 += 8;
      }
      if (paramInt1 == paramInt2) {
        return paramInt1;
      }
      throw zzko.zzf();
    }
    if (paramInt5 == 1)
    {
      paramObject = (zzjn)localZzkl1;
      paramObject.zze(Double.longBitsToDouble(zzir.zzn(paramArrayOfByte, paramInt1)));
      for (;;)
      {
        paramInt1 = i + 8;
        if (paramInt1 >= paramInt2) {
          break;
        }
        i = zzir.zzj(paramArrayOfByte, paramInt1, paramZziq);
        if (paramInt3 != zza) {
          return paramInt1;
        }
        paramObject.zze(Double.longBitsToDouble(zzir.zzn(paramArrayOfByte, i)));
      }
      return paramInt1;
      while (paramInt1 < paramInt2)
      {
        paramInt5 = zzir.zzj(paramArrayOfByte, paramInt1, paramZziq);
        if (paramInt3 != zza) {
          return paramInt1;
        }
        paramInt1 = zzir.zzc(paramObject, paramArrayOfByte, paramInt5, paramInt2, paramInt4, paramZziq);
        localZzkl1.add(zzc);
      }
      return paramInt1;
    }
    label2292:
    paramInt4 = i;
    label2296:
    return paramInt4;
  }
  
  private final int zzw(int paramInt)
  {
    if ((paramInt >= zze) && (paramInt <= zzf)) {
      return zzz(paramInt, 0);
    }
    return -1;
  }
  
  private final int zzx(int paramInt1, int paramInt2)
  {
    if ((paramInt1 >= zze) && (paramInt1 <= zzf)) {
      return zzz(paramInt1, paramInt2);
    }
    return -1;
  }
  
  private final int zzy(int paramInt)
  {
    return zzc[(paramInt + 2)];
  }
  
  private final int zzz(int paramInt1, int paramInt2)
  {
    int i = zzc.length / 3 - 1;
    while (paramInt2 <= i)
    {
      int j = i + paramInt2 >>> 1;
      int k = j * 3;
      int m = zzc[k];
      if (paramInt1 == m) {
        return k;
      }
      if (paramInt1 < m) {
        i = j - 1;
      } else {
        paramInt2 = j + 1;
      }
    }
    return -1;
  }
  
  public final int zza(Object paramObject)
  {
    if (zzi) {
      return zzq(paramObject);
    }
    return zzp(paramObject);
  }
  
  public final int zzb(Object paramObject)
  {
    int m = zzc.length;
    int k = 0;
    for (int j = 0; k < m; j = i)
    {
      i = zzB(k);
      int n = zzc[k];
      long l = 0xFFFFF & i;
      int i1 = zzA(i);
      i = 37;
      Object localObject;
      switch (i1)
      {
      default: 
        i = j;
        break;
      case 68: 
        i = j;
        if (!zzR(paramObject, n, k)) {
          break label1277;
        }
        i = j * 53;
        j = zzmx.zzf(paramObject, l).hashCode();
        break;
      case 67: 
        i = j;
        if (!zzR(paramObject, n, k)) {
          break label1277;
        }
        i = j * 53;
        j = zzkm.zzc(zzC(paramObject, l));
        break;
      case 66: 
        i = j;
        if (!zzR(paramObject, n, k)) {
          break label1277;
        }
        i = j * 53;
        j = zzr(paramObject, l);
        break;
      case 65: 
        i = j;
        if (!zzR(paramObject, n, k)) {
          break label1277;
        }
        i = j * 53;
        j = zzkm.zzc(zzC(paramObject, l));
        break;
      case 64: 
        i = j;
        if (!zzR(paramObject, n, k)) {
          break label1277;
        }
        i = j * 53;
        j = zzr(paramObject, l);
        break;
      case 63: 
        i = j;
        if (!zzR(paramObject, n, k)) {
          break label1277;
        }
        i = j * 53;
        j = zzr(paramObject, l);
        break;
      case 62: 
        i = j;
        if (!zzR(paramObject, n, k)) {
          break label1277;
        }
        i = j * 53;
        j = zzr(paramObject, l);
        break;
      case 61: 
        i = j;
        if (!zzR(paramObject, n, k)) {
          break label1277;
        }
        i = j * 53;
        j = zzmx.zzf(paramObject, l).hashCode();
        break;
      case 60: 
        i = j;
        if (!zzR(paramObject, n, k)) {
          break label1277;
        }
        i = j * 53;
        j = zzmx.zzf(paramObject, l).hashCode();
        break;
      case 59: 
        i = j;
        if (!zzR(paramObject, n, k)) {
          break label1277;
        }
        i = j * 53;
        j = ((String)zzmx.zzf(paramObject, l)).hashCode();
        break;
      case 58: 
        i = j;
        if (!zzR(paramObject, n, k)) {
          break label1277;
        }
        i = j * 53;
        j = zzkm.zza(zzS(paramObject, l));
        break;
      case 57: 
        i = j;
        if (!zzR(paramObject, n, k)) {
          break label1277;
        }
        i = j * 53;
        j = zzr(paramObject, l);
        break;
      case 56: 
        i = j;
        if (!zzR(paramObject, n, k)) {
          break label1277;
        }
        i = j * 53;
        j = zzkm.zzc(zzC(paramObject, l));
        break;
      case 55: 
        i = j;
        if (!zzR(paramObject, n, k)) {
          break label1277;
        }
        i = j * 53;
        j = zzr(paramObject, l);
        break;
      case 54: 
        i = j;
        if (!zzR(paramObject, n, k)) {
          break label1277;
        }
        i = j * 53;
        j = zzkm.zzc(zzC(paramObject, l));
        break;
      case 53: 
        i = j;
        if (!zzR(paramObject, n, k)) {
          break label1277;
        }
        i = j * 53;
        j = zzkm.zzc(zzC(paramObject, l));
        break;
      case 52: 
        i = j;
        if (!zzR(paramObject, n, k)) {
          break label1277;
        }
        i = j * 53;
        j = Float.floatToIntBits(zzo(paramObject, l));
        break;
      case 51: 
        i = j;
        if (!zzR(paramObject, n, k)) {
          break label1277;
        }
        i = j * 53;
        j = zzkm.zzc(Double.doubleToLongBits(zzn(paramObject, l)));
        break;
      case 50: 
        i = j * 53;
        j = zzmx.zzf(paramObject, l).hashCode();
        break;
      case 18: 
      case 19: 
      case 20: 
      case 21: 
      case 22: 
      case 23: 
      case 24: 
      case 25: 
      case 26: 
      case 27: 
      case 28: 
      case 29: 
      case 30: 
      case 31: 
      case 32: 
      case 33: 
      case 34: 
      case 35: 
      case 36: 
      case 37: 
      case 38: 
      case 39: 
      case 40: 
      case 41: 
      case 42: 
      case 43: 
      case 44: 
      case 45: 
      case 46: 
      case 47: 
      case 48: 
      case 49: 
        i = j * 53;
        j = zzmx.zzf(paramObject, l).hashCode();
        break;
      case 17: 
        localObject = zzmx.zzf(paramObject, l);
        if (localObject != null) {
          i = localObject.hashCode();
        }
        break;
      case 16: 
        i = j * 53;
        j = zzkm.zzc(zzmx.zzd(paramObject, l));
        break;
      case 15: 
        i = j * 53;
        j = zzmx.zzc(paramObject, l);
        break;
      case 14: 
        i = j * 53;
        j = zzkm.zzc(zzmx.zzd(paramObject, l));
        break;
      case 13: 
        i = j * 53;
        j = zzmx.zzc(paramObject, l);
        break;
      case 12: 
        i = j * 53;
        j = zzmx.zzc(paramObject, l);
        break;
      case 11: 
        i = j * 53;
        j = zzmx.zzc(paramObject, l);
        break;
      case 10: 
        i = j * 53;
        j = zzmx.zzf(paramObject, l).hashCode();
        break;
      case 9: 
        localObject = zzmx.zzf(paramObject, l);
        if (localObject != null) {
          i = localObject.hashCode();
        }
        i = j * 53 + i;
        break;
      case 8: 
        i = j * 53;
        j = ((String)zzmx.zzf(paramObject, l)).hashCode();
        break;
      case 7: 
        i = j * 53;
        j = zzkm.zza(zzmx.zzw(paramObject, l));
        break;
      case 6: 
        i = j * 53;
        j = zzmx.zzc(paramObject, l);
        break;
      case 5: 
        i = j * 53;
        j = zzkm.zzc(zzmx.zzd(paramObject, l));
        break;
      case 4: 
        i = j * 53;
        j = zzmx.zzc(paramObject, l);
        break;
      case 3: 
        i = j * 53;
        j = zzkm.zzc(zzmx.zzd(paramObject, l));
        break;
      case 2: 
        i = j * 53;
        j = zzkm.zzc(zzmx.zzd(paramObject, l));
        break;
      case 1: 
        i = j * 53;
        j = Float.floatToIntBits(zzmx.zzb(paramObject, l));
        break;
      }
      i = j * 53;
      j = zzkm.zzc(Double.doubleToLongBits(zzmx.zza(paramObject, l)));
      i += j;
      label1277:
      k += 3;
    }
    int i = zzn.zzc(paramObject).hashCode();
    if (!zzh) {
      return j * 53 + i;
    }
    zzo.zza(paramObject);
    throw null;
  }
  
  final int zzc(Object paramObject, byte[] paramArrayOfByte, int paramInt1, int paramInt2, int paramInt3, zziq paramZziq)
    throws IOException
  {
    Object localObject2 = paramObject;
    Object localObject1 = paramArrayOfByte;
    int i1 = paramInt3;
    zziq localZziq = paramZziq;
    Unsafe localUnsafe = zzb;
    int j = 0;
    int i3 = j;
    int i = i3;
    int i2 = -1;
    int k = 1048575;
    Object localObject3;
    for (;;)
    {
      localObject3 = this;
      int i4 = paramInt2;
      if (paramInt1 >= i4) {
        break;
      }
      m = paramInt1 + 1;
      int n = localObject1[paramInt1];
      if (n < 0)
      {
        m = zzir.zzk(n, (byte[])localObject1, m, localZziq);
        n = zza;
      }
      j = n >>> 3;
      int i5 = n & 0x7;
      if (j > i2) {
        paramInt1 = ((zzlo)localObject3).zzx(j, i3 / 3);
      } else {
        paramInt1 = ((zzlo)localObject3).zzw(j);
      }
      if (paramInt1 == -1)
      {
        i3 = n;
        i2 = i;
        paramInt1 = i1;
        i1 = 0;
        n = m;
        m = k;
        i = i3;
        k = i2;
      }
      else
      {
        Object localObject4 = zzc;
        int i6 = localObject4[(paramInt1 + 1)];
        int i7 = zzA(i6);
        i1 = m;
        long l1 = i6 & 0xFFFFF;
        if (i7 <= 17)
        {
          i2 = localObject4[(paramInt1 + 2)];
          boolean bool = true;
          i3 = 1 << (i2 >>> 20);
          i2 &= 0xFFFFF;
          if (i2 != k)
          {
            if (k != 1048575) {
              localUnsafe.putInt(localObject2, k, i);
            }
            i = localUnsafe.getInt(localObject2, i2);
            k = i2;
            i2 = i;
          }
          else
          {
            i2 = i;
          }
          i = n;
          switch (i7)
          {
          default: 
            if (i5 == 3)
            {
              m = zzir.zzc(((zzlo)localObject3).zzE(paramInt1), paramArrayOfByte, i1, paramInt2, j << 3 | 0x4, paramZziq);
              if ((i2 & i3) != 0) {
                break label1156;
              }
              localUnsafe.putObject(localObject2, l1, zzc);
            }
            break;
          case 16: 
            if (i5 == 0)
            {
              m = zzir.zzm((byte[])localObject1, i1, localZziq);
              localUnsafe.putLong(paramObject, l1, zzjh.zzc(zzb));
              i1 = i2 | i3;
              n = j;
              j = i1;
            }
            break;
          case 15: 
            if (i5 == 0)
            {
              m = zzir.zzj((byte[])localObject1, i1, localZziq);
              localUnsafe.putInt(localObject2, l1, zzjh.zzb(zza));
            }
            break;
          case 12: 
            if (i5 == 0)
            {
              m = zzir.zzj((byte[])localObject1, i1, localZziq);
              n = zza;
              localObject3 = ((zzlo)localObject3).zzD(paramInt1);
              if ((localObject3 != null) && (!((zzki)localObject3).zza(n)))
              {
                zzd(paramObject).zzh(i, Long.valueOf(n));
                n = j;
                j = i2;
              }
              else
              {
                localUnsafe.putInt(localObject2, l1, n);
              }
            }
            break;
          case 10: 
            if (i5 == 2)
            {
              m = zzir.zza((byte[])localObject1, i1, localZziq);
              localUnsafe.putObject(localObject2, l1, zzc);
            }
          case 9: 
            for (;;)
            {
              i1 = i2 | i3;
              n = j;
              j = i1;
              i3 = paramInt1;
              paramInt1 = m;
              i1 = i;
              i = j;
              break label918;
              if (i5 != 2) {
                break;
              }
              m = zzir.zzd(((zzlo)localObject3).zzE(paramInt1), (byte[])localObject1, i1, i4, localZziq);
              if ((i2 & i3) == 0) {
                localUnsafe.putObject(localObject2, l1, zzc);
              } else {
                localUnsafe.putObject(localObject2, l1, zzkm.zzg(localUnsafe.getObject(localObject2, l1), zzc));
              }
            }
            i1 = m;
            break;
          case 8: 
            if (i5 == 2)
            {
              if ((0x20000000 & i6) == 0) {
                m = zzir.zzg((byte[])localObject1, i1, localZziq);
              } else {
                m = zzir.zzh((byte[])localObject1, i1, localZziq);
              }
              localUnsafe.putObject(localObject2, l1, zzc);
            }
            break;
          case 7: 
            if (i5 == 0)
            {
              m = zzir.zzm((byte[])localObject1, i1, localZziq);
              if (zzb == 0L) {
                bool = false;
              }
              zzmx.zzm(localObject2, l1, bool);
            }
            break;
          case 6: 
          case 13: 
            if (i5 == 5)
            {
              localUnsafe.putInt(localObject2, l1, zzir.zzb((byte[])localObject1, i1));
              m = i1 + 4;
              n = i2 | i3;
              i1 = i;
              i = n;
              i3 = paramInt1;
              n = j;
              paramInt1 = m;
              m = paramInt3;
              j = i1;
              i2 = n;
              i1 = m;
              continue;
            }
            i1 = m;
            break;
          case 5: 
          case 14: 
            if (i5 == 1)
            {
              long l2 = zzir.zzn((byte[])localObject1, i1);
              localUnsafe.putLong(paramObject, l1, l2);
            }
            break;
          case 4: 
          case 11: 
            if (i5 == 0)
            {
              m = zzir.zzj((byte[])localObject1, i1, localZziq);
              localUnsafe.putInt(localObject2, l1, zza);
            }
            break;
          case 2: 
          case 3: 
            if (i5 == 0)
            {
              m = zzir.zzm((byte[])localObject1, i1, localZziq);
              localUnsafe.putLong(paramObject, l1, zzb);
              n = i2 | i3;
              i2 = j;
              j = n;
            }
            break;
          case 1: 
            if (i5 == 5)
            {
              zzmx.zzp(localObject2, l1, Float.intBitsToFloat(zzir.zzb((byte[])localObject1, i1)));
              m = i1 + 4;
            }
            break;
          case 0: 
            label918:
            if (i5 == 1)
            {
              zzmx.zzo(localObject2, l1, Double.longBitsToDouble(zzir.zzn((byte[])localObject1, i1)));
              m += 8;
              n = i2 | i3;
            }
            for (;;)
            {
              i2 = j;
              j = n;
              i3 = paramInt1;
              paramInt1 = m;
              m = i;
              i = j;
              break label1354;
              i1 = m;
              break;
              label1156:
              localUnsafe.putObject(localObject2, l1, zzkm.zzg(localUnsafe.getObject(localObject2, l1), zzc));
              n = i2 | i3;
              localObject1 = paramArrayOfByte;
            }
            i3 = paramInt3;
            n = i1;
            i1 = paramInt1;
            m = k;
            paramInt1 = i3;
            k = i2;
            break;
          }
        }
        if (i7 == 27)
        {
          if (i5 == 2)
          {
            localObject4 = (zzkl)localUnsafe.getObject(localObject2, l1);
            localObject1 = localObject4;
            if (!((zzkl)localObject4).zzc())
            {
              m = ((List)localObject4).size();
              if (m == 0) {
                m = 10;
              } else {
                m += m;
              }
              localObject1 = ((zzkl)localObject4).zzd(m);
              localUnsafe.putObject(localObject2, l1, localObject1);
            }
            localObject3 = ((zzlo)localObject3).zzE(paramInt1);
            m = n;
            n = zzir.zze((zzlw)localObject3, m, paramArrayOfByte, i1, paramInt2, (zzkl)localObject1, paramZziq);
            localObject1 = paramArrayOfByte;
            i3 = paramInt1;
            i2 = j;
            paramInt1 = n;
            label1354:
            i1 = paramInt3;
            j = m;
            continue;
          }
        }
        else if (i7 <= 49)
        {
          i2 = zzv(paramObject, paramArrayOfByte, i1, paramInt2, n, j, i5, paramInt1, i6, i7, l1, paramZziq);
          m = i2;
          if (i2 != i1) {
            m = i2;
          }
        }
        for (;;)
        {
          localObject2 = paramObject;
          localObject1 = paramArrayOfByte;
          i2 = j;
          i1 = paramInt3;
          localZziq = paramZziq;
          j = n;
          i3 = paramInt1;
          paramInt1 = m;
          break;
          label1508:
          label1537:
          do
          {
            for (;;)
            {
              break label1508;
              i2 = i1;
              i1 = paramInt1;
              if (i7 != 50) {
                break label1537;
              }
              if (i5 == 2)
              {
                i1 = zzs(paramObject, paramArrayOfByte, i2, paramInt2, i1, l1, paramZziq);
                m = i1;
                if (i1 != i2)
                {
                  m = i1;
                  break;
                }
              }
            }
            i2 = i;
            i1 = paramInt1;
            paramInt1 = paramInt3;
            i = n;
            n = m;
            m = k;
            k = i2;
            break label1583;
            i1 = zzt(paramObject, paramArrayOfByte, i2, paramInt2, n, j, i5, i6, i7, l1, i1, paramZziq);
            m = i1;
          } while (i1 == i2);
          m = i1;
        }
      }
      label1583:
      i2 = j;
      if ((i == paramInt1) && (paramInt1 != 0))
      {
        paramArrayOfByte = this;
        paramZziq = paramObject;
        paramInt3 = n;
        j = i;
        i = k;
        k = m;
        m = paramInt1;
        paramObject = paramArrayOfByte;
        paramArrayOfByte = paramZziq;
        break label1762;
      }
      if (zzh)
      {
        localObject1 = zzd;
        if (localObject1 != zzjq.zza)
        {
          if (((zzjq)localObject1).zzb(zzg, i2) == null)
          {
            j = zzir.zzi(i, paramArrayOfByte, n, paramInt2, zzd(paramObject), paramZziq);
            break label1714;
          }
          paramObject = (zzkb)paramObject;
          throw null;
        }
      }
      j = zzir.zzi(i, paramArrayOfByte, n, paramInt2, zzd(paramObject), paramZziq);
      label1714:
      localZziq = paramZziq;
      localObject2 = paramObject;
      i3 = i1;
      localObject1 = paramArrayOfByte;
      i1 = paramInt1;
      paramInt1 = j;
      j = i;
      i = k;
      k = m;
    }
    int m = i1;
    paramArrayOfByte = localObject2;
    paramObject = localObject3;
    paramInt3 = paramInt1;
    label1762:
    if (k != 1048575) {
      localUnsafe.putInt(paramArrayOfByte, k, i);
    }
    paramInt1 = zzk;
    while (paramInt1 < zzl)
    {
      i = zzj[paramInt1];
      k = zzc[i];
      paramZziq = zzmx.zzf(paramArrayOfByte, paramObject.zzB(i) & 0xFFFFF);
      if ((paramZziq == null) || (paramObject.zzD(i) == null))
      {
        paramInt1 += 1;
      }
      else
      {
        paramArrayOfByte = (zzlf)paramZziq;
        paramObject = (zzle)paramObject.zzF(i);
        throw null;
      }
    }
    if (m == 0)
    {
      if (paramInt3 == paramInt2) {
        return paramInt3;
      }
      throw zzko.zze();
    }
    if ((paramInt3 <= paramInt2) && (j == m)) {
      return paramInt3;
    }
    throw zzko.zze();
  }
  
  public final Object zze()
  {
    return ((zzke)zzg).zzl(4, null, null);
  }
  
  public final void zzf(Object paramObject)
  {
    int i = zzk;
    int j;
    for (;;)
    {
      j = zzl;
      if (i >= j) {
        break;
      }
      long l = zzB(zzj[i]) & 0xFFFFF;
      Object localObject = zzmx.zzf(paramObject, l);
      if (localObject != null)
      {
        ((zzlf)localObject).zzc();
        zzmx.zzs(paramObject, l, localObject);
      }
      i += 1;
    }
    int k = zzj.length;
    i = j;
    while (i < k)
    {
      zzm.zza(paramObject, zzj[i]);
      i += 1;
    }
    zzn.zzg(paramObject);
    if (zzh) {
      zzo.zzb(paramObject);
    }
  }
  
  public final void zzg(Object paramObject1, Object paramObject2)
  {
    Objects.requireNonNull(paramObject2);
    int i = 0;
    while (i < zzc.length)
    {
      int j = zzB(i);
      long l = 0xFFFFF & j;
      int k = zzc[i];
      switch (zzA(j))
      {
      default: 
        break;
      case 68: 
        zzI(paramObject1, paramObject2, i);
        break;
      case 61: 
      case 62: 
      case 63: 
      case 64: 
      case 65: 
      case 66: 
      case 67: 
        if (zzR(paramObject2, k, i))
        {
          zzmx.zzs(paramObject1, l, zzmx.zzf(paramObject2, l));
          zzK(paramObject1, k, i);
        }
        break;
      case 60: 
        zzI(paramObject1, paramObject2, i);
        break;
      case 51: 
      case 52: 
      case 53: 
      case 54: 
      case 55: 
      case 56: 
      case 57: 
      case 58: 
      case 59: 
        if (zzR(paramObject2, k, i))
        {
          zzmx.zzs(paramObject1, l, zzmx.zzf(paramObject2, l));
          zzK(paramObject1, k, i);
        }
        break;
      case 50: 
        zzly.zzaa(zzq, paramObject1, paramObject2, l);
        break;
      case 18: 
      case 19: 
      case 20: 
      case 21: 
      case 22: 
      case 23: 
      case 24: 
      case 25: 
      case 26: 
      case 27: 
      case 28: 
      case 29: 
      case 30: 
      case 31: 
      case 32: 
      case 33: 
      case 34: 
      case 35: 
      case 36: 
      case 37: 
      case 38: 
      case 39: 
      case 40: 
      case 41: 
      case 42: 
      case 43: 
      case 44: 
      case 45: 
      case 46: 
      case 47: 
      case 48: 
      case 49: 
        zzm.zzb(paramObject1, paramObject2, l);
        break;
      case 17: 
        zzH(paramObject1, paramObject2, i);
        break;
      case 16: 
        if (zzO(paramObject2, i))
        {
          zzmx.zzr(paramObject1, l, zzmx.zzd(paramObject2, l));
          zzJ(paramObject1, i);
        }
        break;
      case 15: 
        if (zzO(paramObject2, i))
        {
          zzmx.zzq(paramObject1, l, zzmx.zzc(paramObject2, l));
          zzJ(paramObject1, i);
        }
        break;
      case 14: 
        if (zzO(paramObject2, i))
        {
          zzmx.zzr(paramObject1, l, zzmx.zzd(paramObject2, l));
          zzJ(paramObject1, i);
        }
        break;
      case 13: 
        if (zzO(paramObject2, i))
        {
          zzmx.zzq(paramObject1, l, zzmx.zzc(paramObject2, l));
          zzJ(paramObject1, i);
        }
        break;
      case 12: 
        if (zzO(paramObject2, i))
        {
          zzmx.zzq(paramObject1, l, zzmx.zzc(paramObject2, l));
          zzJ(paramObject1, i);
        }
        break;
      case 11: 
        if (zzO(paramObject2, i))
        {
          zzmx.zzq(paramObject1, l, zzmx.zzc(paramObject2, l));
          zzJ(paramObject1, i);
        }
        break;
      case 10: 
        if (zzO(paramObject2, i))
        {
          zzmx.zzs(paramObject1, l, zzmx.zzf(paramObject2, l));
          zzJ(paramObject1, i);
        }
        break;
      case 9: 
        zzH(paramObject1, paramObject2, i);
        break;
      case 8: 
        if (zzO(paramObject2, i))
        {
          zzmx.zzs(paramObject1, l, zzmx.zzf(paramObject2, l));
          zzJ(paramObject1, i);
        }
        break;
      case 7: 
        if (zzO(paramObject2, i))
        {
          zzmx.zzm(paramObject1, l, zzmx.zzw(paramObject2, l));
          zzJ(paramObject1, i);
        }
        break;
      case 6: 
        if (zzO(paramObject2, i))
        {
          zzmx.zzq(paramObject1, l, zzmx.zzc(paramObject2, l));
          zzJ(paramObject1, i);
        }
        break;
      case 5: 
        if (zzO(paramObject2, i))
        {
          zzmx.zzr(paramObject1, l, zzmx.zzd(paramObject2, l));
          zzJ(paramObject1, i);
        }
        break;
      case 4: 
        if (zzO(paramObject2, i))
        {
          zzmx.zzq(paramObject1, l, zzmx.zzc(paramObject2, l));
          zzJ(paramObject1, i);
        }
        break;
      case 3: 
        if (zzO(paramObject2, i))
        {
          zzmx.zzr(paramObject1, l, zzmx.zzd(paramObject2, l));
          zzJ(paramObject1, i);
        }
        break;
      case 2: 
        if (zzO(paramObject2, i))
        {
          zzmx.zzr(paramObject1, l, zzmx.zzd(paramObject2, l));
          zzJ(paramObject1, i);
        }
        break;
      case 1: 
        if (zzO(paramObject2, i))
        {
          zzmx.zzp(paramObject1, l, zzmx.zzb(paramObject2, l));
          zzJ(paramObject1, i);
        }
        break;
      case 0: 
        if (zzO(paramObject2, i))
        {
          zzmx.zzo(paramObject1, l, zzmx.zza(paramObject2, l));
          zzJ(paramObject1, i);
        }
        break;
      }
      i += 3;
    }
    zzly.zzF(zzn, paramObject1, paramObject2);
    if (zzh) {
      zzly.zzE(zzo, paramObject1, paramObject2);
    }
  }
  
  public final void zzh(Object paramObject, byte[] paramArrayOfByte, int paramInt1, int paramInt2, zziq paramZziq)
    throws IOException
  {
    if (zzi)
    {
      zzu(paramObject, paramArrayOfByte, paramInt1, paramInt2, paramZziq);
      return;
    }
    zzc(paramObject, paramArrayOfByte, paramInt1, paramInt2, 0, paramZziq);
  }
  
  public final void zzi(Object paramObject, zznf paramZznf)
    throws IOException
  {
    if (zzi)
    {
      if (!zzh)
      {
        int j = zzc.length;
        int i = 0;
        while (i < j)
        {
          int k = zzB(i);
          int m = zzc[i];
          switch (zzA(k))
          {
          default: 
            break;
          case 68: 
            if (zzR(paramObject, m, i)) {
              paramZznf.zzq(m, zzmx.zzf(paramObject, k & 0xFFFFF), zzE(i));
            }
            break;
          case 67: 
            if (zzR(paramObject, m, i)) {
              paramZznf.zzC(m, zzC(paramObject, k & 0xFFFFF));
            }
            break;
          case 66: 
            if (zzR(paramObject, m, i)) {
              paramZznf.zzA(m, zzr(paramObject, k & 0xFFFFF));
            }
            break;
          case 65: 
            if (zzR(paramObject, m, i)) {
              paramZznf.zzy(m, zzC(paramObject, k & 0xFFFFF));
            }
            break;
          case 64: 
            if (zzR(paramObject, m, i)) {
              paramZznf.zzw(m, zzr(paramObject, k & 0xFFFFF));
            }
            break;
          case 63: 
            if (zzR(paramObject, m, i)) {
              paramZznf.zzi(m, zzr(paramObject, k & 0xFFFFF));
            }
            break;
          case 62: 
            if (zzR(paramObject, m, i)) {
              paramZznf.zzH(m, zzr(paramObject, k & 0xFFFFF));
            }
            break;
          case 61: 
            if (zzR(paramObject, m, i)) {
              paramZznf.zzd(m, (zzjd)zzmx.zzf(paramObject, k & 0xFFFFF));
            }
            break;
          case 60: 
            if (zzR(paramObject, m, i)) {
              paramZznf.zzv(m, zzmx.zzf(paramObject, k & 0xFFFFF), zzE(i));
            }
            break;
          case 59: 
            if (zzR(paramObject, m, i)) {
              zzT(m, zzmx.zzf(paramObject, k & 0xFFFFF), paramZznf);
            }
            break;
          case 58: 
            if (zzR(paramObject, m, i)) {
              paramZznf.zzb(m, zzS(paramObject, k & 0xFFFFF));
            }
            break;
          case 57: 
            if (zzR(paramObject, m, i)) {
              paramZznf.zzk(m, zzr(paramObject, k & 0xFFFFF));
            }
            break;
          case 56: 
            if (zzR(paramObject, m, i)) {
              paramZznf.zzm(m, zzC(paramObject, k & 0xFFFFF));
            }
            break;
          case 55: 
            if (zzR(paramObject, m, i)) {
              paramZznf.zzr(m, zzr(paramObject, k & 0xFFFFF));
            }
            break;
          case 54: 
            if (zzR(paramObject, m, i)) {
              paramZznf.zzJ(m, zzC(paramObject, k & 0xFFFFF));
            }
            break;
          case 53: 
            if (zzR(paramObject, m, i)) {
              paramZznf.zzt(m, zzC(paramObject, k & 0xFFFFF));
            }
            break;
          case 52: 
            if (zzR(paramObject, m, i)) {
              paramZznf.zzo(m, zzo(paramObject, k & 0xFFFFF));
            }
            break;
          case 51: 
            if (zzR(paramObject, m, i)) {
              paramZznf.zzf(m, zzn(paramObject, k & 0xFFFFF));
            }
            break;
          case 50: 
            zzM(paramZznf, m, zzmx.zzf(paramObject, k & 0xFFFFF), i);
            break;
          case 49: 
            zzly.zzO(m, (List)zzmx.zzf(paramObject, k & 0xFFFFF), paramZznf, zzE(i));
            break;
          case 48: 
            zzly.zzV(m, (List)zzmx.zzf(paramObject, k & 0xFFFFF), paramZznf, true);
            break;
          case 47: 
            zzly.zzU(m, (List)zzmx.zzf(paramObject, k & 0xFFFFF), paramZznf, true);
            break;
          case 46: 
            zzly.zzT(m, (List)zzmx.zzf(paramObject, k & 0xFFFFF), paramZznf, true);
            break;
          case 45: 
            zzly.zzS(m, (List)zzmx.zzf(paramObject, k & 0xFFFFF), paramZznf, true);
            break;
          case 44: 
            zzly.zzK(m, (List)zzmx.zzf(paramObject, k & 0xFFFFF), paramZznf, true);
            break;
          case 43: 
            zzly.zzX(m, (List)zzmx.zzf(paramObject, k & 0xFFFFF), paramZznf, true);
            break;
          case 42: 
            zzly.zzH(m, (List)zzmx.zzf(paramObject, k & 0xFFFFF), paramZznf, true);
            break;
          case 41: 
            zzly.zzL(m, (List)zzmx.zzf(paramObject, k & 0xFFFFF), paramZznf, true);
            break;
          case 40: 
            zzly.zzM(m, (List)zzmx.zzf(paramObject, k & 0xFFFFF), paramZznf, true);
            break;
          case 39: 
            zzly.zzP(m, (List)zzmx.zzf(paramObject, k & 0xFFFFF), paramZznf, true);
            break;
          case 38: 
            zzly.zzY(m, (List)zzmx.zzf(paramObject, k & 0xFFFFF), paramZznf, true);
            break;
          case 37: 
            zzly.zzQ(m, (List)zzmx.zzf(paramObject, k & 0xFFFFF), paramZznf, true);
            break;
          case 36: 
            zzly.zzN(m, (List)zzmx.zzf(paramObject, k & 0xFFFFF), paramZznf, true);
            break;
          case 35: 
            zzly.zzJ(m, (List)zzmx.zzf(paramObject, k & 0xFFFFF), paramZznf, true);
            break;
          case 34: 
            zzly.zzV(m, (List)zzmx.zzf(paramObject, k & 0xFFFFF), paramZznf, false);
            break;
          case 33: 
            zzly.zzU(m, (List)zzmx.zzf(paramObject, k & 0xFFFFF), paramZznf, false);
            break;
          case 32: 
            zzly.zzT(m, (List)zzmx.zzf(paramObject, k & 0xFFFFF), paramZznf, false);
            break;
          case 31: 
            zzly.zzS(m, (List)zzmx.zzf(paramObject, k & 0xFFFFF), paramZznf, false);
            break;
          case 30: 
            zzly.zzK(m, (List)zzmx.zzf(paramObject, k & 0xFFFFF), paramZznf, false);
            break;
          case 29: 
            zzly.zzX(m, (List)zzmx.zzf(paramObject, k & 0xFFFFF), paramZznf, false);
            break;
          case 28: 
            zzly.zzI(m, (List)zzmx.zzf(paramObject, k & 0xFFFFF), paramZznf);
            break;
          case 27: 
            zzly.zzR(m, (List)zzmx.zzf(paramObject, k & 0xFFFFF), paramZznf, zzE(i));
            break;
          case 26: 
            zzly.zzW(m, (List)zzmx.zzf(paramObject, k & 0xFFFFF), paramZznf);
            break;
          case 25: 
            zzly.zzH(m, (List)zzmx.zzf(paramObject, k & 0xFFFFF), paramZznf, false);
            break;
          case 24: 
            zzly.zzL(m, (List)zzmx.zzf(paramObject, k & 0xFFFFF), paramZznf, false);
            break;
          case 23: 
            zzly.zzM(m, (List)zzmx.zzf(paramObject, k & 0xFFFFF), paramZznf, false);
            break;
          case 22: 
            zzly.zzP(m, (List)zzmx.zzf(paramObject, k & 0xFFFFF), paramZznf, false);
            break;
          case 21: 
            zzly.zzY(m, (List)zzmx.zzf(paramObject, k & 0xFFFFF), paramZznf, false);
            break;
          case 20: 
            zzly.zzQ(m, (List)zzmx.zzf(paramObject, k & 0xFFFFF), paramZznf, false);
            break;
          case 19: 
            zzly.zzN(m, (List)zzmx.zzf(paramObject, k & 0xFFFFF), paramZznf, false);
            break;
          case 18: 
            zzly.zzJ(m, (List)zzmx.zzf(paramObject, k & 0xFFFFF), paramZznf, false);
            break;
          case 17: 
            if (zzO(paramObject, i)) {
              paramZznf.zzq(m, zzmx.zzf(paramObject, k & 0xFFFFF), zzE(i));
            }
            break;
          case 16: 
            if (zzO(paramObject, i)) {
              paramZznf.zzC(m, zzmx.zzd(paramObject, k & 0xFFFFF));
            }
            break;
          case 15: 
            if (zzO(paramObject, i)) {
              paramZznf.zzA(m, zzmx.zzc(paramObject, k & 0xFFFFF));
            }
            break;
          case 14: 
            if (zzO(paramObject, i)) {
              paramZznf.zzy(m, zzmx.zzd(paramObject, k & 0xFFFFF));
            }
            break;
          case 13: 
            if (zzO(paramObject, i)) {
              paramZznf.zzw(m, zzmx.zzc(paramObject, k & 0xFFFFF));
            }
            break;
          case 12: 
            if (zzO(paramObject, i)) {
              paramZznf.zzi(m, zzmx.zzc(paramObject, k & 0xFFFFF));
            }
            break;
          case 11: 
            if (zzO(paramObject, i)) {
              paramZznf.zzH(m, zzmx.zzc(paramObject, k & 0xFFFFF));
            }
            break;
          case 10: 
            if (zzO(paramObject, i)) {
              paramZznf.zzd(m, (zzjd)zzmx.zzf(paramObject, k & 0xFFFFF));
            }
            break;
          case 9: 
            if (zzO(paramObject, i)) {
              paramZznf.zzv(m, zzmx.zzf(paramObject, k & 0xFFFFF), zzE(i));
            }
            break;
          case 8: 
            if (zzO(paramObject, i)) {
              zzT(m, zzmx.zzf(paramObject, k & 0xFFFFF), paramZznf);
            }
            break;
          case 7: 
            if (zzO(paramObject, i)) {
              paramZznf.zzb(m, zzmx.zzw(paramObject, k & 0xFFFFF));
            }
            break;
          case 6: 
            if (zzO(paramObject, i)) {
              paramZznf.zzk(m, zzmx.zzc(paramObject, k & 0xFFFFF));
            }
            break;
          case 5: 
            if (zzO(paramObject, i)) {
              paramZznf.zzm(m, zzmx.zzd(paramObject, k & 0xFFFFF));
            }
            break;
          case 4: 
            if (zzO(paramObject, i)) {
              paramZznf.zzr(m, zzmx.zzc(paramObject, k & 0xFFFFF));
            }
            break;
          case 3: 
            if (zzO(paramObject, i)) {
              paramZznf.zzJ(m, zzmx.zzd(paramObject, k & 0xFFFFF));
            }
            break;
          case 2: 
            if (zzO(paramObject, i)) {
              paramZznf.zzt(m, zzmx.zzd(paramObject, k & 0xFFFFF));
            }
            break;
          case 1: 
            if (zzO(paramObject, i)) {
              paramZznf.zzo(m, zzmx.zzb(paramObject, k & 0xFFFFF));
            }
            break;
          case 0: 
            if (zzO(paramObject, i)) {
              paramZznf.zzf(m, zzmx.zza(paramObject, k & 0xFFFFF));
            }
            break;
          }
          i += 3;
        }
        zzmn localZzmn = zzn;
        localZzmn.zzi(localZzmn.zzc(paramObject), paramZznf);
        return;
      }
      zzo.zza(paramObject);
      throw null;
    }
    zzL(paramObject, paramZznf);
  }
  
  /* Error */
  public final boolean zzj(Object paramObject1, Object paramObject2)
  {
    // Byte code:
    //   0: aload_0
    //   1: getfield 53	com/google/android/gms/internal/measurement/zzlo:zzc	[I
    //   4: arraylength
    //   5: istore 4
    //   7: iconst_0
    //   8: istore_3
    //   9: iload_3
    //   10: iload 4
    //   12: if_icmpge +948 -> 960
    //   15: aload_0
    //   16: iload_3
    //   17: invokespecial 173	com/google/android/gms/internal/measurement/zzlo:zzB	(I)I
    //   20: istore 5
    //   22: iload 5
    //   24: ldc -82
    //   26: iand
    //   27: i2l
    //   28: lstore 6
    //   30: iload 5
    //   32: invokestatic 217	com/google/android/gms/internal/measurement/zzlo:zzA	(I)I
    //   35: tableswitch	default:+289->324, 0:+881->916, 1:+847->882, 2:+818->853, 3:+789->824, 4:+761->796, 5:+732->767, 6:+704->739, 7:+676->711, 8:+645->680, 9:+614->649, 10:+583->618, 11:+555->590, 12:+527->562, 13:+499->534, 14:+470->505, 15:+442->477, 16:+413->448, 17:+382->417, 18:+358->393, 19:+358->393, 20:+358->393, 21:+358->393, 22:+358->393, 23:+358->393, 24:+358->393, 25:+358->393, 26:+358->393, 27:+358->393, 28:+358->393, 29:+358->393, 30:+358->393, 31:+358->393, 32:+358->393, 33:+358->393, 34:+358->393, 35:+358->393, 36:+358->393, 37:+358->393, 38:+358->393, 39:+358->393, 40:+358->393, 41:+358->393, 42:+358->393, 43:+358->393, 44:+358->393, 45:+358->393, 46:+358->393, 47:+358->393, 48:+358->393, 49:+358->393, 50:+338->373, 51:+292->327, 52:+292->327, 53:+292->327, 54:+292->327, 55:+292->327, 56:+292->327, 57:+292->327, 58:+292->327, 59:+292->327, 60:+292->327, 61:+292->327, 62:+292->327, 63:+292->327, 64:+292->327, 65:+292->327, 66:+292->327, 67:+292->327, 68:+292->327
    //   324: goto +629 -> 953
    //   327: aload_0
    //   328: iload_3
    //   329: invokespecial 203	com/google/android/gms/internal/measurement/zzlo:zzy	(I)I
    //   332: ldc -82
    //   334: iand
    //   335: i2l
    //   336: lstore 8
    //   338: aload_1
    //   339: lload 8
    //   341: invokestatic 208	com/google/android/gms/internal/measurement/zzmx:zzc	(Ljava/lang/Object;J)I
    //   344: aload_2
    //   345: lload 8
    //   347: invokestatic 208	com/google/android/gms/internal/measurement/zzmx:zzc	(Ljava/lang/Object;J)I
    //   350: if_icmpne +601 -> 951
    //   353: aload_1
    //   354: lload 6
    //   356: invokestatic 94	com/google/android/gms/internal/measurement/zzmx:zzf	(Ljava/lang/Object;J)Ljava/lang/Object;
    //   359: aload_2
    //   360: lload 6
    //   362: invokestatic 94	com/google/android/gms/internal/measurement/zzmx:zzf	(Ljava/lang/Object;J)Ljava/lang/Object;
    //   365: invokestatic 868	com/google/android/gms/internal/measurement/zzly:zzZ	(Ljava/lang/Object;Ljava/lang/Object;)Z
    //   368: ifne +585 -> 953
    //   371: iconst_0
    //   372: ireturn
    //   373: aload_1
    //   374: lload 6
    //   376: invokestatic 94	com/google/android/gms/internal/measurement/zzmx:zzf	(Ljava/lang/Object;J)Ljava/lang/Object;
    //   379: aload_2
    //   380: lload 6
    //   382: invokestatic 94	com/google/android/gms/internal/measurement/zzmx:zzf	(Ljava/lang/Object;J)Ljava/lang/Object;
    //   385: invokestatic 868	com/google/android/gms/internal/measurement/zzly:zzZ	(Ljava/lang/Object;Ljava/lang/Object;)Z
    //   388: istore 10
    //   390: goto +20 -> 410
    //   393: aload_1
    //   394: lload 6
    //   396: invokestatic 94	com/google/android/gms/internal/measurement/zzmx:zzf	(Ljava/lang/Object;J)Ljava/lang/Object;
    //   399: aload_2
    //   400: lload 6
    //   402: invokestatic 94	com/google/android/gms/internal/measurement/zzmx:zzf	(Ljava/lang/Object;J)Ljava/lang/Object;
    //   405: invokestatic 868	com/google/android/gms/internal/measurement/zzly:zzZ	(Ljava/lang/Object;Ljava/lang/Object;)Z
    //   408: istore 10
    //   410: iload 10
    //   412: ifne +541 -> 953
    //   415: iconst_0
    //   416: ireturn
    //   417: aload_0
    //   418: aload_1
    //   419: aload_2
    //   420: iload_3
    //   421: invokespecial 870	com/google/android/gms/internal/measurement/zzlo:zzN	(Ljava/lang/Object;Ljava/lang/Object;I)Z
    //   424: ifeq +527 -> 951
    //   427: aload_1
    //   428: lload 6
    //   430: invokestatic 94	com/google/android/gms/internal/measurement/zzmx:zzf	(Ljava/lang/Object;J)Ljava/lang/Object;
    //   433: aload_2
    //   434: lload 6
    //   436: invokestatic 94	com/google/android/gms/internal/measurement/zzmx:zzf	(Ljava/lang/Object;J)Ljava/lang/Object;
    //   439: invokestatic 868	com/google/android/gms/internal/measurement/zzly:zzZ	(Ljava/lang/Object;Ljava/lang/Object;)Z
    //   442: ifeq +509 -> 951
    //   445: goto +508 -> 953
    //   448: aload_0
    //   449: aload_1
    //   450: aload_2
    //   451: iload_3
    //   452: invokespecial 870	com/google/android/gms/internal/measurement/zzlo:zzN	(Ljava/lang/Object;Ljava/lang/Object;I)Z
    //   455: ifeq +496 -> 951
    //   458: aload_1
    //   459: lload 6
    //   461: invokestatic 379	com/google/android/gms/internal/measurement/zzmx:zzd	(Ljava/lang/Object;J)J
    //   464: aload_2
    //   465: lload 6
    //   467: invokestatic 379	com/google/android/gms/internal/measurement/zzmx:zzd	(Ljava/lang/Object;J)J
    //   470: lcmp
    //   471: ifne +480 -> 951
    //   474: goto +479 -> 953
    //   477: aload_0
    //   478: aload_1
    //   479: aload_2
    //   480: iload_3
    //   481: invokespecial 870	com/google/android/gms/internal/measurement/zzlo:zzN	(Ljava/lang/Object;Ljava/lang/Object;I)Z
    //   484: ifeq +467 -> 951
    //   487: aload_1
    //   488: lload 6
    //   490: invokestatic 208	com/google/android/gms/internal/measurement/zzmx:zzc	(Ljava/lang/Object;J)I
    //   493: aload_2
    //   494: lload 6
    //   496: invokestatic 208	com/google/android/gms/internal/measurement/zzmx:zzc	(Ljava/lang/Object;J)I
    //   499: if_icmpne +452 -> 951
    //   502: goto +451 -> 953
    //   505: aload_0
    //   506: aload_1
    //   507: aload_2
    //   508: iload_3
    //   509: invokespecial 870	com/google/android/gms/internal/measurement/zzlo:zzN	(Ljava/lang/Object;Ljava/lang/Object;I)Z
    //   512: ifeq +439 -> 951
    //   515: aload_1
    //   516: lload 6
    //   518: invokestatic 379	com/google/android/gms/internal/measurement/zzmx:zzd	(Ljava/lang/Object;J)J
    //   521: aload_2
    //   522: lload 6
    //   524: invokestatic 379	com/google/android/gms/internal/measurement/zzmx:zzd	(Ljava/lang/Object;J)J
    //   527: lcmp
    //   528: ifne +423 -> 951
    //   531: goto +422 -> 953
    //   534: aload_0
    //   535: aload_1
    //   536: aload_2
    //   537: iload_3
    //   538: invokespecial 870	com/google/android/gms/internal/measurement/zzlo:zzN	(Ljava/lang/Object;Ljava/lang/Object;I)Z
    //   541: ifeq +410 -> 951
    //   544: aload_1
    //   545: lload 6
    //   547: invokestatic 208	com/google/android/gms/internal/measurement/zzmx:zzc	(Ljava/lang/Object;J)I
    //   550: aload_2
    //   551: lload 6
    //   553: invokestatic 208	com/google/android/gms/internal/measurement/zzmx:zzc	(Ljava/lang/Object;J)I
    //   556: if_icmpne +395 -> 951
    //   559: goto +394 -> 953
    //   562: aload_0
    //   563: aload_1
    //   564: aload_2
    //   565: iload_3
    //   566: invokespecial 870	com/google/android/gms/internal/measurement/zzlo:zzN	(Ljava/lang/Object;Ljava/lang/Object;I)Z
    //   569: ifeq +382 -> 951
    //   572: aload_1
    //   573: lload 6
    //   575: invokestatic 208	com/google/android/gms/internal/measurement/zzmx:zzc	(Ljava/lang/Object;J)I
    //   578: aload_2
    //   579: lload 6
    //   581: invokestatic 208	com/google/android/gms/internal/measurement/zzmx:zzc	(Ljava/lang/Object;J)I
    //   584: if_icmpne +367 -> 951
    //   587: goto +366 -> 953
    //   590: aload_0
    //   591: aload_1
    //   592: aload_2
    //   593: iload_3
    //   594: invokespecial 870	com/google/android/gms/internal/measurement/zzlo:zzN	(Ljava/lang/Object;Ljava/lang/Object;I)Z
    //   597: ifeq +354 -> 951
    //   600: aload_1
    //   601: lload 6
    //   603: invokestatic 208	com/google/android/gms/internal/measurement/zzmx:zzc	(Ljava/lang/Object;J)I
    //   606: aload_2
    //   607: lload 6
    //   609: invokestatic 208	com/google/android/gms/internal/measurement/zzmx:zzc	(Ljava/lang/Object;J)I
    //   612: if_icmpne +339 -> 951
    //   615: goto +338 -> 953
    //   618: aload_0
    //   619: aload_1
    //   620: aload_2
    //   621: iload_3
    //   622: invokespecial 870	com/google/android/gms/internal/measurement/zzlo:zzN	(Ljava/lang/Object;Ljava/lang/Object;I)Z
    //   625: ifeq +326 -> 951
    //   628: aload_1
    //   629: lload 6
    //   631: invokestatic 94	com/google/android/gms/internal/measurement/zzmx:zzf	(Ljava/lang/Object;J)Ljava/lang/Object;
    //   634: aload_2
    //   635: lload 6
    //   637: invokestatic 94	com/google/android/gms/internal/measurement/zzmx:zzf	(Ljava/lang/Object;J)Ljava/lang/Object;
    //   640: invokestatic 868	com/google/android/gms/internal/measurement/zzly:zzZ	(Ljava/lang/Object;Ljava/lang/Object;)Z
    //   643: ifeq +308 -> 951
    //   646: goto +307 -> 953
    //   649: aload_0
    //   650: aload_1
    //   651: aload_2
    //   652: iload_3
    //   653: invokespecial 870	com/google/android/gms/internal/measurement/zzlo:zzN	(Ljava/lang/Object;Ljava/lang/Object;I)Z
    //   656: ifeq +295 -> 951
    //   659: aload_1
    //   660: lload 6
    //   662: invokestatic 94	com/google/android/gms/internal/measurement/zzmx:zzf	(Ljava/lang/Object;J)Ljava/lang/Object;
    //   665: aload_2
    //   666: lload 6
    //   668: invokestatic 94	com/google/android/gms/internal/measurement/zzmx:zzf	(Ljava/lang/Object;J)Ljava/lang/Object;
    //   671: invokestatic 868	com/google/android/gms/internal/measurement/zzly:zzZ	(Ljava/lang/Object;Ljava/lang/Object;)Z
    //   674: ifeq +277 -> 951
    //   677: goto +276 -> 953
    //   680: aload_0
    //   681: aload_1
    //   682: aload_2
    //   683: iload_3
    //   684: invokespecial 870	com/google/android/gms/internal/measurement/zzlo:zzN	(Ljava/lang/Object;Ljava/lang/Object;I)Z
    //   687: ifeq +264 -> 951
    //   690: aload_1
    //   691: lload 6
    //   693: invokestatic 94	com/google/android/gms/internal/measurement/zzmx:zzf	(Ljava/lang/Object;J)Ljava/lang/Object;
    //   696: aload_2
    //   697: lload 6
    //   699: invokestatic 94	com/google/android/gms/internal/measurement/zzmx:zzf	(Ljava/lang/Object;J)Ljava/lang/Object;
    //   702: invokestatic 868	com/google/android/gms/internal/measurement/zzly:zzZ	(Ljava/lang/Object;Ljava/lang/Object;)Z
    //   705: ifeq +246 -> 951
    //   708: goto +245 -> 953
    //   711: aload_0
    //   712: aload_1
    //   713: aload_2
    //   714: iload_3
    //   715: invokespecial 870	com/google/android/gms/internal/measurement/zzlo:zzN	(Ljava/lang/Object;Ljava/lang/Object;I)Z
    //   718: ifeq +233 -> 951
    //   721: aload_1
    //   722: lload 6
    //   724: invokestatic 354	com/google/android/gms/internal/measurement/zzmx:zzw	(Ljava/lang/Object;J)Z
    //   727: aload_2
    //   728: lload 6
    //   730: invokestatic 354	com/google/android/gms/internal/measurement/zzmx:zzw	(Ljava/lang/Object;J)Z
    //   733: if_icmpne +218 -> 951
    //   736: goto +217 -> 953
    //   739: aload_0
    //   740: aload_1
    //   741: aload_2
    //   742: iload_3
    //   743: invokespecial 870	com/google/android/gms/internal/measurement/zzlo:zzN	(Ljava/lang/Object;Ljava/lang/Object;I)Z
    //   746: ifeq +205 -> 951
    //   749: aload_1
    //   750: lload 6
    //   752: invokestatic 208	com/google/android/gms/internal/measurement/zzmx:zzc	(Ljava/lang/Object;J)I
    //   755: aload_2
    //   756: lload 6
    //   758: invokestatic 208	com/google/android/gms/internal/measurement/zzmx:zzc	(Ljava/lang/Object;J)I
    //   761: if_icmpne +190 -> 951
    //   764: goto +189 -> 953
    //   767: aload_0
    //   768: aload_1
    //   769: aload_2
    //   770: iload_3
    //   771: invokespecial 870	com/google/android/gms/internal/measurement/zzlo:zzN	(Ljava/lang/Object;Ljava/lang/Object;I)Z
    //   774: ifeq +177 -> 951
    //   777: aload_1
    //   778: lload 6
    //   780: invokestatic 379	com/google/android/gms/internal/measurement/zzmx:zzd	(Ljava/lang/Object;J)J
    //   783: aload_2
    //   784: lload 6
    //   786: invokestatic 379	com/google/android/gms/internal/measurement/zzmx:zzd	(Ljava/lang/Object;J)J
    //   789: lcmp
    //   790: ifne +161 -> 951
    //   793: goto +160 -> 953
    //   796: aload_0
    //   797: aload_1
    //   798: aload_2
    //   799: iload_3
    //   800: invokespecial 870	com/google/android/gms/internal/measurement/zzlo:zzN	(Ljava/lang/Object;Ljava/lang/Object;I)Z
    //   803: ifeq +148 -> 951
    //   806: aload_1
    //   807: lload 6
    //   809: invokestatic 208	com/google/android/gms/internal/measurement/zzmx:zzc	(Ljava/lang/Object;J)I
    //   812: aload_2
    //   813: lload 6
    //   815: invokestatic 208	com/google/android/gms/internal/measurement/zzmx:zzc	(Ljava/lang/Object;J)I
    //   818: if_icmpne +133 -> 951
    //   821: goto +132 -> 953
    //   824: aload_0
    //   825: aload_1
    //   826: aload_2
    //   827: iload_3
    //   828: invokespecial 870	com/google/android/gms/internal/measurement/zzlo:zzN	(Ljava/lang/Object;Ljava/lang/Object;I)Z
    //   831: ifeq +120 -> 951
    //   834: aload_1
    //   835: lload 6
    //   837: invokestatic 379	com/google/android/gms/internal/measurement/zzmx:zzd	(Ljava/lang/Object;J)J
    //   840: aload_2
    //   841: lload 6
    //   843: invokestatic 379	com/google/android/gms/internal/measurement/zzmx:zzd	(Ljava/lang/Object;J)J
    //   846: lcmp
    //   847: ifne +104 -> 951
    //   850: goto +103 -> 953
    //   853: aload_0
    //   854: aload_1
    //   855: aload_2
    //   856: iload_3
    //   857: invokespecial 870	com/google/android/gms/internal/measurement/zzlo:zzN	(Ljava/lang/Object;Ljava/lang/Object;I)Z
    //   860: ifeq +91 -> 951
    //   863: aload_1
    //   864: lload 6
    //   866: invokestatic 379	com/google/android/gms/internal/measurement/zzmx:zzd	(Ljava/lang/Object;J)J
    //   869: aload_2
    //   870: lload 6
    //   872: invokestatic 379	com/google/android/gms/internal/measurement/zzmx:zzd	(Ljava/lang/Object;J)J
    //   875: lcmp
    //   876: ifne +75 -> 951
    //   879: goto +74 -> 953
    //   882: aload_0
    //   883: aload_1
    //   884: aload_2
    //   885: iload_3
    //   886: invokespecial 870	com/google/android/gms/internal/measurement/zzlo:zzN	(Ljava/lang/Object;Ljava/lang/Object;I)Z
    //   889: ifeq +62 -> 951
    //   892: aload_1
    //   893: lload 6
    //   895: invokestatic 356	com/google/android/gms/internal/measurement/zzmx:zzb	(Ljava/lang/Object;J)F
    //   898: invokestatic 800	java/lang/Float:floatToIntBits	(F)I
    //   901: aload_2
    //   902: lload 6
    //   904: invokestatic 356	com/google/android/gms/internal/measurement/zzmx:zzb	(Ljava/lang/Object;J)F
    //   907: invokestatic 800	java/lang/Float:floatToIntBits	(F)I
    //   910: if_icmpne +41 -> 951
    //   913: goto +40 -> 953
    //   916: aload_0
    //   917: aload_1
    //   918: aload_2
    //   919: iload_3
    //   920: invokespecial 870	com/google/android/gms/internal/measurement/zzlo:zzN	(Ljava/lang/Object;Ljava/lang/Object;I)Z
    //   923: ifeq +28 -> 951
    //   926: aload_1
    //   927: lload 6
    //   929: invokestatic 358	com/google/android/gms/internal/measurement/zzmx:zza	(Ljava/lang/Object;J)D
    //   932: invokestatic 803	java/lang/Double:doubleToLongBits	(D)J
    //   935: aload_2
    //   936: lload 6
    //   938: invokestatic 358	com/google/android/gms/internal/measurement/zzmx:zza	(Ljava/lang/Object;J)D
    //   941: invokestatic 803	java/lang/Double:doubleToLongBits	(D)J
    //   944: lcmp
    //   945: ifne +6 -> 951
    //   948: goto +5 -> 953
    //   951: iconst_0
    //   952: ireturn
    //   953: iload_3
    //   954: iconst_3
    //   955: iadd
    //   956: istore_3
    //   957: goto -948 -> 9
    //   960: aload_0
    //   961: getfield 80	com/google/android/gms/internal/measurement/zzlo:zzn	Lcom/google/android/gms/internal/measurement/zzmn;
    //   964: aload_1
    //   965: invokevirtual 363	com/google/android/gms/internal/measurement/zzmn:zzc	(Ljava/lang/Object;)Ljava/lang/Object;
    //   968: aload_0
    //   969: getfield 80	com/google/android/gms/internal/measurement/zzlo:zzn	Lcom/google/android/gms/internal/measurement/zzmn;
    //   972: aload_2
    //   973: invokevirtual 363	com/google/android/gms/internal/measurement/zzmn:zzc	(Ljava/lang/Object;)Ljava/lang/Object;
    //   976: invokevirtual 871	java/lang/Object:equals	(Ljava/lang/Object;)Z
    //   979: ifne +5 -> 984
    //   982: iconst_0
    //   983: ireturn
    //   984: aload_0
    //   985: getfield 68	com/google/android/gms/internal/measurement/zzlo:zzh	Z
    //   988: ifne +5 -> 993
    //   991: iconst_1
    //   992: ireturn
    //   993: aload_0
    //   994: getfield 82	com/google/android/gms/internal/measurement/zzlo:zzo	Lcom/google/android/gms/internal/measurement/zzjr;
    //   997: aload_1
    //   998: invokevirtual 368	com/google/android/gms/internal/measurement/zzjr:zza	(Ljava/lang/Object;)Lcom/google/android/gms/internal/measurement/zzjv;
    //   1001: pop
    //   1002: aload_0
    //   1003: getfield 82	com/google/android/gms/internal/measurement/zzlo:zzo	Lcom/google/android/gms/internal/measurement/zzjr;
    //   1006: aload_2
    //   1007: invokevirtual 368	com/google/android/gms/internal/measurement/zzjr:zza	(Ljava/lang/Object;)Lcom/google/android/gms/internal/measurement/zzjv;
    //   1010: pop
    //   1011: aconst_null
    //   1012: athrow
    // Local variable table:
    //   start	length	slot	name	signature
    //   0	1013	0	this	zzlo
    //   0	1013	1	paramObject1	Object
    //   0	1013	2	paramObject2	Object
    //   8	949	3	i	int
    //   5	8	4	j	int
    //   20	11	5	k	int
    //   28	909	6	l1	long
    //   336	10	8	l2	long
    //   388	23	10	bool	boolean
  }
  
  public final boolean zzk(Object paramObject)
  {
    int j = 1048575;
    int i = 0;
    int k = i;
    while (k < zzk)
    {
      int n = zzj[k];
      int i1 = zzc[n];
      int i2 = zzB(n);
      int i3 = zzc[(n + 2)];
      int m = i3 & 0xFFFFF;
      i3 = 1 << (i3 >>> 20);
      if (m != j)
      {
        if (m != 1048575) {
          i = zzb.getInt(paramObject, m);
        }
        j = m;
      }
      if (((0x10000000 & i2) != 0) && (!zzP(paramObject, n, j, i, i3))) {
        return false;
      }
      m = zzA(i2);
      List localList;
      zzlw localZzlw;
      if ((m != 9) && (m != 17))
      {
        if (m != 27) {
          if ((m != 60) && (m != 68))
          {
            if (m != 49)
            {
              if ((m != 50) || (((zzlf)zzmx.zzf(paramObject, i2 & 0xFFFFF)).isEmpty())) {
                break label361;
              }
              paramObject = (zzle)zzF(n);
              throw null;
            }
          }
          else
          {
            if ((!zzR(paramObject, i1, n)) || (zzQ(paramObject, i2, zzE(n)))) {
              break label361;
            }
            return false;
          }
        }
        localList = (List)zzmx.zzf(paramObject, i2 & 0xFFFFF);
        if (!localList.isEmpty())
        {
          localZzlw = zzE(n);
          m = 0;
        }
      }
      else
      {
        while (m < localList.size())
        {
          if (!localZzlw.zzk(localList.get(m))) {
            return false;
          }
          m += 1;
          continue;
          if ((zzP(paramObject, n, j, i, i3)) && (!zzQ(paramObject, i2, zzE(n)))) {
            return false;
          }
        }
      }
      label361:
      k += 1;
    }
    if (!zzh) {
      return true;
    }
    zzo.zza(paramObject);
    throw null;
  }
}
