package com.google.android.gms.measurement.internal;

import com.google.android.gms.internal.measurement.zzfs;

final class LruCache
{
  private Long id;
  private long size;
  private zzfs value;
  
  /* Error */
  final zzfs get(String paramString, zzfs paramZzfs)
  {
    // Byte code:
    //   0: aload_2
    //   1: invokevirtual 34	com/google/android/gms/internal/measurement/zzfs:getValue	()Ljava/lang/String;
    //   4: astore 11
    //   6: aload 11
    //   8: astore 6
    //   10: aload_2
    //   11: invokevirtual 37	com/google/android/gms/internal/measurement/zzfs:get	()Ljava/util/List;
    //   14: astore 10
    //   16: aload 10
    //   18: astore 7
    //   20: aload_0
    //   21: getfield 16	com/google/android/gms/measurement/internal/LruCache:map	Lcom/google/android/gms/measurement/internal/zzaa;
    //   24: getfield 43	com/google/android/gms/measurement/internal/zzkm:this$0	Lcom/google/android/gms/measurement/internal/zzkz;
    //   27: invokevirtual 49	com/google/android/gms/measurement/internal/zzkz:next	()Lcom/google/android/gms/measurement/internal/zzlb;
    //   30: pop
    //   31: aload_2
    //   32: ldc 51
    //   34: invokestatic 57	com/google/android/gms/measurement/internal/zzlb:write	(Lcom/google/android/gms/internal/measurement/zzfs;Ljava/lang/String;)Ljava/lang/Object;
    //   37: checkcast 59	java/lang/Long
    //   40: astore 13
    //   42: aload 6
    //   44: astore 8
    //   46: aload 7
    //   48: astore 9
    //   50: aload 13
    //   52: ifnull +921 -> 973
    //   55: aload 11
    //   57: ldc 61
    //   59: invokevirtual 67	java/lang/String:equals	(Ljava/lang/Object;)Z
    //   62: ifeq +774 -> 836
    //   65: aload 13
    //   67: invokestatic 73	com/google/android/gms/common/internal/Preconditions:checkNotNull	(Ljava/lang/Object;)Ljava/lang/Object;
    //   70: pop
    //   71: aload_0
    //   72: getfield 16	com/google/android/gms/measurement/internal/LruCache:map	Lcom/google/android/gms/measurement/internal/zzaa;
    //   75: getfield 43	com/google/android/gms/measurement/internal/zzkm:this$0	Lcom/google/android/gms/measurement/internal/zzkz;
    //   78: invokevirtual 49	com/google/android/gms/measurement/internal/zzkz:next	()Lcom/google/android/gms/measurement/internal/zzlb;
    //   81: pop
    //   82: aload_2
    //   83: ldc 75
    //   85: invokestatic 57	com/google/android/gms/measurement/internal/zzlb:write	(Lcom/google/android/gms/internal/measurement/zzfs;Ljava/lang/String;)Ljava/lang/Object;
    //   88: checkcast 63	java/lang/String
    //   91: astore 11
    //   93: aload 11
    //   95: invokestatic 81	android/text/TextUtils:isEmpty	(Ljava/lang/CharSequence;)Z
    //   98: ifeq +25 -> 123
    //   101: aload_0
    //   102: getfield 16	com/google/android/gms/measurement/internal/LruCache:map	Lcom/google/android/gms/measurement/internal/zzaa;
    //   105: getfield 86	com/google/android/gms/measurement/internal/zzgr:this$0	Lcom/google/android/gms/measurement/internal/zzfy;
    //   108: invokevirtual 92	com/google/android/gms/measurement/internal/zzfy:zzay	()Lcom/google/android/gms/measurement/internal/zzeo;
    //   111: invokevirtual 98	com/google/android/gms/measurement/internal/zzeo:getText	()Lcom/google/android/gms/measurement/internal/zzem;
    //   114: ldc 100
    //   116: aload 13
    //   118: invokevirtual 106	com/google/android/gms/measurement/internal/zzem:append	(Ljava/lang/String;Ljava/lang/Object;)V
    //   121: aconst_null
    //   122: areturn
    //   123: aload_0
    //   124: getfield 108	com/google/android/gms/measurement/internal/LruCache:value	Lcom/google/android/gms/internal/measurement/zzfs;
    //   127: ifnull +26 -> 153
    //   130: aload_0
    //   131: getfield 110	com/google/android/gms/measurement/internal/LruCache:id	Ljava/lang/Long;
    //   134: ifnull +19 -> 153
    //   137: aload 13
    //   139: invokevirtual 114	java/lang/Long:longValue	()J
    //   142: aload_0
    //   143: getfield 110	com/google/android/gms/measurement/internal/LruCache:id	Ljava/lang/Long;
    //   146: invokevirtual 114	java/lang/Long:longValue	()J
    //   149: lcmp
    //   150: ifeq +385 -> 535
    //   153: aload_0
    //   154: getfield 16	com/google/android/gms/measurement/internal/LruCache:map	Lcom/google/android/gms/measurement/internal/zzaa;
    //   157: getfield 43	com/google/android/gms/measurement/internal/zzkm:this$0	Lcom/google/android/gms/measurement/internal/zzkz;
    //   160: invokevirtual 118	com/google/android/gms/measurement/internal/zzkz:create	()Lcom/google/android/gms/measurement/internal/zzam;
    //   163: astore 14
    //   165: aload 14
    //   167: invokevirtual 120	com/google/android/gms/measurement/internal/zzgr:append	()V
    //   170: aload 14
    //   172: invokevirtual 124	com/google/android/gms/measurement/internal/zzkn:size	()V
    //   175: aload 14
    //   177: invokevirtual 129	com/google/android/gms/measurement/internal/zzam:get	()Landroid/database/sqlite/SQLiteDatabase;
    //   180: astore 6
    //   182: aload 13
    //   184: invokevirtual 132	java/lang/Object:toString	()Ljava/lang/String;
    //   187: astore 8
    //   189: aload 6
    //   191: ldc -122
    //   193: iconst_2
    //   194: anewarray 63	java/lang/String
    //   197: dup
    //   198: iconst_0
    //   199: aload_1
    //   200: aastore
    //   201: dup
    //   202: iconst_1
    //   203: aload 8
    //   205: aastore
    //   206: invokevirtual 140	android/database/sqlite/SQLiteDatabase:rawQuery	(Ljava/lang/String;[Ljava/lang/String;)Landroid/database/Cursor;
    //   209: astore 9
    //   211: aload 9
    //   213: astore 6
    //   215: aload 6
    //   217: astore 8
    //   219: aload 9
    //   221: invokeinterface 146 1 0
    //   226: istore_3
    //   227: iload_3
    //   228: ifne +40 -> 268
    //   231: aload 14
    //   233: getfield 86	com/google/android/gms/measurement/internal/zzgr:this$0	Lcom/google/android/gms/measurement/internal/zzfy;
    //   236: astore 12
    //   238: aload 6
    //   240: astore 8
    //   242: aload 12
    //   244: invokevirtual 92	com/google/android/gms/measurement/internal/zzfy:zzay	()Lcom/google/android/gms/measurement/internal/zzeo;
    //   247: invokevirtual 148	com/google/android/gms/measurement/internal/zzeo:next	()Lcom/google/android/gms/measurement/internal/zzem;
    //   250: ldc -106
    //   252: invokevirtual 153	com/google/android/gms/measurement/internal/zzem:append	(Ljava/lang/String;)V
    //   255: aload 9
    //   257: invokeinterface 156 1 0
    //   262: aconst_null
    //   263: astore 6
    //   265: goto +199 -> 464
    //   268: aload 6
    //   270: astore 8
    //   272: aload 9
    //   274: iconst_0
    //   275: invokeinterface 160 2 0
    //   280: astore 12
    //   282: aload 6
    //   284: astore 8
    //   286: aload 9
    //   288: iconst_1
    //   289: invokeinterface 164 2 0
    //   294: lstore 4
    //   296: aload 6
    //   298: astore 8
    //   300: invokestatic 168	com/google/android/gms/internal/measurement/zzfs:getKey	()Lcom/google/android/gms/internal/measurement/zzfr;
    //   303: aload 12
    //   305: invokestatic 171	com/google/android/gms/measurement/internal/zzlb:equals	(Lcom/google/android/gms/internal/measurement/zzlk;[B)Lcom/google/android/gms/internal/measurement/zzlk;
    //   308: astore 12
    //   310: aload 6
    //   312: astore 8
    //   314: aload 12
    //   316: checkcast 173	com/google/android/gms/internal/measurement/zzfr
    //   319: astore 12
    //   321: aload 6
    //   323: astore 8
    //   325: aload 12
    //   327: invokevirtual 179	com/google/android/gms/internal/measurement/zzka:zzaE	()Lcom/google/android/gms/internal/measurement/zzke;
    //   330: astore 12
    //   332: aload 6
    //   334: astore 8
    //   336: aload 12
    //   338: checkcast 30	com/google/android/gms/internal/measurement/zzfs
    //   341: astore 12
    //   343: aload 6
    //   345: astore 8
    //   347: aload 12
    //   349: lload 4
    //   351: invokestatic 183	java/lang/Long:valueOf	(J)Ljava/lang/Long;
    //   354: invokestatic 188	android/util/Pair:create	(Ljava/lang/Object;Ljava/lang/Object;)Landroid/util/Pair;
    //   357: astore 12
    //   359: aload 9
    //   361: invokeinterface 156 1 0
    //   366: aload 12
    //   368: astore 6
    //   370: goto +94 -> 464
    //   373: astore 9
    //   375: aload 14
    //   377: getfield 86	com/google/android/gms/measurement/internal/zzgr:this$0	Lcom/google/android/gms/measurement/internal/zzfy;
    //   380: astore 12
    //   382: aload 6
    //   384: astore 8
    //   386: aload 12
    //   388: invokevirtual 92	com/google/android/gms/measurement/internal/zzfy:zzay	()Lcom/google/android/gms/measurement/internal/zzeo;
    //   391: invokevirtual 191	com/google/android/gms/measurement/internal/zzeo:iterator	()Lcom/google/android/gms/measurement/internal/zzem;
    //   394: ldc -63
    //   396: aload_1
    //   397: invokestatic 196	com/google/android/gms/measurement/internal/zzeo:get	(Ljava/lang/String;)Ljava/lang/Object;
    //   400: aload 13
    //   402: aload 9
    //   404: invokevirtual 199	com/google/android/gms/measurement/internal/zzem:append	(Ljava/lang/String;Ljava/lang/Object;Ljava/lang/Object;Ljava/lang/Object;)V
    //   407: goto +47 -> 454
    //   410: astore 9
    //   412: goto +15 -> 427
    //   415: astore_1
    //   416: aconst_null
    //   417: astore 8
    //   419: goto +403 -> 822
    //   422: astore 9
    //   424: aconst_null
    //   425: astore 6
    //   427: aload 6
    //   429: astore 8
    //   431: aload 14
    //   433: getfield 86	com/google/android/gms/measurement/internal/zzgr:this$0	Lcom/google/android/gms/measurement/internal/zzfy;
    //   436: invokevirtual 92	com/google/android/gms/measurement/internal/zzfy:zzay	()Lcom/google/android/gms/measurement/internal/zzeo;
    //   439: invokevirtual 191	com/google/android/gms/measurement/internal/zzeo:iterator	()Lcom/google/android/gms/measurement/internal/zzem;
    //   442: ldc -55
    //   444: aload 9
    //   446: invokevirtual 106	com/google/android/gms/measurement/internal/zzem:append	(Ljava/lang/String;Ljava/lang/Object;)V
    //   449: aload 6
    //   451: ifnull +10 -> 461
    //   454: aload 6
    //   456: invokeinterface 156 1 0
    //   461: aconst_null
    //   462: astore 6
    //   464: aload 6
    //   466: ifnull +330 -> 796
    //   469: aload 6
    //   471: getfield 205	android/util/Pair:first	Ljava/lang/Object;
    //   474: astore 8
    //   476: aload 8
    //   478: ifnonnull +6 -> 484
    //   481: goto +315 -> 796
    //   484: aload_0
    //   485: aload 8
    //   487: checkcast 30	com/google/android/gms/internal/measurement/zzfs
    //   490: putfield 108	com/google/android/gms/measurement/internal/LruCache:value	Lcom/google/android/gms/internal/measurement/zzfs;
    //   493: aload_0
    //   494: aload 6
    //   496: getfield 208	android/util/Pair:second	Ljava/lang/Object;
    //   499: checkcast 59	java/lang/Long
    //   502: invokevirtual 114	java/lang/Long:longValue	()J
    //   505: putfield 210	com/google/android/gms/measurement/internal/LruCache:size	J
    //   508: aload_0
    //   509: getfield 16	com/google/android/gms/measurement/internal/LruCache:map	Lcom/google/android/gms/measurement/internal/zzaa;
    //   512: getfield 43	com/google/android/gms/measurement/internal/zzkm:this$0	Lcom/google/android/gms/measurement/internal/zzkz;
    //   515: invokevirtual 49	com/google/android/gms/measurement/internal/zzkz:next	()Lcom/google/android/gms/measurement/internal/zzlb;
    //   518: pop
    //   519: aload_0
    //   520: aload_0
    //   521: getfield 108	com/google/android/gms/measurement/internal/LruCache:value	Lcom/google/android/gms/internal/measurement/zzfs;
    //   524: ldc 51
    //   526: invokestatic 57	com/google/android/gms/measurement/internal/zzlb:write	(Lcom/google/android/gms/internal/measurement/zzfs;Ljava/lang/String;)Ljava/lang/Object;
    //   529: checkcast 59	java/lang/Long
    //   532: putfield 110	com/google/android/gms/measurement/internal/LruCache:id	Ljava/lang/Long;
    //   535: aload_0
    //   536: getfield 210	com/google/android/gms/measurement/internal/LruCache:size	J
    //   539: lconst_1
    //   540: lsub
    //   541: lstore 4
    //   543: aload_0
    //   544: lload 4
    //   546: putfield 210	com/google/android/gms/measurement/internal/LruCache:size	J
    //   549: lload 4
    //   551: lconst_0
    //   552: lcmp
    //   553: ifgt +83 -> 636
    //   556: aload_0
    //   557: getfield 16	com/google/android/gms/measurement/internal/LruCache:map	Lcom/google/android/gms/measurement/internal/zzaa;
    //   560: getfield 43	com/google/android/gms/measurement/internal/zzkm:this$0	Lcom/google/android/gms/measurement/internal/zzkz;
    //   563: invokevirtual 118	com/google/android/gms/measurement/internal/zzkz:create	()Lcom/google/android/gms/measurement/internal/zzam;
    //   566: astore 6
    //   568: aload 6
    //   570: invokevirtual 120	com/google/android/gms/measurement/internal/zzgr:append	()V
    //   573: aload 6
    //   575: getfield 86	com/google/android/gms/measurement/internal/zzgr:this$0	Lcom/google/android/gms/measurement/internal/zzfy;
    //   578: invokevirtual 92	com/google/android/gms/measurement/internal/zzfy:zzay	()Lcom/google/android/gms/measurement/internal/zzeo;
    //   581: invokevirtual 148	com/google/android/gms/measurement/internal/zzeo:next	()Lcom/google/android/gms/measurement/internal/zzem;
    //   584: ldc -44
    //   586: aload_1
    //   587: invokevirtual 106	com/google/android/gms/measurement/internal/zzem:append	(Ljava/lang/String;Ljava/lang/Object;)V
    //   590: aload 6
    //   592: invokevirtual 129	com/google/android/gms/measurement/internal/zzam:get	()Landroid/database/sqlite/SQLiteDatabase;
    //   595: astore 8
    //   597: aload 8
    //   599: ldc -42
    //   601: iconst_1
    //   602: anewarray 63	java/lang/String
    //   605: dup
    //   606: iconst_0
    //   607: aload_1
    //   608: aastore
    //   609: invokevirtual 218	android/database/sqlite/SQLiteDatabase:execSQL	(Ljava/lang/String;[Ljava/lang/Object;)V
    //   612: goto +49 -> 661
    //   615: astore_1
    //   616: aload 6
    //   618: getfield 86	com/google/android/gms/measurement/internal/zzgr:this$0	Lcom/google/android/gms/measurement/internal/zzfy;
    //   621: invokevirtual 92	com/google/android/gms/measurement/internal/zzfy:zzay	()Lcom/google/android/gms/measurement/internal/zzeo;
    //   624: invokevirtual 191	com/google/android/gms/measurement/internal/zzeo:iterator	()Lcom/google/android/gms/measurement/internal/zzem;
    //   627: ldc -36
    //   629: aload_1
    //   630: invokevirtual 106	com/google/android/gms/measurement/internal/zzem:append	(Ljava/lang/String;Ljava/lang/Object;)V
    //   633: goto +28 -> 661
    //   636: aload_0
    //   637: getfield 16	com/google/android/gms/measurement/internal/LruCache:map	Lcom/google/android/gms/measurement/internal/zzaa;
    //   640: getfield 43	com/google/android/gms/measurement/internal/zzkm:this$0	Lcom/google/android/gms/measurement/internal/zzkz;
    //   643: invokevirtual 118	com/google/android/gms/measurement/internal/zzkz:create	()Lcom/google/android/gms/measurement/internal/zzam;
    //   646: aload_1
    //   647: aload 13
    //   649: aload_0
    //   650: getfield 210	com/google/android/gms/measurement/internal/LruCache:size	J
    //   653: aload_0
    //   654: getfield 108	com/google/android/gms/measurement/internal/LruCache:value	Lcom/google/android/gms/internal/measurement/zzfs;
    //   657: invokevirtual 224	com/google/android/gms/measurement/internal/zzam:put	(Ljava/lang/String;Ljava/lang/Long;JLcom/google/android/gms/internal/measurement/zzfs;)Z
    //   660: pop
    //   661: new 226	java/util/ArrayList
    //   664: dup
    //   665: invokespecial 227	java/util/ArrayList:<init>	()V
    //   668: astore_1
    //   669: aload_0
    //   670: getfield 108	com/google/android/gms/measurement/internal/LruCache:value	Lcom/google/android/gms/internal/measurement/zzfs;
    //   673: invokevirtual 37	com/google/android/gms/internal/measurement/zzfs:get	()Ljava/util/List;
    //   676: invokeinterface 232 1 0
    //   681: astore 6
    //   683: aload 6
    //   685: invokeinterface 237 1 0
    //   690: ifeq +50 -> 740
    //   693: aload 6
    //   695: invokeinterface 240 1 0
    //   700: checkcast 242	com/google/android/gms/internal/measurement/zzfw
    //   703: astore 8
    //   705: aload_0
    //   706: getfield 16	com/google/android/gms/measurement/internal/LruCache:map	Lcom/google/android/gms/measurement/internal/zzaa;
    //   709: getfield 43	com/google/android/gms/measurement/internal/zzkm:this$0	Lcom/google/android/gms/measurement/internal/zzkz;
    //   712: invokevirtual 49	com/google/android/gms/measurement/internal/zzkz:next	()Lcom/google/android/gms/measurement/internal/zzlb;
    //   715: pop
    //   716: aload_2
    //   717: aload 8
    //   719: invokevirtual 243	com/google/android/gms/internal/measurement/zzfw:getValue	()Ljava/lang/String;
    //   722: invokestatic 247	com/google/android/gms/measurement/internal/zzlb:remove	(Lcom/google/android/gms/internal/measurement/zzfs;Ljava/lang/String;)Lcom/google/android/gms/internal/measurement/zzfw;
    //   725: ifnonnull -42 -> 683
    //   728: aload_1
    //   729: aload 8
    //   731: invokeinterface 250 2 0
    //   736: pop
    //   737: goto -54 -> 683
    //   740: aload_1
    //   741: invokeinterface 252 1 0
    //   746: ifne +18 -> 764
    //   749: aload_1
    //   750: aload 10
    //   752: invokeinterface 256 2 0
    //   757: pop
    //   758: aload_1
    //   759: astore 7
    //   761: goto +24 -> 785
    //   764: aload_0
    //   765: getfield 16	com/google/android/gms/measurement/internal/LruCache:map	Lcom/google/android/gms/measurement/internal/zzaa;
    //   768: getfield 86	com/google/android/gms/measurement/internal/zzgr:this$0	Lcom/google/android/gms/measurement/internal/zzfy;
    //   771: invokevirtual 92	com/google/android/gms/measurement/internal/zzfy:zzay	()Lcom/google/android/gms/measurement/internal/zzeo;
    //   774: invokevirtual 98	com/google/android/gms/measurement/internal/zzeo:getText	()Lcom/google/android/gms/measurement/internal/zzem;
    //   777: ldc_w 258
    //   780: aload 11
    //   782: invokevirtual 106	com/google/android/gms/measurement/internal/zzem:append	(Ljava/lang/String;Ljava/lang/Object;)V
    //   785: aload 11
    //   787: astore 8
    //   789: aload 7
    //   791: astore 9
    //   793: goto +180 -> 973
    //   796: aload_0
    //   797: getfield 16	com/google/android/gms/measurement/internal/LruCache:map	Lcom/google/android/gms/measurement/internal/zzaa;
    //   800: getfield 86	com/google/android/gms/measurement/internal/zzgr:this$0	Lcom/google/android/gms/measurement/internal/zzfy;
    //   803: invokevirtual 92	com/google/android/gms/measurement/internal/zzfy:zzay	()Lcom/google/android/gms/measurement/internal/zzeo;
    //   806: invokevirtual 98	com/google/android/gms/measurement/internal/zzeo:getText	()Lcom/google/android/gms/measurement/internal/zzem;
    //   809: ldc_w 260
    //   812: aload 11
    //   814: aload 13
    //   816: invokevirtual 263	com/google/android/gms/measurement/internal/zzem:append	(Ljava/lang/String;Ljava/lang/Object;Ljava/lang/Object;)V
    //   819: aconst_null
    //   820: areturn
    //   821: astore_1
    //   822: aload 8
    //   824: ifnull +10 -> 834
    //   827: aload 8
    //   829: invokeinterface 156 1 0
    //   834: aload_1
    //   835: athrow
    //   836: aload_0
    //   837: aload 13
    //   839: putfield 110	com/google/android/gms/measurement/internal/LruCache:id	Ljava/lang/Long;
    //   842: aload_0
    //   843: aload_2
    //   844: putfield 108	com/google/android/gms/measurement/internal/LruCache:value	Lcom/google/android/gms/internal/measurement/zzfs;
    //   847: aload_0
    //   848: getfield 16	com/google/android/gms/measurement/internal/LruCache:map	Lcom/google/android/gms/measurement/internal/zzaa;
    //   851: getfield 43	com/google/android/gms/measurement/internal/zzkm:this$0	Lcom/google/android/gms/measurement/internal/zzkz;
    //   854: invokevirtual 49	com/google/android/gms/measurement/internal/zzkz:next	()Lcom/google/android/gms/measurement/internal/zzlb;
    //   857: pop
    //   858: lconst_0
    //   859: invokestatic 183	java/lang/Long:valueOf	(J)Ljava/lang/Long;
    //   862: astore 8
    //   864: aload_2
    //   865: ldc_w 265
    //   868: invokestatic 57	com/google/android/gms/measurement/internal/zzlb:write	(Lcom/google/android/gms/internal/measurement/zzfs;Ljava/lang/String;)Ljava/lang/Object;
    //   871: astore 9
    //   873: aload 9
    //   875: ifnull +7 -> 882
    //   878: aload 9
    //   880: astore 8
    //   882: aload 8
    //   884: checkcast 59	java/lang/Long
    //   887: invokevirtual 114	java/lang/Long:longValue	()J
    //   890: lstore 4
    //   892: aload_0
    //   893: lload 4
    //   895: putfield 210	com/google/android/gms/measurement/internal/LruCache:size	J
    //   898: lload 4
    //   900: lconst_0
    //   901: lcmp
    //   902: ifgt +35 -> 937
    //   905: aload_0
    //   906: getfield 16	com/google/android/gms/measurement/internal/LruCache:map	Lcom/google/android/gms/measurement/internal/zzaa;
    //   909: getfield 86	com/google/android/gms/measurement/internal/zzgr:this$0	Lcom/google/android/gms/measurement/internal/zzfy;
    //   912: invokevirtual 92	com/google/android/gms/measurement/internal/zzfy:zzay	()Lcom/google/android/gms/measurement/internal/zzeo;
    //   915: invokevirtual 98	com/google/android/gms/measurement/internal/zzeo:getText	()Lcom/google/android/gms/measurement/internal/zzem;
    //   918: ldc_w 267
    //   921: aload 11
    //   923: invokevirtual 106	com/google/android/gms/measurement/internal/zzem:append	(Ljava/lang/String;Ljava/lang/Object;)V
    //   926: aload 6
    //   928: astore 8
    //   930: aload 7
    //   932: astore 9
    //   934: goto +39 -> 973
    //   937: aload_0
    //   938: getfield 16	com/google/android/gms/measurement/internal/LruCache:map	Lcom/google/android/gms/measurement/internal/zzaa;
    //   941: getfield 43	com/google/android/gms/measurement/internal/zzkm:this$0	Lcom/google/android/gms/measurement/internal/zzkz;
    //   944: invokevirtual 118	com/google/android/gms/measurement/internal/zzkz:create	()Lcom/google/android/gms/measurement/internal/zzam;
    //   947: aload_1
    //   948: aload 13
    //   950: invokestatic 73	com/google/android/gms/common/internal/Preconditions:checkNotNull	(Ljava/lang/Object;)Ljava/lang/Object;
    //   953: checkcast 59	java/lang/Long
    //   956: aload_0
    //   957: getfield 210	com/google/android/gms/measurement/internal/LruCache:size	J
    //   960: aload_2
    //   961: invokevirtual 224	com/google/android/gms/measurement/internal/zzam:put	(Ljava/lang/String;Ljava/lang/Long;JLcom/google/android/gms/internal/measurement/zzfs;)Z
    //   964: pop
    //   965: aload 7
    //   967: astore 9
    //   969: aload 6
    //   971: astore 8
    //   973: aload_2
    //   974: invokevirtual 273	com/google/android/gms/internal/measurement/zzke:zzby	()Lcom/google/android/gms/internal/measurement/zzka;
    //   977: checkcast 173	com/google/android/gms/internal/measurement/zzfr
    //   980: astore_1
    //   981: aload_1
    //   982: aload 8
    //   984: invokevirtual 276	com/google/android/gms/internal/measurement/zzfr:put	(Ljava/lang/String;)Lcom/google/android/gms/internal/measurement/zzfr;
    //   987: pop
    //   988: aload_1
    //   989: invokevirtual 279	com/google/android/gms/internal/measurement/zzfr:descend	()Lcom/google/android/gms/internal/measurement/zzfr;
    //   992: pop
    //   993: aload_1
    //   994: aload 9
    //   996: checkcast 281	java/lang/Iterable
    //   999: invokevirtual 284	com/google/android/gms/internal/measurement/zzfr:descend	(Ljava/lang/Iterable;)Lcom/google/android/gms/internal/measurement/zzfr;
    //   1002: pop
    //   1003: aload_1
    //   1004: invokevirtual 179	com/google/android/gms/internal/measurement/zzka:zzaE	()Lcom/google/android/gms/internal/measurement/zzke;
    //   1007: checkcast 30	com/google/android/gms/internal/measurement/zzfs
    //   1010: areturn
    // Local variable table:
    //   start	length	slot	name	signature
    //   0	1011	0	this	LruCache
    //   0	1011	1	paramString	String
    //   0	1011	2	paramZzfs	zzfs
    //   226	2	3	bool	boolean
    //   294	605	4	l	long
    //   8	962	6	localObject1	Object
    //   18	948	7	localObject2	Object
    //   44	939	8	localObject3	Object
    //   48	312	9	localObject4	Object
    //   373	30	9	localIOException	java.io.IOException
    //   410	1	9	localSQLiteException1	android.database.sqlite.SQLiteException
    //   422	23	9	localSQLiteException2	android.database.sqlite.SQLiteException
    //   791	204	9	localObject5	Object
    //   14	737	10	localList	java.util.List
    //   4	918	11	str	String
    //   236	151	12	localObject6	Object
    //   40	909	13	localLong	Long
    //   163	269	14	localZzam	zzam
    // Exception table:
    //   from	to	target	type
    //   300	310	373	java/io/IOException
    //   325	332	373	java/io/IOException
    //   219	227	410	android/database/sqlite/SQLiteException
    //   242	255	410	android/database/sqlite/SQLiteException
    //   272	282	410	android/database/sqlite/SQLiteException
    //   286	296	410	android/database/sqlite/SQLiteException
    //   300	310	410	android/database/sqlite/SQLiteException
    //   325	332	410	android/database/sqlite/SQLiteException
    //   347	359	410	android/database/sqlite/SQLiteException
    //   386	407	410	android/database/sqlite/SQLiteException
    //   175	182	415	java/lang/Throwable
    //   182	189	415	java/lang/Throwable
    //   189	211	415	java/lang/Throwable
    //   175	182	422	android/database/sqlite/SQLiteException
    //   182	189	422	android/database/sqlite/SQLiteException
    //   189	211	422	android/database/sqlite/SQLiteException
    //   590	597	615	android/database/sqlite/SQLiteException
    //   597	612	615	android/database/sqlite/SQLiteException
    //   219	227	821	java/lang/Throwable
    //   242	255	821	java/lang/Throwable
    //   272	282	821	java/lang/Throwable
    //   286	296	821	java/lang/Throwable
    //   300	310	821	java/lang/Throwable
    //   314	321	821	java/lang/Throwable
    //   325	332	821	java/lang/Throwable
    //   336	343	821	java/lang/Throwable
    //   347	359	821	java/lang/Throwable
    //   386	407	821	java/lang/Throwable
    //   431	449	821	java/lang/Throwable
  }
}
