package com.google.android.gms.measurement.internal;

import java.util.BitSet;
import java.util.Map;
import java.util.Set;

final class zzaa
  extends zzkn
{
  private String zza;
  private Set zzb;
  private Map zzc;
  private Long zzd;
  private Long zze;
  
  zzaa(zzkz paramZzkz)
  {
    super(paramZzkz);
  }
  
  private final zzu zzd(Integer paramInteger)
  {
    if (zzc.containsKey(paramInteger)) {
      return (zzu)zzc.get(paramInteger);
    }
    zzu localZzu = new zzu(this, zza, null);
    zzc.put(paramInteger, localZzu);
    return localZzu;
  }
  
  private final boolean zzf(int paramInt1, int paramInt2)
  {
    zzu localZzu = (zzu)zzc.get(Integer.valueOf(paramInt1));
    if (localZzu == null) {
      return false;
    }
    return zzu.zzb(localZzu).get(paramInt2);
  }
  
  /* Error */
  final java.util.List zza(String arg1, java.util.List arg2, java.util.List arg3, Long arg4, Long arg5)
  {
    // Byte code:
    //   0: ldc 65
    //   2: astore 17
    //   4: aload_1
    //   5: invokestatic 71	com/google/android/gms/common/internal/Preconditions:checkNotEmpty	(Ljava/lang/String;)Ljava/lang/String;
    //   8: pop
    //   9: aload_2
    //   10: invokestatic 74	com/google/android/gms/common/internal/Preconditions:checkNotNull	(Ljava/lang/Object;)Ljava/lang/Object;
    //   13: pop
    //   14: aload_3
    //   15: invokestatic 74	com/google/android/gms/common/internal/Preconditions:checkNotNull	(Ljava/lang/Object;)Ljava/lang/Object;
    //   18: pop
    //   19: aload_0
    //   20: aload_1
    //   21: putfield 35	com/google/android/gms/measurement/internal/zzaa:zza	Ljava/lang/String;
    //   24: aload_0
    //   25: new 76	java/util/HashSet
    //   28: dup
    //   29: invokespecial 79	java/util/HashSet:<init>	()V
    //   32: putfield 81	com/google/android/gms/measurement/internal/zzaa:zzb	Ljava/util/Set;
    //   35: aload_0
    //   36: new 83	c/e/a
    //   39: dup
    //   40: invokespecial 84	c/e/a:<init>	()V
    //   43: putfield 21	com/google/android/gms/measurement/internal/zzaa:zzc	Ljava/util/Map;
    //   46: aload_0
    //   47: aload 4
    //   49: putfield 86	com/google/android/gms/measurement/internal/zzaa:zzd	Ljava/lang/Long;
    //   52: aload_0
    //   53: aload 5
    //   55: putfield 88	com/google/android/gms/measurement/internal/zzaa:zze	Ljava/lang/Long;
    //   58: aload_2
    //   59: invokeinterface 94 1 0
    //   64: astore_1
    //   65: aload_1
    //   66: invokeinterface 100 1 0
    //   71: ifeq +29 -> 100
    //   74: ldc 102
    //   76: aload_1
    //   77: invokeinterface 106 1 0
    //   82: checkcast 108	com/google/android/gms/internal/measurement/zzfs
    //   85: invokevirtual 112	com/google/android/gms/internal/measurement/zzfs:zzh	()Ljava/lang/String;
    //   88: invokevirtual 117	java/lang/String:equals	(Ljava/lang/Object;)Z
    //   91: ifeq -26 -> 65
    //   94: iconst_1
    //   95: istore 6
    //   97: goto +6 -> 103
    //   100: iconst_0
    //   101: istore 6
    //   103: invokestatic 121	com/google/android/gms/internal/measurement/zzny:zzc	()Z
    //   106: pop
    //   107: aload_0
    //   108: getfield 127	com/google/android/gms/measurement/internal/zzgr:zzs	Lcom/google/android/gms/measurement/internal/zzfy;
    //   111: invokevirtual 132	com/google/android/gms/measurement/internal/zzfy:zzf	()Lcom/google/android/gms/measurement/internal/zzag;
    //   114: aload_0
    //   115: getfield 35	com/google/android/gms/measurement/internal/zzaa:zza	Ljava/lang/String;
    //   118: getstatic 138	com/google/android/gms/measurement/internal/zzeb:zzW	Lcom/google/android/gms/measurement/internal/zzea;
    //   121: invokevirtual 143	com/google/android/gms/measurement/internal/zzag:zzs	(Ljava/lang/String;Lcom/google/android/gms/measurement/internal/zzea;)Z
    //   124: istore 8
    //   126: invokestatic 121	com/google/android/gms/internal/measurement/zzny:zzc	()Z
    //   129: pop
    //   130: aload_0
    //   131: getfield 127	com/google/android/gms/measurement/internal/zzgr:zzs	Lcom/google/android/gms/measurement/internal/zzfy;
    //   134: invokevirtual 132	com/google/android/gms/measurement/internal/zzfy:zzf	()Lcom/google/android/gms/measurement/internal/zzag;
    //   137: aload_0
    //   138: getfield 35	com/google/android/gms/measurement/internal/zzaa:zza	Ljava/lang/String;
    //   141: getstatic 146	com/google/android/gms/measurement/internal/zzeb:zzV	Lcom/google/android/gms/measurement/internal/zzea;
    //   144: invokevirtual 143	com/google/android/gms/measurement/internal/zzag:zzs	(Ljava/lang/String;Lcom/google/android/gms/measurement/internal/zzea;)Z
    //   147: istore 9
    //   149: iload 6
    //   151: ifeq +101 -> 252
    //   154: aload_0
    //   155: getfield 151	com/google/android/gms/measurement/internal/zzkm:zzf	Lcom/google/android/gms/measurement/internal/zzkz;
    //   158: invokevirtual 157	com/google/android/gms/measurement/internal/zzkz:zzi	()Lcom/google/android/gms/measurement/internal/zzam;
    //   161: astore_1
    //   162: aload_0
    //   163: getfield 35	com/google/android/gms/measurement/internal/zzaa:zza	Ljava/lang/String;
    //   166: astore 4
    //   168: aload_1
    //   169: invokevirtual 159	com/google/android/gms/measurement/internal/zzkn:zzW	()V
    //   172: aload_1
    //   173: invokevirtual 162	com/google/android/gms/measurement/internal/zzgr:zzg	()V
    //   176: aload 4
    //   178: invokestatic 71	com/google/android/gms/common/internal/Preconditions:checkNotEmpty	(Ljava/lang/String;)Ljava/lang/String;
    //   181: pop
    //   182: new 164	android/content/ContentValues
    //   185: dup
    //   186: invokespecial 165	android/content/ContentValues:<init>	()V
    //   189: astore 5
    //   191: aload 5
    //   193: ldc -89
    //   195: iconst_0
    //   196: invokestatic 50	java/lang/Integer:valueOf	(I)Ljava/lang/Integer;
    //   199: invokevirtual 170	android/content/ContentValues:put	(Ljava/lang/String;Ljava/lang/Integer;)V
    //   202: aload_1
    //   203: invokevirtual 175	com/google/android/gms/measurement/internal/zzam:zzh	()Landroid/database/sqlite/SQLiteDatabase;
    //   206: ldc -79
    //   208: aload 5
    //   210: ldc -77
    //   212: iconst_1
    //   213: anewarray 114	java/lang/String
    //   216: dup
    //   217: iconst_0
    //   218: aload 4
    //   220: aastore
    //   221: invokevirtual 185	android/database/sqlite/SQLiteDatabase:update	(Ljava/lang/String;Landroid/content/ContentValues;Ljava/lang/String;[Ljava/lang/String;)I
    //   224: pop
    //   225: goto +27 -> 252
    //   228: astore 5
    //   230: aload_1
    //   231: getfield 127	com/google/android/gms/measurement/internal/zzgr:zzs	Lcom/google/android/gms/measurement/internal/zzfy;
    //   234: invokevirtual 189	com/google/android/gms/measurement/internal/zzfy:zzay	()Lcom/google/android/gms/measurement/internal/zzeo;
    //   237: invokevirtual 194	com/google/android/gms/measurement/internal/zzeo:zzd	()Lcom/google/android/gms/measurement/internal/zzem;
    //   240: ldc -60
    //   242: aload 4
    //   244: invokestatic 200	com/google/android/gms/measurement/internal/zzeo:zzn	(Ljava/lang/String;)Ljava/lang/Object;
    //   247: aload 5
    //   249: invokevirtual 205	com/google/android/gms/measurement/internal/zzem:zzc	(Ljava/lang/String;Ljava/lang/Object;Ljava/lang/Object;)V
    //   252: invokestatic 211	java/util/Collections:emptyMap	()Ljava/util/Map;
    //   255: astore_1
    //   256: ldc -43
    //   258: astore 21
    //   260: ldc -41
    //   262: astore 18
    //   264: ldc -39
    //   266: astore 19
    //   268: ldc -37
    //   270: astore 14
    //   272: aload_1
    //   273: astore 4
    //   275: iload 9
    //   277: ifeq +385 -> 662
    //   280: aload_1
    //   281: astore 4
    //   283: iload 8
    //   285: ifeq +377 -> 662
    //   288: aload_0
    //   289: getfield 151	com/google/android/gms/measurement/internal/zzkm:zzf	Lcom/google/android/gms/measurement/internal/zzkz;
    //   292: invokevirtual 157	com/google/android/gms/measurement/internal/zzkz:zzi	()Lcom/google/android/gms/measurement/internal/zzam;
    //   295: astore 13
    //   297: aload_0
    //   298: getfield 35	com/google/android/gms/measurement/internal/zzaa:zza	Ljava/lang/String;
    //   301: astore 16
    //   303: aload 16
    //   305: invokestatic 71	com/google/android/gms/common/internal/Preconditions:checkNotEmpty	(Ljava/lang/String;)Ljava/lang/String;
    //   308: pop
    //   309: new 83	c/e/a
    //   312: dup
    //   313: invokespecial 84	c/e/a:<init>	()V
    //   316: astore 15
    //   318: aload 13
    //   320: invokevirtual 175	com/google/android/gms/measurement/internal/zzam:zzh	()Landroid/database/sqlite/SQLiteDatabase;
    //   323: astore_1
    //   324: aload_1
    //   325: ldc -35
    //   327: iconst_2
    //   328: anewarray 114	java/lang/String
    //   331: dup
    //   332: iconst_0
    //   333: ldc -37
    //   335: aastore
    //   336: dup
    //   337: iconst_1
    //   338: ldc -39
    //   340: aastore
    //   341: ldc -33
    //   343: iconst_1
    //   344: anewarray 114	java/lang/String
    //   347: dup
    //   348: iconst_0
    //   349: aload 16
    //   351: aastore
    //   352: aconst_null
    //   353: aconst_null
    //   354: aconst_null
    //   355: invokevirtual 227	android/database/sqlite/SQLiteDatabase:query	(Ljava/lang/String;[Ljava/lang/String;Ljava/lang/String;[Ljava/lang/String;Ljava/lang/String;Ljava/lang/String;Ljava/lang/String;)Landroid/database/Cursor;
    //   358: astore_1
    //   359: aload_1
    //   360: astore 4
    //   362: aload_1
    //   363: invokeinterface 232 1 0
    //   368: ifeq +190 -> 558
    //   371: aload_1
    //   372: astore 4
    //   374: aload_1
    //   375: iconst_1
    //   376: invokeinterface 236 2 0
    //   381: astore 5
    //   383: aload_1
    //   384: astore 4
    //   386: invokestatic 241	com/google/android/gms/internal/measurement/zzej:zzc	()Lcom/google/android/gms/internal/measurement/zzei;
    //   389: aload 5
    //   391: invokestatic 247	com/google/android/gms/measurement/internal/zzlb:zzl	(Lcom/google/android/gms/internal/measurement/zzlk;[B)Lcom/google/android/gms/internal/measurement/zzlk;
    //   394: checkcast 249	com/google/android/gms/internal/measurement/zzei
    //   397: invokevirtual 255	com/google/android/gms/internal/measurement/zzka:zzaE	()Lcom/google/android/gms/internal/measurement/zzke;
    //   400: checkcast 238	com/google/android/gms/internal/measurement/zzej
    //   403: astore 20
    //   405: aload_1
    //   406: astore 4
    //   408: aload 20
    //   410: invokevirtual 258	com/google/android/gms/internal/measurement/zzej:zzo	()Z
    //   413: ifne +6 -> 419
    //   416: goto +114 -> 530
    //   419: aload_1
    //   420: astore 4
    //   422: aload_1
    //   423: iconst_0
    //   424: invokeinterface 262 2 0
    //   429: invokestatic 50	java/lang/Integer:valueOf	(I)Ljava/lang/Integer;
    //   432: astore 22
    //   434: aload_1
    //   435: astore 4
    //   437: aload 15
    //   439: aload 22
    //   441: invokeinterface 31 2 0
    //   446: checkcast 90	java/util/List
    //   449: astore 5
    //   451: aload 5
    //   453: ifnonnull +4642 -> 5095
    //   456: aload_1
    //   457: astore 4
    //   459: new 264	java/util/ArrayList
    //   462: dup
    //   463: invokespecial 265	java/util/ArrayList:<init>	()V
    //   466: astore 5
    //   468: aload_1
    //   469: astore 4
    //   471: aload 15
    //   473: aload 22
    //   475: aload 5
    //   477: invokeinterface 42 3 0
    //   482: pop
    //   483: goto +3 -> 486
    //   486: aload_1
    //   487: astore 4
    //   489: aload 5
    //   491: aload 20
    //   493: invokeinterface 268 2 0
    //   498: pop
    //   499: goto +31 -> 530
    //   502: astore 5
    //   504: aload_1
    //   505: astore 4
    //   507: aload 13
    //   509: getfield 127	com/google/android/gms/measurement/internal/zzgr:zzs	Lcom/google/android/gms/measurement/internal/zzfy;
    //   512: invokevirtual 189	com/google/android/gms/measurement/internal/zzfy:zzay	()Lcom/google/android/gms/measurement/internal/zzeo;
    //   515: invokevirtual 194	com/google/android/gms/measurement/internal/zzeo:zzd	()Lcom/google/android/gms/measurement/internal/zzem;
    //   518: ldc -43
    //   520: aload 16
    //   522: invokestatic 200	com/google/android/gms/measurement/internal/zzeo:zzn	(Ljava/lang/String;)Ljava/lang/Object;
    //   525: aload 5
    //   527: invokevirtual 205	com/google/android/gms/measurement/internal/zzem:zzc	(Ljava/lang/String;Ljava/lang/Object;Ljava/lang/Object;)V
    //   530: aload_1
    //   531: astore 4
    //   533: aload_1
    //   534: invokeinterface 271 1 0
    //   539: istore 10
    //   541: iload 10
    //   543: ifne +12 -> 555
    //   546: aload_1
    //   547: invokeinterface 274 1 0
    //   552: goto +114 -> 666
    //   555: goto -184 -> 371
    //   558: aload_1
    //   559: astore 4
    //   561: invokestatic 211	java/util/Collections:emptyMap	()Ljava/util/Map;
    //   564: astore 5
    //   566: aload 5
    //   568: astore 4
    //   570: aload_1
    //   571: invokeinterface 274 1 0
    //   576: goto +86 -> 662
    //   579: astore_1
    //   580: goto +68 -> 648
    //   583: astore 5
    //   585: goto +14 -> 599
    //   588: astore_1
    //   589: aconst_null
    //   590: astore 4
    //   592: goto +56 -> 648
    //   595: astore 5
    //   597: aconst_null
    //   598: astore_1
    //   599: aload_1
    //   600: astore 4
    //   602: aload 13
    //   604: getfield 127	com/google/android/gms/measurement/internal/zzgr:zzs	Lcom/google/android/gms/measurement/internal/zzfy;
    //   607: invokevirtual 189	com/google/android/gms/measurement/internal/zzfy:zzay	()Lcom/google/android/gms/measurement/internal/zzeo;
    //   610: invokevirtual 194	com/google/android/gms/measurement/internal/zzeo:zzd	()Lcom/google/android/gms/measurement/internal/zzem;
    //   613: ldc -41
    //   615: aload 16
    //   617: invokestatic 200	com/google/android/gms/measurement/internal/zzeo:zzn	(Ljava/lang/String;)Ljava/lang/Object;
    //   620: aload 5
    //   622: invokevirtual 205	com/google/android/gms/measurement/internal/zzem:zzc	(Ljava/lang/String;Ljava/lang/Object;Ljava/lang/Object;)V
    //   625: aload_1
    //   626: astore 4
    //   628: invokestatic 211	java/util/Collections:emptyMap	()Ljava/util/Map;
    //   631: astore 5
    //   633: aload 5
    //   635: astore 4
    //   637: aload_1
    //   638: ifnull +24 -> 662
    //   641: aload 5
    //   643: astore 4
    //   645: goto -75 -> 570
    //   648: aload 4
    //   650: ifnull +10 -> 660
    //   653: aload 4
    //   655: invokeinterface 274 1 0
    //   660: aload_1
    //   661: athrow
    //   662: aload 4
    //   664: astore 15
    //   666: aload_0
    //   667: getfield 151	com/google/android/gms/measurement/internal/zzkm:zzf	Lcom/google/android/gms/measurement/internal/zzkz;
    //   670: invokevirtual 157	com/google/android/gms/measurement/internal/zzkz:zzi	()Lcom/google/android/gms/measurement/internal/zzam;
    //   673: astore 23
    //   675: aload_0
    //   676: getfield 35	com/google/android/gms/measurement/internal/zzaa:zza	Ljava/lang/String;
    //   679: astore 24
    //   681: aload 23
    //   683: invokevirtual 159	com/google/android/gms/measurement/internal/zzkn:zzW	()V
    //   686: aload 23
    //   688: invokevirtual 162	com/google/android/gms/measurement/internal/zzgr:zzg	()V
    //   691: aload 24
    //   693: invokestatic 71	com/google/android/gms/common/internal/Preconditions:checkNotEmpty	(Ljava/lang/String;)Ljava/lang/String;
    //   696: pop
    //   697: aload 23
    //   699: invokevirtual 175	com/google/android/gms/measurement/internal/zzam:zzh	()Landroid/database/sqlite/SQLiteDatabase;
    //   702: astore_1
    //   703: aload_1
    //   704: ldc_w 276
    //   707: iconst_2
    //   708: anewarray 114	java/lang/String
    //   711: dup
    //   712: iconst_0
    //   713: ldc -37
    //   715: aastore
    //   716: dup
    //   717: iconst_1
    //   718: ldc 65
    //   720: aastore
    //   721: ldc -33
    //   723: iconst_1
    //   724: anewarray 114	java/lang/String
    //   727: dup
    //   728: iconst_0
    //   729: aload 24
    //   731: aastore
    //   732: aconst_null
    //   733: aconst_null
    //   734: aconst_null
    //   735: invokevirtual 227	android/database/sqlite/SQLiteDatabase:query	(Ljava/lang/String;[Ljava/lang/String;Ljava/lang/String;[Ljava/lang/String;Ljava/lang/String;Ljava/lang/String;Ljava/lang/String;)Landroid/database/Cursor;
    //   738: astore 20
    //   740: aload 14
    //   742: astore 16
    //   744: aload 19
    //   746: astore 5
    //   748: aload 20
    //   750: astore 13
    //   752: aload 20
    //   754: invokeinterface 232 1 0
    //   759: ifne +37 -> 796
    //   762: aload 14
    //   764: astore 16
    //   766: aload 19
    //   768: astore 5
    //   770: aload 20
    //   772: astore 13
    //   774: invokestatic 211	java/util/Collections:emptyMap	()Ljava/util/Map;
    //   777: astore_1
    //   778: aload 20
    //   780: invokeinterface 274 1 0
    //   785: ldc -37
    //   787: astore 4
    //   789: ldc -39
    //   791: astore 5
    //   793: goto +354 -> 1147
    //   796: aload 14
    //   798: astore 16
    //   800: aload 19
    //   802: astore 5
    //   804: aload 20
    //   806: astore 13
    //   808: new 83	c/e/a
    //   811: dup
    //   812: invokespecial 84	c/e/a:<init>	()V
    //   815: astore 22
    //   817: aload 19
    //   819: astore_1
    //   820: aload 14
    //   822: astore 4
    //   824: aload 22
    //   826: astore 14
    //   828: aload 4
    //   830: astore 16
    //   832: aload_1
    //   833: astore 5
    //   835: aload 20
    //   837: astore 13
    //   839: aload 20
    //   841: iconst_0
    //   842: invokeinterface 262 2 0
    //   847: istore 7
    //   849: aload 4
    //   851: astore 16
    //   853: aload_1
    //   854: astore 5
    //   856: aload 20
    //   858: astore 13
    //   860: aload 20
    //   862: iconst_1
    //   863: invokeinterface 236 2 0
    //   868: astore 19
    //   870: aload 4
    //   872: astore 16
    //   874: aload_1
    //   875: astore 5
    //   877: aload 20
    //   879: astore 13
    //   881: invokestatic 281	com/google/android/gms/internal/measurement/zzgh:zzf	()Lcom/google/android/gms/internal/measurement/zzgg;
    //   884: aload 19
    //   886: invokestatic 247	com/google/android/gms/measurement/internal/zzlb:zzl	(Lcom/google/android/gms/internal/measurement/zzlk;[B)Lcom/google/android/gms/internal/measurement/zzlk;
    //   889: checkcast 283	com/google/android/gms/internal/measurement/zzgg
    //   892: invokevirtual 255	com/google/android/gms/internal/measurement/zzka:zzaE	()Lcom/google/android/gms/internal/measurement/zzke;
    //   895: checkcast 278	com/google/android/gms/internal/measurement/zzgh
    //   898: astore 19
    //   900: aload 4
    //   902: astore 16
    //   904: aload_1
    //   905: astore 5
    //   907: aload 20
    //   909: astore 13
    //   911: aload 14
    //   913: iload 7
    //   915: invokestatic 50	java/lang/Integer:valueOf	(I)Ljava/lang/Integer;
    //   918: aload 19
    //   920: invokeinterface 42 3 0
    //   925: pop
    //   926: goto +65 -> 991
    //   929: astore 19
    //   931: aload 4
    //   933: astore 16
    //   935: aload_1
    //   936: astore 5
    //   938: aload 20
    //   940: astore 13
    //   942: aload 23
    //   944: getfield 127	com/google/android/gms/measurement/internal/zzgr:zzs	Lcom/google/android/gms/measurement/internal/zzfy;
    //   947: invokevirtual 189	com/google/android/gms/measurement/internal/zzfy:zzay	()Lcom/google/android/gms/measurement/internal/zzeo;
    //   950: invokevirtual 194	com/google/android/gms/measurement/internal/zzeo:zzd	()Lcom/google/android/gms/measurement/internal/zzem;
    //   953: astore 22
    //   955: aload 4
    //   957: astore 5
    //   959: aload 20
    //   961: astore 13
    //   963: aload 24
    //   965: invokestatic 200	com/google/android/gms/measurement/internal/zzeo:zzn	(Ljava/lang/String;)Ljava/lang/Object;
    //   968: astore 16
    //   970: aload 20
    //   972: astore 13
    //   974: aload 22
    //   976: ldc_w 285
    //   979: aload 16
    //   981: iload 7
    //   983: invokestatic 50	java/lang/Integer:valueOf	(I)Ljava/lang/Integer;
    //   986: aload 19
    //   988: invokevirtual 288	com/google/android/gms/measurement/internal/zzem:zzd	(Ljava/lang/String;Ljava/lang/Object;Ljava/lang/Object;Ljava/lang/Object;)V
    //   991: aload_1
    //   992: astore 5
    //   994: aload 4
    //   996: astore 16
    //   998: aload 20
    //   1000: astore 13
    //   1002: aload 20
    //   1004: invokeinterface 271 1 0
    //   1009: istore 10
    //   1011: iload 10
    //   1013: ifne +20 -> 1033
    //   1016: aload 20
    //   1018: invokeinterface 274 1 0
    //   1023: aload 14
    //   1025: astore_1
    //   1026: aload 16
    //   1028: astore 4
    //   1030: goto +117 -> 1147
    //   1033: aload 16
    //   1035: astore 4
    //   1037: aload 5
    //   1039: astore_1
    //   1040: goto -212 -> 828
    //   1043: aload_1
    //   1044: astore 5
    //   1046: astore 14
    //   1048: aload 20
    //   1050: astore_1
    //   1051: goto +48 -> 1099
    //   1054: astore 14
    //   1056: aload 5
    //   1058: astore 4
    //   1060: goto +12 -> 1072
    //   1063: astore 14
    //   1065: aload 16
    //   1067: astore 4
    //   1069: aload 5
    //   1071: astore_1
    //   1072: aload_1
    //   1073: astore 5
    //   1075: aload 20
    //   1077: astore_1
    //   1078: goto +21 -> 1099
    //   1081: astore_1
    //   1082: aconst_null
    //   1083: astore_2
    //   1084: goto +3999 -> 5083
    //   1087: astore 14
    //   1089: ldc -37
    //   1091: astore 4
    //   1093: ldc -39
    //   1095: astore 5
    //   1097: aconst_null
    //   1098: astore_1
    //   1099: aload_1
    //   1100: astore 13
    //   1102: aload 23
    //   1104: getfield 127	com/google/android/gms/measurement/internal/zzgr:zzs	Lcom/google/android/gms/measurement/internal/zzfy;
    //   1107: invokevirtual 189	com/google/android/gms/measurement/internal/zzfy:zzay	()Lcom/google/android/gms/measurement/internal/zzeo;
    //   1110: invokevirtual 194	com/google/android/gms/measurement/internal/zzeo:zzd	()Lcom/google/android/gms/measurement/internal/zzem;
    //   1113: ldc_w 290
    //   1116: aload 24
    //   1118: invokestatic 200	com/google/android/gms/measurement/internal/zzeo:zzn	(Ljava/lang/String;)Ljava/lang/Object;
    //   1121: aload 14
    //   1123: invokevirtual 205	com/google/android/gms/measurement/internal/zzem:zzc	(Ljava/lang/String;Ljava/lang/Object;Ljava/lang/Object;)V
    //   1126: aload_1
    //   1127: astore 13
    //   1129: invokestatic 211	java/util/Collections:emptyMap	()Ljava/util/Map;
    //   1132: astore 14
    //   1134: aload_1
    //   1135: ifnull +9 -> 1144
    //   1138: aload_1
    //   1139: invokeinterface 274 1 0
    //   1144: aload 14
    //   1146: astore_1
    //   1147: aload_1
    //   1148: invokeinterface 293 1 0
    //   1153: ifeq +14 -> 1167
    //   1156: ldc -41
    //   1158: astore 18
    //   1160: ldc -43
    //   1162: astore 19
    //   1164: goto +1628 -> 2792
    //   1167: new 76	java/util/HashSet
    //   1170: dup
    //   1171: aload_1
    //   1172: invokeinterface 297 1 0
    //   1177: invokespecial 300	java/util/HashSet:<init>	(Ljava/util/Collection;)V
    //   1180: astore 22
    //   1182: iload 6
    //   1184: ifeq +909 -> 2093
    //   1187: aload_0
    //   1188: getfield 35	com/google/android/gms/measurement/internal/zzaa:zza	Ljava/lang/String;
    //   1191: astore 23
    //   1193: aload_0
    //   1194: getfield 151	com/google/android/gms/measurement/internal/zzkm:zzf	Lcom/google/android/gms/measurement/internal/zzkz;
    //   1197: invokevirtual 157	com/google/android/gms/measurement/internal/zzkz:zzi	()Lcom/google/android/gms/measurement/internal/zzam;
    //   1200: astore 24
    //   1202: aload_0
    //   1203: getfield 35	com/google/android/gms/measurement/internal/zzaa:zza	Ljava/lang/String;
    //   1206: astore 25
    //   1208: aload 24
    //   1210: invokevirtual 159	com/google/android/gms/measurement/internal/zzkn:zzW	()V
    //   1213: aload 24
    //   1215: invokevirtual 162	com/google/android/gms/measurement/internal/zzgr:zzg	()V
    //   1218: aload 25
    //   1220: invokestatic 71	com/google/android/gms/common/internal/Preconditions:checkNotEmpty	(Ljava/lang/String;)Ljava/lang/String;
    //   1223: pop
    //   1224: new 83	c/e/a
    //   1227: dup
    //   1228: invokespecial 84	c/e/a:<init>	()V
    //   1231: astore 19
    //   1233: aload 24
    //   1235: invokevirtual 175	com/google/android/gms/measurement/internal/zzam:zzh	()Landroid/database/sqlite/SQLiteDatabase;
    //   1238: astore 13
    //   1240: aload 13
    //   1242: ldc_w 302
    //   1245: iconst_2
    //   1246: anewarray 114	java/lang/String
    //   1249: dup
    //   1250: iconst_0
    //   1251: aload 25
    //   1253: aastore
    //   1254: dup
    //   1255: iconst_1
    //   1256: aload 25
    //   1258: aastore
    //   1259: invokevirtual 306	android/database/sqlite/SQLiteDatabase:rawQuery	(Ljava/lang/String;[Ljava/lang/String;)Landroid/database/Cursor;
    //   1262: astore 13
    //   1264: aload 13
    //   1266: astore 14
    //   1268: aload 13
    //   1270: invokeinterface 232 1 0
    //   1275: ifeq +131 -> 1406
    //   1278: aload 13
    //   1280: astore 14
    //   1282: aload 13
    //   1284: iconst_0
    //   1285: invokeinterface 262 2 0
    //   1290: invokestatic 50	java/lang/Integer:valueOf	(I)Ljava/lang/Integer;
    //   1293: astore 26
    //   1295: aload 13
    //   1297: astore 14
    //   1299: aload 19
    //   1301: aload 26
    //   1303: invokeinterface 31 2 0
    //   1308: checkcast 90	java/util/List
    //   1311: astore 20
    //   1313: aload 20
    //   1315: astore 16
    //   1317: aload 20
    //   1319: ifnonnull +32 -> 1351
    //   1322: aload 13
    //   1324: astore 14
    //   1326: new 264	java/util/ArrayList
    //   1329: dup
    //   1330: invokespecial 265	java/util/ArrayList:<init>	()V
    //   1333: astore 16
    //   1335: aload 13
    //   1337: astore 14
    //   1339: aload 19
    //   1341: aload 26
    //   1343: aload 16
    //   1345: invokeinterface 42 3 0
    //   1350: pop
    //   1351: aload 13
    //   1353: astore 14
    //   1355: aload 16
    //   1357: aload 13
    //   1359: iconst_1
    //   1360: invokeinterface 262 2 0
    //   1365: invokestatic 50	java/lang/Integer:valueOf	(I)Ljava/lang/Integer;
    //   1368: invokeinterface 268 2 0
    //   1373: pop
    //   1374: aload 13
    //   1376: astore 14
    //   1378: aload 13
    //   1380: invokeinterface 271 1 0
    //   1385: istore 10
    //   1387: iload 10
    //   1389: ifne -111 -> 1278
    //   1392: aload 19
    //   1394: astore 14
    //   1396: aload 13
    //   1398: invokeinterface 274 1 0
    //   1403: goto +93 -> 1496
    //   1406: aload 13
    //   1408: astore 14
    //   1410: invokestatic 211	java/util/Collections:emptyMap	()Ljava/util/Map;
    //   1413: astore 16
    //   1415: aload 16
    //   1417: astore 14
    //   1419: goto -23 -> 1396
    //   1422: astore_1
    //   1423: goto +656 -> 2079
    //   1426: astore 16
    //   1428: goto +15 -> 1443
    //   1431: astore_1
    //   1432: aconst_null
    //   1433: astore 14
    //   1435: goto +644 -> 2079
    //   1438: astore 16
    //   1440: aconst_null
    //   1441: astore 13
    //   1443: aload 13
    //   1445: astore 14
    //   1447: aload 24
    //   1449: getfield 127	com/google/android/gms/measurement/internal/zzgr:zzs	Lcom/google/android/gms/measurement/internal/zzfy;
    //   1452: invokevirtual 189	com/google/android/gms/measurement/internal/zzfy:zzay	()Lcom/google/android/gms/measurement/internal/zzeo;
    //   1455: invokevirtual 194	com/google/android/gms/measurement/internal/zzeo:zzd	()Lcom/google/android/gms/measurement/internal/zzem;
    //   1458: ldc_w 308
    //   1461: aload 25
    //   1463: invokestatic 200	com/google/android/gms/measurement/internal/zzeo:zzn	(Ljava/lang/String;)Ljava/lang/Object;
    //   1466: aload 16
    //   1468: invokevirtual 205	com/google/android/gms/measurement/internal/zzem:zzc	(Ljava/lang/String;Ljava/lang/Object;Ljava/lang/Object;)V
    //   1471: aload 13
    //   1473: astore 14
    //   1475: invokestatic 211	java/util/Collections:emptyMap	()Ljava/util/Map;
    //   1478: astore 16
    //   1480: aload 16
    //   1482: astore 14
    //   1484: aload 13
    //   1486: ifnull +10 -> 1496
    //   1489: aload 16
    //   1491: astore 14
    //   1493: goto -97 -> 1396
    //   1496: aload 23
    //   1498: invokestatic 71	com/google/android/gms/common/internal/Preconditions:checkNotEmpty	(Ljava/lang/String;)Ljava/lang/String;
    //   1501: pop
    //   1502: aload_1
    //   1503: invokestatic 74	com/google/android/gms/common/internal/Preconditions:checkNotNull	(Ljava/lang/Object;)Ljava/lang/Object;
    //   1506: pop
    //   1507: new 83	c/e/a
    //   1510: dup
    //   1511: invokespecial 84	c/e/a:<init>	()V
    //   1514: astore 19
    //   1516: aload_1
    //   1517: invokeinterface 293 1 0
    //   1522: ifeq +14 -> 1536
    //   1525: aload 18
    //   1527: astore 16
    //   1529: aload 16
    //   1531: astore 14
    //   1533: goto +539 -> 2072
    //   1536: aload_1
    //   1537: invokeinterface 297 1 0
    //   1542: invokeinterface 311 1 0
    //   1547: astore 16
    //   1549: aload 18
    //   1551: astore 13
    //   1553: aload 16
    //   1555: astore 18
    //   1557: aload 13
    //   1559: astore 16
    //   1561: aload 18
    //   1563: invokeinterface 100 1 0
    //   1568: ifeq -39 -> 1529
    //   1571: aload 18
    //   1573: invokeinterface 106 1 0
    //   1578: checkcast 46	java/lang/Integer
    //   1581: invokevirtual 315	java/lang/Integer:intValue	()I
    //   1584: istore 7
    //   1586: iload 7
    //   1588: invokestatic 50	java/lang/Integer:valueOf	(I)Ljava/lang/Integer;
    //   1591: astore 16
    //   1593: aload_1
    //   1594: aload 16
    //   1596: invokeinterface 31 2 0
    //   1601: checkcast 278	com/google/android/gms/internal/measurement/zzgh
    //   1604: astore 24
    //   1606: aload 14
    //   1608: aload 16
    //   1610: invokeinterface 31 2 0
    //   1615: checkcast 90	java/util/List
    //   1618: astore 20
    //   1620: aload 20
    //   1622: ifnull +435 -> 2057
    //   1625: aload 20
    //   1627: invokeinterface 316 1 0
    //   1632: ifeq +6 -> 1638
    //   1635: goto +422 -> 2057
    //   1638: aload_0
    //   1639: getfield 151	com/google/android/gms/measurement/internal/zzkm:zzf	Lcom/google/android/gms/measurement/internal/zzkz;
    //   1642: invokevirtual 320	com/google/android/gms/measurement/internal/zzkz:zzu	()Lcom/google/android/gms/measurement/internal/zzlb;
    //   1645: aload 24
    //   1647: invokevirtual 324	com/google/android/gms/internal/measurement/zzgh:zzk	()Ljava/util/List;
    //   1650: aload 20
    //   1652: invokevirtual 328	com/google/android/gms/measurement/internal/zzlb:zzq	(Ljava/util/List;Ljava/util/List;)Ljava/util/List;
    //   1655: astore 16
    //   1657: aload 16
    //   1659: invokeinterface 316 1 0
    //   1664: ifne +390 -> 2054
    //   1667: aload 24
    //   1669: invokevirtual 334	com/google/android/gms/internal/measurement/zzke:zzby	()Lcom/google/android/gms/internal/measurement/zzka;
    //   1672: checkcast 283	com/google/android/gms/internal/measurement/zzgg
    //   1675: astore 23
    //   1677: aload 23
    //   1679: invokevirtual 335	com/google/android/gms/internal/measurement/zzgg:zzf	()Lcom/google/android/gms/internal/measurement/zzgg;
    //   1682: pop
    //   1683: aload 23
    //   1685: aload 16
    //   1687: invokevirtual 338	com/google/android/gms/internal/measurement/zzgg:zzb	(Ljava/lang/Iterable;)Lcom/google/android/gms/internal/measurement/zzgg;
    //   1690: pop
    //   1691: aload_0
    //   1692: getfield 151	com/google/android/gms/measurement/internal/zzkm:zzf	Lcom/google/android/gms/measurement/internal/zzkz;
    //   1695: invokevirtual 320	com/google/android/gms/measurement/internal/zzkz:zzu	()Lcom/google/android/gms/measurement/internal/zzlb;
    //   1698: aload 24
    //   1700: invokevirtual 340	com/google/android/gms/internal/measurement/zzgh:zzn	()Ljava/util/List;
    //   1703: aload 20
    //   1705: invokevirtual 328	com/google/android/gms/measurement/internal/zzlb:zzq	(Ljava/util/List;Ljava/util/List;)Ljava/util/List;
    //   1708: astore 16
    //   1710: aload 23
    //   1712: invokevirtual 342	com/google/android/gms/internal/measurement/zzgg:zzh	()Lcom/google/android/gms/internal/measurement/zzgg;
    //   1715: pop
    //   1716: aload 23
    //   1718: aload 16
    //   1720: invokevirtual 344	com/google/android/gms/internal/measurement/zzgg:zzd	(Ljava/lang/Iterable;)Lcom/google/android/gms/internal/measurement/zzgg;
    //   1723: pop
    //   1724: invokestatic 347	com/google/android/gms/internal/measurement/zzob:zzc	()Z
    //   1727: pop
    //   1728: aload_0
    //   1729: getfield 127	com/google/android/gms/measurement/internal/zzgr:zzs	Lcom/google/android/gms/measurement/internal/zzfy;
    //   1732: invokevirtual 132	com/google/android/gms/measurement/internal/zzfy:zzf	()Lcom/google/android/gms/measurement/internal/zzag;
    //   1735: aconst_null
    //   1736: getstatic 350	com/google/android/gms/measurement/internal/zzeb:zzaA	Lcom/google/android/gms/measurement/internal/zzea;
    //   1739: invokevirtual 143	com/google/android/gms/measurement/internal/zzag:zzs	(Ljava/lang/String;Lcom/google/android/gms/measurement/internal/zzea;)Z
    //   1742: ifeq +182 -> 1924
    //   1745: new 264	java/util/ArrayList
    //   1748: dup
    //   1749: invokespecial 265	java/util/ArrayList:<init>	()V
    //   1752: astore 25
    //   1754: aload 24
    //   1756: invokevirtual 353	com/google/android/gms/internal/measurement/zzgh:zzj	()Ljava/util/List;
    //   1759: invokeinterface 94 1 0
    //   1764: astore 16
    //   1766: aload 16
    //   1768: invokeinterface 100 1 0
    //   1773: ifeq +46 -> 1819
    //   1776: aload 16
    //   1778: invokeinterface 106 1 0
    //   1783: checkcast 355	com/google/android/gms/internal/measurement/zzfq
    //   1786: astore 26
    //   1788: aload 20
    //   1790: aload 26
    //   1792: invokevirtual 357	com/google/android/gms/internal/measurement/zzfq:zza	()I
    //   1795: invokestatic 50	java/lang/Integer:valueOf	(I)Ljava/lang/Integer;
    //   1798: invokeinterface 360 2 0
    //   1803: ifne +13 -> 1816
    //   1806: aload 25
    //   1808: aload 26
    //   1810: invokeinterface 268 2 0
    //   1815: pop
    //   1816: goto -50 -> 1766
    //   1819: aload 23
    //   1821: invokevirtual 362	com/google/android/gms/internal/measurement/zzgg:zze	()Lcom/google/android/gms/internal/measurement/zzgg;
    //   1824: pop
    //   1825: aload 23
    //   1827: aload 25
    //   1829: invokevirtual 364	com/google/android/gms/internal/measurement/zzgg:zza	(Ljava/lang/Iterable;)Lcom/google/android/gms/internal/measurement/zzgg;
    //   1832: pop
    //   1833: new 264	java/util/ArrayList
    //   1836: dup
    //   1837: invokespecial 265	java/util/ArrayList:<init>	()V
    //   1840: astore 16
    //   1842: aload 24
    //   1844: invokevirtual 367	com/google/android/gms/internal/measurement/zzgh:zzm	()Ljava/util/List;
    //   1847: invokeinterface 94 1 0
    //   1852: astore 24
    //   1854: aload 24
    //   1856: invokeinterface 100 1 0
    //   1861: ifeq +46 -> 1907
    //   1864: aload 24
    //   1866: invokeinterface 106 1 0
    //   1871: checkcast 369	com/google/android/gms/internal/measurement/zzgj
    //   1874: astore 25
    //   1876: aload 20
    //   1878: aload 25
    //   1880: invokevirtual 371	com/google/android/gms/internal/measurement/zzgj:zzb	()I
    //   1883: invokestatic 50	java/lang/Integer:valueOf	(I)Ljava/lang/Integer;
    //   1886: invokeinterface 360 2 0
    //   1891: ifne -37 -> 1854
    //   1894: aload 16
    //   1896: aload 25
    //   1898: invokeinterface 268 2 0
    //   1903: pop
    //   1904: goto -50 -> 1854
    //   1907: aload 23
    //   1909: invokevirtual 373	com/google/android/gms/internal/measurement/zzgg:zzg	()Lcom/google/android/gms/internal/measurement/zzgg;
    //   1912: pop
    //   1913: aload 23
    //   1915: aload 16
    //   1917: invokevirtual 375	com/google/android/gms/internal/measurement/zzgg:zzc	(Ljava/lang/Iterable;)Lcom/google/android/gms/internal/measurement/zzgg;
    //   1920: pop
    //   1921: goto +109 -> 2030
    //   1924: iconst_0
    //   1925: istore 6
    //   1927: iload 6
    //   1929: aload 24
    //   1931: invokevirtual 376	com/google/android/gms/internal/measurement/zzgh:zza	()I
    //   1934: if_icmpge +43 -> 1977
    //   1937: aload 20
    //   1939: aload 24
    //   1941: iload 6
    //   1943: invokevirtual 379	com/google/android/gms/internal/measurement/zzgh:zze	(I)Lcom/google/android/gms/internal/measurement/zzfq;
    //   1946: invokevirtual 357	com/google/android/gms/internal/measurement/zzfq:zza	()I
    //   1949: invokestatic 50	java/lang/Integer:valueOf	(I)Ljava/lang/Integer;
    //   1952: invokeinterface 360 2 0
    //   1957: ifeq +11 -> 1968
    //   1960: aload 23
    //   1962: iload 6
    //   1964: invokevirtual 382	com/google/android/gms/internal/measurement/zzgg:zzi	(I)Lcom/google/android/gms/internal/measurement/zzgg;
    //   1967: pop
    //   1968: iload 6
    //   1970: iconst_1
    //   1971: iadd
    //   1972: istore 6
    //   1974: goto -47 -> 1927
    //   1977: iconst_0
    //   1978: istore 6
    //   1980: iload 6
    //   1982: aload 24
    //   1984: invokevirtual 384	com/google/android/gms/internal/measurement/zzgh:zzc	()I
    //   1987: if_icmpge +43 -> 2030
    //   1990: aload 20
    //   1992: aload 24
    //   1994: iload 6
    //   1996: invokevirtual 387	com/google/android/gms/internal/measurement/zzgh:zzi	(I)Lcom/google/android/gms/internal/measurement/zzgj;
    //   1999: invokevirtual 371	com/google/android/gms/internal/measurement/zzgj:zzb	()I
    //   2002: invokestatic 50	java/lang/Integer:valueOf	(I)Ljava/lang/Integer;
    //   2005: invokeinterface 360 2 0
    //   2010: ifeq +11 -> 2021
    //   2013: aload 23
    //   2015: iload 6
    //   2017: invokevirtual 389	com/google/android/gms/internal/measurement/zzgg:zzj	(I)Lcom/google/android/gms/internal/measurement/zzgg;
    //   2020: pop
    //   2021: iload 6
    //   2023: iconst_1
    //   2024: iadd
    //   2025: istore 6
    //   2027: goto -47 -> 1980
    //   2030: aload 19
    //   2032: iload 7
    //   2034: invokestatic 50	java/lang/Integer:valueOf	(I)Ljava/lang/Integer;
    //   2037: aload 23
    //   2039: invokevirtual 255	com/google/android/gms/internal/measurement/zzka:zzaE	()Lcom/google/android/gms/internal/measurement/zzke;
    //   2042: checkcast 278	com/google/android/gms/internal/measurement/zzgh
    //   2045: invokeinterface 42 3 0
    //   2050: pop
    //   2051: goto +18 -> 2069
    //   2054: goto -497 -> 1557
    //   2057: aload 19
    //   2059: aload 16
    //   2061: aload 24
    //   2063: invokeinterface 42 3 0
    //   2068: pop
    //   2069: goto -512 -> 1557
    //   2072: aload 19
    //   2074: astore 13
    //   2076: goto +24 -> 2100
    //   2079: aload 14
    //   2081: ifnull +10 -> 2091
    //   2084: aload 14
    //   2086: invokeinterface 274 1 0
    //   2091: aload_1
    //   2092: athrow
    //   2093: ldc -41
    //   2095: astore 14
    //   2097: aload_1
    //   2098: astore 13
    //   2100: aload 22
    //   2102: invokeinterface 311 1 0
    //   2107: astore 19
    //   2109: aload_1
    //   2110: astore 16
    //   2112: aload 15
    //   2114: astore 18
    //   2116: aload 21
    //   2118: astore_1
    //   2119: aload 19
    //   2121: invokeinterface 100 1 0
    //   2126: ifeq +659 -> 2785
    //   2129: aload 19
    //   2131: invokeinterface 106 1 0
    //   2136: checkcast 46	java/lang/Integer
    //   2139: invokevirtual 315	java/lang/Integer:intValue	()I
    //   2142: istore 7
    //   2144: aload 13
    //   2146: iload 7
    //   2148: invokestatic 50	java/lang/Integer:valueOf	(I)Ljava/lang/Integer;
    //   2151: invokeinterface 31 2 0
    //   2156: checkcast 278	com/google/android/gms/internal/measurement/zzgh
    //   2159: astore 24
    //   2161: new 55	java/util/BitSet
    //   2164: dup
    //   2165: invokespecial 390	java/util/BitSet:<init>	()V
    //   2168: astore 20
    //   2170: new 55	java/util/BitSet
    //   2173: dup
    //   2174: invokespecial 390	java/util/BitSet:<init>	()V
    //   2177: astore 21
    //   2179: new 83	c/e/a
    //   2182: dup
    //   2183: invokespecial 84	c/e/a:<init>	()V
    //   2186: astore 22
    //   2188: aload 24
    //   2190: ifnull +105 -> 2295
    //   2193: aload 24
    //   2195: invokevirtual 376	com/google/android/gms/internal/measurement/zzgh:zza	()I
    //   2198: ifne +6 -> 2204
    //   2201: goto +94 -> 2295
    //   2204: aload 24
    //   2206: invokevirtual 353	com/google/android/gms/internal/measurement/zzgh:zzj	()Ljava/util/List;
    //   2209: invokeinterface 94 1 0
    //   2214: astore 23
    //   2216: aload 23
    //   2218: invokeinterface 100 1 0
    //   2223: ifeq +72 -> 2295
    //   2226: aload 23
    //   2228: invokeinterface 106 1 0
    //   2233: checkcast 355	com/google/android/gms/internal/measurement/zzfq
    //   2236: astore 15
    //   2238: aload 15
    //   2240: invokevirtual 392	com/google/android/gms/internal/measurement/zzfq:zzh	()Z
    //   2243: ifeq -27 -> 2216
    //   2246: aload 15
    //   2248: invokevirtual 357	com/google/android/gms/internal/measurement/zzfq:zza	()I
    //   2251: istore 6
    //   2253: aload 15
    //   2255: invokevirtual 394	com/google/android/gms/internal/measurement/zzfq:zzg	()Z
    //   2258: ifeq +16 -> 2274
    //   2261: aload 15
    //   2263: invokevirtual 397	com/google/android/gms/internal/measurement/zzfq:zzb	()J
    //   2266: invokestatic 402	java/lang/Long:valueOf	(J)Ljava/lang/Long;
    //   2269: astore 15
    //   2271: goto +6 -> 2277
    //   2274: aconst_null
    //   2275: astore 15
    //   2277: aload 22
    //   2279: iload 6
    //   2281: invokestatic 50	java/lang/Integer:valueOf	(I)Ljava/lang/Integer;
    //   2284: aload 15
    //   2286: invokeinterface 42 3 0
    //   2291: pop
    //   2292: goto -76 -> 2216
    //   2295: new 83	c/e/a
    //   2298: dup
    //   2299: invokespecial 84	c/e/a:<init>	()V
    //   2302: astore 23
    //   2304: aload 13
    //   2306: astore 15
    //   2308: aload 24
    //   2310: ifnull +106 -> 2416
    //   2313: aload 24
    //   2315: invokevirtual 384	com/google/android/gms/internal/measurement/zzgh:zzc	()I
    //   2318: ifne +10 -> 2328
    //   2321: aload 13
    //   2323: astore 15
    //   2325: goto +91 -> 2416
    //   2328: aload 24
    //   2330: invokevirtual 367	com/google/android/gms/internal/measurement/zzgh:zzm	()Ljava/util/List;
    //   2333: invokeinterface 94 1 0
    //   2338: astore 25
    //   2340: aload 13
    //   2342: astore 15
    //   2344: aload 25
    //   2346: invokeinterface 100 1 0
    //   2351: ifeq +65 -> 2416
    //   2354: aload 25
    //   2356: invokeinterface 106 1 0
    //   2361: checkcast 369	com/google/android/gms/internal/measurement/zzgj
    //   2364: astore 15
    //   2366: aload 15
    //   2368: invokevirtual 404	com/google/android/gms/internal/measurement/zzgj:zzi	()Z
    //   2371: ifeq -31 -> 2340
    //   2374: aload 15
    //   2376: invokevirtual 405	com/google/android/gms/internal/measurement/zzgj:zza	()I
    //   2379: ifle -39 -> 2340
    //   2382: aload 23
    //   2384: aload 15
    //   2386: invokevirtual 371	com/google/android/gms/internal/measurement/zzgj:zzb	()I
    //   2389: invokestatic 50	java/lang/Integer:valueOf	(I)Ljava/lang/Integer;
    //   2392: aload 15
    //   2394: aload 15
    //   2396: invokevirtual 405	com/google/android/gms/internal/measurement/zzgj:zza	()I
    //   2399: iconst_1
    //   2400: isub
    //   2401: invokevirtual 408	com/google/android/gms/internal/measurement/zzgj:zzc	(I)J
    //   2404: invokestatic 402	java/lang/Long:valueOf	(J)Ljava/lang/Long;
    //   2407: invokeinterface 42 3 0
    //   2412: pop
    //   2413: goto -73 -> 2340
    //   2416: aload_1
    //   2417: astore 13
    //   2419: aload 24
    //   2421: ifnull +113 -> 2534
    //   2424: iconst_0
    //   2425: istore 6
    //   2427: aload_1
    //   2428: astore 13
    //   2430: iload 6
    //   2432: aload 24
    //   2434: invokevirtual 410	com/google/android/gms/internal/measurement/zzgh:zzd	()I
    //   2437: bipush 64
    //   2439: imul
    //   2440: if_icmpge +94 -> 2534
    //   2443: aload 24
    //   2445: invokevirtual 340	com/google/android/gms/internal/measurement/zzgh:zzn	()Ljava/util/List;
    //   2448: iload 6
    //   2450: invokestatic 414	com/google/android/gms/measurement/internal/zzlb:zzv	(Ljava/util/List;I)Z
    //   2453: ifeq +59 -> 2512
    //   2456: aload_0
    //   2457: getfield 127	com/google/android/gms/measurement/internal/zzgr:zzs	Lcom/google/android/gms/measurement/internal/zzfy;
    //   2460: invokevirtual 189	com/google/android/gms/measurement/internal/zzfy:zzay	()Lcom/google/android/gms/measurement/internal/zzeo;
    //   2463: invokevirtual 416	com/google/android/gms/measurement/internal/zzeo:zzj	()Lcom/google/android/gms/measurement/internal/zzem;
    //   2466: ldc_w 418
    //   2469: iload 7
    //   2471: invokestatic 50	java/lang/Integer:valueOf	(I)Ljava/lang/Integer;
    //   2474: iload 6
    //   2476: invokestatic 50	java/lang/Integer:valueOf	(I)Ljava/lang/Integer;
    //   2479: invokevirtual 205	com/google/android/gms/measurement/internal/zzem:zzc	(Ljava/lang/String;Ljava/lang/Object;Ljava/lang/Object;)V
    //   2482: aload 21
    //   2484: iload 6
    //   2486: invokevirtual 422	java/util/BitSet:set	(I)V
    //   2489: aload 24
    //   2491: invokevirtual 324	com/google/android/gms/internal/measurement/zzgh:zzk	()Ljava/util/List;
    //   2494: iload 6
    //   2496: invokestatic 414	com/google/android/gms/measurement/internal/zzlb:zzv	(Ljava/util/List;I)Z
    //   2499: ifeq +13 -> 2512
    //   2502: aload 20
    //   2504: iload 6
    //   2506: invokevirtual 422	java/util/BitSet:set	(I)V
    //   2509: goto +16 -> 2525
    //   2512: aload 22
    //   2514: iload 6
    //   2516: invokestatic 50	java/lang/Integer:valueOf	(I)Ljava/lang/Integer;
    //   2519: invokeinterface 425 2 0
    //   2524: pop
    //   2525: iload 6
    //   2527: iconst_1
    //   2528: iadd
    //   2529: istore 6
    //   2531: goto -104 -> 2427
    //   2534: iload 7
    //   2536: invokestatic 50	java/lang/Integer:valueOf	(I)Ljava/lang/Integer;
    //   2539: astore 24
    //   2541: aload 16
    //   2543: aload 24
    //   2545: invokeinterface 31 2 0
    //   2550: checkcast 278	com/google/android/gms/internal/measurement/zzgh
    //   2553: astore_1
    //   2554: iload 9
    //   2556: ifeq +180 -> 2736
    //   2559: iload 8
    //   2561: ifeq +175 -> 2736
    //   2564: aload 18
    //   2566: aload 24
    //   2568: invokeinterface 31 2 0
    //   2573: checkcast 90	java/util/List
    //   2576: astore 24
    //   2578: aload 24
    //   2580: ifnull +156 -> 2736
    //   2583: aload_0
    //   2584: getfield 88	com/google/android/gms/measurement/internal/zzaa:zze	Ljava/lang/Long;
    //   2587: ifnull +149 -> 2736
    //   2590: aload_0
    //   2591: getfield 86	com/google/android/gms/measurement/internal/zzaa:zzd	Ljava/lang/Long;
    //   2594: ifnonnull +6 -> 2600
    //   2597: goto +139 -> 2736
    //   2600: aload 24
    //   2602: invokeinterface 94 1 0
    //   2607: astore 24
    //   2609: aload 24
    //   2611: invokeinterface 100 1 0
    //   2616: ifeq +120 -> 2736
    //   2619: aload 24
    //   2621: invokeinterface 106 1 0
    //   2626: checkcast 238	com/google/android/gms/internal/measurement/zzej
    //   2629: astore 25
    //   2631: aload 25
    //   2633: invokevirtual 426	com/google/android/gms/internal/measurement/zzej:zzb	()I
    //   2636: istore 6
    //   2638: aload_0
    //   2639: getfield 88	com/google/android/gms/measurement/internal/zzaa:zze	Ljava/lang/Long;
    //   2642: invokevirtual 429	java/lang/Long:longValue	()J
    //   2645: ldc2_w 430
    //   2648: ldiv
    //   2649: lstore 11
    //   2651: aload 25
    //   2653: invokevirtual 433	com/google/android/gms/internal/measurement/zzej:zzm	()Z
    //   2656: ifeq +16 -> 2672
    //   2659: aload_0
    //   2660: getfield 86	com/google/android/gms/measurement/internal/zzaa:zzd	Ljava/lang/Long;
    //   2663: invokevirtual 429	java/lang/Long:longValue	()J
    //   2666: ldc2_w 430
    //   2669: ldiv
    //   2670: lstore 11
    //   2672: iload 6
    //   2674: invokestatic 50	java/lang/Integer:valueOf	(I)Ljava/lang/Integer;
    //   2677: astore 25
    //   2679: aload 22
    //   2681: aload 25
    //   2683: invokeinterface 27 2 0
    //   2688: ifeq +18 -> 2706
    //   2691: aload 22
    //   2693: aload 25
    //   2695: lload 11
    //   2697: invokestatic 402	java/lang/Long:valueOf	(J)Ljava/lang/Long;
    //   2700: invokeinterface 42 3 0
    //   2705: pop
    //   2706: aload 23
    //   2708: aload 25
    //   2710: invokeinterface 27 2 0
    //   2715: ifeq -106 -> 2609
    //   2718: aload 23
    //   2720: aload 25
    //   2722: lload 11
    //   2724: invokestatic 402	java/lang/Long:valueOf	(J)Ljava/lang/Long;
    //   2727: invokeinterface 42 3 0
    //   2732: pop
    //   2733: goto -124 -> 2609
    //   2736: new 33	com/google/android/gms/measurement/internal/zzu
    //   2739: dup
    //   2740: aload_0
    //   2741: aload_0
    //   2742: getfield 35	com/google/android/gms/measurement/internal/zzaa:zza	Ljava/lang/String;
    //   2745: aload_1
    //   2746: aload 20
    //   2748: aload 21
    //   2750: aload 22
    //   2752: aload 23
    //   2754: aconst_null
    //   2755: invokespecial 436	com/google/android/gms/measurement/internal/zzu:<init>	(Lcom/google/android/gms/measurement/internal/zzaa;Ljava/lang/String;Lcom/google/android/gms/internal/measurement/zzgh;Ljava/util/BitSet;Ljava/util/BitSet;Ljava/util/Map;Ljava/util/Map;Lcom/google/android/gms/measurement/internal/zzt;)V
    //   2758: astore_1
    //   2759: aload_0
    //   2760: getfield 21	com/google/android/gms/measurement/internal/zzaa:zzc	Ljava/util/Map;
    //   2763: iload 7
    //   2765: invokestatic 50	java/lang/Integer:valueOf	(I)Ljava/lang/Integer;
    //   2768: aload_1
    //   2769: invokeinterface 42 3 0
    //   2774: pop
    //   2775: aload 13
    //   2777: astore_1
    //   2778: aload 15
    //   2780: astore 13
    //   2782: goto -663 -> 2119
    //   2785: aload_1
    //   2786: astore 19
    //   2788: aload 14
    //   2790: astore 18
    //   2792: aload 4
    //   2794: astore_1
    //   2795: aload_2
    //   2796: invokeinterface 316 1 0
    //   2801: ifeq +17 -> 2818
    //   2804: aload 5
    //   2806: astore_2
    //   2807: aload 17
    //   2809: astore 13
    //   2811: aload 13
    //   2813: astore 14
    //   2815: goto +1022 -> 3837
    //   2818: new 438	com/google/android/gms/measurement/internal/zzw
    //   2821: dup
    //   2822: aload_0
    //   2823: aconst_null
    //   2824: invokespecial 441	com/google/android/gms/measurement/internal/zzw:<init>	(Lcom/google/android/gms/measurement/internal/zzaa;Lcom/google/android/gms/measurement/internal/zzv;)V
    //   2827: astore 20
    //   2829: new 83	c/e/a
    //   2832: dup
    //   2833: invokespecial 84	c/e/a:<init>	()V
    //   2836: astore 23
    //   2838: aload_2
    //   2839: invokeinterface 94 1 0
    //   2844: astore_2
    //   2845: aload_1
    //   2846: astore 4
    //   2848: aload 17
    //   2850: astore 15
    //   2852: aload_2
    //   2853: astore 17
    //   2855: aload 15
    //   2857: astore 13
    //   2859: aload 4
    //   2861: astore_1
    //   2862: aload 5
    //   2864: astore_2
    //   2865: aload 17
    //   2867: invokeinterface 100 1 0
    //   2872: ifeq -61 -> 2811
    //   2875: aload 17
    //   2877: invokeinterface 106 1 0
    //   2882: checkcast 108	com/google/android/gms/internal/measurement/zzfs
    //   2885: astore_1
    //   2886: aload 20
    //   2888: aload_0
    //   2889: getfield 35	com/google/android/gms/measurement/internal/zzaa:zza	Ljava/lang/String;
    //   2892: aload_1
    //   2893: invokevirtual 444	com/google/android/gms/measurement/internal/zzw:zza	(Ljava/lang/String;Lcom/google/android/gms/internal/measurement/zzfs;)Lcom/google/android/gms/internal/measurement/zzfs;
    //   2896: astore 24
    //   2898: aload 24
    //   2900: ifnull -45 -> 2855
    //   2903: aload_0
    //   2904: getfield 151	com/google/android/gms/measurement/internal/zzkm:zzf	Lcom/google/android/gms/measurement/internal/zzkz;
    //   2907: invokevirtual 157	com/google/android/gms/measurement/internal/zzkz:zzi	()Lcom/google/android/gms/measurement/internal/zzam;
    //   2910: astore_2
    //   2911: aload_0
    //   2912: getfield 35	com/google/android/gms/measurement/internal/zzaa:zza	Ljava/lang/String;
    //   2915: astore 13
    //   2917: aload 24
    //   2919: invokevirtual 112	com/google/android/gms/internal/measurement/zzfs:zzh	()Ljava/lang/String;
    //   2922: astore 14
    //   2924: aload_2
    //   2925: aload 13
    //   2927: aload_1
    //   2928: invokevirtual 112	com/google/android/gms/internal/measurement/zzfs:zzh	()Ljava/lang/String;
    //   2931: invokevirtual 447	com/google/android/gms/measurement/internal/zzam:zzn	(Ljava/lang/String;Ljava/lang/String;)Lcom/google/android/gms/measurement/internal/zzas;
    //   2934: astore 16
    //   2936: aload 16
    //   2938: ifnonnull +65 -> 3003
    //   2941: aload_2
    //   2942: getfield 127	com/google/android/gms/measurement/internal/zzgr:zzs	Lcom/google/android/gms/measurement/internal/zzfy;
    //   2945: invokevirtual 189	com/google/android/gms/measurement/internal/zzfy:zzay	()Lcom/google/android/gms/measurement/internal/zzeo;
    //   2948: invokevirtual 449	com/google/android/gms/measurement/internal/zzeo:zzk	()Lcom/google/android/gms/measurement/internal/zzem;
    //   2951: ldc_w 451
    //   2954: aload 13
    //   2956: invokestatic 200	com/google/android/gms/measurement/internal/zzeo:zzn	(Ljava/lang/String;)Ljava/lang/Object;
    //   2959: aload_2
    //   2960: getfield 127	com/google/android/gms/measurement/internal/zzgr:zzs	Lcom/google/android/gms/measurement/internal/zzfy;
    //   2963: invokevirtual 454	com/google/android/gms/measurement/internal/zzfy:zzj	()Lcom/google/android/gms/measurement/internal/zzej;
    //   2966: aload 14
    //   2968: invokevirtual 458	com/google/android/gms/measurement/internal/zzej:zzd	(Ljava/lang/String;)Ljava/lang/String;
    //   2971: invokevirtual 205	com/google/android/gms/measurement/internal/zzem:zzc	(Ljava/lang/String;Ljava/lang/Object;Ljava/lang/Object;)V
    //   2974: new 460	com/google/android/gms/measurement/internal/zzas
    //   2977: dup
    //   2978: aload 13
    //   2980: aload_1
    //   2981: invokevirtual 112	com/google/android/gms/internal/measurement/zzfs:zzh	()Ljava/lang/String;
    //   2984: lconst_1
    //   2985: lconst_1
    //   2986: lconst_1
    //   2987: aload_1
    //   2988: invokevirtual 462	com/google/android/gms/internal/measurement/zzfs:zzd	()J
    //   2991: lconst_0
    //   2992: aconst_null
    //   2993: aconst_null
    //   2994: aconst_null
    //   2995: aconst_null
    //   2996: invokespecial 465	com/google/android/gms/measurement/internal/zzas:<init>	(Ljava/lang/String;Ljava/lang/String;JJJJJLjava/lang/Long;Ljava/lang/Long;Ljava/lang/Long;Ljava/lang/Boolean;)V
    //   2999: astore_1
    //   3000: goto +72 -> 3072
    //   3003: new 460	com/google/android/gms/measurement/internal/zzas
    //   3006: dup
    //   3007: aload 16
    //   3009: getfield 466	com/google/android/gms/measurement/internal/zzas:zza	Ljava/lang/String;
    //   3012: aload 16
    //   3014: getfield 468	com/google/android/gms/measurement/internal/zzas:zzb	Ljava/lang/String;
    //   3017: aload 16
    //   3019: getfield 471	com/google/android/gms/measurement/internal/zzas:zzc	J
    //   3022: lconst_1
    //   3023: ladd
    //   3024: aload 16
    //   3026: getfield 473	com/google/android/gms/measurement/internal/zzas:zzd	J
    //   3029: lconst_1
    //   3030: ladd
    //   3031: aload 16
    //   3033: getfield 475	com/google/android/gms/measurement/internal/zzas:zze	J
    //   3036: lconst_1
    //   3037: ladd
    //   3038: aload 16
    //   3040: getfield 477	com/google/android/gms/measurement/internal/zzas:zzf	J
    //   3043: aload 16
    //   3045: getfield 479	com/google/android/gms/measurement/internal/zzas:zzg	J
    //   3048: aload 16
    //   3050: getfield 481	com/google/android/gms/measurement/internal/zzas:zzh	Ljava/lang/Long;
    //   3053: aload 16
    //   3055: getfield 483	com/google/android/gms/measurement/internal/zzas:zzi	Ljava/lang/Long;
    //   3058: aload 16
    //   3060: getfield 485	com/google/android/gms/measurement/internal/zzas:zzj	Ljava/lang/Long;
    //   3063: aload 16
    //   3065: getfield 488	com/google/android/gms/measurement/internal/zzas:zzk	Ljava/lang/Boolean;
    //   3068: invokespecial 465	com/google/android/gms/measurement/internal/zzas:<init>	(Ljava/lang/String;Ljava/lang/String;JJJJJLjava/lang/Long;Ljava/lang/Long;Ljava/lang/Long;Ljava/lang/Boolean;)V
    //   3071: astore_1
    //   3072: aload_0
    //   3073: getfield 151	com/google/android/gms/measurement/internal/zzkm:zzf	Lcom/google/android/gms/measurement/internal/zzkz;
    //   3076: invokevirtual 157	com/google/android/gms/measurement/internal/zzkz:zzi	()Lcom/google/android/gms/measurement/internal/zzam;
    //   3079: aload_1
    //   3080: invokevirtual 492	com/google/android/gms/measurement/internal/zzam:zzE	(Lcom/google/android/gms/measurement/internal/zzas;)V
    //   3083: aload_1
    //   3084: getfield 471	com/google/android/gms/measurement/internal/zzas:zzc	J
    //   3087: lstore 11
    //   3089: aload 24
    //   3091: invokevirtual 112	com/google/android/gms/internal/measurement/zzfs:zzh	()Ljava/lang/String;
    //   3094: astore 25
    //   3096: aload 23
    //   3098: aload 25
    //   3100: invokeinterface 31 2 0
    //   3105: checkcast 23	java/util/Map
    //   3108: astore 13
    //   3110: aload 13
    //   3112: ifnonnull +488 -> 3600
    //   3115: aload_0
    //   3116: getfield 151	com/google/android/gms/measurement/internal/zzkm:zzf	Lcom/google/android/gms/measurement/internal/zzkz;
    //   3119: invokevirtual 157	com/google/android/gms/measurement/internal/zzkz:zzi	()Lcom/google/android/gms/measurement/internal/zzam;
    //   3122: astore 26
    //   3124: aload_0
    //   3125: getfield 35	com/google/android/gms/measurement/internal/zzaa:zza	Ljava/lang/String;
    //   3128: astore 27
    //   3130: aload 26
    //   3132: invokevirtual 159	com/google/android/gms/measurement/internal/zzkn:zzW	()V
    //   3135: aload 26
    //   3137: invokevirtual 162	com/google/android/gms/measurement/internal/zzgr:zzg	()V
    //   3140: aload 27
    //   3142: invokestatic 71	com/google/android/gms/common/internal/Preconditions:checkNotEmpty	(Ljava/lang/String;)Ljava/lang/String;
    //   3145: pop
    //   3146: aload 25
    //   3148: invokestatic 71	com/google/android/gms/common/internal/Preconditions:checkNotEmpty	(Ljava/lang/String;)Ljava/lang/String;
    //   3151: pop
    //   3152: new 83	c/e/a
    //   3155: dup
    //   3156: invokespecial 84	c/e/a:<init>	()V
    //   3159: astore 21
    //   3161: aload 26
    //   3163: invokevirtual 175	com/google/android/gms/measurement/internal/zzam:zzh	()Landroid/database/sqlite/SQLiteDatabase;
    //   3166: astore_2
    //   3167: aload_2
    //   3168: ldc -35
    //   3170: iconst_2
    //   3171: anewarray 114	java/lang/String
    //   3174: dup
    //   3175: iconst_0
    //   3176: aload 4
    //   3178: aastore
    //   3179: dup
    //   3180: iconst_1
    //   3181: aload 5
    //   3183: aastore
    //   3184: ldc_w 494
    //   3187: iconst_2
    //   3188: anewarray 114	java/lang/String
    //   3191: dup
    //   3192: iconst_0
    //   3193: aload 27
    //   3195: aastore
    //   3196: dup
    //   3197: iconst_1
    //   3198: aload 25
    //   3200: aastore
    //   3201: aconst_null
    //   3202: aconst_null
    //   3203: aconst_null
    //   3204: invokevirtual 227	android/database/sqlite/SQLiteDatabase:query	(Ljava/lang/String;[Ljava/lang/String;Ljava/lang/String;[Ljava/lang/String;Ljava/lang/String;Ljava/lang/String;Ljava/lang/String;)Landroid/database/Cursor;
    //   3207: astore 14
    //   3209: aload 14
    //   3211: astore 16
    //   3213: aload 14
    //   3215: invokeinterface 232 1 0
    //   3220: istore 8
    //   3222: iload 8
    //   3224: ifeq +223 -> 3447
    //   3227: aload 14
    //   3229: astore 16
    //   3231: aload 14
    //   3233: iconst_1
    //   3234: invokeinterface 236 2 0
    //   3239: astore_2
    //   3240: aload 14
    //   3242: astore 16
    //   3244: invokestatic 241	com/google/android/gms/internal/measurement/zzej:zzc	()Lcom/google/android/gms/internal/measurement/zzei;
    //   3247: aload_2
    //   3248: invokestatic 247	com/google/android/gms/measurement/internal/zzlb:zzl	(Lcom/google/android/gms/internal/measurement/zzlk;[B)Lcom/google/android/gms/internal/measurement/zzlk;
    //   3251: checkcast 249	com/google/android/gms/internal/measurement/zzei
    //   3254: invokevirtual 255	com/google/android/gms/internal/measurement/zzka:zzaE	()Lcom/google/android/gms/internal/measurement/zzke;
    //   3257: checkcast 238	com/google/android/gms/internal/measurement/zzej
    //   3260: astore 28
    //   3262: aload 14
    //   3264: astore 16
    //   3266: aload 14
    //   3268: iconst_0
    //   3269: invokeinterface 262 2 0
    //   3274: invokestatic 50	java/lang/Integer:valueOf	(I)Ljava/lang/Integer;
    //   3277: astore 29
    //   3279: aload 14
    //   3281: astore 16
    //   3283: aload 21
    //   3285: aload 29
    //   3287: invokeinterface 31 2 0
    //   3292: checkcast 90	java/util/List
    //   3295: astore 13
    //   3297: aload 13
    //   3299: ifnonnull +1799 -> 5098
    //   3302: aload_1
    //   3303: astore 13
    //   3305: aload 13
    //   3307: astore_2
    //   3308: aload 14
    //   3310: astore 16
    //   3312: new 264	java/util/ArrayList
    //   3315: dup
    //   3316: invokespecial 265	java/util/ArrayList:<init>	()V
    //   3319: astore 22
    //   3321: aload 13
    //   3323: astore_2
    //   3324: aload 14
    //   3326: astore 16
    //   3328: aload 21
    //   3330: aload 29
    //   3332: aload 22
    //   3334: invokeinterface 42 3 0
    //   3339: pop
    //   3340: aload 22
    //   3342: astore 13
    //   3344: goto +3 -> 3347
    //   3347: aload_1
    //   3348: astore_2
    //   3349: aload 14
    //   3351: astore 16
    //   3353: aload 13
    //   3355: aload 28
    //   3357: invokeinterface 268 2 0
    //   3362: pop
    //   3363: goto +34 -> 3397
    //   3366: astore 13
    //   3368: aload_1
    //   3369: astore_2
    //   3370: aload 14
    //   3372: astore 16
    //   3374: aload 26
    //   3376: getfield 127	com/google/android/gms/measurement/internal/zzgr:zzs	Lcom/google/android/gms/measurement/internal/zzfy;
    //   3379: invokevirtual 189	com/google/android/gms/measurement/internal/zzfy:zzay	()Lcom/google/android/gms/measurement/internal/zzeo;
    //   3382: invokevirtual 194	com/google/android/gms/measurement/internal/zzeo:zzd	()Lcom/google/android/gms/measurement/internal/zzem;
    //   3385: aload 19
    //   3387: aload 27
    //   3389: invokestatic 200	com/google/android/gms/measurement/internal/zzeo:zzn	(Ljava/lang/String;)Ljava/lang/Object;
    //   3392: aload 13
    //   3394: invokevirtual 205	com/google/android/gms/measurement/internal/zzem:zzc	(Ljava/lang/String;Ljava/lang/Object;Ljava/lang/Object;)V
    //   3397: aload_1
    //   3398: astore_2
    //   3399: aload 14
    //   3401: astore 16
    //   3403: aload 14
    //   3405: invokeinterface 271 1 0
    //   3410: istore 8
    //   3412: iload 8
    //   3414: ifne +20 -> 3434
    //   3417: aload 14
    //   3419: invokeinterface 274 1 0
    //   3424: aload 21
    //   3426: astore 13
    //   3428: aload_1
    //   3429: astore 14
    //   3431: goto +140 -> 3571
    //   3434: goto -207 -> 3227
    //   3437: astore 13
    //   3439: aload_1
    //   3440: astore_2
    //   3441: aload 14
    //   3443: astore_1
    //   3444: goto +70 -> 3514
    //   3447: aload_1
    //   3448: astore_2
    //   3449: aload 14
    //   3451: astore 16
    //   3453: invokestatic 211	java/util/Collections:emptyMap	()Ljava/util/Map;
    //   3456: astore 13
    //   3458: aload 14
    //   3460: invokeinterface 274 1 0
    //   3465: aload_1
    //   3466: astore 14
    //   3468: goto +103 -> 3571
    //   3471: astore 13
    //   3473: aload 14
    //   3475: astore_1
    //   3476: goto +38 -> 3514
    //   3479: astore_1
    //   3480: goto +106 -> 3586
    //   3483: astore 13
    //   3485: aload_1
    //   3486: astore_2
    //   3487: aload 14
    //   3489: astore_1
    //   3490: goto +24 -> 3514
    //   3493: astore 13
    //   3495: goto +11 -> 3506
    //   3498: astore_1
    //   3499: aconst_null
    //   3500: astore 16
    //   3502: goto +84 -> 3586
    //   3505: astore_2
    //   3506: aconst_null
    //   3507: astore 14
    //   3509: aload_1
    //   3510: astore_2
    //   3511: aload 14
    //   3513: astore_1
    //   3514: aload_1
    //   3515: astore 16
    //   3517: aload 26
    //   3519: getfield 127	com/google/android/gms/measurement/internal/zzgr:zzs	Lcom/google/android/gms/measurement/internal/zzfy;
    //   3522: invokevirtual 189	com/google/android/gms/measurement/internal/zzfy:zzay	()Lcom/google/android/gms/measurement/internal/zzeo;
    //   3525: invokevirtual 194	com/google/android/gms/measurement/internal/zzeo:zzd	()Lcom/google/android/gms/measurement/internal/zzem;
    //   3528: aload 18
    //   3530: aload 27
    //   3532: invokestatic 200	com/google/android/gms/measurement/internal/zzeo:zzn	(Ljava/lang/String;)Ljava/lang/Object;
    //   3535: aload 13
    //   3537: invokevirtual 205	com/google/android/gms/measurement/internal/zzem:zzc	(Ljava/lang/String;Ljava/lang/Object;Ljava/lang/Object;)V
    //   3540: aload_1
    //   3541: astore 16
    //   3543: invokestatic 211	java/util/Collections:emptyMap	()Ljava/util/Map;
    //   3546: astore 21
    //   3548: aload 21
    //   3550: astore 13
    //   3552: aload_2
    //   3553: astore 14
    //   3555: aload_1
    //   3556: ifnull +15 -> 3571
    //   3559: aload 21
    //   3561: astore 13
    //   3563: aload_1
    //   3564: astore 14
    //   3566: aload_2
    //   3567: astore_1
    //   3568: goto -110 -> 3458
    //   3571: aload 23
    //   3573: aload 25
    //   3575: aload 13
    //   3577: invokeinterface 42 3 0
    //   3582: pop
    //   3583: goto +20 -> 3603
    //   3586: aload 16
    //   3588: ifnull +10 -> 3598
    //   3591: aload 16
    //   3593: invokeinterface 274 1 0
    //   3598: aload_1
    //   3599: athrow
    //   3600: aload_1
    //   3601: astore 14
    //   3603: aload 13
    //   3605: invokeinterface 297 1 0
    //   3610: invokeinterface 311 1 0
    //   3615: astore_1
    //   3616: aload_1
    //   3617: invokeinterface 100 1 0
    //   3622: ifeq +212 -> 3834
    //   3625: aload_1
    //   3626: invokeinterface 106 1 0
    //   3631: checkcast 46	java/lang/Integer
    //   3634: invokevirtual 315	java/lang/Integer:intValue	()I
    //   3637: istore 6
    //   3639: aload_0
    //   3640: getfield 81	com/google/android/gms/measurement/internal/zzaa:zzb	Ljava/util/Set;
    //   3643: astore_2
    //   3644: iload 6
    //   3646: invokestatic 50	java/lang/Integer:valueOf	(I)Ljava/lang/Integer;
    //   3649: astore 16
    //   3651: aload_2
    //   3652: aload 16
    //   3654: invokeinterface 495 2 0
    //   3659: ifeq +24 -> 3683
    //   3662: aload_0
    //   3663: getfield 127	com/google/android/gms/measurement/internal/zzgr:zzs	Lcom/google/android/gms/measurement/internal/zzfy;
    //   3666: invokevirtual 189	com/google/android/gms/measurement/internal/zzfy:zzay	()Lcom/google/android/gms/measurement/internal/zzeo;
    //   3669: invokevirtual 416	com/google/android/gms/measurement/internal/zzeo:zzj	()Lcom/google/android/gms/measurement/internal/zzem;
    //   3672: ldc_w 497
    //   3675: aload 16
    //   3677: invokevirtual 500	com/google/android/gms/measurement/internal/zzem:zzb	(Ljava/lang/String;Ljava/lang/Object;)V
    //   3680: goto -64 -> 3616
    //   3683: aload 13
    //   3685: aload 16
    //   3687: invokeinterface 31 2 0
    //   3692: checkcast 90	java/util/List
    //   3695: invokeinterface 94 1 0
    //   3700: astore_2
    //   3701: iconst_1
    //   3702: istore 8
    //   3704: aload_2
    //   3705: invokeinterface 100 1 0
    //   3710: ifeq +101 -> 3811
    //   3713: aload_2
    //   3714: invokeinterface 106 1 0
    //   3719: checkcast 238	com/google/android/gms/internal/measurement/zzej
    //   3722: astore 16
    //   3724: new 502	com/google/android/gms/measurement/internal/zzx
    //   3727: dup
    //   3728: aload_0
    //   3729: aload_0
    //   3730: getfield 35	com/google/android/gms/measurement/internal/zzaa:zza	Ljava/lang/String;
    //   3733: iload 6
    //   3735: aload 16
    //   3737: invokespecial 505	com/google/android/gms/measurement/internal/zzx:<init>	(Lcom/google/android/gms/measurement/internal/zzaa;Ljava/lang/String;ILcom/google/android/gms/internal/measurement/zzej;)V
    //   3740: astore 21
    //   3742: aload 21
    //   3744: aload_0
    //   3745: getfield 86	com/google/android/gms/measurement/internal/zzaa:zzd	Ljava/lang/Long;
    //   3748: aload_0
    //   3749: getfield 88	com/google/android/gms/measurement/internal/zzaa:zze	Ljava/lang/Long;
    //   3752: aload 24
    //   3754: lload 11
    //   3756: aload 14
    //   3758: aload_0
    //   3759: iload 6
    //   3761: aload 16
    //   3763: invokevirtual 426	com/google/android/gms/internal/measurement/zzej:zzb	()I
    //   3766: invokespecial 507	com/google/android/gms/measurement/internal/zzaa:zzf	(II)Z
    //   3769: invokevirtual 510	com/google/android/gms/measurement/internal/zzx:zzd	(Ljava/lang/Long;Ljava/lang/Long;Lcom/google/android/gms/internal/measurement/zzfs;JLcom/google/android/gms/measurement/internal/zzas;Z)Z
    //   3772: istore 8
    //   3774: iload 8
    //   3776: ifeq +20 -> 3796
    //   3779: aload_0
    //   3780: iload 6
    //   3782: invokestatic 50	java/lang/Integer:valueOf	(I)Ljava/lang/Integer;
    //   3785: invokespecial 512	com/google/android/gms/measurement/internal/zzaa:zzd	(Ljava/lang/Integer;)Lcom/google/android/gms/measurement/internal/zzu;
    //   3788: aload 21
    //   3790: invokevirtual 515	com/google/android/gms/measurement/internal/zzu:zzc	(Lcom/google/android/gms/measurement/internal/zzy;)V
    //   3793: goto -89 -> 3704
    //   3796: aload_0
    //   3797: getfield 81	com/google/android/gms/measurement/internal/zzaa:zzb	Ljava/util/Set;
    //   3800: iload 6
    //   3802: invokestatic 50	java/lang/Integer:valueOf	(I)Ljava/lang/Integer;
    //   3805: invokeinterface 516 2 0
    //   3810: pop
    //   3811: iload 8
    //   3813: ifne -197 -> 3616
    //   3816: aload_0
    //   3817: getfield 81	com/google/android/gms/measurement/internal/zzaa:zzb	Ljava/util/Set;
    //   3820: iload 6
    //   3822: invokestatic 50	java/lang/Integer:valueOf	(I)Ljava/lang/Integer;
    //   3825: invokeinterface 516 2 0
    //   3830: pop
    //   3831: goto -215 -> 3616
    //   3834: goto -979 -> 2855
    //   3837: aload_3
    //   3838: invokeinterface 316 1 0
    //   3843: ifeq +8 -> 3851
    //   3846: aload_1
    //   3847: astore_2
    //   3848: goto +952 -> 4800
    //   3851: new 83	c/e/a
    //   3854: dup
    //   3855: invokespecial 84	c/e/a:<init>	()V
    //   3858: astore 17
    //   3860: aload_3
    //   3861: invokeinterface 94 1 0
    //   3866: astore_3
    //   3867: aload_2
    //   3868: astore 15
    //   3870: aload_1
    //   3871: astore 5
    //   3873: aload_3
    //   3874: astore_1
    //   3875: aload 5
    //   3877: astore_2
    //   3878: aload_1
    //   3879: invokeinterface 100 1 0
    //   3884: ifeq -36 -> 3848
    //   3887: aload_1
    //   3888: invokeinterface 106 1 0
    //   3893: checkcast 518	com/google/android/gms/internal/measurement/zzgl
    //   3896: astore 19
    //   3898: aload 19
    //   3900: invokevirtual 520	com/google/android/gms/internal/measurement/zzgl:zzf	()Ljava/lang/String;
    //   3903: astore 20
    //   3905: aload 17
    //   3907: aload 20
    //   3909: invokeinterface 31 2 0
    //   3914: checkcast 23	java/util/Map
    //   3917: astore_2
    //   3918: aload_2
    //   3919: ifnonnull +449 -> 4368
    //   3922: aload_0
    //   3923: getfield 151	com/google/android/gms/measurement/internal/zzkm:zzf	Lcom/google/android/gms/measurement/internal/zzkz;
    //   3926: invokevirtual 157	com/google/android/gms/measurement/internal/zzkz:zzi	()Lcom/google/android/gms/measurement/internal/zzam;
    //   3929: astore 21
    //   3931: aload_0
    //   3932: getfield 35	com/google/android/gms/measurement/internal/zzaa:zza	Ljava/lang/String;
    //   3935: astore 22
    //   3937: aload 21
    //   3939: invokevirtual 159	com/google/android/gms/measurement/internal/zzkn:zzW	()V
    //   3942: aload 21
    //   3944: invokevirtual 162	com/google/android/gms/measurement/internal/zzgr:zzg	()V
    //   3947: aload 22
    //   3949: invokestatic 71	com/google/android/gms/common/internal/Preconditions:checkNotEmpty	(Ljava/lang/String;)Ljava/lang/String;
    //   3952: pop
    //   3953: aload 20
    //   3955: invokestatic 71	com/google/android/gms/common/internal/Preconditions:checkNotEmpty	(Ljava/lang/String;)Ljava/lang/String;
    //   3958: pop
    //   3959: new 83	c/e/a
    //   3962: dup
    //   3963: invokespecial 84	c/e/a:<init>	()V
    //   3966: astore 16
    //   3968: aload 21
    //   3970: invokevirtual 175	com/google/android/gms/measurement/internal/zzam:zzh	()Landroid/database/sqlite/SQLiteDatabase;
    //   3973: astore_2
    //   3974: aload_2
    //   3975: ldc_w 522
    //   3978: iconst_2
    //   3979: anewarray 114	java/lang/String
    //   3982: dup
    //   3983: iconst_0
    //   3984: aload 5
    //   3986: aastore
    //   3987: dup
    //   3988: iconst_1
    //   3989: aload 15
    //   3991: aastore
    //   3992: ldc_w 524
    //   3995: iconst_2
    //   3996: anewarray 114	java/lang/String
    //   3999: dup
    //   4000: iconst_0
    //   4001: aload 22
    //   4003: aastore
    //   4004: dup
    //   4005: iconst_1
    //   4006: aload 20
    //   4008: aastore
    //   4009: aconst_null
    //   4010: aconst_null
    //   4011: aconst_null
    //   4012: invokevirtual 227	android/database/sqlite/SQLiteDatabase:query	(Ljava/lang/String;[Ljava/lang/String;Ljava/lang/String;[Ljava/lang/String;Ljava/lang/String;Ljava/lang/String;Ljava/lang/String;)Landroid/database/Cursor;
    //   4015: astore_3
    //   4016: aload_1
    //   4017: astore_2
    //   4018: aload_3
    //   4019: astore 4
    //   4021: aload_3
    //   4022: invokeinterface 232 1 0
    //   4027: ifeq +210 -> 4237
    //   4030: aload_1
    //   4031: astore_2
    //   4032: aload_3
    //   4033: astore 4
    //   4035: aload_3
    //   4036: iconst_1
    //   4037: invokeinterface 236 2 0
    //   4042: astore 13
    //   4044: aload_1
    //   4045: astore_2
    //   4046: aload_3
    //   4047: astore 4
    //   4049: invokestatic 529	com/google/android/gms/internal/measurement/zzes:zzc	()Lcom/google/android/gms/internal/measurement/zzer;
    //   4052: aload 13
    //   4054: invokestatic 247	com/google/android/gms/measurement/internal/zzlb:zzl	(Lcom/google/android/gms/internal/measurement/zzlk;[B)Lcom/google/android/gms/internal/measurement/zzlk;
    //   4057: checkcast 531	com/google/android/gms/internal/measurement/zzer
    //   4060: invokevirtual 255	com/google/android/gms/internal/measurement/zzka:zzaE	()Lcom/google/android/gms/internal/measurement/zzke;
    //   4063: checkcast 526	com/google/android/gms/internal/measurement/zzes
    //   4066: astore 23
    //   4068: aload_1
    //   4069: astore_2
    //   4070: aload_3
    //   4071: astore 4
    //   4073: aload_3
    //   4074: iconst_0
    //   4075: invokeinterface 262 2 0
    //   4080: invokestatic 50	java/lang/Integer:valueOf	(I)Ljava/lang/Integer;
    //   4083: astore 24
    //   4085: aload_1
    //   4086: astore_2
    //   4087: aload_3
    //   4088: astore 4
    //   4090: aload 16
    //   4092: aload 24
    //   4094: invokeinterface 31 2 0
    //   4099: checkcast 90	java/util/List
    //   4102: astore 13
    //   4104: aload 13
    //   4106: ifnonnull +995 -> 5101
    //   4109: aload_1
    //   4110: astore_2
    //   4111: aload_3
    //   4112: astore 4
    //   4114: new 264	java/util/ArrayList
    //   4117: dup
    //   4118: invokespecial 265	java/util/ArrayList:<init>	()V
    //   4121: astore 13
    //   4123: aload_1
    //   4124: astore_2
    //   4125: aload_3
    //   4126: astore 4
    //   4128: aload 16
    //   4130: aload 24
    //   4132: aload 13
    //   4134: invokeinterface 42 3 0
    //   4139: pop
    //   4140: goto +3 -> 4143
    //   4143: aload_1
    //   4144: astore_2
    //   4145: aload_3
    //   4146: astore 4
    //   4148: aload 13
    //   4150: aload 23
    //   4152: invokeinterface 268 2 0
    //   4157: pop
    //   4158: goto +43 -> 4201
    //   4161: astore 13
    //   4163: aload_1
    //   4164: astore_2
    //   4165: aload_3
    //   4166: astore 4
    //   4168: aload 21
    //   4170: getfield 127	com/google/android/gms/measurement/internal/zzgr:zzs	Lcom/google/android/gms/measurement/internal/zzfy;
    //   4173: invokevirtual 189	com/google/android/gms/measurement/internal/zzfy:zzay	()Lcom/google/android/gms/measurement/internal/zzeo;
    //   4176: invokevirtual 194	com/google/android/gms/measurement/internal/zzeo:zzd	()Lcom/google/android/gms/measurement/internal/zzem;
    //   4179: astore 23
    //   4181: aload_1
    //   4182: astore_2
    //   4183: aload_3
    //   4184: astore 4
    //   4186: aload 23
    //   4188: ldc_w 533
    //   4191: aload 22
    //   4193: invokestatic 200	com/google/android/gms/measurement/internal/zzeo:zzn	(Ljava/lang/String;)Ljava/lang/Object;
    //   4196: aload 13
    //   4198: invokevirtual 205	com/google/android/gms/measurement/internal/zzem:zzc	(Ljava/lang/String;Ljava/lang/Object;Ljava/lang/Object;)V
    //   4201: aload_1
    //   4202: astore_2
    //   4203: aload_3
    //   4204: astore 4
    //   4206: aload_3
    //   4207: invokeinterface 271 1 0
    //   4212: istore 8
    //   4214: iload 8
    //   4216: ifne +18 -> 4234
    //   4219: aload_3
    //   4220: invokeinterface 274 1 0
    //   4225: aload 16
    //   4227: astore_2
    //   4228: aload_1
    //   4229: astore 4
    //   4231: goto +105 -> 4336
    //   4234: goto -204 -> 4030
    //   4237: aload_1
    //   4238: astore_2
    //   4239: aload_3
    //   4240: astore 4
    //   4242: invokestatic 211	java/util/Collections:emptyMap	()Ljava/util/Map;
    //   4245: astore 13
    //   4247: aload 13
    //   4249: astore_2
    //   4250: aload_3
    //   4251: invokeinterface 274 1 0
    //   4256: aload_1
    //   4257: astore 4
    //   4259: goto +77 -> 4336
    //   4262: astore 13
    //   4264: aload_2
    //   4265: astore_1
    //   4266: goto +20 -> 4286
    //   4269: astore 13
    //   4271: aload_2
    //   4272: astore_1
    //   4273: goto +13 -> 4286
    //   4276: astore_1
    //   4277: aconst_null
    //   4278: astore_2
    //   4279: goto +77 -> 4356
    //   4282: astore 13
    //   4284: aconst_null
    //   4285: astore_3
    //   4286: aload_3
    //   4287: astore 4
    //   4289: aload 21
    //   4291: getfield 127	com/google/android/gms/measurement/internal/zzgr:zzs	Lcom/google/android/gms/measurement/internal/zzfy;
    //   4294: invokevirtual 189	com/google/android/gms/measurement/internal/zzfy:zzay	()Lcom/google/android/gms/measurement/internal/zzeo;
    //   4297: invokevirtual 194	com/google/android/gms/measurement/internal/zzeo:zzd	()Lcom/google/android/gms/measurement/internal/zzem;
    //   4300: aload 18
    //   4302: aload 22
    //   4304: invokestatic 200	com/google/android/gms/measurement/internal/zzeo:zzn	(Ljava/lang/String;)Ljava/lang/Object;
    //   4307: aload 13
    //   4309: invokevirtual 205	com/google/android/gms/measurement/internal/zzem:zzc	(Ljava/lang/String;Ljava/lang/Object;Ljava/lang/Object;)V
    //   4312: aload_3
    //   4313: astore 4
    //   4315: invokestatic 211	java/util/Collections:emptyMap	()Ljava/util/Map;
    //   4318: astore 13
    //   4320: aload 13
    //   4322: astore_2
    //   4323: aload_1
    //   4324: astore 4
    //   4326: aload_3
    //   4327: ifnull +9 -> 4336
    //   4330: aload 13
    //   4332: astore_2
    //   4333: goto -83 -> 4250
    //   4336: aload 17
    //   4338: aload 20
    //   4340: aload_2
    //   4341: invokeinterface 42 3 0
    //   4346: pop
    //   4347: aload_2
    //   4348: astore_1
    //   4349: goto +24 -> 4373
    //   4352: astore_1
    //   4353: aload 4
    //   4355: astore_2
    //   4356: aload_2
    //   4357: ifnull +9 -> 4366
    //   4360: aload_2
    //   4361: invokeinterface 274 1 0
    //   4366: aload_1
    //   4367: athrow
    //   4368: aload_1
    //   4369: astore 4
    //   4371: aload_2
    //   4372: astore_1
    //   4373: aload_1
    //   4374: invokeinterface 297 1 0
    //   4379: invokeinterface 311 1 0
    //   4384: astore_3
    //   4385: aload_3
    //   4386: invokeinterface 100 1 0
    //   4391: ifeq +403 -> 4794
    //   4394: aload_3
    //   4395: invokeinterface 106 1 0
    //   4400: checkcast 46	java/lang/Integer
    //   4403: invokevirtual 315	java/lang/Integer:intValue	()I
    //   4406: istore 6
    //   4408: aload_0
    //   4409: getfield 81	com/google/android/gms/measurement/internal/zzaa:zzb	Ljava/util/Set;
    //   4412: astore_2
    //   4413: iload 6
    //   4415: invokestatic 50	java/lang/Integer:valueOf	(I)Ljava/lang/Integer;
    //   4418: astore 13
    //   4420: aload_2
    //   4421: aload 13
    //   4423: invokeinterface 495 2 0
    //   4428: ifeq +24 -> 4452
    //   4431: aload_0
    //   4432: getfield 127	com/google/android/gms/measurement/internal/zzgr:zzs	Lcom/google/android/gms/measurement/internal/zzfy;
    //   4435: invokevirtual 189	com/google/android/gms/measurement/internal/zzfy:zzay	()Lcom/google/android/gms/measurement/internal/zzeo;
    //   4438: invokevirtual 416	com/google/android/gms/measurement/internal/zzeo:zzj	()Lcom/google/android/gms/measurement/internal/zzem;
    //   4441: ldc_w 497
    //   4444: aload 13
    //   4446: invokevirtual 500	com/google/android/gms/measurement/internal/zzem:zzb	(Ljava/lang/String;Ljava/lang/Object;)V
    //   4449: goto +345 -> 4794
    //   4452: aload_1
    //   4453: aload 13
    //   4455: invokeinterface 31 2 0
    //   4460: checkcast 90	java/util/List
    //   4463: invokeinterface 94 1 0
    //   4468: astore 13
    //   4470: iconst_1
    //   4471: istore 8
    //   4473: aload 13
    //   4475: invokeinterface 100 1 0
    //   4480: ifeq +291 -> 4771
    //   4483: aload 13
    //   4485: invokeinterface 106 1 0
    //   4490: checkcast 526	com/google/android/gms/internal/measurement/zzes
    //   4493: astore 16
    //   4495: aload_0
    //   4496: getfield 127	com/google/android/gms/measurement/internal/zzgr:zzs	Lcom/google/android/gms/measurement/internal/zzfy;
    //   4499: invokevirtual 189	com/google/android/gms/measurement/internal/zzfy:zzay	()Lcom/google/android/gms/measurement/internal/zzeo;
    //   4502: invokevirtual 535	com/google/android/gms/measurement/internal/zzeo:zzq	()Ljava/lang/String;
    //   4505: iconst_2
    //   4506: invokestatic 541	android/util/Log:isLoggable	(Ljava/lang/String;I)Z
    //   4509: ifeq +97 -> 4606
    //   4512: aload_0
    //   4513: getfield 127	com/google/android/gms/measurement/internal/zzgr:zzs	Lcom/google/android/gms/measurement/internal/zzfy;
    //   4516: invokevirtual 189	com/google/android/gms/measurement/internal/zzfy:zzay	()Lcom/google/android/gms/measurement/internal/zzeo;
    //   4519: invokevirtual 416	com/google/android/gms/measurement/internal/zzeo:zzj	()Lcom/google/android/gms/measurement/internal/zzem;
    //   4522: astore 20
    //   4524: aload 16
    //   4526: invokevirtual 543	com/google/android/gms/internal/measurement/zzes:zzj	()Z
    //   4529: ifeq +15 -> 4544
    //   4532: aload 16
    //   4534: invokevirtual 544	com/google/android/gms/internal/measurement/zzes:zza	()I
    //   4537: invokestatic 50	java/lang/Integer:valueOf	(I)Ljava/lang/Integer;
    //   4540: astore_2
    //   4541: goto +5 -> 4546
    //   4544: aconst_null
    //   4545: astore_2
    //   4546: aload 20
    //   4548: ldc_w 546
    //   4551: iload 6
    //   4553: invokestatic 50	java/lang/Integer:valueOf	(I)Ljava/lang/Integer;
    //   4556: aload_2
    //   4557: aload_0
    //   4558: getfield 127	com/google/android/gms/measurement/internal/zzgr:zzs	Lcom/google/android/gms/measurement/internal/zzfy;
    //   4561: invokevirtual 454	com/google/android/gms/measurement/internal/zzfy:zzj	()Lcom/google/android/gms/measurement/internal/zzej;
    //   4564: aload 16
    //   4566: invokevirtual 548	com/google/android/gms/internal/measurement/zzes:zze	()Ljava/lang/String;
    //   4569: invokevirtual 550	com/google/android/gms/measurement/internal/zzej:zzf	(Ljava/lang/String;)Ljava/lang/String;
    //   4572: invokevirtual 288	com/google/android/gms/measurement/internal/zzem:zzd	(Ljava/lang/String;Ljava/lang/Object;Ljava/lang/Object;Ljava/lang/Object;)V
    //   4575: aload_0
    //   4576: getfield 127	com/google/android/gms/measurement/internal/zzgr:zzs	Lcom/google/android/gms/measurement/internal/zzfy;
    //   4579: invokevirtual 189	com/google/android/gms/measurement/internal/zzfy:zzay	()Lcom/google/android/gms/measurement/internal/zzeo;
    //   4582: invokevirtual 416	com/google/android/gms/measurement/internal/zzeo:zzj	()Lcom/google/android/gms/measurement/internal/zzem;
    //   4585: ldc_w 552
    //   4588: aload_0
    //   4589: getfield 151	com/google/android/gms/measurement/internal/zzkm:zzf	Lcom/google/android/gms/measurement/internal/zzkz;
    //   4592: invokevirtual 320	com/google/android/gms/measurement/internal/zzkz:zzu	()Lcom/google/android/gms/measurement/internal/zzlb;
    //   4595: aload 16
    //   4597: invokevirtual 556	com/google/android/gms/measurement/internal/zzlb:zzp	(Lcom/google/android/gms/internal/measurement/zzes;)Ljava/lang/String;
    //   4600: invokevirtual 500	com/google/android/gms/measurement/internal/zzem:zzb	(Ljava/lang/String;Ljava/lang/Object;)V
    //   4603: goto +3 -> 4606
    //   4606: aload 16
    //   4608: invokevirtual 543	com/google/android/gms/internal/measurement/zzes:zzj	()Z
    //   4611: ifeq +100 -> 4711
    //   4614: aload 16
    //   4616: invokevirtual 544	com/google/android/gms/internal/measurement/zzes:zza	()I
    //   4619: sipush 256
    //   4622: if_icmple +6 -> 4628
    //   4625: goto +86 -> 4711
    //   4628: new 558	com/google/android/gms/measurement/internal/zzz
    //   4631: dup
    //   4632: aload_0
    //   4633: aload_0
    //   4634: getfield 35	com/google/android/gms/measurement/internal/zzaa:zza	Ljava/lang/String;
    //   4637: iload 6
    //   4639: aload 16
    //   4641: invokespecial 561	com/google/android/gms/measurement/internal/zzz:<init>	(Lcom/google/android/gms/measurement/internal/zzaa;Ljava/lang/String;ILcom/google/android/gms/internal/measurement/zzes;)V
    //   4644: astore_2
    //   4645: aload_2
    //   4646: aload_0
    //   4647: getfield 86	com/google/android/gms/measurement/internal/zzaa:zzd	Ljava/lang/Long;
    //   4650: aload_0
    //   4651: getfield 88	com/google/android/gms/measurement/internal/zzaa:zze	Ljava/lang/Long;
    //   4654: aload 19
    //   4656: aload_0
    //   4657: iload 6
    //   4659: aload 16
    //   4661: invokevirtual 544	com/google/android/gms/internal/measurement/zzes:zza	()I
    //   4664: invokespecial 507	com/google/android/gms/measurement/internal/zzaa:zzf	(II)Z
    //   4667: invokevirtual 564	com/google/android/gms/measurement/internal/zzz:zzd	(Ljava/lang/Long;Ljava/lang/Long;Lcom/google/android/gms/internal/measurement/zzgl;Z)Z
    //   4670: istore 8
    //   4672: iload 8
    //   4674: ifeq +19 -> 4693
    //   4677: aload_0
    //   4678: iload 6
    //   4680: invokestatic 50	java/lang/Integer:valueOf	(I)Ljava/lang/Integer;
    //   4683: invokespecial 512	com/google/android/gms/measurement/internal/zzaa:zzd	(Ljava/lang/Integer;)Lcom/google/android/gms/measurement/internal/zzu;
    //   4686: aload_2
    //   4687: invokevirtual 515	com/google/android/gms/measurement/internal/zzu:zzc	(Lcom/google/android/gms/measurement/internal/zzy;)V
    //   4690: goto -217 -> 4473
    //   4693: aload_0
    //   4694: getfield 81	com/google/android/gms/measurement/internal/zzaa:zzb	Ljava/util/Set;
    //   4697: iload 6
    //   4699: invokestatic 50	java/lang/Integer:valueOf	(I)Ljava/lang/Integer;
    //   4702: invokeinterface 516 2 0
    //   4707: pop
    //   4708: goto +63 -> 4771
    //   4711: aload_0
    //   4712: getfield 127	com/google/android/gms/measurement/internal/zzgr:zzs	Lcom/google/android/gms/measurement/internal/zzfy;
    //   4715: invokevirtual 189	com/google/android/gms/measurement/internal/zzfy:zzay	()Lcom/google/android/gms/measurement/internal/zzeo;
    //   4718: invokevirtual 449	com/google/android/gms/measurement/internal/zzeo:zzk	()Lcom/google/android/gms/measurement/internal/zzem;
    //   4721: astore 13
    //   4723: aload_0
    //   4724: getfield 35	com/google/android/gms/measurement/internal/zzaa:zza	Ljava/lang/String;
    //   4727: invokestatic 200	com/google/android/gms/measurement/internal/zzeo:zzn	(Ljava/lang/String;)Ljava/lang/Object;
    //   4730: astore 20
    //   4732: aload 16
    //   4734: invokevirtual 543	com/google/android/gms/internal/measurement/zzes:zzj	()Z
    //   4737: ifeq +15 -> 4752
    //   4740: aload 16
    //   4742: invokevirtual 544	com/google/android/gms/internal/measurement/zzes:zza	()I
    //   4745: invokestatic 50	java/lang/Integer:valueOf	(I)Ljava/lang/Integer;
    //   4748: astore_2
    //   4749: goto +5 -> 4754
    //   4752: aconst_null
    //   4753: astore_2
    //   4754: aload 13
    //   4756: ldc_w 566
    //   4759: aload 20
    //   4761: aload_2
    //   4762: invokestatic 569	java/lang/String:valueOf	(Ljava/lang/Object;)Ljava/lang/String;
    //   4765: invokevirtual 205	com/google/android/gms/measurement/internal/zzem:zzc	(Ljava/lang/String;Ljava/lang/Object;Ljava/lang/Object;)V
    //   4768: goto +8 -> 4776
    //   4771: iload 8
    //   4773: ifne +18 -> 4791
    //   4776: aload_0
    //   4777: getfield 81	com/google/android/gms/measurement/internal/zzaa:zzb	Ljava/util/Set;
    //   4780: iload 6
    //   4782: invokestatic 50	java/lang/Integer:valueOf	(I)Ljava/lang/Integer;
    //   4785: invokeinterface 516 2 0
    //   4790: pop
    //   4791: goto -406 -> 4385
    //   4794: aload 4
    //   4796: astore_1
    //   4797: goto -922 -> 3875
    //   4800: new 264	java/util/ArrayList
    //   4803: dup
    //   4804: invokespecial 265	java/util/ArrayList:<init>	()V
    //   4807: astore_3
    //   4808: aload_0
    //   4809: getfield 21	com/google/android/gms/measurement/internal/zzaa:zzc	Ljava/util/Map;
    //   4812: invokeinterface 297 1 0
    //   4817: astore_1
    //   4818: aload_1
    //   4819: aload_0
    //   4820: getfield 81	com/google/android/gms/measurement/internal/zzaa:zzb	Ljava/util/Set;
    //   4823: invokeinterface 573 2 0
    //   4828: pop
    //   4829: aload_1
    //   4830: invokeinterface 311 1 0
    //   4835: astore 4
    //   4837: aload 4
    //   4839: invokeinterface 100 1 0
    //   4844: ifeq +233 -> 5077
    //   4847: aload 4
    //   4849: invokeinterface 106 1 0
    //   4854: checkcast 46	java/lang/Integer
    //   4857: invokevirtual 315	java/lang/Integer:intValue	()I
    //   4860: istore 6
    //   4862: aload_0
    //   4863: getfield 21	com/google/android/gms/measurement/internal/zzaa:zzc	Ljava/util/Map;
    //   4866: astore 5
    //   4868: iload 6
    //   4870: invokestatic 50	java/lang/Integer:valueOf	(I)Ljava/lang/Integer;
    //   4873: astore_1
    //   4874: aload 5
    //   4876: aload_1
    //   4877: invokeinterface 31 2 0
    //   4882: checkcast 33	com/google/android/gms/measurement/internal/zzu
    //   4885: astore 5
    //   4887: aload 5
    //   4889: invokestatic 74	com/google/android/gms/common/internal/Preconditions:checkNotNull	(Ljava/lang/Object;)Ljava/lang/Object;
    //   4892: pop
    //   4893: aload 5
    //   4895: iload 6
    //   4897: invokevirtual 576	com/google/android/gms/measurement/internal/zzu:zza	(I)Lcom/google/android/gms/internal/measurement/zzfo;
    //   4900: astore 15
    //   4902: aload_3
    //   4903: aload 15
    //   4905: invokeinterface 268 2 0
    //   4910: pop
    //   4911: aload_0
    //   4912: getfield 151	com/google/android/gms/measurement/internal/zzkm:zzf	Lcom/google/android/gms/measurement/internal/zzkz;
    //   4915: invokevirtual 157	com/google/android/gms/measurement/internal/zzkz:zzi	()Lcom/google/android/gms/measurement/internal/zzam;
    //   4918: astore 5
    //   4920: aload_0
    //   4921: getfield 35	com/google/android/gms/measurement/internal/zzaa:zza	Ljava/lang/String;
    //   4924: astore 13
    //   4926: aload 15
    //   4928: invokevirtual 581	com/google/android/gms/internal/measurement/zzfo:zzd	()Lcom/google/android/gms/internal/measurement/zzgh;
    //   4931: astore 15
    //   4933: aload 5
    //   4935: invokevirtual 159	com/google/android/gms/measurement/internal/zzkn:zzW	()V
    //   4938: aload 5
    //   4940: invokevirtual 162	com/google/android/gms/measurement/internal/zzgr:zzg	()V
    //   4943: aload 13
    //   4945: invokestatic 71	com/google/android/gms/common/internal/Preconditions:checkNotEmpty	(Ljava/lang/String;)Ljava/lang/String;
    //   4948: pop
    //   4949: aload 15
    //   4951: invokestatic 74	com/google/android/gms/common/internal/Preconditions:checkNotNull	(Ljava/lang/Object;)Ljava/lang/Object;
    //   4954: pop
    //   4955: aload 15
    //   4957: invokevirtual 587	com/google/android/gms/internal/measurement/zzin:zzbv	()[B
    //   4960: astore 16
    //   4962: new 164	android/content/ContentValues
    //   4965: dup
    //   4966: invokespecial 165	android/content/ContentValues:<init>	()V
    //   4969: astore 15
    //   4971: aload 15
    //   4973: ldc_w 589
    //   4976: aload 13
    //   4978: invokevirtual 592	android/content/ContentValues:put	(Ljava/lang/String;Ljava/lang/String;)V
    //   4981: aload 15
    //   4983: aload_2
    //   4984: aload_1
    //   4985: invokevirtual 170	android/content/ContentValues:put	(Ljava/lang/String;Ljava/lang/Integer;)V
    //   4988: aload 15
    //   4990: aload 14
    //   4992: aload 16
    //   4994: invokevirtual 595	android/content/ContentValues:put	(Ljava/lang/String;[B)V
    //   4997: aload 5
    //   4999: invokevirtual 175	com/google/android/gms/measurement/internal/zzam:zzh	()Landroid/database/sqlite/SQLiteDatabase;
    //   5002: astore_1
    //   5003: aload_1
    //   5004: ldc_w 276
    //   5007: aconst_null
    //   5008: aload 15
    //   5010: iconst_5
    //   5011: invokevirtual 599	android/database/sqlite/SQLiteDatabase:insertWithOnConflict	(Ljava/lang/String;Ljava/lang/String;Landroid/content/ContentValues;I)J
    //   5014: ldc2_w 600
    //   5017: lcmp
    //   5018: ifne +56 -> 5074
    //   5021: aload 5
    //   5023: getfield 127	com/google/android/gms/measurement/internal/zzgr:zzs	Lcom/google/android/gms/measurement/internal/zzfy;
    //   5026: invokevirtual 189	com/google/android/gms/measurement/internal/zzfy:zzay	()Lcom/google/android/gms/measurement/internal/zzeo;
    //   5029: invokevirtual 194	com/google/android/gms/measurement/internal/zzeo:zzd	()Lcom/google/android/gms/measurement/internal/zzem;
    //   5032: ldc_w 603
    //   5035: aload 13
    //   5037: invokestatic 200	com/google/android/gms/measurement/internal/zzeo:zzn	(Ljava/lang/String;)Ljava/lang/Object;
    //   5040: invokevirtual 500	com/google/android/gms/measurement/internal/zzem:zzb	(Ljava/lang/String;Ljava/lang/Object;)V
    //   5043: goto +31 -> 5074
    //   5046: astore_1
    //   5047: goto +4 -> 5051
    //   5050: astore_1
    //   5051: aload 5
    //   5053: getfield 127	com/google/android/gms/measurement/internal/zzgr:zzs	Lcom/google/android/gms/measurement/internal/zzfy;
    //   5056: invokevirtual 189	com/google/android/gms/measurement/internal/zzfy:zzay	()Lcom/google/android/gms/measurement/internal/zzeo;
    //   5059: invokevirtual 194	com/google/android/gms/measurement/internal/zzeo:zzd	()Lcom/google/android/gms/measurement/internal/zzem;
    //   5062: ldc_w 605
    //   5065: aload 13
    //   5067: invokestatic 200	com/google/android/gms/measurement/internal/zzeo:zzn	(Ljava/lang/String;)Ljava/lang/Object;
    //   5070: aload_1
    //   5071: invokevirtual 205	com/google/android/gms/measurement/internal/zzem:zzc	(Ljava/lang/String;Ljava/lang/Object;Ljava/lang/Object;)V
    //   5074: goto -237 -> 4837
    //   5077: aload_3
    //   5078: areturn
    //   5079: astore_1
    //   5080: aload 13
    //   5082: astore_2
    //   5083: aload_2
    //   5084: ifnull +9 -> 5093
    //   5087: aload_2
    //   5088: invokeinterface 274 1 0
    //   5093: aload_1
    //   5094: athrow
    //   5095: goto -4609 -> 486
    //   5098: goto -1751 -> 3347
    //   5101: goto -958 -> 4143
    // Exception table:
    //   from	to	target	type
    //   202	225	228	android/database/sqlite/SQLiteException
    //   386	405	502	java/io/IOException
    //   362	371	579	finally
    //   374	383	579	finally
    //   386	405	579	finally
    //   408	416	579	finally
    //   422	434	579	finally
    //   437	451	579	finally
    //   459	468	579	finally
    //   471	483	579	finally
    //   489	499	579	finally
    //   507	530	579	finally
    //   533	541	579	finally
    //   561	566	579	finally
    //   602	625	579	finally
    //   628	633	579	finally
    //   362	371	583	android/database/sqlite/SQLiteException
    //   374	383	583	android/database/sqlite/SQLiteException
    //   386	405	583	android/database/sqlite/SQLiteException
    //   408	416	583	android/database/sqlite/SQLiteException
    //   422	434	583	android/database/sqlite/SQLiteException
    //   437	451	583	android/database/sqlite/SQLiteException
    //   459	468	583	android/database/sqlite/SQLiteException
    //   471	483	583	android/database/sqlite/SQLiteException
    //   489	499	583	android/database/sqlite/SQLiteException
    //   507	530	583	android/database/sqlite/SQLiteException
    //   533	541	583	android/database/sqlite/SQLiteException
    //   561	566	583	android/database/sqlite/SQLiteException
    //   324	359	588	finally
    //   324	359	595	android/database/sqlite/SQLiteException
    //   881	900	929	java/io/IOException
    //   974	991	1043	android/database/sqlite/SQLiteException
    //   1002	1011	1043	android/database/sqlite/SQLiteException
    //   963	970	1054	android/database/sqlite/SQLiteException
    //   752	762	1063	android/database/sqlite/SQLiteException
    //   774	778	1063	android/database/sqlite/SQLiteException
    //   808	817	1063	android/database/sqlite/SQLiteException
    //   839	849	1063	android/database/sqlite/SQLiteException
    //   860	870	1063	android/database/sqlite/SQLiteException
    //   881	900	1063	android/database/sqlite/SQLiteException
    //   911	926	1063	android/database/sqlite/SQLiteException
    //   942	955	1063	android/database/sqlite/SQLiteException
    //   703	740	1081	finally
    //   703	740	1087	android/database/sqlite/SQLiteException
    //   1268	1278	1422	finally
    //   1282	1295	1422	finally
    //   1299	1313	1422	finally
    //   1326	1335	1422	finally
    //   1339	1351	1422	finally
    //   1355	1374	1422	finally
    //   1378	1387	1422	finally
    //   1410	1415	1422	finally
    //   1447	1471	1422	finally
    //   1475	1480	1422	finally
    //   1268	1278	1426	android/database/sqlite/SQLiteException
    //   1282	1295	1426	android/database/sqlite/SQLiteException
    //   1299	1313	1426	android/database/sqlite/SQLiteException
    //   1326	1335	1426	android/database/sqlite/SQLiteException
    //   1339	1351	1426	android/database/sqlite/SQLiteException
    //   1355	1374	1426	android/database/sqlite/SQLiteException
    //   1378	1387	1426	android/database/sqlite/SQLiteException
    //   1410	1415	1426	android/database/sqlite/SQLiteException
    //   1240	1264	1431	finally
    //   1240	1264	1438	android/database/sqlite/SQLiteException
    //   3244	3262	3366	java/io/IOException
    //   3231	3240	3437	android/database/sqlite/SQLiteException
    //   3244	3262	3437	android/database/sqlite/SQLiteException
    //   3266	3279	3437	android/database/sqlite/SQLiteException
    //   3283	3297	3437	android/database/sqlite/SQLiteException
    //   3312	3321	3471	android/database/sqlite/SQLiteException
    //   3328	3340	3471	android/database/sqlite/SQLiteException
    //   3353	3363	3471	android/database/sqlite/SQLiteException
    //   3374	3397	3471	android/database/sqlite/SQLiteException
    //   3403	3412	3471	android/database/sqlite/SQLiteException
    //   3453	3458	3471	android/database/sqlite/SQLiteException
    //   3213	3222	3479	finally
    //   3231	3240	3479	finally
    //   3244	3262	3479	finally
    //   3266	3279	3479	finally
    //   3283	3297	3479	finally
    //   3312	3321	3479	finally
    //   3328	3340	3479	finally
    //   3353	3363	3479	finally
    //   3374	3397	3479	finally
    //   3403	3412	3479	finally
    //   3453	3458	3479	finally
    //   3517	3540	3479	finally
    //   3543	3548	3479	finally
    //   3213	3222	3483	android/database/sqlite/SQLiteException
    //   3167	3209	3493	android/database/sqlite/SQLiteException
    //   3167	3209	3498	finally
    //   4049	4068	4161	java/io/IOException
    //   4186	4201	4262	android/database/sqlite/SQLiteException
    //   4206	4214	4262	android/database/sqlite/SQLiteException
    //   4242	4247	4262	android/database/sqlite/SQLiteException
    //   4021	4030	4269	android/database/sqlite/SQLiteException
    //   4035	4044	4269	android/database/sqlite/SQLiteException
    //   4049	4068	4269	android/database/sqlite/SQLiteException
    //   4073	4085	4269	android/database/sqlite/SQLiteException
    //   4090	4104	4269	android/database/sqlite/SQLiteException
    //   4114	4123	4269	android/database/sqlite/SQLiteException
    //   4128	4140	4269	android/database/sqlite/SQLiteException
    //   4148	4158	4269	android/database/sqlite/SQLiteException
    //   4168	4181	4269	android/database/sqlite/SQLiteException
    //   3974	4016	4276	finally
    //   3974	4016	4282	android/database/sqlite/SQLiteException
    //   4021	4030	4352	finally
    //   4035	4044	4352	finally
    //   4049	4068	4352	finally
    //   4073	4085	4352	finally
    //   4090	4104	4352	finally
    //   4114	4123	4352	finally
    //   4128	4140	4352	finally
    //   4148	4158	4352	finally
    //   4168	4181	4352	finally
    //   4186	4201	4352	finally
    //   4206	4214	4352	finally
    //   4242	4247	4352	finally
    //   4289	4312	4352	finally
    //   4315	4320	4352	finally
    //   5003	5043	5046	android/database/sqlite/SQLiteException
    //   4997	5003	5050	android/database/sqlite/SQLiteException
    //   752	762	5079	finally
    //   774	778	5079	finally
    //   808	817	5079	finally
    //   839	849	5079	finally
    //   860	870	5079	finally
    //   881	900	5079	finally
    //   911	926	5079	finally
    //   942	955	5079	finally
    //   963	970	5079	finally
    //   974	991	5079	finally
    //   1002	1011	5079	finally
    //   1102	1126	5079	finally
    //   1129	1134	5079	finally
  }
  
  protected final boolean zzb()
  {
    return false;
  }
}
