package com.google.android.gms.measurement.internal;

import android.content.ContentValues;
import android.content.Context;
import android.database.Cursor;
import android.database.sqlite.SQLiteDatabase;
import android.database.sqlite.SQLiteException;
import android.text.TextUtils;
import com.google.android.gms.common.internal.Preconditions;
import com.google.android.gms.common.util.Clock;
import com.google.android.gms.common.util.VisibleForTesting;
import com.google.android.gms.internal.measurement.zzeg;
import com.google.android.gms.internal.measurement.zzeh;
import com.google.android.gms.internal.measurement.zzei;
import com.google.android.gms.internal.measurement.zzek;
import com.google.android.gms.internal.measurement.zzel;
import com.google.android.gms.internal.measurement.zzer;
import com.google.android.gms.internal.measurement.zzes;
import com.google.android.gms.internal.measurement.zzfs;
import com.google.android.gms.internal.measurement.zzin;
import com.google.android.gms.internal.measurement.zzka;
import com.google.android.gms.internal.measurement.zzke;
import com.google.android.gms.internal.measurement.zzns;
import java.io.File;
import java.util.ArrayList;
import java.util.Iterator;
import java.util.List;

final class zzam
  extends zzkn
{
  private static final String[] zza = { "last_bundled_timestamp", "ALTER TABLE events ADD COLUMN last_bundled_timestamp INTEGER;", "last_bundled_day", "ALTER TABLE events ADD COLUMN last_bundled_day INTEGER;", "last_sampled_complex_event_id", "ALTER TABLE events ADD COLUMN last_sampled_complex_event_id INTEGER;", "last_sampling_rate", "ALTER TABLE events ADD COLUMN last_sampling_rate INTEGER;", "last_exempt_from_sampling", "ALTER TABLE events ADD COLUMN last_exempt_from_sampling INTEGER;", "current_session_count", "ALTER TABLE events ADD COLUMN current_session_count INTEGER;" };
  private static final String[] zzb = { "origin", "ALTER TABLE user_attributes ADD COLUMN origin TEXT;" };
  private static final String[] zzc = { "app_version", "ALTER TABLE apps ADD COLUMN app_version TEXT;", "app_store", "ALTER TABLE apps ADD COLUMN app_store TEXT;", "gmp_version", "ALTER TABLE apps ADD COLUMN gmp_version INTEGER;", "dev_cert_hash", "ALTER TABLE apps ADD COLUMN dev_cert_hash INTEGER;", "measurement_enabled", "ALTER TABLE apps ADD COLUMN measurement_enabled INTEGER;", "last_bundle_start_timestamp", "ALTER TABLE apps ADD COLUMN last_bundle_start_timestamp INTEGER;", "day", "ALTER TABLE apps ADD COLUMN day INTEGER;", "daily_public_events_count", "ALTER TABLE apps ADD COLUMN daily_public_events_count INTEGER;", "daily_events_count", "ALTER TABLE apps ADD COLUMN daily_events_count INTEGER;", "daily_conversions_count", "ALTER TABLE apps ADD COLUMN daily_conversions_count INTEGER;", "remote_config", "ALTER TABLE apps ADD COLUMN remote_config BLOB;", "config_fetched_time", "ALTER TABLE apps ADD COLUMN config_fetched_time INTEGER;", "failed_config_fetch_time", "ALTER TABLE apps ADD COLUMN failed_config_fetch_time INTEGER;", "app_version_int", "ALTER TABLE apps ADD COLUMN app_version_int INTEGER;", "firebase_instance_id", "ALTER TABLE apps ADD COLUMN firebase_instance_id TEXT;", "daily_error_events_count", "ALTER TABLE apps ADD COLUMN daily_error_events_count INTEGER;", "daily_realtime_events_count", "ALTER TABLE apps ADD COLUMN daily_realtime_events_count INTEGER;", "health_monitor_sample", "ALTER TABLE apps ADD COLUMN health_monitor_sample TEXT;", "android_id", "ALTER TABLE apps ADD COLUMN android_id INTEGER;", "adid_reporting_enabled", "ALTER TABLE apps ADD COLUMN adid_reporting_enabled INTEGER;", "ssaid_reporting_enabled", "ALTER TABLE apps ADD COLUMN ssaid_reporting_enabled INTEGER;", "admob_app_id", "ALTER TABLE apps ADD COLUMN admob_app_id TEXT;", "linked_admob_app_id", "ALTER TABLE apps ADD COLUMN linked_admob_app_id TEXT;", "dynamite_version", "ALTER TABLE apps ADD COLUMN dynamite_version INTEGER;", "safelisted_events", "ALTER TABLE apps ADD COLUMN safelisted_events TEXT;", "ga_app_id", "ALTER TABLE apps ADD COLUMN ga_app_id TEXT;", "config_last_modified_time", "ALTER TABLE apps ADD COLUMN config_last_modified_time TEXT;", "e_tag", "ALTER TABLE apps ADD COLUMN e_tag TEXT;", "session_stitching_token", "ALTER TABLE apps ADD COLUMN session_stitching_token TEXT;" };
  private static final String[] zzd = { "realtime", "ALTER TABLE raw_events ADD COLUMN realtime INTEGER;" };
  private static final String[] zze = { "has_realtime", "ALTER TABLE queue ADD COLUMN has_realtime INTEGER;", "retry_count", "ALTER TABLE queue ADD COLUMN retry_count INTEGER;" };
  private static final String[] zzg = { "session_scoped", "ALTER TABLE event_filters ADD COLUMN session_scoped BOOLEAN;" };
  private static final String[] zzh = { "session_scoped", "ALTER TABLE property_filters ADD COLUMN session_scoped BOOLEAN;" };
  private static final String[] zzi = { "previous_install_count", "ALTER TABLE app2 ADD COLUMN previous_install_count INTEGER;" };
  private final zzal zzj;
  private final zzkj zzk = new zzkj(zzs.zzav());
  
  zzam(zzkz paramZzkz)
  {
    super(paramZzkz);
    zzs.zzf();
    zzj = new zzal(this, zzs.zzau(), "google_app_measurement.db");
  }
  
  static final void zzV(ContentValues paramContentValues, String paramString, Object paramObject)
  {
    Preconditions.checkNotEmpty("value");
    Preconditions.checkNotNull(paramObject);
    if ((paramObject instanceof String))
    {
      paramContentValues.put("value", (String)paramObject);
      return;
    }
    if ((paramObject instanceof Long))
    {
      paramContentValues.put("value", (Long)paramObject);
      return;
    }
    if ((paramObject instanceof Double))
    {
      paramContentValues.put("value", (Double)paramObject);
      return;
    }
    throw new IllegalArgumentException("Invalid value type");
  }
  
  /* Error */
  private final long zzZ(String paramString, String[] paramArrayOfString)
  {
    // Byte code:
    //   0: aload_0
    //   1: invokevirtual 297	com/google/android/gms/measurement/internal/zzam:zzh	()Landroid/database/sqlite/SQLiteDatabase;
    //   4: astore 7
    //   6: aconst_null
    //   7: astore 6
    //   9: aconst_null
    //   10: astore 5
    //   12: aload 7
    //   14: aload_1
    //   15: aload_2
    //   16: invokevirtual 303	android/database/sqlite/SQLiteDatabase:rawQuery	(Ljava/lang/String;[Ljava/lang/String;)Landroid/database/Cursor;
    //   19: astore_2
    //   20: aload_2
    //   21: astore 5
    //   23: aload_2
    //   24: astore 6
    //   26: aload_2
    //   27: invokeinterface 309 1 0
    //   32: ifeq +25 -> 57
    //   35: aload_2
    //   36: astore 5
    //   38: aload_2
    //   39: astore 6
    //   41: aload_2
    //   42: iconst_0
    //   43: invokeinterface 313 2 0
    //   48: lstore_3
    //   49: aload_2
    //   50: invokeinterface 316 1 0
    //   55: lload_3
    //   56: lreturn
    //   57: aload_2
    //   58: astore 5
    //   60: aload_2
    //   61: astore 6
    //   63: new 294	android/database/sqlite/SQLiteException
    //   66: dup
    //   67: ldc_w 318
    //   70: invokespecial 319	android/database/sqlite/SQLiteException:<init>	(Ljava/lang/String;)V
    //   73: athrow
    //   74: astore_1
    //   75: goto +32 -> 107
    //   78: astore_2
    //   79: aload 6
    //   81: astore 5
    //   83: aload_0
    //   84: getfield 216	com/google/android/gms/measurement/internal/zzgr:zzs	Lcom/google/android/gms/measurement/internal/zzfy;
    //   87: invokevirtual 323	com/google/android/gms/measurement/internal/zzfy:zzay	()Lcom/google/android/gms/measurement/internal/zzeo;
    //   90: invokevirtual 328	com/google/android/gms/measurement/internal/zzeo:zzd	()Lcom/google/android/gms/measurement/internal/zzem;
    //   93: ldc_w 330
    //   96: aload_1
    //   97: aload_2
    //   98: invokevirtual 335	com/google/android/gms/measurement/internal/zzem:zzc	(Ljava/lang/String;Ljava/lang/Object;Ljava/lang/Object;)V
    //   101: aload 6
    //   103: astore 5
    //   105: aload_2
    //   106: athrow
    //   107: aload 5
    //   109: ifnull +10 -> 119
    //   112: aload 5
    //   114: invokeinterface 316 1 0
    //   119: aload_1
    //   120: athrow
    // Local variable table:
    //   start	length	slot	name	signature
    //   0	121	0	this	zzam
    //   0	121	1	paramString	String
    //   0	121	2	paramArrayOfString	String[]
    //   48	8	3	l	long
    //   10	103	5	arrayOfString1	String[]
    //   7	95	6	arrayOfString2	String[]
    //   4	9	7	localSQLiteDatabase	SQLiteDatabase
    // Exception table:
    //   from	to	target	type
    //   12	20	74	finally
    //   26	35	74	finally
    //   41	49	74	finally
    //   63	74	74	finally
    //   83	101	74	finally
    //   105	107	74	finally
    //   12	20	78	android/database/sqlite/SQLiteException
    //   26	35	78	android/database/sqlite/SQLiteException
    //   41	49	78	android/database/sqlite/SQLiteException
    //   63	74	78	android/database/sqlite/SQLiteException
  }
  
  /* Error */
  private final long zzaa(String paramString, String[] paramArrayOfString, long paramLong)
  {
    // Byte code:
    //   0: aload_0
    //   1: invokevirtual 297	com/google/android/gms/measurement/internal/zzam:zzh	()Landroid/database/sqlite/SQLiteDatabase;
    //   4: astore 7
    //   6: aconst_null
    //   7: astore 6
    //   9: aconst_null
    //   10: astore 5
    //   12: aload 7
    //   14: aload_1
    //   15: aload_2
    //   16: invokevirtual 303	android/database/sqlite/SQLiteDatabase:rawQuery	(Ljava/lang/String;[Ljava/lang/String;)Landroid/database/Cursor;
    //   19: astore_2
    //   20: aload_2
    //   21: astore 5
    //   23: aload_2
    //   24: astore 6
    //   26: aload_2
    //   27: invokeinterface 309 1 0
    //   32: ifeq +25 -> 57
    //   35: aload_2
    //   36: astore 5
    //   38: aload_2
    //   39: astore 6
    //   41: aload_2
    //   42: iconst_0
    //   43: invokeinterface 313 2 0
    //   48: lstore_3
    //   49: aload_2
    //   50: invokeinterface 316 1 0
    //   55: lload_3
    //   56: lreturn
    //   57: aload_2
    //   58: invokeinterface 316 1 0
    //   63: lload_3
    //   64: lreturn
    //   65: astore_1
    //   66: goto +32 -> 98
    //   69: astore_2
    //   70: aload 6
    //   72: astore 5
    //   74: aload_0
    //   75: getfield 216	com/google/android/gms/measurement/internal/zzgr:zzs	Lcom/google/android/gms/measurement/internal/zzfy;
    //   78: invokevirtual 323	com/google/android/gms/measurement/internal/zzfy:zzay	()Lcom/google/android/gms/measurement/internal/zzeo;
    //   81: invokevirtual 328	com/google/android/gms/measurement/internal/zzeo:zzd	()Lcom/google/android/gms/measurement/internal/zzem;
    //   84: ldc_w 330
    //   87: aload_1
    //   88: aload_2
    //   89: invokevirtual 335	com/google/android/gms/measurement/internal/zzem:zzc	(Ljava/lang/String;Ljava/lang/Object;Ljava/lang/Object;)V
    //   92: aload 6
    //   94: astore 5
    //   96: aload_2
    //   97: athrow
    //   98: aload 5
    //   100: ifnull +10 -> 110
    //   103: aload 5
    //   105: invokeinterface 316 1 0
    //   110: aload_1
    //   111: athrow
    // Local variable table:
    //   start	length	slot	name	signature
    //   0	112	0	this	zzam
    //   0	112	1	paramString	String
    //   0	112	2	paramArrayOfString	String[]
    //   0	112	3	paramLong	long
    //   10	94	5	arrayOfString1	String[]
    //   7	86	6	arrayOfString2	String[]
    //   4	9	7	localSQLiteDatabase	SQLiteDatabase
    // Exception table:
    //   from	to	target	type
    //   12	20	65	finally
    //   26	35	65	finally
    //   41	49	65	finally
    //   74	92	65	finally
    //   96	98	65	finally
    //   12	20	69	android/database/sqlite/SQLiteException
    //   26	35	69	android/database/sqlite/SQLiteException
    //   41	49	69	android/database/sqlite/SQLiteException
  }
  
  public final void zzA(String paramString1, String paramString2)
  {
    Preconditions.checkNotEmpty(paramString1);
    Preconditions.checkNotEmpty(paramString2);
    zzg();
    zzW();
    try
    {
      zzh().delete("user_attributes", "app_id=? and name=?", new String[] { paramString1, paramString2 });
      return;
    }
    catch (SQLiteException localSQLiteException)
    {
      zzs.zzay().zzd().zzd("Error deleting user property. appId", zzeo.zzn(paramString1), zzs.zzj().zzf(paramString2), localSQLiteException);
    }
  }
  
  final void zzB(String paramString, List paramList)
  {
    Object localObject1 = "app_id=? and audience_id=?";
    Preconditions.checkNotNull(paramList);
    int j = 0;
    Object localObject2;
    Object localObject3;
    Object localObject6;
    Object localObject8;
    int i;
    Object localObject9;
    while (j < paramList.size())
    {
      localObject2 = (zzeg)((zzeh)paramList.get(j)).zzby();
      if (((zzeg)localObject2).zza() != 0)
      {
        localObject3 = localObject2;
        int k = 0;
        while (k < ((zzeg)localObject3).zza())
        {
          localObject6 = (zzei)((zzeg)localObject3).zze(k).zzby();
          localObject7 = (zzei)((zzka)localObject6).zzaB();
          localObject8 = zzgv.zzb(((zzei)localObject6).zze());
          if (localObject8 != null)
          {
            ((zzei)localObject7).zzb((String)localObject8);
            i = 1;
          }
          else
          {
            i = 0;
          }
          int n = 0;
          int m = i;
          i = n;
          while (i < ((zzei)localObject6).zza())
          {
            localObject9 = ((zzei)localObject6).zzd(i);
            localObject8 = zzij.zzb(((zzel)localObject9).zze(), zzgw.zza, zzgw.zzb);
            if (localObject8 != null)
            {
              localObject9 = (zzek)((zzke)localObject9).zzby();
              ((zzek)localObject9).zza((String)localObject8);
              ((zzei)localObject7).zzc(i, (zzel)((zzka)localObject9).zzaE());
              m = 1;
            }
            i += 1;
          }
          localObject6 = localObject3;
          if (m != 0)
          {
            ((zzeg)localObject3).zzc(k, (zzei)localObject7);
            paramList.set(j, (zzeh)((zzka)localObject2).zzaE());
            localObject6 = localObject2;
          }
          k += 1;
          localObject3 = localObject6;
        }
      }
      else
      {
        localObject3 = localObject2;
      }
      if (((zzeg)localObject3).zzb() != 0)
      {
        i = 0;
        while (i < ((zzeg)localObject3).zzb())
        {
          localObject8 = ((zzeg)localObject3).zzf(i);
          localObject7 = zzij.zzb(((zzes)localObject8).zze(), zzgx.zza, zzgx.zzb);
          localObject6 = localObject3;
          if (localObject7 != null)
          {
            localObject6 = (zzer)((zzke)localObject8).zzby();
            ((zzer)localObject6).zza((String)localObject7);
            ((zzeg)localObject3).zzd(i, (zzer)localObject6);
            paramList.set(j, (zzeh)((zzka)localObject2).zzaE());
            localObject6 = localObject2;
          }
          i += 1;
          localObject3 = localObject6;
        }
      }
      j += 1;
    }
    zzW();
    zzg();
    Preconditions.checkNotEmpty(paramString);
    Preconditions.checkNotNull(paramList);
    Object localObject7 = zzh();
    ((SQLiteDatabase)localObject7).beginTransaction();
    for (;;)
    {
      try
      {
        zzW();
        zzg();
        Preconditions.checkNotEmpty(paramString);
        localObject2 = zzh();
        ((SQLiteDatabase)localObject2).delete("property_filters", "app_id=?", new String[] { paramString });
        ((SQLiteDatabase)localObject2).delete("event_filters", "app_id=?", new String[] { paramString });
        localObject3 = paramList.iterator();
        localObject2 = localObject1;
        localObject1 = localObject3;
        if (((Iterator)localObject1).hasNext())
        {
          localObject6 = (zzeh)((Iterator)localObject1).next();
          zzW();
          zzg();
          Preconditions.checkNotEmpty(paramString);
          Preconditions.checkNotNull(localObject6);
          bool = ((zzeh)localObject6).zzk();
          if (bool) {}
        }
        try
        {
          zzs.zzay().zzk().zzb("Audience with no ID. appId", zzeo.zzn(paramString));
        }
        finally
        {
          com.google.android.gms.internal.measurement.zzej localZzej;
          Object localObject10;
          Object localObject4;
          break label1782;
        }
        i = ((zzeh)localObject6).zza();
        localObject3 = ((zzeh)localObject6).zzg().iterator();
        if (((Iterator)localObject3).hasNext())
        {
          if (((com.google.android.gms.internal.measurement.zzej)((Iterator)localObject3).next()).zzp()) {
            continue;
          }
          zzs.zzay().zzk().zzc("Event filter with no ID. Audience definition ignored. appId, audienceId", zzeo.zzn(paramString), Integer.valueOf(i));
          continue;
        }
        localObject3 = ((zzeh)localObject6).zzh().iterator();
        if (((Iterator)localObject3).hasNext())
        {
          if (((zzes)((Iterator)localObject3).next()).zzj()) {
            continue;
          }
          zzs.zzay().zzk().zzc("Property filter with no ID. Audience definition ignored. appId, audienceId", zzeo.zzn(paramString), Integer.valueOf(i));
          continue;
        }
        localObject8 = ((zzeh)localObject6).zzg().iterator();
        boolean bool = ((Iterator)localObject8).hasNext();
        if (bool)
        {
          localZzej = (com.google.android.gms.internal.measurement.zzej)((Iterator)localObject8).next();
          zzW();
          zzg();
          Preconditions.checkNotEmpty(paramString);
          Preconditions.checkNotNull(localZzej);
          if (localZzej.zzg().isEmpty())
          {
            localObject6 = zzs.zzay().zzk();
            localObject8 = zzeo.zzn(paramString);
            if (!localZzej.zzp()) {
              break label1789;
            }
            localObject3 = Integer.valueOf(localZzej.zzb());
            ((zzem)localObject6).zzd("Event filter had no event name. Audience definition ignored. appId, audienceId, filterId", localObject8, Integer.valueOf(i), String.valueOf(localObject3));
          }
          else
          {
            localObject9 = localZzej.zzbv();
            localObject10 = new ContentValues();
            ((ContentValues)localObject10).put("app_id", paramString);
            ((ContentValues)localObject10).put("audience_id", Integer.valueOf(i));
            if (!localZzej.zzp()) {
              break label1795;
            }
            localObject3 = Integer.valueOf(localZzej.zzb());
            ((ContentValues)localObject10).put("filter_id", (Integer)localObject3);
            ((ContentValues)localObject10).put("event_name", localZzej.zzg());
            if (!localZzej.zzq()) {
              break label1801;
            }
            localObject3 = Boolean.valueOf(localZzej.zzn());
            ((ContentValues)localObject10).put("session_scoped", (Boolean)localObject3);
            ((ContentValues)localObject10).put("data", (byte[])localObject9);
            try
            {
              if (zzh().insertWithOnConflict("event_filters", null, (ContentValues)localObject10, 5) == -1L) {
                zzs.zzay().zzd().zzb("Failed to insert event filter (got -1). appId", zzeo.zzn(paramString));
              }
            }
            catch (SQLiteException localSQLiteException1)
            {
              zzs.zzay().zzd().zzc("Error storing event filter. appId", zzeo.zzn(paramString), localSQLiteException1);
              continue;
            }
          }
        }
        else
        {
          localObject4 = ((zzeh)localObject6).zzh().iterator();
          if (!((Iterator)localObject4).hasNext()) {
            break label1825;
          }
          localObject10 = (zzes)((Iterator)localObject4).next();
          zzW();
          zzg();
          Preconditions.checkNotEmpty(paramString);
          Preconditions.checkNotNull(localObject10);
          if (((zzes)localObject10).zze().isEmpty())
          {
            localObject6 = zzs.zzay().zzk();
            localObject8 = zzeo.zzn(paramString);
            if (!((zzes)localObject10).zzj()) {
              break label1807;
            }
            localObject4 = Integer.valueOf(((zzes)localObject10).zza());
            ((zzem)localObject6).zzd("Property filter had no property name. Audience definition ignored. appId, audienceId, filterId", localObject8, Integer.valueOf(i), String.valueOf(localObject4));
          }
          else
          {
            localObject8 = ((zzin)localObject10).zzbv();
            localObject9 = new ContentValues();
            ((ContentValues)localObject9).put("app_id", paramString);
            ((ContentValues)localObject9).put("audience_id", Integer.valueOf(i));
            if (!((zzes)localObject10).zzj()) {
              break label1813;
            }
            localObject6 = Integer.valueOf(((zzes)localObject10).zza());
            ((ContentValues)localObject9).put("filter_id", (Integer)localObject6);
            ((ContentValues)localObject9).put("property_name", ((zzes)localObject10).zze());
            if (!((zzes)localObject10).zzk()) {
              break label1819;
            }
            localObject6 = Boolean.valueOf(((zzes)localObject10).zzi());
            ((ContentValues)localObject9).put("session_scoped", (Boolean)localObject6);
            ((ContentValues)localObject9).put("data", (byte[])localObject8);
            try
            {
              if (zzh().insertWithOnConflict("property_filters", null, (ContentValues)localObject9, 5) == -1L) {
                zzs.zzay().zzd().zzb("Failed to insert property filter (got -1). appId", zzeo.zzn(paramString));
              }
            }
            catch (SQLiteException localSQLiteException2)
            {
              zzs.zzay().zzd().zzc("Error storing property filter. appId", zzeo.zzn(paramString), localSQLiteException2);
            }
          }
        }
        zzW();
        zzg();
        Preconditions.checkNotEmpty(paramString);
        localObject5 = zzh();
        ((SQLiteDatabase)localObject5).delete("property_filters", (String)localObject2, new String[] { paramString, String.valueOf(i) });
        ((SQLiteDatabase)localObject5).delete("event_filters", (String)localObject2, new String[] { paramString, String.valueOf(i) });
        continue;
        localObject1 = new ArrayList();
        localObject2 = paramList.iterator();
        if (((Iterator)localObject2).hasNext())
        {
          paramList = (zzeh)((Iterator)localObject2).next();
          if (!paramList.zzk()) {
            break label1828;
          }
          paramList = Integer.valueOf(paramList.zza());
          ((List)localObject1).add(paramList);
          continue;
        }
        Preconditions.checkNotEmpty(paramString);
        zzW();
        zzg();
        paramList = zzh();
        try
        {
          long l = zzZ("select count(1) from audience_filter_values where app_id=?", new String[] { paramString });
          j = Math.max(0, Math.min(2000, zzs.zzf().zze(paramString, zzeb.zzE)));
          if (l > j)
          {
            localObject2 = new ArrayList();
            i = 0;
            if (i < ((List)localObject1).size())
            {
              localObject5 = (Integer)((List)localObject1).get(i);
              if (localObject5 != null)
              {
                ((List)localObject2).add(Integer.toString(((Integer)localObject5).intValue()));
                i += 1;
              }
            }
            else
            {
              localObject2 = TextUtils.join(",", (Iterable)localObject2);
              localObject1 = new StringBuilder();
              ((StringBuilder)localObject1).append("(");
              ((StringBuilder)localObject1).append((String)localObject2);
              ((StringBuilder)localObject1).append(")");
              localObject2 = new StringBuilder();
              ((StringBuilder)localObject2).append("audience_id in (select audience_id from audience_filter_values where app_id=? and audience_id not in ");
              ((StringBuilder)localObject2).append(((StringBuilder)localObject1).toString());
              ((StringBuilder)localObject2).append(" order by rowid desc limit -1 offset ?)");
              localObject1 = Integer.toString(j);
              paramList.delete("audience_filter_values", ((StringBuilder)localObject2).toString(), new String[] { paramString, localObject1 });
            }
          }
        }
        catch (SQLiteException paramList)
        {
          zzs.zzay().zzd().zzc("Database error querying filters. appId", zzeo.zzn(paramString), paramList);
        }
        ((SQLiteDatabase)localObject7).setTransactionSuccessful();
        ((SQLiteDatabase)localObject7).endTransaction();
        return;
      }
      finally {}
      label1782:
      ((SQLiteDatabase)localObject7).endTransaction();
      throw paramString;
      label1789:
      Object localObject5 = null;
      continue;
      label1795:
      localObject5 = null;
      continue;
      label1801:
      localObject5 = null;
      continue;
      label1807:
      localObject5 = null;
      continue;
      label1813:
      localObject6 = null;
      continue;
      label1819:
      localObject6 = null;
      continue;
      label1825:
      continue;
      label1828:
      paramList = null;
    }
  }
  
  public final void zzC()
  {
    zzW();
    zzh().setTransactionSuccessful();
  }
  
  public final void zzD(zzh paramZzh)
  {
    Preconditions.checkNotNull(paramZzh);
    zzg();
    zzW();
    String str = paramZzh.zzt();
    Preconditions.checkNotNull(str);
    ContentValues localContentValues = new ContentValues();
    localContentValues.put("app_id", str);
    localContentValues.put("app_instance_id", paramZzh.zzu());
    localContentValues.put("gmp_app_id", paramZzh.zzy());
    localContentValues.put("resettable_device_id_hash", paramZzh.zzA());
    localContentValues.put("last_bundle_index", Long.valueOf(paramZzh.zzo()));
    localContentValues.put("last_bundle_start_timestamp", Long.valueOf(paramZzh.zzp()));
    localContentValues.put("last_bundle_end_timestamp", Long.valueOf(paramZzh.zzn()));
    localContentValues.put("app_version", paramZzh.zzw());
    localContentValues.put("app_store", paramZzh.zzv());
    localContentValues.put("gmp_version", Long.valueOf(paramZzh.zzm()));
    localContentValues.put("dev_cert_hash", Long.valueOf(paramZzh.zzj()));
    localContentValues.put("measurement_enabled", Boolean.valueOf(paramZzh.zzai()));
    localContentValues.put("day", Long.valueOf(paramZzh.zzi()));
    localContentValues.put("daily_public_events_count", Long.valueOf(paramZzh.zzg()));
    localContentValues.put("daily_events_count", Long.valueOf(paramZzh.zzf()));
    localContentValues.put("daily_conversions_count", Long.valueOf(paramZzh.zzd()));
    localContentValues.put("config_fetched_time", Long.valueOf(paramZzh.zzc()));
    localContentValues.put("failed_config_fetch_time", Long.valueOf(paramZzh.zzl()));
    localContentValues.put("app_version_int", Long.valueOf(paramZzh.zzb()));
    localContentValues.put("firebase_instance_id", paramZzh.zzx());
    localContentValues.put("daily_error_events_count", Long.valueOf(paramZzh.zze()));
    localContentValues.put("daily_realtime_events_count", Long.valueOf(paramZzh.zzh()));
    localContentValues.put("health_monitor_sample", paramZzh.zzz());
    paramZzh.zza();
    localContentValues.put("android_id", Long.valueOf(0L));
    localContentValues.put("adid_reporting_enabled", Boolean.valueOf(paramZzh.zzah()));
    localContentValues.put("admob_app_id", paramZzh.zzr());
    localContentValues.put("dynamite_version", Long.valueOf(paramZzh.zzk()));
    localContentValues.put("session_stitching_token", paramZzh.zzB());
    paramZzh = paramZzh.zzC();
    if (paramZzh != null) {
      if (paramZzh.isEmpty()) {
        zzs.zzay().zzk().zzb("Safelisted events should not be an empty list. appId", str);
      } else {
        localContentValues.put("safelisted_events", TextUtils.join(",", paramZzh));
      }
    }
    zzns.zzc();
    if ((zzs.zzf().zzs(null, zzeb.zzai)) && (!localContentValues.containsKey("safelisted_events"))) {
      localContentValues.put("safelisted_events", null);
    }
    try
    {
      paramZzh = zzh();
      if ((paramZzh.update("apps", localContentValues, "app_id = ?", new String[] { str }) == 0L) && (paramZzh.insertWithOnConflict("apps", null, localContentValues, 5) == -1L)) {
        zzs.zzay().zzd().zzb("Failed to insert/update app (got -1). appId", zzeo.zzn(str));
      }
      return;
    }
    catch (SQLiteException paramZzh)
    {
      zzs.zzay().zzd().zzc("Error storing app. appId", zzeo.zzn(str), paramZzh);
    }
  }
  
  public final void zzE(zzas paramZzas)
  {
    Preconditions.checkNotNull(paramZzas);
    zzg();
    zzW();
    ContentValues localContentValues = new ContentValues();
    localContentValues.put("app_id", zza);
    localContentValues.put("name", zzb);
    localContentValues.put("lifetime_count", Long.valueOf(zzc));
    localContentValues.put("current_bundle_count", Long.valueOf(zzd));
    localContentValues.put("last_fire_timestamp", Long.valueOf(zzf));
    localContentValues.put("last_bundled_timestamp", Long.valueOf(zzg));
    localContentValues.put("last_bundled_day", zzh);
    localContentValues.put("last_sampled_complex_event_id", zzi);
    localContentValues.put("last_sampling_rate", zzj);
    localContentValues.put("current_session_count", Long.valueOf(zze));
    Object localObject = zzk;
    if ((localObject != null) && (((Boolean)localObject).booleanValue())) {
      localObject = Long.valueOf(1L);
    } else {
      localObject = null;
    }
    localContentValues.put("last_exempt_from_sampling", (Long)localObject);
    try
    {
      if (zzh().insertWithOnConflict("events", null, localContentValues, 5) == -1L) {
        zzs.zzay().zzd().zzb("Failed to insert/update event aggregates (got -1). appId", zzeo.zzn(zza));
      }
      return;
    }
    catch (SQLiteException localSQLiteException)
    {
      zzs.zzay().zzd().zzc("Error storing event aggregates. appId", zzeo.zzn(zza), localSQLiteException);
    }
  }
  
  public final boolean zzF()
  {
    return zzZ("select count(1) > 0 from raw_events", null) != 0L;
  }
  
  public final boolean zzG()
  {
    return zzZ("select count(1) > 0 from queue where has_realtime = 1", null) != 0L;
  }
  
  public final boolean zzH()
  {
    return zzZ("select count(1) > 0 from raw_events where realtime = 1", null) != 0L;
  }
  
  @VisibleForTesting
  protected final boolean zzI()
  {
    Context localContext = zzs.zzau();
    zzs.zzf();
    return localContext.getDatabasePath("google_app_measurement.db").exists();
  }
  
  public final boolean zzJ(String paramString, Long paramLong, long paramLong1, zzfs paramZzfs)
  {
    zzg();
    zzW();
    Preconditions.checkNotNull(paramZzfs);
    Preconditions.checkNotEmpty(paramString);
    Preconditions.checkNotNull(paramLong);
    paramZzfs = paramZzfs.zzbv();
    zzs.zzay().zzj().zzc("Saving complex main event, appId, data size", zzs.zzj().zzd(paramString), Integer.valueOf(paramZzfs.length));
    ContentValues localContentValues = new ContentValues();
    localContentValues.put("app_id", paramString);
    localContentValues.put("event_id", paramLong);
    localContentValues.put("children_to_process", Long.valueOf(paramLong1));
    localContentValues.put("main_event", paramZzfs);
    try
    {
      if (zzh().insertWithOnConflict("main_event_params", null, localContentValues, 5) == -1L)
      {
        zzs.zzay().zzd().zzb("Failed to insert complex main event (got -1). appId", zzeo.zzn(paramString));
        return false;
      }
      return true;
    }
    catch (SQLiteException paramLong)
    {
      zzs.zzay().zzd().zzc("Error storing complex main event. appId", zzeo.zzn(paramString), paramLong);
    }
    return false;
  }
  
  public final boolean zzK(zzac paramZzac)
  {
    Preconditions.checkNotNull(paramZzac);
    zzg();
    zzW();
    String str = zza;
    Preconditions.checkNotNull(str);
    if (zzp(str, zzc.zzb) == null)
    {
      long l = zzZ("SELECT COUNT(1) FROM conditional_properties WHERE app_id=?", new String[] { str });
      zzs.zzf();
      if (l >= 1000L) {
        return false;
      }
    }
    ContentValues localContentValues = new ContentValues();
    localContentValues.put("app_id", str);
    localContentValues.put("origin", zzb);
    localContentValues.put("name", zzc.zzb);
    zzV(localContentValues, "value", Preconditions.checkNotNull(zzc.zza()));
    localContentValues.put("active", Boolean.valueOf(zze));
    localContentValues.put("trigger_event_name", zzf);
    localContentValues.put("trigger_timeout", Long.valueOf(zzh));
    localContentValues.put("timed_out_event", zzs.zzv().zzan(zzg));
    localContentValues.put("creation_timestamp", Long.valueOf(zzd));
    localContentValues.put("triggered_event", zzs.zzv().zzan(zzi));
    localContentValues.put("triggered_timestamp", Long.valueOf(zzc.zzc));
    localContentValues.put("time_to_live", Long.valueOf(zzj));
    localContentValues.put("expired_event", zzs.zzv().zzan(zzk));
    try
    {
      if (zzh().insertWithOnConflict("conditional_properties", null, localContentValues, 5) == -1L)
      {
        zzs.zzay().zzd().zzb("Failed to insert/update conditional user property (got -1)", zzeo.zzn(str));
        return true;
      }
    }
    catch (SQLiteException paramZzac)
    {
      zzs.zzay().zzd().zzc("Error storing conditional user property", zzeo.zzn(str), paramZzac);
    }
    return true;
  }
  
  public final boolean zzL(zzle paramZzle)
  {
    Preconditions.checkNotNull(paramZzle);
    zzg();
    zzW();
    if (zzp(zza, zzc) == null) {
      if (zzlh.zzai(zzc))
      {
        if (zzZ("select count(1) from user_attributes where app_id=? and name not like '!_%' escape '!'", new String[] { zza }) >= zzs.zzf().zzf(zza, zzeb.zzF, 25, 100)) {
          return false;
        }
      }
      else if (!"_npa".equals(zzc))
      {
        long l = zzZ("select count(1) from user_attributes where app_id=? and origin=? AND name like '!_%' escape '!'", new String[] { zza, zzb });
        zzs.zzf();
        if (l >= 25L) {
          return false;
        }
      }
    }
    ContentValues localContentValues = new ContentValues();
    localContentValues.put("app_id", zza);
    localContentValues.put("origin", zzb);
    localContentValues.put("name", zzc);
    localContentValues.put("set_timestamp", Long.valueOf(zzd));
    zzV(localContentValues, "value", zze);
    try
    {
      if (zzh().insertWithOnConflict("user_attributes", null, localContentValues, 5) == -1L)
      {
        zzs.zzay().zzd().zzb("Failed to insert/update user property (got -1). appId", zzeo.zzn(zza));
        return true;
      }
    }
    catch (SQLiteException localSQLiteException)
    {
      zzs.zzay().zzd().zzc("Error storing user property. appId", zzeo.zzn(zza), localSQLiteException);
    }
    return true;
  }
  
  /* Error */
  public final void zzU(String paramString, long paramLong1, long paramLong2, zzkw paramZzkw)
  {
    // Byte code:
    //   0: aload 6
    //   2: invokestatic 267	com/google/android/gms/common/internal/Preconditions:checkNotNull	(Ljava/lang/Object;)Ljava/lang/Object;
    //   5: pop
    //   6: aload_0
    //   7: invokevirtual 342	com/google/android/gms/measurement/internal/zzgr:zzg	()V
    //   10: aload_0
    //   11: invokevirtual 345	com/google/android/gms/measurement/internal/zzkn:zzW	()V
    //   14: aconst_null
    //   15: astore 12
    //   17: aconst_null
    //   18: astore 10
    //   20: aconst_null
    //   21: astore 11
    //   23: aconst_null
    //   24: astore 13
    //   26: aload_0
    //   27: invokevirtual 297	com/google/android/gms/measurement/internal/zzam:zzh	()Landroid/database/sqlite/SQLiteDatabase;
    //   30: astore 15
    //   32: aconst_null
    //   33: invokestatic 992	android/text/TextUtils:isEmpty	(Ljava/lang/CharSequence;)Z
    //   36: istore 8
    //   38: ldc_w 994
    //   41: astore_1
    //   42: iload 8
    //   44: ifeq +229 -> 273
    //   47: lload 4
    //   49: ldc2_w 577
    //   52: lcmp
    //   53: istore 7
    //   55: iload 7
    //   57: ifeq +29 -> 86
    //   60: iconst_2
    //   61: anewarray 21	java/lang/String
    //   64: astore 9
    //   66: aload 9
    //   68: iconst_0
    //   69: lload 4
    //   71: invokestatic 997	java/lang/String:valueOf	(J)Ljava/lang/String;
    //   74: aastore
    //   75: aload 9
    //   77: iconst_1
    //   78: lload_2
    //   79: invokestatic 997	java/lang/String:valueOf	(J)Ljava/lang/String;
    //   82: aastore
    //   83: goto +17 -> 100
    //   86: iconst_1
    //   87: anewarray 21	java/lang/String
    //   90: astore 9
    //   92: aload 9
    //   94: iconst_0
    //   95: lload_2
    //   96: invokestatic 997	java/lang/String:valueOf	(J)Ljava/lang/String;
    //   99: aastore
    //   100: iload 7
    //   102: ifeq +7 -> 109
    //   105: ldc_w 999
    //   108: astore_1
    //   109: new 644	java/lang/StringBuilder
    //   112: dup
    //   113: invokespecial 645	java/lang/StringBuilder:<init>	()V
    //   116: astore 12
    //   118: aload 12
    //   120: ldc_w 1001
    //   123: invokevirtual 651	java/lang/StringBuilder:append	(Ljava/lang/String;)Ljava/lang/StringBuilder;
    //   126: pop
    //   127: aload 12
    //   129: aload_1
    //   130: invokevirtual 651	java/lang/StringBuilder:append	(Ljava/lang/String;)Ljava/lang/StringBuilder;
    //   133: pop
    //   134: aload 12
    //   136: ldc_w 1003
    //   139: invokevirtual 651	java/lang/StringBuilder:append	(Ljava/lang/String;)Ljava/lang/StringBuilder;
    //   142: pop
    //   143: aload 15
    //   145: aload 12
    //   147: invokevirtual 657	java/lang/StringBuilder:toString	()Ljava/lang/String;
    //   150: aload 9
    //   152: invokevirtual 303	android/database/sqlite/SQLiteDatabase:rawQuery	(Ljava/lang/String;[Ljava/lang/String;)Landroid/database/Cursor;
    //   155: astore 12
    //   157: aload 13
    //   159: astore 11
    //   161: aload 12
    //   163: astore 10
    //   165: aload 12
    //   167: astore_1
    //   168: aload 12
    //   170: invokeinterface 309 1 0
    //   175: istore 8
    //   177: iload 8
    //   179: ifne +11 -> 190
    //   182: aload 12
    //   184: invokeinterface 316 1 0
    //   189: return
    //   190: aload 13
    //   192: astore 11
    //   194: aload 12
    //   196: astore 10
    //   198: aload 12
    //   200: astore_1
    //   201: aload 12
    //   203: iconst_0
    //   204: invokeinterface 1006 2 0
    //   209: astore 9
    //   211: aload 9
    //   213: astore 11
    //   215: aload 12
    //   217: astore 10
    //   219: aload 12
    //   221: astore_1
    //   222: aload 12
    //   224: iconst_1
    //   225: invokeinterface 1006 2 0
    //   230: astore 13
    //   232: aload 9
    //   234: astore 11
    //   236: aload 12
    //   238: astore 10
    //   240: aload 12
    //   242: astore_1
    //   243: aload 12
    //   245: invokeinterface 316 1 0
    //   250: aload 12
    //   252: astore_1
    //   253: aload 13
    //   255: astore 11
    //   257: goto +202 -> 459
    //   260: astore 12
    //   262: aload 11
    //   264: astore 9
    //   266: aload 10
    //   268: astore 6
    //   270: goto +833 -> 1103
    //   273: lload 4
    //   275: ldc2_w 577
    //   278: lcmp
    //   279: istore 7
    //   281: iload 7
    //   283: ifeq +26 -> 309
    //   286: iconst_2
    //   287: anewarray 21	java/lang/String
    //   290: astore 9
    //   292: aload 9
    //   294: iconst_0
    //   295: aconst_null
    //   296: aastore
    //   297: aload 9
    //   299: iconst_1
    //   300: lload 4
    //   302: invokestatic 997	java/lang/String:valueOf	(J)Ljava/lang/String;
    //   305: aastore
    //   306: goto +13 -> 319
    //   309: iconst_1
    //   310: anewarray 21	java/lang/String
    //   313: dup
    //   314: iconst_0
    //   315: aconst_null
    //   316: aastore
    //   317: astore 9
    //   319: iload 7
    //   321: ifeq +7 -> 328
    //   324: ldc_w 1008
    //   327: astore_1
    //   328: new 644	java/lang/StringBuilder
    //   331: dup
    //   332: invokespecial 645	java/lang/StringBuilder:<init>	()V
    //   335: astore 14
    //   337: aload 14
    //   339: ldc_w 1010
    //   342: invokevirtual 651	java/lang/StringBuilder:append	(Ljava/lang/String;)Ljava/lang/StringBuilder;
    //   345: pop
    //   346: aload 14
    //   348: aload_1
    //   349: invokevirtual 651	java/lang/StringBuilder:append	(Ljava/lang/String;)Ljava/lang/StringBuilder;
    //   352: pop
    //   353: aload 14
    //   355: ldc_w 1012
    //   358: invokevirtual 651	java/lang/StringBuilder:append	(Ljava/lang/String;)Ljava/lang/StringBuilder;
    //   361: pop
    //   362: aload 15
    //   364: aload 14
    //   366: invokevirtual 657	java/lang/StringBuilder:toString	()Ljava/lang/String;
    //   369: aload 9
    //   371: invokevirtual 303	android/database/sqlite/SQLiteDatabase:rawQuery	(Ljava/lang/String;[Ljava/lang/String;)Landroid/database/Cursor;
    //   374: astore 9
    //   376: aload 13
    //   378: astore 11
    //   380: aload 9
    //   382: astore 10
    //   384: aload 9
    //   386: astore_1
    //   387: aload 9
    //   389: invokeinterface 309 1 0
    //   394: istore 8
    //   396: iload 8
    //   398: ifne +11 -> 409
    //   401: aload 9
    //   403: invokeinterface 316 1 0
    //   408: return
    //   409: aload 13
    //   411: astore 11
    //   413: aload 9
    //   415: astore 10
    //   417: aload 9
    //   419: astore_1
    //   420: aload 9
    //   422: iconst_0
    //   423: invokeinterface 1006 2 0
    //   428: astore 14
    //   430: aload 13
    //   432: astore 11
    //   434: aload 9
    //   436: astore 10
    //   438: aload 9
    //   440: astore_1
    //   441: aload 9
    //   443: invokeinterface 316 1 0
    //   448: aload 14
    //   450: astore 11
    //   452: aload 9
    //   454: astore_1
    //   455: aload 12
    //   457: astore 9
    //   459: aload 15
    //   461: ldc_w 1014
    //   464: iconst_1
    //   465: anewarray 21	java/lang/String
    //   468: dup
    //   469: iconst_0
    //   470: ldc_w 1016
    //   473: aastore
    //   474: ldc_w 1018
    //   477: iconst_2
    //   478: anewarray 21	java/lang/String
    //   481: dup
    //   482: iconst_0
    //   483: aload 9
    //   485: aastore
    //   486: dup
    //   487: iconst_1
    //   488: aload 11
    //   490: aastore
    //   491: aconst_null
    //   492: aconst_null
    //   493: ldc_w 1020
    //   496: ldc_w 1022
    //   499: invokevirtual 1026	android/database/sqlite/SQLiteDatabase:query	(Ljava/lang/String;[Ljava/lang/String;Ljava/lang/String;[Ljava/lang/String;Ljava/lang/String;Ljava/lang/String;Ljava/lang/String;Ljava/lang/String;)Landroid/database/Cursor;
    //   502: astore 10
    //   504: aload 10
    //   506: invokeinterface 309 1 0
    //   511: ifne +32 -> 543
    //   514: aload_0
    //   515: getfield 216	com/google/android/gms/measurement/internal/zzgr:zzs	Lcom/google/android/gms/measurement/internal/zzfy;
    //   518: invokevirtual 323	com/google/android/gms/measurement/internal/zzfy:zzay	()Lcom/google/android/gms/measurement/internal/zzeo;
    //   521: invokevirtual 328	com/google/android/gms/measurement/internal/zzeo:zzd	()Lcom/google/android/gms/measurement/internal/zzem;
    //   524: ldc_w 1028
    //   527: aload 9
    //   529: invokestatic 359	com/google/android/gms/measurement/internal/zzeo:zzn	(Ljava/lang/String;)Ljava/lang/Object;
    //   532: invokevirtual 501	com/google/android/gms/measurement/internal/zzem:zzb	(Ljava/lang/String;Ljava/lang/Object;)V
    //   535: aload 10
    //   537: invokeinterface 316 1 0
    //   542: return
    //   543: aload 10
    //   545: iconst_0
    //   546: invokeinterface 1032 2 0
    //   551: astore_1
    //   552: invokestatic 1037	com/google/android/gms/internal/measurement/zzgc:zzt	()Lcom/google/android/gms/internal/measurement/zzgb;
    //   555: aload_1
    //   556: invokestatic 1042	com/google/android/gms/measurement/internal/zzlb:zzl	(Lcom/google/android/gms/internal/measurement/zzlk;[B)Lcom/google/android/gms/internal/measurement/zzlk;
    //   559: checkcast 1044	com/google/android/gms/internal/measurement/zzgb
    //   562: invokevirtual 440	com/google/android/gms/internal/measurement/zzka:zzaE	()Lcom/google/android/gms/internal/measurement/zzke;
    //   565: checkcast 1034	com/google/android/gms/internal/measurement/zzgc
    //   568: astore_1
    //   569: aload 10
    //   571: invokeinterface 1047 1 0
    //   576: ifeq +24 -> 600
    //   579: aload_0
    //   580: getfield 216	com/google/android/gms/measurement/internal/zzgr:zzs	Lcom/google/android/gms/measurement/internal/zzfy;
    //   583: invokevirtual 323	com/google/android/gms/measurement/internal/zzfy:zzay	()Lcom/google/android/gms/measurement/internal/zzeo;
    //   586: invokevirtual 496	com/google/android/gms/measurement/internal/zzeo:zzk	()Lcom/google/android/gms/measurement/internal/zzem;
    //   589: ldc_w 1049
    //   592: aload 9
    //   594: invokestatic 359	com/google/android/gms/measurement/internal/zzeo:zzn	(Ljava/lang/String;)Ljava/lang/Object;
    //   597: invokevirtual 501	com/google/android/gms/measurement/internal/zzem:zzb	(Ljava/lang/String;Ljava/lang/Object;)V
    //   600: aload 10
    //   602: invokeinterface 316 1 0
    //   607: aload_1
    //   608: invokestatic 267	com/google/android/gms/common/internal/Preconditions:checkNotNull	(Ljava/lang/Object;)Ljava/lang/Object;
    //   611: pop
    //   612: aload 6
    //   614: aload_1
    //   615: putfield 1054	com/google/android/gms/measurement/internal/zzkw:zza	Lcom/google/android/gms/internal/measurement/zzgc;
    //   618: lload 4
    //   620: ldc2_w 577
    //   623: lcmp
    //   624: ifeq +34 -> 658
    //   627: ldc_w 1056
    //   630: astore_1
    //   631: iconst_3
    //   632: anewarray 21	java/lang/String
    //   635: dup
    //   636: iconst_0
    //   637: aload 9
    //   639: aastore
    //   640: dup
    //   641: iconst_1
    //   642: aload 11
    //   644: aastore
    //   645: dup
    //   646: iconst_2
    //   647: lload 4
    //   649: invokestatic 997	java/lang/String:valueOf	(J)Ljava/lang/String;
    //   652: aastore
    //   653: astore 11
    //   655: goto +23 -> 678
    //   658: ldc_w 1018
    //   661: astore_1
    //   662: iconst_2
    //   663: anewarray 21	java/lang/String
    //   666: dup
    //   667: iconst_0
    //   668: aload 9
    //   670: aastore
    //   671: dup
    //   672: iconst_1
    //   673: aload 11
    //   675: aastore
    //   676: astore 11
    //   678: aload 15
    //   680: ldc_w 1058
    //   683: iconst_4
    //   684: anewarray 21	java/lang/String
    //   687: dup
    //   688: iconst_0
    //   689: ldc_w 1020
    //   692: aastore
    //   693: dup
    //   694: iconst_1
    //   695: ldc_w 794
    //   698: aastore
    //   699: dup
    //   700: iconst_2
    //   701: ldc_w 1060
    //   704: aastore
    //   705: dup
    //   706: iconst_3
    //   707: ldc_w 569
    //   710: aastore
    //   711: aload_1
    //   712: aload 11
    //   714: aconst_null
    //   715: aconst_null
    //   716: ldc_w 1020
    //   719: aconst_null
    //   720: invokevirtual 1026	android/database/sqlite/SQLiteDatabase:query	(Ljava/lang/String;[Ljava/lang/String;Ljava/lang/String;[Ljava/lang/String;Ljava/lang/String;Ljava/lang/String;Ljava/lang/String;Ljava/lang/String;)Landroid/database/Cursor;
    //   723: astore 12
    //   725: aload 9
    //   727: astore 11
    //   729: aload 12
    //   731: astore 10
    //   733: aload 12
    //   735: astore_1
    //   736: aload 12
    //   738: invokeinterface 309 1 0
    //   743: ifeq +227 -> 970
    //   746: aload 9
    //   748: astore 11
    //   750: aload 12
    //   752: astore 10
    //   754: aload 12
    //   756: astore_1
    //   757: aload 12
    //   759: iconst_0
    //   760: invokeinterface 313 2 0
    //   765: lstore_2
    //   766: aload 9
    //   768: astore 11
    //   770: aload 12
    //   772: astore 10
    //   774: aload 12
    //   776: astore_1
    //   777: aload 12
    //   779: iconst_3
    //   780: invokeinterface 1032 2 0
    //   785: astore 13
    //   787: aload 9
    //   789: astore 11
    //   791: aload 12
    //   793: astore 10
    //   795: aload 12
    //   797: astore_1
    //   798: invokestatic 1065	com/google/android/gms/internal/measurement/zzfs:zze	()Lcom/google/android/gms/internal/measurement/zzfr;
    //   801: aload 13
    //   803: invokestatic 1042	com/google/android/gms/measurement/internal/zzlb:zzl	(Lcom/google/android/gms/internal/measurement/zzlk;[B)Lcom/google/android/gms/internal/measurement/zzlk;
    //   806: checkcast 1067	com/google/android/gms/internal/measurement/zzfr
    //   809: astore 13
    //   811: aload 9
    //   813: astore 11
    //   815: aload 12
    //   817: astore 10
    //   819: aload 12
    //   821: astore_1
    //   822: aload 13
    //   824: aload 12
    //   826: iconst_1
    //   827: invokeinterface 1006 2 0
    //   832: invokevirtual 1070	com/google/android/gms/internal/measurement/zzfr:zzi	(Ljava/lang/String;)Lcom/google/android/gms/internal/measurement/zzfr;
    //   835: pop
    //   836: aload 9
    //   838: astore 11
    //   840: aload 12
    //   842: astore 10
    //   844: aload 12
    //   846: astore_1
    //   847: aload 13
    //   849: aload 12
    //   851: iconst_2
    //   852: invokeinterface 313 2 0
    //   857: invokevirtual 1073	com/google/android/gms/internal/measurement/zzfr:zzm	(J)Lcom/google/android/gms/internal/measurement/zzfr;
    //   860: pop
    //   861: aload 9
    //   863: astore 11
    //   865: aload 12
    //   867: astore 10
    //   869: aload 12
    //   871: astore_1
    //   872: aload 6
    //   874: lload_2
    //   875: aload 13
    //   877: invokevirtual 440	com/google/android/gms/internal/measurement/zzka:zzaE	()Lcom/google/android/gms/internal/measurement/zzke;
    //   880: checkcast 1062	com/google/android/gms/internal/measurement/zzfs
    //   883: invokevirtual 1076	com/google/android/gms/measurement/internal/zzkw:zza	(JLcom/google/android/gms/internal/measurement/zzfs;)Z
    //   886: istore 8
    //   888: iload 8
    //   890: ifne +47 -> 937
    //   893: aload 12
    //   895: invokeinterface 316 1 0
    //   900: return
    //   901: astore 13
    //   903: aload 9
    //   905: astore 11
    //   907: aload 12
    //   909: astore 10
    //   911: aload 12
    //   913: astore_1
    //   914: aload_0
    //   915: getfield 216	com/google/android/gms/measurement/internal/zzgr:zzs	Lcom/google/android/gms/measurement/internal/zzfy;
    //   918: invokevirtual 323	com/google/android/gms/measurement/internal/zzfy:zzay	()Lcom/google/android/gms/measurement/internal/zzeo;
    //   921: invokevirtual 328	com/google/android/gms/measurement/internal/zzeo:zzd	()Lcom/google/android/gms/measurement/internal/zzem;
    //   924: ldc_w 1078
    //   927: aload 9
    //   929: invokestatic 359	com/google/android/gms/measurement/internal/zzeo:zzn	(Ljava/lang/String;)Ljava/lang/Object;
    //   932: aload 13
    //   934: invokevirtual 335	com/google/android/gms/measurement/internal/zzem:zzc	(Ljava/lang/String;Ljava/lang/Object;Ljava/lang/Object;)V
    //   937: aload 9
    //   939: astore 11
    //   941: aload 12
    //   943: astore 10
    //   945: aload 12
    //   947: astore_1
    //   948: aload 12
    //   950: invokeinterface 1047 1 0
    //   955: istore 8
    //   957: iload 8
    //   959: ifne -213 -> 746
    //   962: aload 12
    //   964: invokeinterface 316 1 0
    //   969: return
    //   970: aload 9
    //   972: astore 11
    //   974: aload 12
    //   976: astore 10
    //   978: aload 12
    //   980: astore_1
    //   981: aload_0
    //   982: getfield 216	com/google/android/gms/measurement/internal/zzgr:zzs	Lcom/google/android/gms/measurement/internal/zzfy;
    //   985: invokevirtual 323	com/google/android/gms/measurement/internal/zzfy:zzay	()Lcom/google/android/gms/measurement/internal/zzeo;
    //   988: invokevirtual 496	com/google/android/gms/measurement/internal/zzeo:zzk	()Lcom/google/android/gms/measurement/internal/zzem;
    //   991: ldc_w 1080
    //   994: aload 9
    //   996: invokestatic 359	com/google/android/gms/measurement/internal/zzeo:zzn	(Ljava/lang/String;)Ljava/lang/Object;
    //   999: invokevirtual 501	com/google/android/gms/measurement/internal/zzem:zzb	(Ljava/lang/String;Ljava/lang/Object;)V
    //   1002: aload 12
    //   1004: invokeinterface 316 1 0
    //   1009: return
    //   1010: astore_1
    //   1011: aload_0
    //   1012: getfield 216	com/google/android/gms/measurement/internal/zzgr:zzs	Lcom/google/android/gms/measurement/internal/zzfy;
    //   1015: invokevirtual 323	com/google/android/gms/measurement/internal/zzfy:zzay	()Lcom/google/android/gms/measurement/internal/zzeo;
    //   1018: invokevirtual 328	com/google/android/gms/measurement/internal/zzeo:zzd	()Lcom/google/android/gms/measurement/internal/zzem;
    //   1021: ldc_w 1082
    //   1024: aload 9
    //   1026: invokestatic 359	com/google/android/gms/measurement/internal/zzeo:zzn	(Ljava/lang/String;)Ljava/lang/Object;
    //   1029: aload_1
    //   1030: invokevirtual 335	com/google/android/gms/measurement/internal/zzem:zzc	(Ljava/lang/String;Ljava/lang/Object;Ljava/lang/Object;)V
    //   1033: aload 10
    //   1035: invokeinterface 316 1 0
    //   1040: return
    //   1041: astore_1
    //   1042: goto +9 -> 1051
    //   1045: astore 12
    //   1047: goto +13 -> 1060
    //   1050: astore_1
    //   1051: aload 10
    //   1053: astore 6
    //   1055: goto +95 -> 1150
    //   1058: astore 12
    //   1060: aload 10
    //   1062: astore 6
    //   1064: goto +39 -> 1103
    //   1067: astore 9
    //   1069: aload_1
    //   1070: astore 6
    //   1072: aload 9
    //   1074: astore_1
    //   1075: goto +75 -> 1150
    //   1078: astore 12
    //   1080: aload_1
    //   1081: astore 6
    //   1083: goto +20 -> 1103
    //   1086: astore_1
    //   1087: aload 11
    //   1089: astore 6
    //   1091: goto +59 -> 1150
    //   1094: astore 12
    //   1096: aconst_null
    //   1097: astore 6
    //   1099: aload 10
    //   1101: astore 9
    //   1103: aload 6
    //   1105: astore_1
    //   1106: aload_0
    //   1107: getfield 216	com/google/android/gms/measurement/internal/zzgr:zzs	Lcom/google/android/gms/measurement/internal/zzfy;
    //   1110: invokevirtual 323	com/google/android/gms/measurement/internal/zzfy:zzay	()Lcom/google/android/gms/measurement/internal/zzeo;
    //   1113: invokevirtual 328	com/google/android/gms/measurement/internal/zzeo:zzd	()Lcom/google/android/gms/measurement/internal/zzem;
    //   1116: ldc_w 1084
    //   1119: aload 9
    //   1121: invokestatic 359	com/google/android/gms/measurement/internal/zzeo:zzn	(Ljava/lang/String;)Ljava/lang/Object;
    //   1124: aload 12
    //   1126: invokevirtual 335	com/google/android/gms/measurement/internal/zzem:zzc	(Ljava/lang/String;Ljava/lang/Object;Ljava/lang/Object;)V
    //   1129: aload 6
    //   1131: ifnull +10 -> 1141
    //   1134: aload 6
    //   1136: invokeinterface 316 1 0
    //   1141: return
    //   1142: astore 9
    //   1144: aload_1
    //   1145: astore 6
    //   1147: aload 9
    //   1149: astore_1
    //   1150: aload 6
    //   1152: ifnull +10 -> 1162
    //   1155: aload 6
    //   1157: invokeinterface 316 1 0
    //   1162: aload_1
    //   1163: athrow
    // Local variable table:
    //   start	length	slot	name	signature
    //   0	1164	0	this	zzam
    //   0	1164	1	paramString	String
    //   0	1164	2	paramLong1	long
    //   0	1164	4	paramLong2	long
    //   0	1164	6	paramZzkw	zzkw
    //   53	267	7	bool1	boolean
    //   36	922	8	bool2	boolean
    //   64	961	9	localObject1	Object
    //   1067	6	9	localObject2	Object
    //   1101	19	9	localObject3	Object
    //   1142	6	9	localObject4	Object
    //   18	1082	10	localObject5	Object
    //   21	1067	11	localObject6	Object
    //   15	236	12	localObject7	Object
    //   260	196	12	localSQLiteException1	SQLiteException
    //   723	280	12	localCursor	Cursor
    //   1045	1	12	localSQLiteException2	SQLiteException
    //   1058	1	12	localSQLiteException3	SQLiteException
    //   1078	1	12	localSQLiteException4	SQLiteException
    //   1094	31	12	localSQLiteException5	SQLiteException
    //   24	852	13	localObject8	Object
    //   901	32	13	localIOException	java.io.IOException
    //   335	114	14	localObject9	Object
    //   30	649	15	localSQLiteDatabase	SQLiteDatabase
    // Exception table:
    //   from	to	target	type
    //   168	177	260	android/database/sqlite/SQLiteException
    //   201	211	260	android/database/sqlite/SQLiteException
    //   222	232	260	android/database/sqlite/SQLiteException
    //   243	250	260	android/database/sqlite/SQLiteException
    //   387	396	260	android/database/sqlite/SQLiteException
    //   420	430	260	android/database/sqlite/SQLiteException
    //   441	448	260	android/database/sqlite/SQLiteException
    //   736	746	260	android/database/sqlite/SQLiteException
    //   757	766	260	android/database/sqlite/SQLiteException
    //   777	787	260	android/database/sqlite/SQLiteException
    //   798	811	260	android/database/sqlite/SQLiteException
    //   822	836	260	android/database/sqlite/SQLiteException
    //   847	861	260	android/database/sqlite/SQLiteException
    //   872	888	260	android/database/sqlite/SQLiteException
    //   914	937	260	android/database/sqlite/SQLiteException
    //   948	957	260	android/database/sqlite/SQLiteException
    //   981	1002	260	android/database/sqlite/SQLiteException
    //   798	811	901	java/io/IOException
    //   552	569	1010	java/io/IOException
    //   678	725	1041	finally
    //   1011	1033	1041	finally
    //   678	725	1045	android/database/sqlite/SQLiteException
    //   1011	1033	1045	android/database/sqlite/SQLiteException
    //   504	535	1050	finally
    //   543	552	1050	finally
    //   552	569	1050	finally
    //   569	600	1050	finally
    //   600	618	1050	finally
    //   631	655	1050	finally
    //   662	678	1050	finally
    //   504	535	1058	android/database/sqlite/SQLiteException
    //   543	552	1058	android/database/sqlite/SQLiteException
    //   552	569	1058	android/database/sqlite/SQLiteException
    //   569	600	1058	android/database/sqlite/SQLiteException
    //   600	618	1058	android/database/sqlite/SQLiteException
    //   631	655	1058	android/database/sqlite/SQLiteException
    //   662	678	1058	android/database/sqlite/SQLiteException
    //   459	504	1067	finally
    //   459	504	1078	android/database/sqlite/SQLiteException
    //   26	38	1086	finally
    //   60	83	1086	finally
    //   86	100	1086	finally
    //   109	157	1086	finally
    //   286	292	1086	finally
    //   297	306	1086	finally
    //   309	319	1086	finally
    //   328	376	1086	finally
    //   26	38	1094	android/database/sqlite/SQLiteException
    //   60	83	1094	android/database/sqlite/SQLiteException
    //   86	100	1094	android/database/sqlite/SQLiteException
    //   109	157	1094	android/database/sqlite/SQLiteException
    //   286	292	1094	android/database/sqlite/SQLiteException
    //   297	306	1094	android/database/sqlite/SQLiteException
    //   309	319	1094	android/database/sqlite/SQLiteException
    //   328	376	1094	android/database/sqlite/SQLiteException
    //   168	177	1142	finally
    //   201	211	1142	finally
    //   222	232	1142	finally
    //   243	250	1142	finally
    //   387	396	1142	finally
    //   420	430	1142	finally
    //   441	448	1142	finally
    //   736	746	1142	finally
    //   757	766	1142	finally
    //   777	787	1142	finally
    //   798	811	1142	finally
    //   822	836	1142	finally
    //   847	861	1142	finally
    //   872	888	1142	finally
    //   914	937	1142	finally
    //   948	957	1142	finally
    //   981	1002	1142	finally
    //   1106	1129	1142	finally
  }
  
  public final int zza(String paramString1, String paramString2)
  {
    Preconditions.checkNotEmpty(paramString1);
    Preconditions.checkNotEmpty(paramString2);
    zzg();
    zzW();
    try
    {
      int i = zzh().delete("conditional_properties", "app_id=? and name=?", new String[] { paramString1, paramString2 });
      return i;
    }
    catch (SQLiteException localSQLiteException)
    {
      zzs.zzay().zzd().zzd("Error deleting conditional property", zzeo.zzn(paramString1), zzs.zzj().zzf(paramString2), localSQLiteException);
    }
    return 0;
  }
  
  protected final boolean zzb()
  {
    return false;
  }
  
  /* Error */
  @VisibleForTesting
  protected final long zzc(String paramString1, String paramString2)
  {
    // Byte code:
    //   0: aload_1
    //   1: invokestatic 263	com/google/android/gms/common/internal/Preconditions:checkNotEmpty	(Ljava/lang/String;)Ljava/lang/String;
    //   4: pop
    //   5: ldc_w 1090
    //   8: invokestatic 263	com/google/android/gms/common/internal/Preconditions:checkNotEmpty	(Ljava/lang/String;)Ljava/lang/String;
    //   11: pop
    //   12: aload_0
    //   13: invokevirtual 342	com/google/android/gms/measurement/internal/zzgr:zzg	()V
    //   16: aload_0
    //   17: invokevirtual 345	com/google/android/gms/measurement/internal/zzkn:zzW	()V
    //   20: aload_0
    //   21: invokevirtual 297	com/google/android/gms/measurement/internal/zzam:zzh	()Landroid/database/sqlite/SQLiteDatabase;
    //   24: astore 7
    //   26: aload 7
    //   28: invokevirtual 473	android/database/sqlite/SQLiteDatabase:beginTransaction	()V
    //   31: new 644	java/lang/StringBuilder
    //   34: dup
    //   35: invokespecial 645	java/lang/StringBuilder:<init>	()V
    //   38: astore_2
    //   39: aload_2
    //   40: ldc_w 1092
    //   43: invokevirtual 651	java/lang/StringBuilder:append	(Ljava/lang/String;)Ljava/lang/StringBuilder;
    //   46: pop
    //   47: aload_2
    //   48: ldc_w 1090
    //   51: invokevirtual 651	java/lang/StringBuilder:append	(Ljava/lang/String;)Ljava/lang/StringBuilder;
    //   54: pop
    //   55: aload_2
    //   56: ldc_w 1094
    //   59: invokevirtual 651	java/lang/StringBuilder:append	(Ljava/lang/String;)Ljava/lang/StringBuilder;
    //   62: pop
    //   63: aload_0
    //   64: aload_2
    //   65: invokevirtual 657	java/lang/StringBuilder:toString	()Ljava/lang/String;
    //   68: iconst_1
    //   69: anewarray 21	java/lang/String
    //   72: dup
    //   73: iconst_0
    //   74: aload_1
    //   75: aastore
    //   76: ldc2_w 577
    //   79: invokespecial 1096	com/google/android/gms/measurement/internal/zzam:zzaa	(Ljava/lang/String;[Ljava/lang/String;J)J
    //   82: lstore 5
    //   84: lload 5
    //   86: lstore_3
    //   87: lload 5
    //   89: ldc2_w 577
    //   92: lcmp
    //   93: ifne +94 -> 187
    //   96: new 269	android/content/ContentValues
    //   99: dup
    //   100: invokespecial 543	android/content/ContentValues:<init>	()V
    //   103: astore_2
    //   104: aload_2
    //   105: ldc_w 545
    //   108: aload_1
    //   109: invokevirtual 273	android/content/ContentValues:put	(Ljava/lang/String;Ljava/lang/String;)V
    //   112: iconst_0
    //   113: invokestatic 518	java/lang/Integer:valueOf	(I)Ljava/lang/Integer;
    //   116: astore 8
    //   118: aload_2
    //   119: ldc_w 1090
    //   122: aload 8
    //   124: invokevirtual 550	android/content/ContentValues:put	(Ljava/lang/String;Ljava/lang/Integer;)V
    //   127: aload_2
    //   128: ldc -57
    //   130: aload 8
    //   132: invokevirtual 550	android/content/ContentValues:put	(Ljava/lang/String;Ljava/lang/Integer;)V
    //   135: aload 7
    //   137: ldc_w 1098
    //   140: aconst_null
    //   141: aload_2
    //   142: iconst_5
    //   143: invokevirtual 576	android/database/sqlite/SQLiteDatabase:insertWithOnConflict	(Ljava/lang/String;Ljava/lang/String;Landroid/content/ContentValues;I)J
    //   146: ldc2_w 577
    //   149: lcmp
    //   150: ifne +35 -> 185
    //   153: aload_0
    //   154: getfield 216	com/google/android/gms/measurement/internal/zzgr:zzs	Lcom/google/android/gms/measurement/internal/zzfy;
    //   157: invokevirtual 323	com/google/android/gms/measurement/internal/zzfy:zzay	()Lcom/google/android/gms/measurement/internal/zzeo;
    //   160: invokevirtual 328	com/google/android/gms/measurement/internal/zzeo:zzd	()Lcom/google/android/gms/measurement/internal/zzem;
    //   163: ldc_w 1100
    //   166: aload_1
    //   167: invokestatic 359	com/google/android/gms/measurement/internal/zzeo:zzn	(Ljava/lang/String;)Ljava/lang/Object;
    //   170: ldc_w 1090
    //   173: invokevirtual 335	com/google/android/gms/measurement/internal/zzem:zzc	(Ljava/lang/String;Ljava/lang/Object;Ljava/lang/Object;)V
    //   176: aload 7
    //   178: invokevirtual 669	android/database/sqlite/SQLiteDatabase:endTransaction	()V
    //   181: ldc2_w 577
    //   184: lreturn
    //   185: lconst_0
    //   186: lstore_3
    //   187: new 269	android/content/ContentValues
    //   190: dup
    //   191: invokespecial 543	android/content/ContentValues:<init>	()V
    //   194: astore_2
    //   195: aload_2
    //   196: ldc_w 545
    //   199: aload_1
    //   200: invokevirtual 273	android/content/ContentValues:put	(Ljava/lang/String;Ljava/lang/String;)V
    //   203: aload_2
    //   204: ldc_w 1090
    //   207: lconst_1
    //   208: lload_3
    //   209: ladd
    //   210: invokestatic 699	java/lang/Long:valueOf	(J)Ljava/lang/Long;
    //   213: invokevirtual 278	android/content/ContentValues:put	(Ljava/lang/String;Ljava/lang/Long;)V
    //   216: aload 7
    //   218: ldc_w 1098
    //   221: aload_2
    //   222: ldc_w 778
    //   225: iconst_1
    //   226: anewarray 21	java/lang/String
    //   229: dup
    //   230: iconst_0
    //   231: aload_1
    //   232: aastore
    //   233: invokevirtual 782	android/database/sqlite/SQLiteDatabase:update	(Ljava/lang/String;Landroid/content/ContentValues;Ljava/lang/String;[Ljava/lang/String;)I
    //   236: i2l
    //   237: lconst_0
    //   238: lcmp
    //   239: ifne +35 -> 274
    //   242: aload_0
    //   243: getfield 216	com/google/android/gms/measurement/internal/zzgr:zzs	Lcom/google/android/gms/measurement/internal/zzfy;
    //   246: invokevirtual 323	com/google/android/gms/measurement/internal/zzfy:zzay	()Lcom/google/android/gms/measurement/internal/zzeo;
    //   249: invokevirtual 328	com/google/android/gms/measurement/internal/zzeo:zzd	()Lcom/google/android/gms/measurement/internal/zzem;
    //   252: ldc_w 1102
    //   255: aload_1
    //   256: invokestatic 359	com/google/android/gms/measurement/internal/zzeo:zzn	(Ljava/lang/String;)Ljava/lang/Object;
    //   259: ldc_w 1090
    //   262: invokevirtual 335	com/google/android/gms/measurement/internal/zzem:zzc	(Ljava/lang/String;Ljava/lang/Object;Ljava/lang/Object;)V
    //   265: aload 7
    //   267: invokevirtual 669	android/database/sqlite/SQLiteDatabase:endTransaction	()V
    //   270: ldc2_w 577
    //   273: lreturn
    //   274: aload 7
    //   276: invokevirtual 666	android/database/sqlite/SQLiteDatabase:setTransactionSuccessful	()V
    //   279: goto +38 -> 317
    //   282: astore_2
    //   283: goto +10 -> 293
    //   286: astore_1
    //   287: goto +37 -> 324
    //   290: astore_2
    //   291: lconst_0
    //   292: lstore_3
    //   293: aload_0
    //   294: getfield 216	com/google/android/gms/measurement/internal/zzgr:zzs	Lcom/google/android/gms/measurement/internal/zzfy;
    //   297: invokevirtual 323	com/google/android/gms/measurement/internal/zzfy:zzay	()Lcom/google/android/gms/measurement/internal/zzeo;
    //   300: invokevirtual 328	com/google/android/gms/measurement/internal/zzeo:zzd	()Lcom/google/android/gms/measurement/internal/zzem;
    //   303: ldc_w 1104
    //   306: aload_1
    //   307: invokestatic 359	com/google/android/gms/measurement/internal/zzeo:zzn	(Ljava/lang/String;)Ljava/lang/Object;
    //   310: ldc_w 1090
    //   313: aload_2
    //   314: invokevirtual 369	com/google/android/gms/measurement/internal/zzem:zzd	(Ljava/lang/String;Ljava/lang/Object;Ljava/lang/Object;Ljava/lang/Object;)V
    //   317: aload 7
    //   319: invokevirtual 669	android/database/sqlite/SQLiteDatabase:endTransaction	()V
    //   322: lload_3
    //   323: lreturn
    //   324: aload 7
    //   326: invokevirtual 669	android/database/sqlite/SQLiteDatabase:endTransaction	()V
    //   329: aload_1
    //   330: athrow
    // Local variable table:
    //   start	length	slot	name	signature
    //   0	331	0	this	zzam
    //   0	331	1	paramString1	String
    //   0	331	2	paramString2	String
    //   86	237	3	l1	long
    //   82	6	5	l2	long
    //   24	301	7	localSQLiteDatabase	SQLiteDatabase
    //   116	15	8	localInteger	Integer
    // Exception table:
    //   from	to	target	type
    //   187	265	282	android/database/sqlite/SQLiteException
    //   274	279	282	android/database/sqlite/SQLiteException
    //   31	84	286	finally
    //   96	176	286	finally
    //   187	265	286	finally
    //   274	279	286	finally
    //   293	317	286	finally
    //   31	84	290	android/database/sqlite/SQLiteException
    //   96	176	290	android/database/sqlite/SQLiteException
  }
  
  public final long zzd()
  {
    return zzaa("select max(bundle_end_timestamp) from queue", null, 0L);
  }
  
  public final long zze()
  {
    return zzaa("select max(timestamp) from raw_events", null, 0L);
  }
  
  public final long zzf(String paramString)
  {
    Preconditions.checkNotEmpty(paramString);
    return zzaa("select count(1) from events where app_id=? and name not like '!_%' escape '!'", new String[] { paramString }, 0L);
  }
  
  @VisibleForTesting
  final SQLiteDatabase zzh()
  {
    zzg();
    try
    {
      SQLiteDatabase localSQLiteDatabase = zzj.getWritableDatabase();
      return localSQLiteDatabase;
    }
    catch (SQLiteException localSQLiteException)
    {
      zzs.zzay().zzk().zzb("Error opening database", localSQLiteException);
      throw localSQLiteException;
    }
  }
  
  /* Error */
  public final android.os.Bundle zzi(String paramString)
  {
    // Byte code:
    //   0: aload_0
    //   1: invokevirtual 342	com/google/android/gms/measurement/internal/zzgr:zzg	()V
    //   4: aload_0
    //   5: invokevirtual 345	com/google/android/gms/measurement/internal/zzkn:zzW	()V
    //   8: aconst_null
    //   9: astore_2
    //   10: aload_0
    //   11: invokevirtual 297	com/google/android/gms/measurement/internal/zzam:zzh	()Landroid/database/sqlite/SQLiteDatabase;
    //   14: ldc_w 1119
    //   17: iconst_1
    //   18: anewarray 21	java/lang/String
    //   21: dup
    //   22: iconst_0
    //   23: aload_1
    //   24: aastore
    //   25: invokevirtual 303	android/database/sqlite/SQLiteDatabase:rawQuery	(Ljava/lang/String;[Ljava/lang/String;)Landroid/database/Cursor;
    //   28: astore_3
    //   29: aload_3
    //   30: astore_2
    //   31: aload_3
    //   32: invokeinterface 309 1 0
    //   37: ifne +29 -> 66
    //   40: aload_3
    //   41: astore_2
    //   42: aload_0
    //   43: getfield 216	com/google/android/gms/measurement/internal/zzgr:zzs	Lcom/google/android/gms/measurement/internal/zzfy;
    //   46: invokevirtual 323	com/google/android/gms/measurement/internal/zzfy:zzay	()Lcom/google/android/gms/measurement/internal/zzeo;
    //   49: invokevirtual 859	com/google/android/gms/measurement/internal/zzeo:zzj	()Lcom/google/android/gms/measurement/internal/zzem;
    //   52: ldc_w 1121
    //   55: invokevirtual 1123	com/google/android/gms/measurement/internal/zzem:zza	(Ljava/lang/String;)V
    //   58: aload_3
    //   59: invokeinterface 316 1 0
    //   64: aconst_null
    //   65: areturn
    //   66: aload_3
    //   67: astore_2
    //   68: aload_3
    //   69: iconst_0
    //   70: invokeinterface 1032 2 0
    //   75: astore 4
    //   77: aload_3
    //   78: astore_2
    //   79: invokestatic 1065	com/google/android/gms/internal/measurement/zzfs:zze	()Lcom/google/android/gms/internal/measurement/zzfr;
    //   82: aload 4
    //   84: invokestatic 1042	com/google/android/gms/measurement/internal/zzlb:zzl	(Lcom/google/android/gms/internal/measurement/zzlk;[B)Lcom/google/android/gms/internal/measurement/zzlk;
    //   87: checkcast 1067	com/google/android/gms/internal/measurement/zzfr
    //   90: invokevirtual 440	com/google/android/gms/internal/measurement/zzka:zzaE	()Lcom/google/android/gms/internal/measurement/zzke;
    //   93: checkcast 1062	com/google/android/gms/internal/measurement/zzfs
    //   96: astore 4
    //   98: aload_3
    //   99: astore_2
    //   100: aload_0
    //   101: getfield 1128	com/google/android/gms/measurement/internal/zzkm:zzf	Lcom/google/android/gms/measurement/internal/zzkz;
    //   104: invokevirtual 1133	com/google/android/gms/measurement/internal/zzkz:zzu	()Lcom/google/android/gms/measurement/internal/zzlb;
    //   107: pop
    //   108: aload_3
    //   109: astore_2
    //   110: aload 4
    //   112: invokevirtual 1135	com/google/android/gms/internal/measurement/zzfs:zzi	()Ljava/util/List;
    //   115: astore 4
    //   117: aload_3
    //   118: astore_2
    //   119: new 1137	android/os/Bundle
    //   122: dup
    //   123: invokespecial 1138	android/os/Bundle:<init>	()V
    //   126: astore_1
    //   127: aload_3
    //   128: astore_2
    //   129: aload 4
    //   131: invokeinterface 483 1 0
    //   136: astore 4
    //   138: aload_3
    //   139: astore_2
    //   140: aload 4
    //   142: invokeinterface 488 1 0
    //   147: ifeq +130 -> 277
    //   150: aload_3
    //   151: astore_2
    //   152: aload 4
    //   154: invokeinterface 492 1 0
    //   159: checkcast 1140	com/google/android/gms/internal/measurement/zzfw
    //   162: astore 5
    //   164: aload_3
    //   165: astore_2
    //   166: aload 5
    //   168: invokevirtual 1141	com/google/android/gms/internal/measurement/zzfw:zzg	()Ljava/lang/String;
    //   171: astore 6
    //   173: aload_3
    //   174: astore_2
    //   175: aload 5
    //   177: invokevirtual 1143	com/google/android/gms/internal/measurement/zzfw:zzu	()Z
    //   180: ifeq +19 -> 199
    //   183: aload_3
    //   184: astore_2
    //   185: aload_1
    //   186: aload 6
    //   188: aload 5
    //   190: invokevirtual 1146	com/google/android/gms/internal/measurement/zzfw:zza	()D
    //   193: invokevirtual 1150	android/os/Bundle:putDouble	(Ljava/lang/String;D)V
    //   196: goto -58 -> 138
    //   199: aload_3
    //   200: astore_2
    //   201: aload 5
    //   203: invokevirtual 1152	com/google/android/gms/internal/measurement/zzfw:zzv	()Z
    //   206: ifeq +19 -> 225
    //   209: aload_3
    //   210: astore_2
    //   211: aload_1
    //   212: aload 6
    //   214: aload 5
    //   216: invokevirtual 1155	com/google/android/gms/internal/measurement/zzfw:zzb	()F
    //   219: invokevirtual 1159	android/os/Bundle:putFloat	(Ljava/lang/String;F)V
    //   222: goto -84 -> 138
    //   225: aload_3
    //   226: astore_2
    //   227: aload 5
    //   229: invokevirtual 1161	com/google/android/gms/internal/measurement/zzfw:zzy	()Z
    //   232: ifeq +19 -> 251
    //   235: aload_3
    //   236: astore_2
    //   237: aload_1
    //   238: aload 6
    //   240: aload 5
    //   242: invokevirtual 1163	com/google/android/gms/internal/measurement/zzfw:zzh	()Ljava/lang/String;
    //   245: invokevirtual 1166	android/os/Bundle:putString	(Ljava/lang/String;Ljava/lang/String;)V
    //   248: goto -110 -> 138
    //   251: aload_3
    //   252: astore_2
    //   253: aload 5
    //   255: invokevirtual 1168	com/google/android/gms/internal/measurement/zzfw:zzw	()Z
    //   258: ifeq -120 -> 138
    //   261: aload_3
    //   262: astore_2
    //   263: aload_1
    //   264: aload 6
    //   266: aload 5
    //   268: invokevirtual 1169	com/google/android/gms/internal/measurement/zzfw:zzd	()J
    //   271: invokevirtual 1173	android/os/Bundle:putLong	(Ljava/lang/String;J)V
    //   274: goto -136 -> 138
    //   277: aload_3
    //   278: invokeinterface 316 1 0
    //   283: aload_1
    //   284: areturn
    //   285: astore 4
    //   287: aload_3
    //   288: astore_2
    //   289: aload_0
    //   290: getfield 216	com/google/android/gms/measurement/internal/zzgr:zzs	Lcom/google/android/gms/measurement/internal/zzfy;
    //   293: invokevirtual 323	com/google/android/gms/measurement/internal/zzfy:zzay	()Lcom/google/android/gms/measurement/internal/zzeo;
    //   296: invokevirtual 328	com/google/android/gms/measurement/internal/zzeo:zzd	()Lcom/google/android/gms/measurement/internal/zzem;
    //   299: ldc_w 1175
    //   302: aload_1
    //   303: invokestatic 359	com/google/android/gms/measurement/internal/zzeo:zzn	(Ljava/lang/String;)Ljava/lang/Object;
    //   306: aload 4
    //   308: invokevirtual 335	com/google/android/gms/measurement/internal/zzem:zzc	(Ljava/lang/String;Ljava/lang/Object;Ljava/lang/Object;)V
    //   311: aload_3
    //   312: invokeinterface 316 1 0
    //   317: aconst_null
    //   318: areturn
    //   319: astore_2
    //   320: aload_3
    //   321: astore_1
    //   322: aload_2
    //   323: astore_3
    //   324: goto +10 -> 334
    //   327: astore_1
    //   328: goto +38 -> 366
    //   331: astore_3
    //   332: aconst_null
    //   333: astore_1
    //   334: aload_1
    //   335: astore_2
    //   336: aload_0
    //   337: getfield 216	com/google/android/gms/measurement/internal/zzgr:zzs	Lcom/google/android/gms/measurement/internal/zzfy;
    //   340: invokevirtual 323	com/google/android/gms/measurement/internal/zzfy:zzay	()Lcom/google/android/gms/measurement/internal/zzeo;
    //   343: invokevirtual 328	com/google/android/gms/measurement/internal/zzeo:zzd	()Lcom/google/android/gms/measurement/internal/zzem;
    //   346: ldc_w 1177
    //   349: aload_3
    //   350: invokevirtual 501	com/google/android/gms/measurement/internal/zzem:zzb	(Ljava/lang/String;Ljava/lang/Object;)V
    //   353: aload_1
    //   354: ifnull +9 -> 363
    //   357: aload_1
    //   358: invokeinterface 316 1 0
    //   363: aconst_null
    //   364: areturn
    //   365: astore_1
    //   366: aload_2
    //   367: ifnull +9 -> 376
    //   370: aload_2
    //   371: invokeinterface 316 1 0
    //   376: aload_1
    //   377: athrow
    // Local variable table:
    //   start	length	slot	name	signature
    //   0	378	0	this	zzam
    //   0	378	1	paramString	String
    //   9	280	2	localObject1	Object
    //   319	4	2	localSQLiteException1	SQLiteException
    //   335	36	2	str1	String
    //   28	296	3	localObject2	Object
    //   331	19	3	localSQLiteException2	SQLiteException
    //   75	78	4	localObject3	Object
    //   285	22	4	localIOException	java.io.IOException
    //   162	105	5	localZzfw	com.google.android.gms.internal.measurement.zzfw
    //   171	94	6	str2	String
    // Exception table:
    //   from	to	target	type
    //   79	98	285	java/io/IOException
    //   31	40	319	android/database/sqlite/SQLiteException
    //   42	58	319	android/database/sqlite/SQLiteException
    //   68	77	319	android/database/sqlite/SQLiteException
    //   79	98	319	android/database/sqlite/SQLiteException
    //   100	108	319	android/database/sqlite/SQLiteException
    //   110	117	319	android/database/sqlite/SQLiteException
    //   119	127	319	android/database/sqlite/SQLiteException
    //   129	138	319	android/database/sqlite/SQLiteException
    //   140	150	319	android/database/sqlite/SQLiteException
    //   152	164	319	android/database/sqlite/SQLiteException
    //   166	173	319	android/database/sqlite/SQLiteException
    //   175	183	319	android/database/sqlite/SQLiteException
    //   185	196	319	android/database/sqlite/SQLiteException
    //   201	209	319	android/database/sqlite/SQLiteException
    //   211	222	319	android/database/sqlite/SQLiteException
    //   227	235	319	android/database/sqlite/SQLiteException
    //   237	248	319	android/database/sqlite/SQLiteException
    //   253	261	319	android/database/sqlite/SQLiteException
    //   263	274	319	android/database/sqlite/SQLiteException
    //   289	311	319	android/database/sqlite/SQLiteException
    //   10	29	327	finally
    //   10	29	331	android/database/sqlite/SQLiteException
    //   31	40	365	finally
    //   42	58	365	finally
    //   68	77	365	finally
    //   79	98	365	finally
    //   100	108	365	finally
    //   110	117	365	finally
    //   119	127	365	finally
    //   129	138	365	finally
    //   140	150	365	finally
    //   152	164	365	finally
    //   166	173	365	finally
    //   175	183	365	finally
    //   185	196	365	finally
    //   201	209	365	finally
    //   211	222	365	finally
    //   227	235	365	finally
    //   237	248	365	finally
    //   253	261	365	finally
    //   263	274	365	finally
    //   289	311	365	finally
    //   336	353	365	finally
  }
  
  /* Error */
  public final zzh zzj(String paramString)
  {
    // Byte code:
    //   0: aload_1
    //   1: invokestatic 263	com/google/android/gms/common/internal/Preconditions:checkNotEmpty	(Ljava/lang/String;)Ljava/lang/String;
    //   4: pop
    //   5: aload_0
    //   6: invokevirtual 342	com/google/android/gms/measurement/internal/zzgr:zzg	()V
    //   9: aload_0
    //   10: invokevirtual 345	com/google/android/gms/measurement/internal/zzkn:zzW	()V
    //   13: aconst_null
    //   14: astore 6
    //   16: aload_0
    //   17: invokevirtual 297	com/google/android/gms/measurement/internal/zzam:zzh	()Landroid/database/sqlite/SQLiteDatabase;
    //   20: astore 7
    //   22: iconst_1
    //   23: istore_3
    //   24: aload 7
    //   26: ldc_w 776
    //   29: bipush 29
    //   31: anewarray 21	java/lang/String
    //   34: dup
    //   35: iconst_0
    //   36: ldc_w 679
    //   39: aastore
    //   40: dup
    //   41: iconst_1
    //   42: ldc_w 684
    //   45: aastore
    //   46: dup
    //   47: iconst_2
    //   48: ldc_w 689
    //   51: aastore
    //   52: dup
    //   53: iconst_3
    //   54: ldc_w 693
    //   57: aastore
    //   58: dup
    //   59: iconst_4
    //   60: ldc 75
    //   62: aastore
    //   63: dup
    //   64: iconst_5
    //   65: ldc_w 703
    //   68: aastore
    //   69: dup
    //   70: bipush 6
    //   72: ldc 55
    //   74: aastore
    //   75: dup
    //   76: bipush 7
    //   78: ldc 59
    //   80: aastore
    //   81: dup
    //   82: bipush 8
    //   84: ldc 63
    //   86: aastore
    //   87: dup
    //   88: bipush 9
    //   90: ldc 67
    //   92: aastore
    //   93: dup
    //   94: bipush 10
    //   96: ldc 71
    //   98: aastore
    //   99: dup
    //   100: bipush 11
    //   102: ldc 79
    //   104: aastore
    //   105: dup
    //   106: bipush 12
    //   108: ldc 83
    //   110: aastore
    //   111: dup
    //   112: bipush 13
    //   114: ldc 87
    //   116: aastore
    //   117: dup
    //   118: bipush 14
    //   120: ldc 91
    //   122: aastore
    //   123: dup
    //   124: bipush 15
    //   126: ldc 99
    //   128: aastore
    //   129: dup
    //   130: bipush 16
    //   132: ldc 103
    //   134: aastore
    //   135: dup
    //   136: bipush 17
    //   138: ldc 107
    //   140: aastore
    //   141: dup
    //   142: bipush 18
    //   144: ldc 111
    //   146: aastore
    //   147: dup
    //   148: bipush 19
    //   150: ldc 115
    //   152: aastore
    //   153: dup
    //   154: bipush 20
    //   156: ldc 119
    //   158: aastore
    //   159: dup
    //   160: bipush 21
    //   162: ldc 123
    //   164: aastore
    //   165: dup
    //   166: bipush 22
    //   168: ldc 127
    //   170: aastore
    //   171: dup
    //   172: bipush 23
    //   174: ldc -125
    //   176: aastore
    //   177: dup
    //   178: bipush 24
    //   180: ldc -117
    //   182: aastore
    //   183: dup
    //   184: bipush 25
    //   186: ldc -109
    //   188: aastore
    //   189: dup
    //   190: bipush 26
    //   192: ldc -105
    //   194: aastore
    //   195: dup
    //   196: bipush 27
    //   198: ldc -101
    //   200: aastore
    //   201: dup
    //   202: bipush 28
    //   204: ldc -89
    //   206: aastore
    //   207: ldc_w 477
    //   210: iconst_1
    //   211: anewarray 21	java/lang/String
    //   214: dup
    //   215: iconst_0
    //   216: aload_1
    //   217: aastore
    //   218: aconst_null
    //   219: aconst_null
    //   220: aconst_null
    //   221: invokevirtual 1181	android/database/sqlite/SQLiteDatabase:query	(Ljava/lang/String;[Ljava/lang/String;Ljava/lang/String;[Ljava/lang/String;Ljava/lang/String;Ljava/lang/String;Ljava/lang/String;)Landroid/database/Cursor;
    //   224: astore 7
    //   226: aload 7
    //   228: astore 6
    //   230: aload 7
    //   232: invokeinterface 309 1 0
    //   237: istore_2
    //   238: iload_2
    //   239: ifne +12 -> 251
    //   242: aload 7
    //   244: invokeinterface 316 1 0
    //   249: aconst_null
    //   250: areturn
    //   251: aload 7
    //   253: astore 6
    //   255: new 674	com/google/android/gms/measurement/internal/zzh
    //   258: dup
    //   259: aload_0
    //   260: getfield 1128	com/google/android/gms/measurement/internal/zzkm:zzf	Lcom/google/android/gms/measurement/internal/zzkz;
    //   263: invokevirtual 1184	com/google/android/gms/measurement/internal/zzkz:zzq	()Lcom/google/android/gms/measurement/internal/zzfy;
    //   266: aload_1
    //   267: invokespecial 1187	com/google/android/gms/measurement/internal/zzh:<init>	(Lcom/google/android/gms/measurement/internal/zzfy;Ljava/lang/String;)V
    //   270: astore 8
    //   272: aload 7
    //   274: astore 6
    //   276: aload 8
    //   278: aload 7
    //   280: iconst_0
    //   281: invokeinterface 1006 2 0
    //   286: invokevirtual 1189	com/google/android/gms/measurement/internal/zzh:zzH	(Ljava/lang/String;)V
    //   289: aload 7
    //   291: astore 6
    //   293: aload 8
    //   295: aload 7
    //   297: iconst_1
    //   298: invokeinterface 1006 2 0
    //   303: invokevirtual 1191	com/google/android/gms/measurement/internal/zzh:zzW	(Ljava/lang/String;)V
    //   306: aload 7
    //   308: astore 6
    //   310: aload 8
    //   312: aload 7
    //   314: iconst_2
    //   315: invokeinterface 1006 2 0
    //   320: invokevirtual 1194	com/google/android/gms/measurement/internal/zzh:zzae	(Ljava/lang/String;)V
    //   323: aload 7
    //   325: astore 6
    //   327: aload 8
    //   329: aload 7
    //   331: iconst_3
    //   332: invokeinterface 313 2 0
    //   337: invokevirtual 1197	com/google/android/gms/measurement/internal/zzh:zzaa	(J)V
    //   340: aload 7
    //   342: astore 6
    //   344: aload 8
    //   346: aload 7
    //   348: iconst_4
    //   349: invokeinterface 313 2 0
    //   354: invokevirtual 1200	com/google/android/gms/measurement/internal/zzh:zzab	(J)V
    //   357: aload 7
    //   359: astore 6
    //   361: aload 8
    //   363: aload 7
    //   365: iconst_5
    //   366: invokeinterface 313 2 0
    //   371: invokevirtual 1202	com/google/android/gms/measurement/internal/zzh:zzZ	(J)V
    //   374: aload 7
    //   376: astore 6
    //   378: aload 8
    //   380: aload 7
    //   382: bipush 6
    //   384: invokeinterface 1006 2 0
    //   389: invokevirtual 1204	com/google/android/gms/measurement/internal/zzh:zzJ	(Ljava/lang/String;)V
    //   392: aload 7
    //   394: astore 6
    //   396: aload 8
    //   398: aload 7
    //   400: bipush 7
    //   402: invokeinterface 1006 2 0
    //   407: invokevirtual 1206	com/google/android/gms/measurement/internal/zzh:zzI	(Ljava/lang/String;)V
    //   410: aload 7
    //   412: astore 6
    //   414: aload 8
    //   416: aload 7
    //   418: bipush 8
    //   420: invokeinterface 313 2 0
    //   425: invokevirtual 1209	com/google/android/gms/measurement/internal/zzh:zzX	(J)V
    //   428: aload 7
    //   430: astore 6
    //   432: aload 8
    //   434: aload 7
    //   436: bipush 9
    //   438: invokeinterface 313 2 0
    //   443: invokevirtual 1211	com/google/android/gms/measurement/internal/zzh:zzS	(J)V
    //   446: aload 7
    //   448: astore 6
    //   450: aload 7
    //   452: bipush 10
    //   454: invokeinterface 1215 2 0
    //   459: ifne +600 -> 1059
    //   462: aload 7
    //   464: astore 6
    //   466: aload 7
    //   468: bipush 10
    //   470: invokeinterface 1219 2 0
    //   475: ifeq +579 -> 1054
    //   478: goto +581 -> 1059
    //   481: aload 7
    //   483: astore 6
    //   485: aload 8
    //   487: iload_2
    //   488: invokevirtual 1223	com/google/android/gms/measurement/internal/zzh:zzac	(Z)V
    //   491: aload 7
    //   493: astore 6
    //   495: aload 8
    //   497: aload 7
    //   499: bipush 11
    //   501: invokeinterface 313 2 0
    //   506: invokevirtual 1225	com/google/android/gms/measurement/internal/zzh:zzR	(J)V
    //   509: aload 7
    //   511: astore 6
    //   513: aload 8
    //   515: aload 7
    //   517: bipush 12
    //   519: invokeinterface 313 2 0
    //   524: invokevirtual 1227	com/google/android/gms/measurement/internal/zzh:zzP	(J)V
    //   527: aload 7
    //   529: astore 6
    //   531: aload 8
    //   533: aload 7
    //   535: bipush 13
    //   537: invokeinterface 313 2 0
    //   542: invokevirtual 1229	com/google/android/gms/measurement/internal/zzh:zzO	(J)V
    //   545: aload 7
    //   547: astore 6
    //   549: aload 8
    //   551: aload 7
    //   553: bipush 14
    //   555: invokeinterface 313 2 0
    //   560: invokevirtual 1231	com/google/android/gms/measurement/internal/zzh:zzM	(J)V
    //   563: aload 7
    //   565: astore 6
    //   567: aload 8
    //   569: aload 7
    //   571: bipush 15
    //   573: invokeinterface 313 2 0
    //   578: invokevirtual 1233	com/google/android/gms/measurement/internal/zzh:zzL	(J)V
    //   581: aload 7
    //   583: astore 6
    //   585: aload 8
    //   587: aload 7
    //   589: bipush 16
    //   591: invokeinterface 313 2 0
    //   596: invokevirtual 1235	com/google/android/gms/measurement/internal/zzh:zzU	(J)V
    //   599: aload 7
    //   601: astore 6
    //   603: aload 7
    //   605: bipush 17
    //   607: invokeinterface 1215 2 0
    //   612: ifeq +11 -> 623
    //   615: ldc2_w 1236
    //   618: lstore 4
    //   620: goto +19 -> 639
    //   623: aload 7
    //   625: astore 6
    //   627: aload 7
    //   629: bipush 17
    //   631: invokeinterface 1219 2 0
    //   636: i2l
    //   637: lstore 4
    //   639: aload 7
    //   641: astore 6
    //   643: aload 8
    //   645: lload 4
    //   647: invokevirtual 1239	com/google/android/gms/measurement/internal/zzh:zzK	(J)V
    //   650: aload 7
    //   652: astore 6
    //   654: aload 8
    //   656: aload 7
    //   658: bipush 18
    //   660: invokeinterface 1006 2 0
    //   665: invokevirtual 1241	com/google/android/gms/measurement/internal/zzh:zzV	(Ljava/lang/String;)V
    //   668: aload 7
    //   670: astore 6
    //   672: aload 8
    //   674: aload 7
    //   676: bipush 19
    //   678: invokeinterface 313 2 0
    //   683: invokevirtual 1243	com/google/android/gms/measurement/internal/zzh:zzN	(J)V
    //   686: aload 7
    //   688: astore 6
    //   690: aload 8
    //   692: aload 7
    //   694: bipush 20
    //   696: invokeinterface 313 2 0
    //   701: invokevirtual 1245	com/google/android/gms/measurement/internal/zzh:zzQ	(J)V
    //   704: aload 7
    //   706: astore 6
    //   708: aload 8
    //   710: aload 7
    //   712: bipush 21
    //   714: invokeinterface 1006 2 0
    //   719: invokevirtual 1248	com/google/android/gms/measurement/internal/zzh:zzY	(Ljava/lang/String;)V
    //   722: iload_3
    //   723: istore_2
    //   724: aload 7
    //   726: astore 6
    //   728: aload 7
    //   730: bipush 23
    //   732: invokeinterface 1215 2 0
    //   737: ifne +24 -> 761
    //   740: aload 7
    //   742: astore 6
    //   744: aload 7
    //   746: bipush 23
    //   748: invokeinterface 1219 2 0
    //   753: ifeq +311 -> 1064
    //   756: iload_3
    //   757: istore_2
    //   758: goto +3 -> 761
    //   761: aload 7
    //   763: astore 6
    //   765: aload 8
    //   767: iload_2
    //   768: invokevirtual 1250	com/google/android/gms/measurement/internal/zzh:zzG	(Z)V
    //   771: aload 7
    //   773: astore 6
    //   775: aload 8
    //   777: aload 7
    //   779: bipush 24
    //   781: invokeinterface 1006 2 0
    //   786: invokevirtual 1252	com/google/android/gms/measurement/internal/zzh:zzF	(Ljava/lang/String;)V
    //   789: aload 7
    //   791: astore 6
    //   793: aload 7
    //   795: bipush 25
    //   797: invokeinterface 1215 2 0
    //   802: ifeq +9 -> 811
    //   805: lconst_0
    //   806: lstore 4
    //   808: goto +18 -> 826
    //   811: aload 7
    //   813: astore 6
    //   815: aload 7
    //   817: bipush 25
    //   819: invokeinterface 313 2 0
    //   824: lstore 4
    //   826: aload 7
    //   828: astore 6
    //   830: aload 8
    //   832: lload 4
    //   834: invokevirtual 1254	com/google/android/gms/measurement/internal/zzh:zzT	(J)V
    //   837: aload 7
    //   839: astore 6
    //   841: aload 7
    //   843: bipush 26
    //   845: invokeinterface 1215 2 0
    //   850: ifne +31 -> 881
    //   853: aload 7
    //   855: astore 6
    //   857: aload 8
    //   859: aload 7
    //   861: bipush 26
    //   863: invokeinterface 1006 2 0
    //   868: ldc_w 636
    //   871: iconst_m1
    //   872: invokevirtual 1258	java/lang/String:split	(Ljava/lang/String;I)[Ljava/lang/String;
    //   875: invokestatic 1264	java/util/Arrays:asList	([Ljava/lang/Object;)Ljava/util/List;
    //   878: invokevirtual 1268	com/google/android/gms/measurement/internal/zzh:zzaf	(Ljava/util/List;)V
    //   881: aload 7
    //   883: astore 6
    //   885: invokestatic 1271	com/google/android/gms/internal/measurement/zzoz:zzc	()Z
    //   888: pop
    //   889: aload 7
    //   891: astore 6
    //   893: aload_0
    //   894: getfield 216	com/google/android/gms/measurement/internal/zzgr:zzs	Lcom/google/android/gms/measurement/internal/zzfy;
    //   897: invokevirtual 231	com/google/android/gms/measurement/internal/zzfy:zzf	()Lcom/google/android/gms/measurement/internal/zzag;
    //   900: aconst_null
    //   901: getstatic 1274	com/google/android/gms/measurement/internal/zzeb:zzar	Lcom/google/android/gms/measurement/internal/zzea;
    //   904: invokevirtual 770	com/google/android/gms/measurement/internal/zzag:zzs	(Ljava/lang/String;Lcom/google/android/gms/measurement/internal/zzea;)Z
    //   907: ifeq +21 -> 928
    //   910: aload 7
    //   912: astore 6
    //   914: aload 8
    //   916: aload 7
    //   918: bipush 28
    //   920: invokeinterface 1006 2 0
    //   925: invokevirtual 1277	com/google/android/gms/measurement/internal/zzh:zzag	(Ljava/lang/String;)V
    //   928: aload 7
    //   930: astore 6
    //   932: aload 8
    //   934: invokevirtual 1279	com/google/android/gms/measurement/internal/zzh:zzD	()V
    //   937: aload 7
    //   939: astore 6
    //   941: aload 7
    //   943: invokeinterface 1047 1 0
    //   948: ifeq +27 -> 975
    //   951: aload 7
    //   953: astore 6
    //   955: aload_0
    //   956: getfield 216	com/google/android/gms/measurement/internal/zzgr:zzs	Lcom/google/android/gms/measurement/internal/zzfy;
    //   959: invokevirtual 323	com/google/android/gms/measurement/internal/zzfy:zzay	()Lcom/google/android/gms/measurement/internal/zzeo;
    //   962: invokevirtual 328	com/google/android/gms/measurement/internal/zzeo:zzd	()Lcom/google/android/gms/measurement/internal/zzem;
    //   965: ldc_w 1281
    //   968: aload_1
    //   969: invokestatic 359	com/google/android/gms/measurement/internal/zzeo:zzn	(Ljava/lang/String;)Ljava/lang/Object;
    //   972: invokevirtual 501	com/google/android/gms/measurement/internal/zzem:zzb	(Ljava/lang/String;Ljava/lang/Object;)V
    //   975: aload 7
    //   977: invokeinterface 316 1 0
    //   982: aload 8
    //   984: areturn
    //   985: astore 8
    //   987: goto +12 -> 999
    //   990: astore_1
    //   991: goto +49 -> 1040
    //   994: astore 8
    //   996: aconst_null
    //   997: astore 7
    //   999: aload 7
    //   1001: astore 6
    //   1003: aload_0
    //   1004: getfield 216	com/google/android/gms/measurement/internal/zzgr:zzs	Lcom/google/android/gms/measurement/internal/zzfy;
    //   1007: invokevirtual 323	com/google/android/gms/measurement/internal/zzfy:zzay	()Lcom/google/android/gms/measurement/internal/zzeo;
    //   1010: invokevirtual 328	com/google/android/gms/measurement/internal/zzeo:zzd	()Lcom/google/android/gms/measurement/internal/zzem;
    //   1013: ldc_w 1283
    //   1016: aload_1
    //   1017: invokestatic 359	com/google/android/gms/measurement/internal/zzeo:zzn	(Ljava/lang/String;)Ljava/lang/Object;
    //   1020: aload 8
    //   1022: invokevirtual 335	com/google/android/gms/measurement/internal/zzem:zzc	(Ljava/lang/String;Ljava/lang/Object;Ljava/lang/Object;)V
    //   1025: aload 7
    //   1027: ifnull +10 -> 1037
    //   1030: aload 7
    //   1032: invokeinterface 316 1 0
    //   1037: aconst_null
    //   1038: areturn
    //   1039: astore_1
    //   1040: aload 6
    //   1042: ifnull +10 -> 1052
    //   1045: aload 6
    //   1047: invokeinterface 316 1 0
    //   1052: aload_1
    //   1053: athrow
    //   1054: iconst_0
    //   1055: istore_2
    //   1056: goto -575 -> 481
    //   1059: iconst_1
    //   1060: istore_2
    //   1061: goto -580 -> 481
    //   1064: iconst_0
    //   1065: istore_2
    //   1066: goto -305 -> 761
    // Local variable table:
    //   start	length	slot	name	signature
    //   0	1069	0	this	zzam
    //   0	1069	1	paramString	String
    //   237	829	2	bool1	boolean
    //   23	734	3	bool2	boolean
    //   618	215	4	l	long
    //   14	1032	6	localObject1	Object
    //   20	1011	7	localObject2	Object
    //   270	713	8	localZzh	zzh
    //   985	1	8	localSQLiteException1	SQLiteException
    //   994	27	8	localSQLiteException2	SQLiteException
    // Exception table:
    //   from	to	target	type
    //   230	238	985	android/database/sqlite/SQLiteException
    //   255	272	985	android/database/sqlite/SQLiteException
    //   276	289	985	android/database/sqlite/SQLiteException
    //   293	306	985	android/database/sqlite/SQLiteException
    //   310	323	985	android/database/sqlite/SQLiteException
    //   327	340	985	android/database/sqlite/SQLiteException
    //   344	357	985	android/database/sqlite/SQLiteException
    //   361	374	985	android/database/sqlite/SQLiteException
    //   378	392	985	android/database/sqlite/SQLiteException
    //   396	410	985	android/database/sqlite/SQLiteException
    //   414	428	985	android/database/sqlite/SQLiteException
    //   432	446	985	android/database/sqlite/SQLiteException
    //   450	462	985	android/database/sqlite/SQLiteException
    //   466	478	985	android/database/sqlite/SQLiteException
    //   485	491	985	android/database/sqlite/SQLiteException
    //   495	509	985	android/database/sqlite/SQLiteException
    //   513	527	985	android/database/sqlite/SQLiteException
    //   531	545	985	android/database/sqlite/SQLiteException
    //   549	563	985	android/database/sqlite/SQLiteException
    //   567	581	985	android/database/sqlite/SQLiteException
    //   585	599	985	android/database/sqlite/SQLiteException
    //   603	615	985	android/database/sqlite/SQLiteException
    //   627	639	985	android/database/sqlite/SQLiteException
    //   643	650	985	android/database/sqlite/SQLiteException
    //   654	668	985	android/database/sqlite/SQLiteException
    //   672	686	985	android/database/sqlite/SQLiteException
    //   690	704	985	android/database/sqlite/SQLiteException
    //   708	722	985	android/database/sqlite/SQLiteException
    //   728	740	985	android/database/sqlite/SQLiteException
    //   744	756	985	android/database/sqlite/SQLiteException
    //   765	771	985	android/database/sqlite/SQLiteException
    //   775	789	985	android/database/sqlite/SQLiteException
    //   793	805	985	android/database/sqlite/SQLiteException
    //   815	826	985	android/database/sqlite/SQLiteException
    //   830	837	985	android/database/sqlite/SQLiteException
    //   841	853	985	android/database/sqlite/SQLiteException
    //   857	881	985	android/database/sqlite/SQLiteException
    //   885	889	985	android/database/sqlite/SQLiteException
    //   893	910	985	android/database/sqlite/SQLiteException
    //   914	928	985	android/database/sqlite/SQLiteException
    //   932	937	985	android/database/sqlite/SQLiteException
    //   941	951	985	android/database/sqlite/SQLiteException
    //   955	975	985	android/database/sqlite/SQLiteException
    //   16	22	990	finally
    //   24	226	990	finally
    //   16	22	994	android/database/sqlite/SQLiteException
    //   24	226	994	android/database/sqlite/SQLiteException
    //   230	238	1039	finally
    //   255	272	1039	finally
    //   276	289	1039	finally
    //   293	306	1039	finally
    //   310	323	1039	finally
    //   327	340	1039	finally
    //   344	357	1039	finally
    //   361	374	1039	finally
    //   378	392	1039	finally
    //   396	410	1039	finally
    //   414	428	1039	finally
    //   432	446	1039	finally
    //   450	462	1039	finally
    //   466	478	1039	finally
    //   485	491	1039	finally
    //   495	509	1039	finally
    //   513	527	1039	finally
    //   531	545	1039	finally
    //   549	563	1039	finally
    //   567	581	1039	finally
    //   585	599	1039	finally
    //   603	615	1039	finally
    //   627	639	1039	finally
    //   643	650	1039	finally
    //   654	668	1039	finally
    //   672	686	1039	finally
    //   690	704	1039	finally
    //   708	722	1039	finally
    //   728	740	1039	finally
    //   744	756	1039	finally
    //   765	771	1039	finally
    //   775	789	1039	finally
    //   793	805	1039	finally
    //   815	826	1039	finally
    //   830	837	1039	finally
    //   841	853	1039	finally
    //   857	881	1039	finally
    //   885	889	1039	finally
    //   893	910	1039	finally
    //   914	928	1039	finally
    //   932	937	1039	finally
    //   941	951	1039	finally
    //   955	975	1039	finally
    //   1003	1025	1039	finally
  }
  
  /* Error */
  public final zzac zzk(String paramString1, String paramString2)
  {
    // Byte code:
    //   0: aload_1
    //   1: invokestatic 263	com/google/android/gms/common/internal/Preconditions:checkNotEmpty	(Ljava/lang/String;)Ljava/lang/String;
    //   4: pop
    //   5: aload_2
    //   6: invokestatic 263	com/google/android/gms/common/internal/Preconditions:checkNotEmpty	(Ljava/lang/String;)Ljava/lang/String;
    //   9: pop
    //   10: aload_0
    //   11: invokevirtual 342	com/google/android/gms/measurement/internal/zzgr:zzg	()V
    //   14: aload_0
    //   15: invokevirtual 345	com/google/android/gms/measurement/internal/zzkn:zzW	()V
    //   18: aconst_null
    //   19: astore 12
    //   21: aload_0
    //   22: invokevirtual 297	com/google/android/gms/measurement/internal/zzam:zzh	()Landroid/database/sqlite/SQLiteDatabase;
    //   25: ldc_w 945
    //   28: bipush 11
    //   30: anewarray 21	java/lang/String
    //   33: dup
    //   34: iconst_0
    //   35: ldc 49
    //   37: aastore
    //   38: dup
    //   39: iconst_1
    //   40: ldc_w 257
    //   43: aastore
    //   44: dup
    //   45: iconst_2
    //   46: ldc_w 900
    //   49: aastore
    //   50: dup
    //   51: iconst_3
    //   52: ldc_w 905
    //   55: aastore
    //   56: dup
    //   57: iconst_4
    //   58: ldc_w 909
    //   61: aastore
    //   62: dup
    //   63: iconst_5
    //   64: ldc_w 913
    //   67: aastore
    //   68: dup
    //   69: bipush 6
    //   71: ldc_w 927
    //   74: aastore
    //   75: dup
    //   76: bipush 7
    //   78: ldc_w 930
    //   81: aastore
    //   82: dup
    //   83: bipush 8
    //   85: ldc_w 934
    //   88: aastore
    //   89: dup
    //   90: bipush 9
    //   92: ldc_w 937
    //   95: aastore
    //   96: dup
    //   97: bipush 10
    //   99: ldc_w 941
    //   102: aastore
    //   103: ldc_w 349
    //   106: iconst_2
    //   107: anewarray 21	java/lang/String
    //   110: dup
    //   111: iconst_0
    //   112: aload_1
    //   113: aastore
    //   114: dup
    //   115: iconst_1
    //   116: aload_2
    //   117: aastore
    //   118: aconst_null
    //   119: aconst_null
    //   120: aconst_null
    //   121: invokevirtual 1181	android/database/sqlite/SQLiteDatabase:query	(Ljava/lang/String;[Ljava/lang/String;Ljava/lang/String;[Ljava/lang/String;Ljava/lang/String;Ljava/lang/String;Ljava/lang/String;)Landroid/database/Cursor;
    //   124: astore 13
    //   126: aload 13
    //   128: astore 12
    //   130: aload 13
    //   132: invokeinterface 309 1 0
    //   137: istore_3
    //   138: iload_3
    //   139: ifne +12 -> 151
    //   142: aload 13
    //   144: invokeinterface 316 1 0
    //   149: aconst_null
    //   150: areturn
    //   151: aload 13
    //   153: astore 12
    //   155: aload 13
    //   157: iconst_0
    //   158: invokeinterface 1006 2 0
    //   163: astore 15
    //   165: aload 15
    //   167: astore 14
    //   169: aload 15
    //   171: ifnonnull +8 -> 179
    //   174: ldc_w 994
    //   177: astore 14
    //   179: aload 13
    //   181: astore 12
    //   183: aload_0
    //   184: aload 13
    //   186: iconst_1
    //   187: invokevirtual 1287	com/google/android/gms/measurement/internal/zzam:zzq	(Landroid/database/Cursor;I)Ljava/lang/Object;
    //   190: astore 15
    //   192: aload 13
    //   194: astore 12
    //   196: aload 13
    //   198: iconst_2
    //   199: invokeinterface 1219 2 0
    //   204: ifeq +383 -> 587
    //   207: iconst_1
    //   208: istore_3
    //   209: goto +3 -> 212
    //   212: aload 13
    //   214: astore 12
    //   216: aload 13
    //   218: iconst_3
    //   219: invokeinterface 1006 2 0
    //   224: astore 16
    //   226: aload 13
    //   228: astore 12
    //   230: aload 13
    //   232: iconst_4
    //   233: invokeinterface 313 2 0
    //   238: lstore 4
    //   240: aload 13
    //   242: astore 12
    //   244: aload_0
    //   245: getfield 1128	com/google/android/gms/measurement/internal/zzkm:zzf	Lcom/google/android/gms/measurement/internal/zzkz;
    //   248: invokevirtual 1133	com/google/android/gms/measurement/internal/zzkz:zzu	()Lcom/google/android/gms/measurement/internal/zzlb;
    //   251: astore 18
    //   253: aload 13
    //   255: astore 12
    //   257: aload 13
    //   259: iconst_5
    //   260: invokeinterface 1032 2 0
    //   265: astore 19
    //   267: aload 13
    //   269: astore 12
    //   271: getstatic 1293	com/google/android/gms/measurement/internal/zzaw:CREATOR	Landroid/os/Parcelable$Creator;
    //   274: astore 17
    //   276: aload 13
    //   278: astore 12
    //   280: aload 18
    //   282: aload 19
    //   284: aload 17
    //   286: invokevirtual 1296	com/google/android/gms/measurement/internal/zzlb:zzh	([BLandroid/os/Parcelable$Creator;)Landroid/os/Parcelable;
    //   289: checkcast 1289	com/google/android/gms/measurement/internal/zzaw
    //   292: astore 18
    //   294: aload 13
    //   296: astore 12
    //   298: aload 13
    //   300: bipush 6
    //   302: invokeinterface 313 2 0
    //   307: lstore 6
    //   309: aload 13
    //   311: astore 12
    //   313: aload_0
    //   314: getfield 1128	com/google/android/gms/measurement/internal/zzkm:zzf	Lcom/google/android/gms/measurement/internal/zzkz;
    //   317: invokevirtual 1133	com/google/android/gms/measurement/internal/zzkz:zzu	()Lcom/google/android/gms/measurement/internal/zzlb;
    //   320: aload 13
    //   322: bipush 7
    //   324: invokeinterface 1032 2 0
    //   329: aload 17
    //   331: invokevirtual 1296	com/google/android/gms/measurement/internal/zzlb:zzh	([BLandroid/os/Parcelable$Creator;)Landroid/os/Parcelable;
    //   334: checkcast 1289	com/google/android/gms/measurement/internal/zzaw
    //   337: astore 19
    //   339: aload 13
    //   341: astore 12
    //   343: aload 13
    //   345: bipush 8
    //   347: invokeinterface 313 2 0
    //   352: lstore 8
    //   354: aload 13
    //   356: astore 12
    //   358: aload 13
    //   360: bipush 9
    //   362: invokeinterface 313 2 0
    //   367: lstore 10
    //   369: aload 13
    //   371: astore 12
    //   373: aload_0
    //   374: getfield 1128	com/google/android/gms/measurement/internal/zzkm:zzf	Lcom/google/android/gms/measurement/internal/zzkz;
    //   377: invokevirtual 1133	com/google/android/gms/measurement/internal/zzkz:zzu	()Lcom/google/android/gms/measurement/internal/zzlb;
    //   380: aload 13
    //   382: bipush 10
    //   384: invokeinterface 1032 2 0
    //   389: aload 17
    //   391: invokevirtual 1296	com/google/android/gms/measurement/internal/zzlb:zzh	([BLandroid/os/Parcelable$Creator;)Landroid/os/Parcelable;
    //   394: checkcast 1289	com/google/android/gms/measurement/internal/zzaw
    //   397: astore 17
    //   399: aload 13
    //   401: astore 12
    //   403: new 879	com/google/android/gms/measurement/internal/zzac
    //   406: dup
    //   407: aload_1
    //   408: aload 14
    //   410: new 885	com/google/android/gms/measurement/internal/zzlc
    //   413: dup
    //   414: aload_2
    //   415: lload 8
    //   417: aload 15
    //   419: aload 14
    //   421: invokespecial 1299	com/google/android/gms/measurement/internal/zzlc:<init>	(Ljava/lang/String;JLjava/lang/Object;Ljava/lang/String;)V
    //   424: lload 6
    //   426: iload_3
    //   427: aload 16
    //   429: aload 18
    //   431: lload 4
    //   433: aload 19
    //   435: lload 10
    //   437: aload 17
    //   439: invokespecial 1302	com/google/android/gms/measurement/internal/zzac:<init>	(Ljava/lang/String;Ljava/lang/String;Lcom/google/android/gms/measurement/internal/zzlc;JZLjava/lang/String;Lcom/google/android/gms/measurement/internal/zzaw;JLcom/google/android/gms/measurement/internal/zzaw;JLcom/google/android/gms/measurement/internal/zzaw;)V
    //   442: astore 14
    //   444: aload 13
    //   446: astore 12
    //   448: aload 13
    //   450: invokeinterface 1047 1 0
    //   455: ifeq +38 -> 493
    //   458: aload 13
    //   460: astore 12
    //   462: aload_0
    //   463: getfield 216	com/google/android/gms/measurement/internal/zzgr:zzs	Lcom/google/android/gms/measurement/internal/zzfy;
    //   466: invokevirtual 323	com/google/android/gms/measurement/internal/zzfy:zzay	()Lcom/google/android/gms/measurement/internal/zzeo;
    //   469: invokevirtual 328	com/google/android/gms/measurement/internal/zzeo:zzd	()Lcom/google/android/gms/measurement/internal/zzem;
    //   472: ldc_w 1304
    //   475: aload_1
    //   476: invokestatic 359	com/google/android/gms/measurement/internal/zzeo:zzn	(Ljava/lang/String;)Ljava/lang/Object;
    //   479: aload_0
    //   480: getfield 216	com/google/android/gms/measurement/internal/zzgr:zzs	Lcom/google/android/gms/measurement/internal/zzfy;
    //   483: invokevirtual 362	com/google/android/gms/measurement/internal/zzfy:zzj	()Lcom/google/android/gms/measurement/internal/zzej;
    //   486: aload_2
    //   487: invokevirtual 366	com/google/android/gms/measurement/internal/zzej:zzf	(Ljava/lang/String;)Ljava/lang/String;
    //   490: invokevirtual 335	com/google/android/gms/measurement/internal/zzem:zzc	(Ljava/lang/String;Ljava/lang/Object;Ljava/lang/Object;)V
    //   493: aload 13
    //   495: invokeinterface 316 1 0
    //   500: aload 14
    //   502: areturn
    //   503: astore 14
    //   505: goto +15 -> 520
    //   508: astore_1
    //   509: aload 12
    //   511: astore_2
    //   512: goto +63 -> 575
    //   515: astore 14
    //   517: aconst_null
    //   518: astore 13
    //   520: aload 13
    //   522: astore 12
    //   524: aload_0
    //   525: getfield 216	com/google/android/gms/measurement/internal/zzgr:zzs	Lcom/google/android/gms/measurement/internal/zzfy;
    //   528: invokevirtual 323	com/google/android/gms/measurement/internal/zzfy:zzay	()Lcom/google/android/gms/measurement/internal/zzeo;
    //   531: invokevirtual 328	com/google/android/gms/measurement/internal/zzeo:zzd	()Lcom/google/android/gms/measurement/internal/zzem;
    //   534: ldc_w 1306
    //   537: aload_1
    //   538: invokestatic 359	com/google/android/gms/measurement/internal/zzeo:zzn	(Ljava/lang/String;)Ljava/lang/Object;
    //   541: aload_0
    //   542: getfield 216	com/google/android/gms/measurement/internal/zzgr:zzs	Lcom/google/android/gms/measurement/internal/zzfy;
    //   545: invokevirtual 362	com/google/android/gms/measurement/internal/zzfy:zzj	()Lcom/google/android/gms/measurement/internal/zzej;
    //   548: aload_2
    //   549: invokevirtual 366	com/google/android/gms/measurement/internal/zzej:zzf	(Ljava/lang/String;)Ljava/lang/String;
    //   552: aload 14
    //   554: invokevirtual 369	com/google/android/gms/measurement/internal/zzem:zzd	(Ljava/lang/String;Ljava/lang/Object;Ljava/lang/Object;Ljava/lang/Object;)V
    //   557: aload 13
    //   559: ifnull +10 -> 569
    //   562: aload 13
    //   564: invokeinterface 316 1 0
    //   569: aconst_null
    //   570: areturn
    //   571: astore_1
    //   572: aload 12
    //   574: astore_2
    //   575: aload_2
    //   576: ifnull +9 -> 585
    //   579: aload_2
    //   580: invokeinterface 316 1 0
    //   585: aload_1
    //   586: athrow
    //   587: iconst_0
    //   588: istore_3
    //   589: goto -377 -> 212
    // Local variable table:
    //   start	length	slot	name	signature
    //   0	592	0	this	zzam
    //   0	592	1	paramString1	String
    //   0	592	2	paramString2	String
    //   137	452	3	bool	boolean
    //   238	194	4	l1	long
    //   307	118	6	l2	long
    //   352	64	8	l3	long
    //   367	69	10	l4	long
    //   19	554	12	localObject1	Object
    //   124	439	13	localCursor	Cursor
    //   167	334	14	localObject2	Object
    //   503	1	14	localSQLiteException1	SQLiteException
    //   515	38	14	localSQLiteException2	SQLiteException
    //   163	255	15	localObject3	Object
    //   224	204	16	str	String
    //   274	164	17	localObject4	Object
    //   251	179	18	localObject5	Object
    //   265	169	19	localObject6	Object
    // Exception table:
    //   from	to	target	type
    //   130	138	503	android/database/sqlite/SQLiteException
    //   155	165	503	android/database/sqlite/SQLiteException
    //   183	192	503	android/database/sqlite/SQLiteException
    //   196	207	503	android/database/sqlite/SQLiteException
    //   216	226	503	android/database/sqlite/SQLiteException
    //   230	240	503	android/database/sqlite/SQLiteException
    //   244	253	503	android/database/sqlite/SQLiteException
    //   257	267	503	android/database/sqlite/SQLiteException
    //   271	276	503	android/database/sqlite/SQLiteException
    //   280	294	503	android/database/sqlite/SQLiteException
    //   298	309	503	android/database/sqlite/SQLiteException
    //   313	339	503	android/database/sqlite/SQLiteException
    //   343	354	503	android/database/sqlite/SQLiteException
    //   358	369	503	android/database/sqlite/SQLiteException
    //   373	399	503	android/database/sqlite/SQLiteException
    //   403	444	503	android/database/sqlite/SQLiteException
    //   448	458	503	android/database/sqlite/SQLiteException
    //   462	493	503	android/database/sqlite/SQLiteException
    //   21	126	508	finally
    //   21	126	515	android/database/sqlite/SQLiteException
    //   130	138	571	finally
    //   155	165	571	finally
    //   183	192	571	finally
    //   196	207	571	finally
    //   216	226	571	finally
    //   230	240	571	finally
    //   244	253	571	finally
    //   257	267	571	finally
    //   271	276	571	finally
    //   280	294	571	finally
    //   298	309	571	finally
    //   313	339	571	finally
    //   343	354	571	finally
    //   358	369	571	finally
    //   373	399	571	finally
    //   403	444	571	finally
    //   448	458	571	finally
    //   462	493	571	finally
    //   524	557	571	finally
  }
  
  public final zzak zzl(long paramLong, String paramString, boolean paramBoolean1, boolean paramBoolean2, boolean paramBoolean3, boolean paramBoolean4, boolean paramBoolean5)
  {
    return zzm(paramLong, paramString, 1L, false, false, paramBoolean3, false, paramBoolean5);
  }
  
  /* Error */
  public final zzak zzm(long paramLong1, String paramString, long paramLong2, boolean paramBoolean1, boolean paramBoolean2, boolean paramBoolean3, boolean paramBoolean4, boolean paramBoolean5)
  {
    // Byte code:
    //   0: aload_3
    //   1: invokestatic 263	com/google/android/gms/common/internal/Preconditions:checkNotEmpty	(Ljava/lang/String;)Ljava/lang/String;
    //   4: pop
    //   5: aload_0
    //   6: invokevirtual 342	com/google/android/gms/measurement/internal/zzgr:zzg	()V
    //   9: aload_0
    //   10: invokevirtual 345	com/google/android/gms/measurement/internal/zzkn:zzW	()V
    //   13: new 1312	com/google/android/gms/measurement/internal/zzak
    //   16: dup
    //   17: invokespecial 1313	com/google/android/gms/measurement/internal/zzak:<init>	()V
    //   20: astore 15
    //   22: aconst_null
    //   23: astore 14
    //   25: aconst_null
    //   26: astore 13
    //   28: aload 13
    //   30: astore 11
    //   32: aload 14
    //   34: astore 12
    //   36: aload_0
    //   37: invokevirtual 297	com/google/android/gms/measurement/internal/zzam:zzh	()Landroid/database/sqlite/SQLiteDatabase;
    //   40: astore 16
    //   42: aload 13
    //   44: astore 11
    //   46: aload 14
    //   48: astore 12
    //   50: aload 16
    //   52: ldc_w 776
    //   55: bipush 6
    //   57: anewarray 21	java/lang/String
    //   60: dup
    //   61: iconst_0
    //   62: ldc 79
    //   64: aastore
    //   65: dup
    //   66: iconst_1
    //   67: ldc 87
    //   69: aastore
    //   70: dup
    //   71: iconst_2
    //   72: ldc 83
    //   74: aastore
    //   75: dup
    //   76: iconst_3
    //   77: ldc 91
    //   79: aastore
    //   80: dup
    //   81: iconst_4
    //   82: ldc 115
    //   84: aastore
    //   85: dup
    //   86: iconst_5
    //   87: ldc 119
    //   89: aastore
    //   90: ldc_w 477
    //   93: iconst_1
    //   94: anewarray 21	java/lang/String
    //   97: dup
    //   98: iconst_0
    //   99: aload_3
    //   100: aastore
    //   101: aconst_null
    //   102: aconst_null
    //   103: aconst_null
    //   104: invokevirtual 1181	android/database/sqlite/SQLiteDatabase:query	(Ljava/lang/String;[Ljava/lang/String;Ljava/lang/String;[Ljava/lang/String;Ljava/lang/String;Ljava/lang/String;Ljava/lang/String;)Landroid/database/Cursor;
    //   107: astore 13
    //   109: aload 13
    //   111: astore 11
    //   113: aload 13
    //   115: astore 12
    //   117: aload 13
    //   119: invokeinterface 309 1 0
    //   124: ifne +41 -> 165
    //   127: aload 13
    //   129: astore 11
    //   131: aload 13
    //   133: astore 12
    //   135: aload_0
    //   136: getfield 216	com/google/android/gms/measurement/internal/zzgr:zzs	Lcom/google/android/gms/measurement/internal/zzfy;
    //   139: invokevirtual 323	com/google/android/gms/measurement/internal/zzfy:zzay	()Lcom/google/android/gms/measurement/internal/zzeo;
    //   142: invokevirtual 496	com/google/android/gms/measurement/internal/zzeo:zzk	()Lcom/google/android/gms/measurement/internal/zzem;
    //   145: ldc_w 1315
    //   148: aload_3
    //   149: invokestatic 359	com/google/android/gms/measurement/internal/zzeo:zzn	(Ljava/lang/String;)Ljava/lang/Object;
    //   152: invokevirtual 501	com/google/android/gms/measurement/internal/zzem:zzb	(Ljava/lang/String;Ljava/lang/Object;)V
    //   155: aload 13
    //   157: invokeinterface 316 1 0
    //   162: aload 15
    //   164: areturn
    //   165: aload 13
    //   167: astore 11
    //   169: aload 13
    //   171: astore 12
    //   173: aload 13
    //   175: iconst_0
    //   176: invokeinterface 313 2 0
    //   181: lload_1
    //   182: lcmp
    //   183: ifne +108 -> 291
    //   186: aload 13
    //   188: astore 11
    //   190: aload 13
    //   192: astore 12
    //   194: aload 15
    //   196: aload 13
    //   198: iconst_1
    //   199: invokeinterface 313 2 0
    //   204: putfield 1317	com/google/android/gms/measurement/internal/zzak:zzb	J
    //   207: aload 13
    //   209: astore 11
    //   211: aload 13
    //   213: astore 12
    //   215: aload 15
    //   217: aload 13
    //   219: iconst_2
    //   220: invokeinterface 313 2 0
    //   225: putfield 1319	com/google/android/gms/measurement/internal/zzak:zza	J
    //   228: aload 13
    //   230: astore 11
    //   232: aload 13
    //   234: astore 12
    //   236: aload 15
    //   238: aload 13
    //   240: iconst_3
    //   241: invokeinterface 313 2 0
    //   246: putfield 1320	com/google/android/gms/measurement/internal/zzak:zzc	J
    //   249: aload 13
    //   251: astore 11
    //   253: aload 13
    //   255: astore 12
    //   257: aload 15
    //   259: aload 13
    //   261: iconst_4
    //   262: invokeinterface 313 2 0
    //   267: putfield 1321	com/google/android/gms/measurement/internal/zzak:zzd	J
    //   270: aload 13
    //   272: astore 11
    //   274: aload 13
    //   276: astore 12
    //   278: aload 15
    //   280: aload 13
    //   282: iconst_5
    //   283: invokeinterface 313 2 0
    //   288: putfield 1322	com/google/android/gms/measurement/internal/zzak:zze	J
    //   291: iload 6
    //   293: ifeq +24 -> 317
    //   296: aload 13
    //   298: astore 11
    //   300: aload 13
    //   302: astore 12
    //   304: aload 15
    //   306: aload 15
    //   308: getfield 1317	com/google/android/gms/measurement/internal/zzak:zzb	J
    //   311: lload 4
    //   313: ladd
    //   314: putfield 1317	com/google/android/gms/measurement/internal/zzak:zzb	J
    //   317: iload 7
    //   319: ifeq +24 -> 343
    //   322: aload 13
    //   324: astore 11
    //   326: aload 13
    //   328: astore 12
    //   330: aload 15
    //   332: aload 15
    //   334: getfield 1319	com/google/android/gms/measurement/internal/zzak:zza	J
    //   337: lload 4
    //   339: ladd
    //   340: putfield 1319	com/google/android/gms/measurement/internal/zzak:zza	J
    //   343: iload 8
    //   345: ifeq +24 -> 369
    //   348: aload 13
    //   350: astore 11
    //   352: aload 13
    //   354: astore 12
    //   356: aload 15
    //   358: aload 15
    //   360: getfield 1320	com/google/android/gms/measurement/internal/zzak:zzc	J
    //   363: lload 4
    //   365: ladd
    //   366: putfield 1320	com/google/android/gms/measurement/internal/zzak:zzc	J
    //   369: iload 9
    //   371: ifeq +24 -> 395
    //   374: aload 13
    //   376: astore 11
    //   378: aload 13
    //   380: astore 12
    //   382: aload 15
    //   384: aload 15
    //   386: getfield 1321	com/google/android/gms/measurement/internal/zzak:zzd	J
    //   389: lload 4
    //   391: ladd
    //   392: putfield 1321	com/google/android/gms/measurement/internal/zzak:zzd	J
    //   395: iload 10
    //   397: ifeq +24 -> 421
    //   400: aload 13
    //   402: astore 11
    //   404: aload 13
    //   406: astore 12
    //   408: aload 15
    //   410: aload 15
    //   412: getfield 1322	com/google/android/gms/measurement/internal/zzak:zze	J
    //   415: lload 4
    //   417: ladd
    //   418: putfield 1322	com/google/android/gms/measurement/internal/zzak:zze	J
    //   421: aload 13
    //   423: astore 11
    //   425: aload 13
    //   427: astore 12
    //   429: new 269	android/content/ContentValues
    //   432: dup
    //   433: invokespecial 543	android/content/ContentValues:<init>	()V
    //   436: astore 14
    //   438: aload 13
    //   440: astore 11
    //   442: aload 13
    //   444: astore 12
    //   446: aload 14
    //   448: ldc 79
    //   450: lload_1
    //   451: invokestatic 699	java/lang/Long:valueOf	(J)Ljava/lang/Long;
    //   454: invokevirtual 278	android/content/ContentValues:put	(Ljava/lang/String;Ljava/lang/Long;)V
    //   457: aload 13
    //   459: astore 11
    //   461: aload 13
    //   463: astore 12
    //   465: aload 14
    //   467: ldc 83
    //   469: aload 15
    //   471: getfield 1319	com/google/android/gms/measurement/internal/zzak:zza	J
    //   474: invokestatic 699	java/lang/Long:valueOf	(J)Ljava/lang/Long;
    //   477: invokevirtual 278	android/content/ContentValues:put	(Ljava/lang/String;Ljava/lang/Long;)V
    //   480: aload 13
    //   482: astore 11
    //   484: aload 13
    //   486: astore 12
    //   488: aload 14
    //   490: ldc 87
    //   492: aload 15
    //   494: getfield 1317	com/google/android/gms/measurement/internal/zzak:zzb	J
    //   497: invokestatic 699	java/lang/Long:valueOf	(J)Ljava/lang/Long;
    //   500: invokevirtual 278	android/content/ContentValues:put	(Ljava/lang/String;Ljava/lang/Long;)V
    //   503: aload 13
    //   505: astore 11
    //   507: aload 13
    //   509: astore 12
    //   511: aload 14
    //   513: ldc 91
    //   515: aload 15
    //   517: getfield 1320	com/google/android/gms/measurement/internal/zzak:zzc	J
    //   520: invokestatic 699	java/lang/Long:valueOf	(J)Ljava/lang/Long;
    //   523: invokevirtual 278	android/content/ContentValues:put	(Ljava/lang/String;Ljava/lang/Long;)V
    //   526: aload 13
    //   528: astore 11
    //   530: aload 13
    //   532: astore 12
    //   534: aload 14
    //   536: ldc 115
    //   538: aload 15
    //   540: getfield 1321	com/google/android/gms/measurement/internal/zzak:zzd	J
    //   543: invokestatic 699	java/lang/Long:valueOf	(J)Ljava/lang/Long;
    //   546: invokevirtual 278	android/content/ContentValues:put	(Ljava/lang/String;Ljava/lang/Long;)V
    //   549: aload 13
    //   551: astore 11
    //   553: aload 13
    //   555: astore 12
    //   557: aload 14
    //   559: ldc 119
    //   561: aload 15
    //   563: getfield 1322	com/google/android/gms/measurement/internal/zzak:zze	J
    //   566: invokestatic 699	java/lang/Long:valueOf	(J)Ljava/lang/Long;
    //   569: invokevirtual 278	android/content/ContentValues:put	(Ljava/lang/String;Ljava/lang/Long;)V
    //   572: aload 13
    //   574: astore 11
    //   576: aload 13
    //   578: astore 12
    //   580: aload 16
    //   582: ldc_w 776
    //   585: aload 14
    //   587: ldc_w 477
    //   590: iconst_1
    //   591: anewarray 21	java/lang/String
    //   594: dup
    //   595: iconst_0
    //   596: aload_3
    //   597: aastore
    //   598: invokevirtual 782	android/database/sqlite/SQLiteDatabase:update	(Ljava/lang/String;Landroid/content/ContentValues;Ljava/lang/String;[Ljava/lang/String;)I
    //   601: pop
    //   602: aload 13
    //   604: invokeinterface 316 1 0
    //   609: aload 15
    //   611: areturn
    //   612: astore_3
    //   613: goto +46 -> 659
    //   616: astore 13
    //   618: aload 12
    //   620: astore 11
    //   622: aload_0
    //   623: getfield 216	com/google/android/gms/measurement/internal/zzgr:zzs	Lcom/google/android/gms/measurement/internal/zzfy;
    //   626: invokevirtual 323	com/google/android/gms/measurement/internal/zzfy:zzay	()Lcom/google/android/gms/measurement/internal/zzeo;
    //   629: invokevirtual 328	com/google/android/gms/measurement/internal/zzeo:zzd	()Lcom/google/android/gms/measurement/internal/zzem;
    //   632: ldc_w 1324
    //   635: aload_3
    //   636: invokestatic 359	com/google/android/gms/measurement/internal/zzeo:zzn	(Ljava/lang/String;)Ljava/lang/Object;
    //   639: aload 13
    //   641: invokevirtual 335	com/google/android/gms/measurement/internal/zzem:zzc	(Ljava/lang/String;Ljava/lang/Object;Ljava/lang/Object;)V
    //   644: aload 12
    //   646: ifnull +10 -> 656
    //   649: aload 12
    //   651: invokeinterface 316 1 0
    //   656: aload 15
    //   658: areturn
    //   659: aload 11
    //   661: ifnull +10 -> 671
    //   664: aload 11
    //   666: invokeinterface 316 1 0
    //   671: aload_3
    //   672: athrow
    // Local variable table:
    //   start	length	slot	name	signature
    //   0	673	0	this	zzam
    //   0	673	1	paramLong1	long
    //   0	673	3	paramString	String
    //   0	673	4	paramLong2	long
    //   0	673	6	paramBoolean1	boolean
    //   0	673	7	paramBoolean2	boolean
    //   0	673	8	paramBoolean3	boolean
    //   0	673	9	paramBoolean4	boolean
    //   0	673	10	paramBoolean5	boolean
    //   30	635	11	localObject1	Object
    //   34	616	12	localObject2	Object
    //   26	577	13	localCursor	Cursor
    //   616	24	13	localSQLiteException	SQLiteException
    //   23	563	14	localContentValues	ContentValues
    //   20	637	15	localZzak	zzak
    //   40	541	16	localSQLiteDatabase	SQLiteDatabase
    // Exception table:
    //   from	to	target	type
    //   36	42	612	finally
    //   50	109	612	finally
    //   117	127	612	finally
    //   135	155	612	finally
    //   173	186	612	finally
    //   194	207	612	finally
    //   215	228	612	finally
    //   236	249	612	finally
    //   257	270	612	finally
    //   278	291	612	finally
    //   304	317	612	finally
    //   330	343	612	finally
    //   356	369	612	finally
    //   382	395	612	finally
    //   408	421	612	finally
    //   429	438	612	finally
    //   446	457	612	finally
    //   465	480	612	finally
    //   488	503	612	finally
    //   511	526	612	finally
    //   534	549	612	finally
    //   557	572	612	finally
    //   580	602	612	finally
    //   622	644	612	finally
    //   36	42	616	android/database/sqlite/SQLiteException
    //   50	109	616	android/database/sqlite/SQLiteException
    //   117	127	616	android/database/sqlite/SQLiteException
    //   135	155	616	android/database/sqlite/SQLiteException
    //   173	186	616	android/database/sqlite/SQLiteException
    //   194	207	616	android/database/sqlite/SQLiteException
    //   215	228	616	android/database/sqlite/SQLiteException
    //   236	249	616	android/database/sqlite/SQLiteException
    //   257	270	616	android/database/sqlite/SQLiteException
    //   278	291	616	android/database/sqlite/SQLiteException
    //   304	317	616	android/database/sqlite/SQLiteException
    //   330	343	616	android/database/sqlite/SQLiteException
    //   356	369	616	android/database/sqlite/SQLiteException
    //   382	395	616	android/database/sqlite/SQLiteException
    //   408	421	616	android/database/sqlite/SQLiteException
    //   429	438	616	android/database/sqlite/SQLiteException
    //   446	457	616	android/database/sqlite/SQLiteException
    //   465	480	616	android/database/sqlite/SQLiteException
    //   488	503	616	android/database/sqlite/SQLiteException
    //   511	526	616	android/database/sqlite/SQLiteException
    //   534	549	616	android/database/sqlite/SQLiteException
    //   557	572	616	android/database/sqlite/SQLiteException
    //   580	602	616	android/database/sqlite/SQLiteException
  }
  
  /* Error */
  public final zzas zzn(String paramString1, String paramString2)
  {
    // Byte code:
    //   0: aload_1
    //   1: invokestatic 263	com/google/android/gms/common/internal/Preconditions:checkNotEmpty	(Ljava/lang/String;)Ljava/lang/String;
    //   4: pop
    //   5: aload_2
    //   6: invokestatic 263	com/google/android/gms/common/internal/Preconditions:checkNotEmpty	(Ljava/lang/String;)Ljava/lang/String;
    //   9: pop
    //   10: aload_0
    //   11: invokevirtual 342	com/google/android/gms/measurement/internal/zzgr:zzg	()V
    //   14: aload_0
    //   15: invokevirtual 345	com/google/android/gms/measurement/internal/zzkn:zzW	()V
    //   18: new 599	java/util/ArrayList
    //   21: dup
    //   22: bipush 9
    //   24: anewarray 21	java/lang/String
    //   27: dup
    //   28: iconst_0
    //   29: ldc_w 798
    //   32: aastore
    //   33: dup
    //   34: iconst_1
    //   35: ldc_w 803
    //   38: aastore
    //   39: dup
    //   40: iconst_2
    //   41: ldc_w 807
    //   44: aastore
    //   45: dup
    //   46: iconst_3
    //   47: ldc 23
    //   49: aastore
    //   50: dup
    //   51: iconst_4
    //   52: ldc 27
    //   54: aastore
    //   55: dup
    //   56: iconst_5
    //   57: ldc 31
    //   59: aastore
    //   60: dup
    //   61: bipush 6
    //   63: ldc 35
    //   65: aastore
    //   66: dup
    //   67: bipush 7
    //   69: ldc 39
    //   71: aastore
    //   72: dup
    //   73: bipush 8
    //   75: ldc 43
    //   77: aastore
    //   78: invokestatic 1264	java/util/Arrays:asList	([Ljava/lang/Object;)Ljava/util/List;
    //   81: invokespecial 1328	java/util/ArrayList:<init>	(Ljava/util/Collection;)V
    //   84: astore 15
    //   86: aconst_null
    //   87: astore 16
    //   89: aload_0
    //   90: invokevirtual 297	com/google/android/gms/measurement/internal/zzam:zzh	()Landroid/database/sqlite/SQLiteDatabase;
    //   93: astore 17
    //   95: iconst_0
    //   96: istore_3
    //   97: aload 17
    //   99: ldc_w 828
    //   102: aload 15
    //   104: iconst_0
    //   105: anewarray 21	java/lang/String
    //   108: invokevirtual 1332	java/util/ArrayList:toArray	([Ljava/lang/Object;)[Ljava/lang/Object;
    //   111: checkcast 1333	[Ljava/lang/String;
    //   114: ldc_w 349
    //   117: iconst_2
    //   118: anewarray 21	java/lang/String
    //   121: dup
    //   122: iconst_0
    //   123: aload_1
    //   124: aastore
    //   125: dup
    //   126: iconst_1
    //   127: aload_2
    //   128: aastore
    //   129: aconst_null
    //   130: aconst_null
    //   131: aconst_null
    //   132: invokevirtual 1181	android/database/sqlite/SQLiteDatabase:query	(Ljava/lang/String;[Ljava/lang/String;Ljava/lang/String;[Ljava/lang/String;Ljava/lang/String;Ljava/lang/String;Ljava/lang/String;)Landroid/database/Cursor;
    //   135: astore 15
    //   137: aload 15
    //   139: invokeinterface 309 1 0
    //   144: istore 4
    //   146: iload 4
    //   148: ifne +12 -> 160
    //   151: aload 15
    //   153: invokeinterface 316 1 0
    //   158: aconst_null
    //   159: areturn
    //   160: aload 15
    //   162: iconst_0
    //   163: invokeinterface 313 2 0
    //   168: lstore 9
    //   170: aload 15
    //   172: iconst_1
    //   173: invokeinterface 313 2 0
    //   178: lstore 11
    //   180: aload 15
    //   182: iconst_2
    //   183: invokeinterface 313 2 0
    //   188: lstore 13
    //   190: aload 15
    //   192: iconst_3
    //   193: invokeinterface 1215 2 0
    //   198: ifeq +9 -> 207
    //   201: lconst_0
    //   202: lstore 5
    //   204: goto +13 -> 217
    //   207: aload 15
    //   209: iconst_3
    //   210: invokeinterface 313 2 0
    //   215: lstore 5
    //   217: aload 15
    //   219: iconst_4
    //   220: invokeinterface 1215 2 0
    //   225: ifeq +9 -> 234
    //   228: aconst_null
    //   229: astore 16
    //   231: goto +16 -> 247
    //   234: aload 15
    //   236: iconst_4
    //   237: invokeinterface 313 2 0
    //   242: invokestatic 699	java/lang/Long:valueOf	(J)Ljava/lang/Long;
    //   245: astore 16
    //   247: aload 15
    //   249: iconst_5
    //   250: invokeinterface 1215 2 0
    //   255: ifeq +9 -> 264
    //   258: aconst_null
    //   259: astore 17
    //   261: goto +16 -> 277
    //   264: aload 15
    //   266: iconst_5
    //   267: invokeinterface 313 2 0
    //   272: invokestatic 699	java/lang/Long:valueOf	(J)Ljava/lang/Long;
    //   275: astore 17
    //   277: aload 15
    //   279: bipush 6
    //   281: invokeinterface 1215 2 0
    //   286: ifeq +9 -> 295
    //   289: aconst_null
    //   290: astore 18
    //   292: goto +17 -> 309
    //   295: aload 15
    //   297: bipush 6
    //   299: invokeinterface 313 2 0
    //   304: invokestatic 699	java/lang/Long:valueOf	(J)Ljava/lang/Long;
    //   307: astore 18
    //   309: aload 15
    //   311: bipush 7
    //   313: invokeinterface 1215 2 0
    //   318: ifne +226 -> 544
    //   321: aload 15
    //   323: bipush 7
    //   325: invokeinterface 313 2 0
    //   330: lconst_1
    //   331: lcmp
    //   332: ifne +5 -> 337
    //   335: iconst_1
    //   336: istore_3
    //   337: iload_3
    //   338: invokestatic 564	java/lang/Boolean:valueOf	(Z)Ljava/lang/Boolean;
    //   341: astore 19
    //   343: goto +3 -> 346
    //   346: aload 15
    //   348: bipush 8
    //   350: invokeinterface 1215 2 0
    //   355: ifeq +9 -> 364
    //   358: lconst_0
    //   359: lstore 7
    //   361: goto +14 -> 375
    //   364: aload 15
    //   366: bipush 8
    //   368: invokeinterface 313 2 0
    //   373: lstore 7
    //   375: aload 15
    //   377: astore 20
    //   379: new 789	com/google/android/gms/measurement/internal/zzas
    //   382: dup
    //   383: aload_1
    //   384: aload_2
    //   385: lload 9
    //   387: lload 11
    //   389: lload 7
    //   391: lload 13
    //   393: lload 5
    //   395: aload 16
    //   397: aload 17
    //   399: aload 18
    //   401: aload 19
    //   403: invokespecial 1336	com/google/android/gms/measurement/internal/zzas:<init>	(Ljava/lang/String;Ljava/lang/String;JJJJJLjava/lang/Long;Ljava/lang/Long;Ljava/lang/Long;Ljava/lang/Boolean;)V
    //   406: astore 16
    //   408: aload 20
    //   410: invokeinterface 1047 1 0
    //   415: ifeq +23 -> 438
    //   418: aload_0
    //   419: getfield 216	com/google/android/gms/measurement/internal/zzgr:zzs	Lcom/google/android/gms/measurement/internal/zzfy;
    //   422: invokevirtual 323	com/google/android/gms/measurement/internal/zzfy:zzay	()Lcom/google/android/gms/measurement/internal/zzeo;
    //   425: invokevirtual 328	com/google/android/gms/measurement/internal/zzeo:zzd	()Lcom/google/android/gms/measurement/internal/zzem;
    //   428: ldc_w 1338
    //   431: aload_1
    //   432: invokestatic 359	com/google/android/gms/measurement/internal/zzeo:zzn	(Ljava/lang/String;)Ljava/lang/Object;
    //   435: invokevirtual 501	com/google/android/gms/measurement/internal/zzem:zzb	(Ljava/lang/String;Ljava/lang/Object;)V
    //   438: aload 20
    //   440: invokeinterface 316 1 0
    //   445: aload 16
    //   447: areturn
    //   448: astore_1
    //   449: goto +9 -> 458
    //   452: astore 16
    //   454: goto +12 -> 466
    //   457: astore_1
    //   458: aload 15
    //   460: astore_2
    //   461: goto +71 -> 532
    //   464: astore 16
    //   466: goto +15 -> 481
    //   469: astore_1
    //   470: aload 16
    //   472: astore_2
    //   473: goto +59 -> 532
    //   476: astore 16
    //   478: aconst_null
    //   479: astore 15
    //   481: aload_0
    //   482: getfield 216	com/google/android/gms/measurement/internal/zzgr:zzs	Lcom/google/android/gms/measurement/internal/zzfy;
    //   485: invokevirtual 323	com/google/android/gms/measurement/internal/zzfy:zzay	()Lcom/google/android/gms/measurement/internal/zzeo;
    //   488: invokevirtual 328	com/google/android/gms/measurement/internal/zzeo:zzd	()Lcom/google/android/gms/measurement/internal/zzem;
    //   491: ldc_w 1340
    //   494: aload_1
    //   495: invokestatic 359	com/google/android/gms/measurement/internal/zzeo:zzn	(Ljava/lang/String;)Ljava/lang/Object;
    //   498: aload_0
    //   499: getfield 216	com/google/android/gms/measurement/internal/zzgr:zzs	Lcom/google/android/gms/measurement/internal/zzfy;
    //   502: invokevirtual 362	com/google/android/gms/measurement/internal/zzfy:zzj	()Lcom/google/android/gms/measurement/internal/zzej;
    //   505: aload_2
    //   506: invokevirtual 863	com/google/android/gms/measurement/internal/zzej:zzd	(Ljava/lang/String;)Ljava/lang/String;
    //   509: aload 16
    //   511: invokevirtual 369	com/google/android/gms/measurement/internal/zzem:zzd	(Ljava/lang/String;Ljava/lang/Object;Ljava/lang/Object;Ljava/lang/Object;)V
    //   514: aload 15
    //   516: ifnull +10 -> 526
    //   519: aload 15
    //   521: invokeinterface 316 1 0
    //   526: aconst_null
    //   527: areturn
    //   528: astore_1
    //   529: aload 15
    //   531: astore_2
    //   532: aload_2
    //   533: ifnull +9 -> 542
    //   536: aload_2
    //   537: invokeinterface 316 1 0
    //   542: aload_1
    //   543: athrow
    //   544: aconst_null
    //   545: astore 19
    //   547: goto -201 -> 346
    // Local variable table:
    //   start	length	slot	name	signature
    //   0	550	0	this	zzam
    //   0	550	1	paramString1	String
    //   0	550	2	paramString2	String
    //   96	242	3	bool1	boolean
    //   144	3	4	bool2	boolean
    //   202	192	5	l1	long
    //   359	31	7	l2	long
    //   168	218	9	l3	long
    //   178	210	11	l4	long
    //   188	204	13	l5	long
    //   84	446	15	localObject1	Object
    //   87	359	16	localObject2	Object
    //   452	1	16	localSQLiteException1	SQLiteException
    //   464	7	16	localSQLiteException2	SQLiteException
    //   476	34	16	localSQLiteException3	SQLiteException
    //   93	305	17	localObject3	Object
    //   290	110	18	localLong	Long
    //   341	205	19	localBoolean	Boolean
    //   377	62	20	localObject4	Object
    // Exception table:
    //   from	to	target	type
    //   379	438	448	finally
    //   379	438	452	android/database/sqlite/SQLiteException
    //   137	146	457	finally
    //   160	201	457	finally
    //   207	217	457	finally
    //   217	228	457	finally
    //   234	247	457	finally
    //   247	258	457	finally
    //   264	277	457	finally
    //   277	289	457	finally
    //   295	309	457	finally
    //   309	321	457	finally
    //   321	335	457	finally
    //   337	343	457	finally
    //   346	358	457	finally
    //   364	375	457	finally
    //   137	146	464	android/database/sqlite/SQLiteException
    //   160	201	464	android/database/sqlite/SQLiteException
    //   207	217	464	android/database/sqlite/SQLiteException
    //   217	228	464	android/database/sqlite/SQLiteException
    //   234	247	464	android/database/sqlite/SQLiteException
    //   247	258	464	android/database/sqlite/SQLiteException
    //   264	277	464	android/database/sqlite/SQLiteException
    //   277	289	464	android/database/sqlite/SQLiteException
    //   295	309	464	android/database/sqlite/SQLiteException
    //   309	321	464	android/database/sqlite/SQLiteException
    //   321	335	464	android/database/sqlite/SQLiteException
    //   337	343	464	android/database/sqlite/SQLiteException
    //   346	358	464	android/database/sqlite/SQLiteException
    //   364	375	464	android/database/sqlite/SQLiteException
    //   89	95	469	finally
    //   97	137	469	finally
    //   89	95	476	android/database/sqlite/SQLiteException
    //   97	137	476	android/database/sqlite/SQLiteException
    //   481	514	528	finally
  }
  
  /* Error */
  public final zzle zzp(String paramString1, String paramString2)
  {
    // Byte code:
    //   0: aload_1
    //   1: invokestatic 263	com/google/android/gms/common/internal/Preconditions:checkNotEmpty	(Ljava/lang/String;)Ljava/lang/String;
    //   4: pop
    //   5: aload_2
    //   6: invokestatic 263	com/google/android/gms/common/internal/Preconditions:checkNotEmpty	(Ljava/lang/String;)Ljava/lang/String;
    //   9: pop
    //   10: aload_0
    //   11: invokevirtual 342	com/google/android/gms/measurement/internal/zzgr:zzg	()V
    //   14: aload_0
    //   15: invokevirtual 345	com/google/android/gms/measurement/internal/zzkn:zzW	()V
    //   18: aconst_null
    //   19: astore 6
    //   21: aload_0
    //   22: invokevirtual 297	com/google/android/gms/measurement/internal/zzam:zzh	()Landroid/database/sqlite/SQLiteDatabase;
    //   25: ldc_w 347
    //   28: iconst_3
    //   29: anewarray 21	java/lang/String
    //   32: dup
    //   33: iconst_0
    //   34: ldc_w 977
    //   37: aastore
    //   38: dup
    //   39: iconst_1
    //   40: ldc_w 257
    //   43: aastore
    //   44: dup
    //   45: iconst_2
    //   46: ldc 49
    //   48: aastore
    //   49: ldc_w 349
    //   52: iconst_2
    //   53: anewarray 21	java/lang/String
    //   56: dup
    //   57: iconst_0
    //   58: aload_1
    //   59: aastore
    //   60: dup
    //   61: iconst_1
    //   62: aload_2
    //   63: aastore
    //   64: aconst_null
    //   65: aconst_null
    //   66: aconst_null
    //   67: invokevirtual 1181	android/database/sqlite/SQLiteDatabase:query	(Ljava/lang/String;[Ljava/lang/String;Ljava/lang/String;[Ljava/lang/String;Ljava/lang/String;Ljava/lang/String;Ljava/lang/String;)Landroid/database/Cursor;
    //   70: astore 7
    //   72: aload 7
    //   74: astore 6
    //   76: aload 7
    //   78: invokeinterface 309 1 0
    //   83: istore_3
    //   84: iload_3
    //   85: ifne +12 -> 97
    //   88: aload 7
    //   90: invokeinterface 316 1 0
    //   95: aconst_null
    //   96: areturn
    //   97: aload 7
    //   99: astore 6
    //   101: aload 7
    //   103: iconst_0
    //   104: invokeinterface 313 2 0
    //   109: lstore 4
    //   111: aload 7
    //   113: astore 6
    //   115: aload_0
    //   116: aload 7
    //   118: iconst_1
    //   119: invokevirtual 1287	com/google/android/gms/measurement/internal/zzam:zzq	(Landroid/database/Cursor;I)Ljava/lang/Object;
    //   122: astore 8
    //   124: aload 8
    //   126: ifnonnull +12 -> 138
    //   129: aload 7
    //   131: invokeinterface 316 1 0
    //   136: aconst_null
    //   137: areturn
    //   138: aload 7
    //   140: astore 6
    //   142: new 953	com/google/android/gms/measurement/internal/zzle
    //   145: dup
    //   146: aload_1
    //   147: aload 7
    //   149: iconst_2
    //   150: invokeinterface 1006 2 0
    //   155: aload_2
    //   156: lload 4
    //   158: aload 8
    //   160: invokespecial 1343	com/google/android/gms/measurement/internal/zzle:<init>	(Ljava/lang/String;Ljava/lang/String;Ljava/lang/String;JLjava/lang/Object;)V
    //   163: astore 8
    //   165: aload 7
    //   167: astore 6
    //   169: aload 7
    //   171: invokeinterface 1047 1 0
    //   176: ifeq +27 -> 203
    //   179: aload 7
    //   181: astore 6
    //   183: aload_0
    //   184: getfield 216	com/google/android/gms/measurement/internal/zzgr:zzs	Lcom/google/android/gms/measurement/internal/zzfy;
    //   187: invokevirtual 323	com/google/android/gms/measurement/internal/zzfy:zzay	()Lcom/google/android/gms/measurement/internal/zzeo;
    //   190: invokevirtual 328	com/google/android/gms/measurement/internal/zzeo:zzd	()Lcom/google/android/gms/measurement/internal/zzem;
    //   193: ldc_w 1345
    //   196: aload_1
    //   197: invokestatic 359	com/google/android/gms/measurement/internal/zzeo:zzn	(Ljava/lang/String;)Ljava/lang/Object;
    //   200: invokevirtual 501	com/google/android/gms/measurement/internal/zzem:zzb	(Ljava/lang/String;Ljava/lang/Object;)V
    //   203: aload 7
    //   205: invokeinterface 316 1 0
    //   210: aload 8
    //   212: areturn
    //   213: astore 8
    //   215: goto +15 -> 230
    //   218: astore_1
    //   219: aload 6
    //   221: astore_2
    //   222: goto +63 -> 285
    //   225: astore 8
    //   227: aconst_null
    //   228: astore 7
    //   230: aload 7
    //   232: astore 6
    //   234: aload_0
    //   235: getfield 216	com/google/android/gms/measurement/internal/zzgr:zzs	Lcom/google/android/gms/measurement/internal/zzfy;
    //   238: invokevirtual 323	com/google/android/gms/measurement/internal/zzfy:zzay	()Lcom/google/android/gms/measurement/internal/zzeo;
    //   241: invokevirtual 328	com/google/android/gms/measurement/internal/zzeo:zzd	()Lcom/google/android/gms/measurement/internal/zzem;
    //   244: ldc_w 1347
    //   247: aload_1
    //   248: invokestatic 359	com/google/android/gms/measurement/internal/zzeo:zzn	(Ljava/lang/String;)Ljava/lang/Object;
    //   251: aload_0
    //   252: getfield 216	com/google/android/gms/measurement/internal/zzgr:zzs	Lcom/google/android/gms/measurement/internal/zzfy;
    //   255: invokevirtual 362	com/google/android/gms/measurement/internal/zzfy:zzj	()Lcom/google/android/gms/measurement/internal/zzej;
    //   258: aload_2
    //   259: invokevirtual 366	com/google/android/gms/measurement/internal/zzej:zzf	(Ljava/lang/String;)Ljava/lang/String;
    //   262: aload 8
    //   264: invokevirtual 369	com/google/android/gms/measurement/internal/zzem:zzd	(Ljava/lang/String;Ljava/lang/Object;Ljava/lang/Object;Ljava/lang/Object;)V
    //   267: aload 7
    //   269: ifnull +10 -> 279
    //   272: aload 7
    //   274: invokeinterface 316 1 0
    //   279: aconst_null
    //   280: areturn
    //   281: astore_1
    //   282: aload 6
    //   284: astore_2
    //   285: aload_2
    //   286: ifnull +9 -> 295
    //   289: aload_2
    //   290: invokeinterface 316 1 0
    //   295: aload_1
    //   296: athrow
    // Local variable table:
    //   start	length	slot	name	signature
    //   0	297	0	this	zzam
    //   0	297	1	paramString1	String
    //   0	297	2	paramString2	String
    //   83	2	3	bool	boolean
    //   109	48	4	l	long
    //   19	264	6	localObject1	Object
    //   70	203	7	localCursor	Cursor
    //   122	89	8	localObject2	Object
    //   213	1	8	localSQLiteException1	SQLiteException
    //   225	38	8	localSQLiteException2	SQLiteException
    // Exception table:
    //   from	to	target	type
    //   76	84	213	android/database/sqlite/SQLiteException
    //   101	111	213	android/database/sqlite/SQLiteException
    //   115	124	213	android/database/sqlite/SQLiteException
    //   142	165	213	android/database/sqlite/SQLiteException
    //   169	179	213	android/database/sqlite/SQLiteException
    //   183	203	213	android/database/sqlite/SQLiteException
    //   21	72	218	finally
    //   21	72	225	android/database/sqlite/SQLiteException
    //   76	84	281	finally
    //   101	111	281	finally
    //   115	124	281	finally
    //   142	165	281	finally
    //   169	179	281	finally
    //   183	203	281	finally
    //   234	267	281	finally
  }
  
  @VisibleForTesting
  final Object zzq(Cursor paramCursor, int paramInt)
  {
    int i = paramCursor.getType(paramInt);
    if (i != 0)
    {
      if (i != 1)
      {
        if (i != 2)
        {
          if (i != 3)
          {
            if (i != 4)
            {
              zzs.zzay().zzd().zzb("Loaded invalid unknown value type, ignoring it", Integer.valueOf(i));
              return null;
            }
            zzs.zzay().zzd().zza("Loaded invalid blob type value, ignoring it");
            return null;
          }
          return paramCursor.getString(paramInt);
        }
        return Double.valueOf(paramCursor.getDouble(paramInt));
      }
      return Long.valueOf(paramCursor.getLong(paramInt));
    }
    zzs.zzay().zzd().zza("Loaded invalid null value from database");
    return null;
  }
  
  /* Error */
  public final String zzr()
  {
    // Byte code:
    //   0: aload_0
    //   1: invokevirtual 297	com/google/android/gms/measurement/internal/zzam:zzh	()Landroid/database/sqlite/SQLiteDatabase;
    //   4: astore_2
    //   5: aconst_null
    //   6: astore_1
    //   7: aload_2
    //   8: ldc_w 1365
    //   11: aconst_null
    //   12: invokevirtual 303	android/database/sqlite/SQLiteDatabase:rawQuery	(Ljava/lang/String;[Ljava/lang/String;)Landroid/database/Cursor;
    //   15: astore_2
    //   16: aload_2
    //   17: astore_1
    //   18: aload_2
    //   19: invokeinterface 309 1 0
    //   24: ifeq +21 -> 45
    //   27: aload_2
    //   28: astore_1
    //   29: aload_2
    //   30: iconst_0
    //   31: invokeinterface 1006 2 0
    //   36: astore_3
    //   37: aload_2
    //   38: invokeinterface 316 1 0
    //   43: aload_3
    //   44: areturn
    //   45: aload_2
    //   46: invokeinterface 316 1 0
    //   51: aconst_null
    //   52: areturn
    //   53: astore_3
    //   54: goto +10 -> 64
    //   57: astore_2
    //   58: goto +38 -> 96
    //   61: astore_3
    //   62: aconst_null
    //   63: astore_2
    //   64: aload_2
    //   65: astore_1
    //   66: aload_0
    //   67: getfield 216	com/google/android/gms/measurement/internal/zzgr:zzs	Lcom/google/android/gms/measurement/internal/zzfy;
    //   70: invokevirtual 323	com/google/android/gms/measurement/internal/zzfy:zzay	()Lcom/google/android/gms/measurement/internal/zzeo;
    //   73: invokevirtual 328	com/google/android/gms/measurement/internal/zzeo:zzd	()Lcom/google/android/gms/measurement/internal/zzem;
    //   76: ldc_w 1367
    //   79: aload_3
    //   80: invokevirtual 501	com/google/android/gms/measurement/internal/zzem:zzb	(Ljava/lang/String;Ljava/lang/Object;)V
    //   83: aload_2
    //   84: ifnull +9 -> 93
    //   87: aload_2
    //   88: invokeinterface 316 1 0
    //   93: aconst_null
    //   94: areturn
    //   95: astore_2
    //   96: aload_1
    //   97: ifnull +9 -> 106
    //   100: aload_1
    //   101: invokeinterface 316 1 0
    //   106: aload_2
    //   107: athrow
    // Local variable table:
    //   start	length	slot	name	signature
    //   0	108	0	this	zzam
    //   6	95	1	localObject1	Object
    //   4	42	2	localObject2	Object
    //   57	1	2	localObject3	Object
    //   63	25	2	localObject4	Object
    //   95	12	2	localObject5	Object
    //   36	8	3	str	String
    //   53	1	3	localSQLiteException1	SQLiteException
    //   61	19	3	localSQLiteException2	SQLiteException
    // Exception table:
    //   from	to	target	type
    //   18	27	53	android/database/sqlite/SQLiteException
    //   29	37	53	android/database/sqlite/SQLiteException
    //   7	16	57	finally
    //   7	16	61	android/database/sqlite/SQLiteException
    //   18	27	95	finally
    //   29	37	95	finally
    //   66	83	95	finally
  }
  
  public final List zzs(String paramString1, String paramString2, String paramString3)
  {
    Preconditions.checkNotEmpty(paramString1);
    zzg();
    zzW();
    ArrayList localArrayList = new ArrayList(3);
    localArrayList.add(paramString1);
    paramString1 = new StringBuilder("app_id=?");
    if (!TextUtils.isEmpty(paramString2))
    {
      localArrayList.add(paramString2);
      paramString1.append(" and origin=?");
    }
    if (!TextUtils.isEmpty(paramString3))
    {
      localArrayList.add(String.valueOf(paramString3).concat("*"));
      paramString1.append(" and name glob ?");
    }
    paramString2 = (String[])localArrayList.toArray(new String[localArrayList.size()]);
    return zzt(paramString1.toString(), paramString2);
  }
  
  /* Error */
  public final List zzt(String paramString, String[] paramArrayOfString)
  {
    // Byte code:
    //   0: aload_0
    //   1: invokevirtual 342	com/google/android/gms/measurement/internal/zzgr:zzg	()V
    //   4: aload_0
    //   5: invokevirtual 345	com/google/android/gms/measurement/internal/zzkn:zzW	()V
    //   8: new 599	java/util/ArrayList
    //   11: dup
    //   12: invokespecial 600	java/util/ArrayList:<init>	()V
    //   15: astore 17
    //   17: aconst_null
    //   18: astore 16
    //   20: aconst_null
    //   21: astore 15
    //   23: aload 15
    //   25: astore 13
    //   27: aload 16
    //   29: astore 14
    //   31: aload_0
    //   32: invokevirtual 297	com/google/android/gms/measurement/internal/zzam:zzh	()Landroid/database/sqlite/SQLiteDatabase;
    //   35: astore 18
    //   37: aload 15
    //   39: astore 13
    //   41: aload 16
    //   43: astore 14
    //   45: aload_0
    //   46: getfield 216	com/google/android/gms/measurement/internal/zzgr:zzs	Lcom/google/android/gms/measurement/internal/zzfy;
    //   49: invokevirtual 231	com/google/android/gms/measurement/internal/zzfy:zzf	()Lcom/google/android/gms/measurement/internal/zzag;
    //   52: pop
    //   53: aload 15
    //   55: astore 13
    //   57: aload 16
    //   59: astore 14
    //   61: aload 18
    //   63: ldc_w 945
    //   66: bipush 13
    //   68: anewarray 21	java/lang/String
    //   71: dup
    //   72: iconst_0
    //   73: ldc_w 545
    //   76: aastore
    //   77: dup
    //   78: iconst_1
    //   79: ldc 49
    //   81: aastore
    //   82: dup
    //   83: iconst_2
    //   84: ldc_w 794
    //   87: aastore
    //   88: dup
    //   89: iconst_3
    //   90: ldc_w 257
    //   93: aastore
    //   94: dup
    //   95: iconst_4
    //   96: ldc_w 900
    //   99: aastore
    //   100: dup
    //   101: iconst_5
    //   102: ldc_w 905
    //   105: aastore
    //   106: dup
    //   107: bipush 6
    //   109: ldc_w 909
    //   112: aastore
    //   113: dup
    //   114: bipush 7
    //   116: ldc_w 913
    //   119: aastore
    //   120: dup
    //   121: bipush 8
    //   123: ldc_w 927
    //   126: aastore
    //   127: dup
    //   128: bipush 9
    //   130: ldc_w 930
    //   133: aastore
    //   134: dup
    //   135: bipush 10
    //   137: ldc_w 934
    //   140: aastore
    //   141: dup
    //   142: bipush 11
    //   144: ldc_w 937
    //   147: aastore
    //   148: dup
    //   149: bipush 12
    //   151: ldc_w 941
    //   154: aastore
    //   155: aload_1
    //   156: aload_2
    //   157: aconst_null
    //   158: aconst_null
    //   159: ldc_w 1020
    //   162: ldc_w 1387
    //   165: invokevirtual 1026	android/database/sqlite/SQLiteDatabase:query	(Ljava/lang/String;[Ljava/lang/String;Ljava/lang/String;[Ljava/lang/String;Ljava/lang/String;Ljava/lang/String;Ljava/lang/String;Ljava/lang/String;)Landroid/database/Cursor;
    //   168: astore_1
    //   169: aload_1
    //   170: astore 13
    //   172: aload_1
    //   173: astore 14
    //   175: aload_1
    //   176: invokeinterface 309 1 0
    //   181: ifeq +457 -> 638
    //   184: aload_1
    //   185: astore 13
    //   187: aload_1
    //   188: astore 14
    //   190: aload 17
    //   192: invokeinterface 379 1 0
    //   197: istore_3
    //   198: aload_1
    //   199: astore 13
    //   201: aload_1
    //   202: astore 14
    //   204: aload_0
    //   205: getfield 216	com/google/android/gms/measurement/internal/zzgr:zzs	Lcom/google/android/gms/measurement/internal/zzfy;
    //   208: invokevirtual 231	com/google/android/gms/measurement/internal/zzfy:zzf	()Lcom/google/android/gms/measurement/internal/zzag;
    //   211: pop
    //   212: iload_3
    //   213: sipush 1000
    //   216: if_icmplt +56 -> 272
    //   219: aload_1
    //   220: astore 13
    //   222: aload_1
    //   223: astore 14
    //   225: aload_0
    //   226: getfield 216	com/google/android/gms/measurement/internal/zzgr:zzs	Lcom/google/android/gms/measurement/internal/zzfy;
    //   229: invokevirtual 323	com/google/android/gms/measurement/internal/zzfy:zzay	()Lcom/google/android/gms/measurement/internal/zzeo;
    //   232: invokevirtual 328	com/google/android/gms/measurement/internal/zzeo:zzd	()Lcom/google/android/gms/measurement/internal/zzem;
    //   235: astore_2
    //   236: aload_1
    //   237: astore 13
    //   239: aload_1
    //   240: astore 14
    //   242: aload_0
    //   243: getfield 216	com/google/android/gms/measurement/internal/zzgr:zzs	Lcom/google/android/gms/measurement/internal/zzfy;
    //   246: invokevirtual 231	com/google/android/gms/measurement/internal/zzfy:zzf	()Lcom/google/android/gms/measurement/internal/zzag;
    //   249: pop
    //   250: aload_1
    //   251: astore 13
    //   253: aload_1
    //   254: astore 14
    //   256: aload_2
    //   257: ldc_w 1389
    //   260: sipush 1000
    //   263: invokestatic 518	java/lang/Integer:valueOf	(I)Ljava/lang/Integer;
    //   266: invokevirtual 501	com/google/android/gms/measurement/internal/zzem:zzb	(Ljava/lang/String;Ljava/lang/Object;)V
    //   269: goto +360 -> 629
    //   272: aload_1
    //   273: astore 13
    //   275: aload_1
    //   276: astore 14
    //   278: aload_1
    //   279: iconst_0
    //   280: invokeinterface 1006 2 0
    //   285: astore_2
    //   286: aload_1
    //   287: astore 13
    //   289: aload_1
    //   290: astore 14
    //   292: aload_1
    //   293: iconst_1
    //   294: invokeinterface 1006 2 0
    //   299: astore 15
    //   301: aload_1
    //   302: astore 13
    //   304: aload_1
    //   305: astore 14
    //   307: aload_1
    //   308: iconst_2
    //   309: invokeinterface 1006 2 0
    //   314: astore 16
    //   316: aload_1
    //   317: astore 13
    //   319: aload_1
    //   320: astore 14
    //   322: aload_0
    //   323: aload_1
    //   324: iconst_3
    //   325: invokevirtual 1287	com/google/android/gms/measurement/internal/zzam:zzq	(Landroid/database/Cursor;I)Ljava/lang/Object;
    //   328: astore 18
    //   330: aload_1
    //   331: astore 13
    //   333: aload_1
    //   334: astore 14
    //   336: aload_1
    //   337: iconst_4
    //   338: invokeinterface 1219 2 0
    //   343: ifeq +366 -> 709
    //   346: iconst_1
    //   347: istore 4
    //   349: goto +3 -> 352
    //   352: aload_1
    //   353: astore 13
    //   355: aload_1
    //   356: astore 14
    //   358: aload_1
    //   359: iconst_5
    //   360: invokeinterface 1006 2 0
    //   365: astore 19
    //   367: aload_1
    //   368: astore 13
    //   370: aload_1
    //   371: astore 14
    //   373: aload_1
    //   374: bipush 6
    //   376: invokeinterface 313 2 0
    //   381: lstore 5
    //   383: aload_1
    //   384: astore 13
    //   386: aload_1
    //   387: astore 14
    //   389: aload_0
    //   390: getfield 1128	com/google/android/gms/measurement/internal/zzkm:zzf	Lcom/google/android/gms/measurement/internal/zzkz;
    //   393: invokevirtual 1133	com/google/android/gms/measurement/internal/zzkz:zzu	()Lcom/google/android/gms/measurement/internal/zzlb;
    //   396: astore 21
    //   398: aload_1
    //   399: astore 13
    //   401: aload_1
    //   402: astore 14
    //   404: aload_1
    //   405: bipush 7
    //   407: invokeinterface 1032 2 0
    //   412: astore 22
    //   414: aload_1
    //   415: astore 13
    //   417: aload_1
    //   418: astore 14
    //   420: getstatic 1293	com/google/android/gms/measurement/internal/zzaw:CREATOR	Landroid/os/Parcelable$Creator;
    //   423: astore 20
    //   425: aload_1
    //   426: astore 13
    //   428: aload_1
    //   429: astore 14
    //   431: aload 21
    //   433: aload 22
    //   435: aload 20
    //   437: invokevirtual 1296	com/google/android/gms/measurement/internal/zzlb:zzh	([BLandroid/os/Parcelable$Creator;)Landroid/os/Parcelable;
    //   440: checkcast 1289	com/google/android/gms/measurement/internal/zzaw
    //   443: astore 21
    //   445: aload_1
    //   446: astore 13
    //   448: aload_1
    //   449: astore 14
    //   451: aload_1
    //   452: bipush 8
    //   454: invokeinterface 313 2 0
    //   459: lstore 7
    //   461: aload_1
    //   462: astore 13
    //   464: aload_1
    //   465: astore 14
    //   467: aload_0
    //   468: getfield 1128	com/google/android/gms/measurement/internal/zzkm:zzf	Lcom/google/android/gms/measurement/internal/zzkz;
    //   471: invokevirtual 1133	com/google/android/gms/measurement/internal/zzkz:zzu	()Lcom/google/android/gms/measurement/internal/zzlb;
    //   474: aload_1
    //   475: bipush 9
    //   477: invokeinterface 1032 2 0
    //   482: aload 20
    //   484: invokevirtual 1296	com/google/android/gms/measurement/internal/zzlb:zzh	([BLandroid/os/Parcelable$Creator;)Landroid/os/Parcelable;
    //   487: checkcast 1289	com/google/android/gms/measurement/internal/zzaw
    //   490: astore 22
    //   492: aload_1
    //   493: astore 13
    //   495: aload_1
    //   496: astore 14
    //   498: aload_1
    //   499: bipush 10
    //   501: invokeinterface 313 2 0
    //   506: lstore 9
    //   508: aload_1
    //   509: astore 13
    //   511: aload_1
    //   512: astore 14
    //   514: aload_1
    //   515: bipush 11
    //   517: invokeinterface 313 2 0
    //   522: lstore 11
    //   524: aload_1
    //   525: astore 13
    //   527: aload_1
    //   528: astore 14
    //   530: aload_0
    //   531: getfield 1128	com/google/android/gms/measurement/internal/zzkm:zzf	Lcom/google/android/gms/measurement/internal/zzkz;
    //   534: invokevirtual 1133	com/google/android/gms/measurement/internal/zzkz:zzu	()Lcom/google/android/gms/measurement/internal/zzlb;
    //   537: aload_1
    //   538: bipush 12
    //   540: invokeinterface 1032 2 0
    //   545: aload 20
    //   547: invokevirtual 1296	com/google/android/gms/measurement/internal/zzlb:zzh	([BLandroid/os/Parcelable$Creator;)Landroid/os/Parcelable;
    //   550: checkcast 1289	com/google/android/gms/measurement/internal/zzaw
    //   553: astore 20
    //   555: aload_1
    //   556: astore 13
    //   558: aload_1
    //   559: astore 14
    //   561: aload 17
    //   563: new 879	com/google/android/gms/measurement/internal/zzac
    //   566: dup
    //   567: aload_2
    //   568: aload 15
    //   570: new 885	com/google/android/gms/measurement/internal/zzlc
    //   573: dup
    //   574: aload 16
    //   576: lload 9
    //   578: aload 18
    //   580: aload 15
    //   582: invokespecial 1299	com/google/android/gms/measurement/internal/zzlc:<init>	(Ljava/lang/String;JLjava/lang/Object;Ljava/lang/String;)V
    //   585: lload 7
    //   587: iload 4
    //   589: aload 19
    //   591: aload 21
    //   593: lload 5
    //   595: aload 22
    //   597: lload 11
    //   599: aload 20
    //   601: invokespecial 1302	com/google/android/gms/measurement/internal/zzac:<init>	(Ljava/lang/String;Ljava/lang/String;Lcom/google/android/gms/measurement/internal/zzlc;JZLjava/lang/String;Lcom/google/android/gms/measurement/internal/zzaw;JLcom/google/android/gms/measurement/internal/zzaw;JLcom/google/android/gms/measurement/internal/zzaw;)V
    //   604: invokeinterface 604 2 0
    //   609: pop
    //   610: aload_1
    //   611: astore 13
    //   613: aload_1
    //   614: astore 14
    //   616: aload_1
    //   617: invokeinterface 1047 1 0
    //   622: istore 4
    //   624: iload 4
    //   626: ifne -442 -> 184
    //   629: aload_1
    //   630: invokeinterface 316 1 0
    //   635: aload 17
    //   637: areturn
    //   638: aload_1
    //   639: invokeinterface 316 1 0
    //   644: aload 17
    //   646: areturn
    //   647: astore_1
    //   648: goto +47 -> 695
    //   651: astore_1
    //   652: aload 14
    //   654: astore 13
    //   656: aload_0
    //   657: getfield 216	com/google/android/gms/measurement/internal/zzgr:zzs	Lcom/google/android/gms/measurement/internal/zzfy;
    //   660: invokevirtual 323	com/google/android/gms/measurement/internal/zzfy:zzay	()Lcom/google/android/gms/measurement/internal/zzeo;
    //   663: invokevirtual 328	com/google/android/gms/measurement/internal/zzeo:zzd	()Lcom/google/android/gms/measurement/internal/zzem;
    //   666: ldc_w 1391
    //   669: aload_1
    //   670: invokevirtual 501	com/google/android/gms/measurement/internal/zzem:zzb	(Ljava/lang/String;Ljava/lang/Object;)V
    //   673: aload 14
    //   675: astore 13
    //   677: invokestatic 1396	java/util/Collections:emptyList	()Ljava/util/List;
    //   680: astore_1
    //   681: aload 14
    //   683: ifnull +10 -> 693
    //   686: aload 14
    //   688: invokeinterface 316 1 0
    //   693: aload_1
    //   694: areturn
    //   695: aload 13
    //   697: ifnull +10 -> 707
    //   700: aload 13
    //   702: invokeinterface 316 1 0
    //   707: aload_1
    //   708: athrow
    //   709: iconst_0
    //   710: istore 4
    //   712: goto -360 -> 352
    // Local variable table:
    //   start	length	slot	name	signature
    //   0	715	0	this	zzam
    //   0	715	1	paramString	String
    //   0	715	2	paramArrayOfString	String[]
    //   197	20	3	i	int
    //   347	364	4	bool	boolean
    //   381	213	5	l1	long
    //   459	127	7	l2	long
    //   506	71	9	l3	long
    //   522	76	11	l4	long
    //   25	676	13	localObject1	Object
    //   29	658	14	str1	String
    //   21	560	15	str2	String
    //   18	557	16	str3	String
    //   15	630	17	localArrayList	ArrayList
    //   35	544	18	localObject2	Object
    //   365	225	19	str4	String
    //   423	177	20	localObject3	Object
    //   396	196	21	localObject4	Object
    //   412	184	22	localObject5	Object
    // Exception table:
    //   from	to	target	type
    //   31	37	647	finally
    //   45	53	647	finally
    //   61	169	647	finally
    //   175	184	647	finally
    //   190	198	647	finally
    //   204	212	647	finally
    //   225	236	647	finally
    //   242	250	647	finally
    //   256	269	647	finally
    //   278	286	647	finally
    //   292	301	647	finally
    //   307	316	647	finally
    //   322	330	647	finally
    //   336	346	647	finally
    //   358	367	647	finally
    //   373	383	647	finally
    //   389	398	647	finally
    //   404	414	647	finally
    //   420	425	647	finally
    //   431	445	647	finally
    //   451	461	647	finally
    //   467	492	647	finally
    //   498	508	647	finally
    //   514	524	647	finally
    //   530	555	647	finally
    //   561	610	647	finally
    //   616	624	647	finally
    //   656	673	647	finally
    //   677	681	647	finally
    //   31	37	651	android/database/sqlite/SQLiteException
    //   45	53	651	android/database/sqlite/SQLiteException
    //   61	169	651	android/database/sqlite/SQLiteException
    //   175	184	651	android/database/sqlite/SQLiteException
    //   190	198	651	android/database/sqlite/SQLiteException
    //   204	212	651	android/database/sqlite/SQLiteException
    //   225	236	651	android/database/sqlite/SQLiteException
    //   242	250	651	android/database/sqlite/SQLiteException
    //   256	269	651	android/database/sqlite/SQLiteException
    //   278	286	651	android/database/sqlite/SQLiteException
    //   292	301	651	android/database/sqlite/SQLiteException
    //   307	316	651	android/database/sqlite/SQLiteException
    //   322	330	651	android/database/sqlite/SQLiteException
    //   336	346	651	android/database/sqlite/SQLiteException
    //   358	367	651	android/database/sqlite/SQLiteException
    //   373	383	651	android/database/sqlite/SQLiteException
    //   389	398	651	android/database/sqlite/SQLiteException
    //   404	414	651	android/database/sqlite/SQLiteException
    //   420	425	651	android/database/sqlite/SQLiteException
    //   431	445	651	android/database/sqlite/SQLiteException
    //   451	461	651	android/database/sqlite/SQLiteException
    //   467	492	651	android/database/sqlite/SQLiteException
    //   498	508	651	android/database/sqlite/SQLiteException
    //   514	524	651	android/database/sqlite/SQLiteException
    //   530	555	651	android/database/sqlite/SQLiteException
    //   561	610	651	android/database/sqlite/SQLiteException
    //   616	624	651	android/database/sqlite/SQLiteException
  }
  
  /* Error */
  public final List zzu(String paramString)
  {
    // Byte code:
    //   0: aload_1
    //   1: invokestatic 263	com/google/android/gms/common/internal/Preconditions:checkNotEmpty	(Ljava/lang/String;)Ljava/lang/String;
    //   4: pop
    //   5: aload_0
    //   6: invokevirtual 342	com/google/android/gms/measurement/internal/zzgr:zzg	()V
    //   9: aload_0
    //   10: invokevirtual 345	com/google/android/gms/measurement/internal/zzkn:zzW	()V
    //   13: new 599	java/util/ArrayList
    //   16: dup
    //   17: invokespecial 600	java/util/ArrayList:<init>	()V
    //   20: astore 10
    //   22: aconst_null
    //   23: astore 8
    //   25: aconst_null
    //   26: astore 7
    //   28: aload 7
    //   30: astore 5
    //   32: aload 8
    //   34: astore 6
    //   36: aload_0
    //   37: invokevirtual 297	com/google/android/gms/measurement/internal/zzam:zzh	()Landroid/database/sqlite/SQLiteDatabase;
    //   40: astore 9
    //   42: aload 7
    //   44: astore 5
    //   46: aload 8
    //   48: astore 6
    //   50: aload_0
    //   51: getfield 216	com/google/android/gms/measurement/internal/zzgr:zzs	Lcom/google/android/gms/measurement/internal/zzfy;
    //   54: invokevirtual 231	com/google/android/gms/measurement/internal/zzfy:zzf	()Lcom/google/android/gms/measurement/internal/zzag;
    //   57: pop
    //   58: aload 7
    //   60: astore 5
    //   62: aload 8
    //   64: astore 6
    //   66: aload 9
    //   68: ldc_w 347
    //   71: iconst_4
    //   72: anewarray 21	java/lang/String
    //   75: dup
    //   76: iconst_0
    //   77: ldc_w 794
    //   80: aastore
    //   81: dup
    //   82: iconst_1
    //   83: ldc 49
    //   85: aastore
    //   86: dup
    //   87: iconst_2
    //   88: ldc_w 977
    //   91: aastore
    //   92: dup
    //   93: iconst_3
    //   94: ldc_w 257
    //   97: aastore
    //   98: ldc_w 477
    //   101: iconst_1
    //   102: anewarray 21	java/lang/String
    //   105: dup
    //   106: iconst_0
    //   107: aload_1
    //   108: aastore
    //   109: aconst_null
    //   110: aconst_null
    //   111: ldc_w 1020
    //   114: ldc_w 1399
    //   117: invokevirtual 1026	android/database/sqlite/SQLiteDatabase:query	(Ljava/lang/String;[Ljava/lang/String;Ljava/lang/String;[Ljava/lang/String;Ljava/lang/String;Ljava/lang/String;Ljava/lang/String;Ljava/lang/String;)Landroid/database/Cursor;
    //   120: astore 7
    //   122: aload 7
    //   124: astore 5
    //   126: aload 7
    //   128: astore 6
    //   130: aload 7
    //   132: invokeinterface 309 1 0
    //   137: ifeq +186 -> 323
    //   140: aload 7
    //   142: astore 5
    //   144: aload 7
    //   146: astore 6
    //   148: aload 7
    //   150: iconst_0
    //   151: invokeinterface 1006 2 0
    //   156: astore 11
    //   158: aload 7
    //   160: astore 5
    //   162: aload 7
    //   164: astore 6
    //   166: aload 7
    //   168: iconst_1
    //   169: invokeinterface 1006 2 0
    //   174: astore 9
    //   176: aload 9
    //   178: astore 8
    //   180: aload 9
    //   182: ifnonnull +8 -> 190
    //   185: ldc_w 994
    //   188: astore 8
    //   190: aload 7
    //   192: astore 5
    //   194: aload 7
    //   196: astore 6
    //   198: aload 7
    //   200: iconst_2
    //   201: invokeinterface 313 2 0
    //   206: lstore_2
    //   207: aload 7
    //   209: astore 5
    //   211: aload 7
    //   213: astore 6
    //   215: aload_0
    //   216: aload 7
    //   218: iconst_3
    //   219: invokevirtual 1287	com/google/android/gms/measurement/internal/zzam:zzq	(Landroid/database/Cursor;I)Ljava/lang/Object;
    //   222: astore 9
    //   224: aload 9
    //   226: ifnonnull +34 -> 260
    //   229: aload 7
    //   231: astore 5
    //   233: aload 7
    //   235: astore 6
    //   237: aload_0
    //   238: getfield 216	com/google/android/gms/measurement/internal/zzgr:zzs	Lcom/google/android/gms/measurement/internal/zzfy;
    //   241: invokevirtual 323	com/google/android/gms/measurement/internal/zzfy:zzay	()Lcom/google/android/gms/measurement/internal/zzeo;
    //   244: invokevirtual 328	com/google/android/gms/measurement/internal/zzeo:zzd	()Lcom/google/android/gms/measurement/internal/zzem;
    //   247: ldc_w 1401
    //   250: aload_1
    //   251: invokestatic 359	com/google/android/gms/measurement/internal/zzeo:zzn	(Ljava/lang/String;)Ljava/lang/Object;
    //   254: invokevirtual 501	com/google/android/gms/measurement/internal/zzem:zzb	(Ljava/lang/String;Ljava/lang/Object;)V
    //   257: goto +34 -> 291
    //   260: aload 7
    //   262: astore 5
    //   264: aload 7
    //   266: astore 6
    //   268: aload 10
    //   270: new 953	com/google/android/gms/measurement/internal/zzle
    //   273: dup
    //   274: aload_1
    //   275: aload 8
    //   277: aload 11
    //   279: lload_2
    //   280: aload 9
    //   282: invokespecial 1343	com/google/android/gms/measurement/internal/zzle:<init>	(Ljava/lang/String;Ljava/lang/String;Ljava/lang/String;JLjava/lang/Object;)V
    //   285: invokeinterface 604 2 0
    //   290: pop
    //   291: aload 7
    //   293: astore 5
    //   295: aload 7
    //   297: astore 6
    //   299: aload 7
    //   301: invokeinterface 1047 1 0
    //   306: istore 4
    //   308: iload 4
    //   310: ifne -170 -> 140
    //   313: aload 7
    //   315: invokeinterface 316 1 0
    //   320: aload 10
    //   322: areturn
    //   323: aload 7
    //   325: invokeinterface 316 1 0
    //   330: aload 10
    //   332: areturn
    //   333: astore_1
    //   334: goto +53 -> 387
    //   337: astore 7
    //   339: aload 6
    //   341: astore 5
    //   343: aload_0
    //   344: getfield 216	com/google/android/gms/measurement/internal/zzgr:zzs	Lcom/google/android/gms/measurement/internal/zzfy;
    //   347: invokevirtual 323	com/google/android/gms/measurement/internal/zzfy:zzay	()Lcom/google/android/gms/measurement/internal/zzeo;
    //   350: invokevirtual 328	com/google/android/gms/measurement/internal/zzeo:zzd	()Lcom/google/android/gms/measurement/internal/zzem;
    //   353: ldc_w 1403
    //   356: aload_1
    //   357: invokestatic 359	com/google/android/gms/measurement/internal/zzeo:zzn	(Ljava/lang/String;)Ljava/lang/Object;
    //   360: aload 7
    //   362: invokevirtual 335	com/google/android/gms/measurement/internal/zzem:zzc	(Ljava/lang/String;Ljava/lang/Object;Ljava/lang/Object;)V
    //   365: aload 6
    //   367: astore 5
    //   369: invokestatic 1396	java/util/Collections:emptyList	()Ljava/util/List;
    //   372: astore_1
    //   373: aload 6
    //   375: ifnull +10 -> 385
    //   378: aload 6
    //   380: invokeinterface 316 1 0
    //   385: aload_1
    //   386: areturn
    //   387: aload 5
    //   389: ifnull +10 -> 399
    //   392: aload 5
    //   394: invokeinterface 316 1 0
    //   399: aload_1
    //   400: athrow
    // Local variable table:
    //   start	length	slot	name	signature
    //   0	401	0	this	zzam
    //   0	401	1	paramString	String
    //   206	74	2	l	long
    //   306	3	4	bool	boolean
    //   30	363	5	localObject1	Object
    //   34	345	6	localObject2	Object
    //   26	298	7	localCursor	Cursor
    //   337	24	7	localSQLiteException	SQLiteException
    //   23	253	8	localObject3	Object
    //   40	241	9	localObject4	Object
    //   20	311	10	localArrayList	ArrayList
    //   156	122	11	str	String
    // Exception table:
    //   from	to	target	type
    //   36	42	333	finally
    //   50	58	333	finally
    //   66	122	333	finally
    //   130	140	333	finally
    //   148	158	333	finally
    //   166	176	333	finally
    //   198	207	333	finally
    //   215	224	333	finally
    //   237	257	333	finally
    //   268	291	333	finally
    //   299	308	333	finally
    //   343	365	333	finally
    //   369	373	333	finally
    //   36	42	337	android/database/sqlite/SQLiteException
    //   50	58	337	android/database/sqlite/SQLiteException
    //   66	122	337	android/database/sqlite/SQLiteException
    //   130	140	337	android/database/sqlite/SQLiteException
    //   148	158	337	android/database/sqlite/SQLiteException
    //   166	176	337	android/database/sqlite/SQLiteException
    //   198	207	337	android/database/sqlite/SQLiteException
    //   215	224	337	android/database/sqlite/SQLiteException
    //   237	257	337	android/database/sqlite/SQLiteException
    //   268	291	337	android/database/sqlite/SQLiteException
    //   299	308	337	android/database/sqlite/SQLiteException
  }
  
  /* Error */
  public final List zzv(String paramString1, String paramString2, String paramString3)
  {
    // Byte code:
    //   0: aload_1
    //   1: invokestatic 263	com/google/android/gms/common/internal/Preconditions:checkNotEmpty	(Ljava/lang/String;)Ljava/lang/String;
    //   4: pop
    //   5: aload_0
    //   6: invokevirtual 342	com/google/android/gms/measurement/internal/zzgr:zzg	()V
    //   9: aload_0
    //   10: invokevirtual 345	com/google/android/gms/measurement/internal/zzkn:zzW	()V
    //   13: new 599	java/util/ArrayList
    //   16: dup
    //   17: invokespecial 600	java/util/ArrayList:<init>	()V
    //   20: astore 14
    //   22: aconst_null
    //   23: astore 13
    //   25: aconst_null
    //   26: astore 10
    //   28: aconst_null
    //   29: astore 12
    //   31: aload 13
    //   33: astore 9
    //   35: new 599	java/util/ArrayList
    //   38: dup
    //   39: iconst_3
    //   40: invokespecial 1371	java/util/ArrayList:<init>	(I)V
    //   43: astore 16
    //   45: aload 13
    //   47: astore 9
    //   49: aload 16
    //   51: aload_1
    //   52: invokeinterface 604 2 0
    //   57: pop
    //   58: aload 13
    //   60: astore 9
    //   62: new 644	java/lang/StringBuilder
    //   65: dup
    //   66: ldc_w 477
    //   69: invokespecial 1372	java/lang/StringBuilder:<init>	(Ljava/lang/String;)V
    //   72: astore 15
    //   74: aload 13
    //   76: astore 9
    //   78: aload_2
    //   79: invokestatic 992	android/text/TextUtils:isEmpty	(Ljava/lang/CharSequence;)Z
    //   82: istore 5
    //   84: iload 5
    //   86: ifne +743 -> 829
    //   89: aload_2
    //   90: astore 11
    //   92: aload 12
    //   94: astore 10
    //   96: aload 11
    //   98: astore 8
    //   100: aload 13
    //   102: astore 9
    //   104: aload 16
    //   106: aload 11
    //   108: invokeinterface 604 2 0
    //   113: pop
    //   114: aload 12
    //   116: astore 10
    //   118: aload 11
    //   120: astore 8
    //   122: aload 13
    //   124: astore 9
    //   126: aload 15
    //   128: ldc_w 1374
    //   131: invokevirtual 651	java/lang/StringBuilder:append	(Ljava/lang/String;)Ljava/lang/StringBuilder;
    //   134: pop
    //   135: goto +3 -> 138
    //   138: aload 12
    //   140: astore 10
    //   142: aload_2
    //   143: astore 8
    //   145: aload 13
    //   147: astore 9
    //   149: aload_3
    //   150: invokestatic 992	android/text/TextUtils:isEmpty	(Ljava/lang/CharSequence;)Z
    //   153: ifne +105 -> 258
    //   156: aload 12
    //   158: astore 10
    //   160: aload_2
    //   161: astore 8
    //   163: aload 13
    //   165: astore 9
    //   167: new 644	java/lang/StringBuilder
    //   170: dup
    //   171: invokespecial 645	java/lang/StringBuilder:<init>	()V
    //   174: astore 11
    //   176: aload 12
    //   178: astore 10
    //   180: aload_2
    //   181: astore 8
    //   183: aload 13
    //   185: astore 9
    //   187: aload 11
    //   189: aload_3
    //   190: invokevirtual 651	java/lang/StringBuilder:append	(Ljava/lang/String;)Ljava/lang/StringBuilder;
    //   193: pop
    //   194: aload 12
    //   196: astore 10
    //   198: aload_2
    //   199: astore 8
    //   201: aload 13
    //   203: astore 9
    //   205: aload 11
    //   207: ldc_w 1376
    //   210: invokevirtual 651	java/lang/StringBuilder:append	(Ljava/lang/String;)Ljava/lang/StringBuilder;
    //   213: pop
    //   214: aload 12
    //   216: astore 10
    //   218: aload_2
    //   219: astore 8
    //   221: aload 13
    //   223: astore 9
    //   225: aload 16
    //   227: aload 11
    //   229: invokevirtual 657	java/lang/StringBuilder:toString	()Ljava/lang/String;
    //   232: invokeinterface 604 2 0
    //   237: pop
    //   238: aload 12
    //   240: astore 10
    //   242: aload_2
    //   243: astore 8
    //   245: aload 13
    //   247: astore 9
    //   249: aload 15
    //   251: ldc_w 1381
    //   254: invokevirtual 651	java/lang/StringBuilder:append	(Ljava/lang/String;)Ljava/lang/StringBuilder;
    //   257: pop
    //   258: aload 12
    //   260: astore 10
    //   262: aload_2
    //   263: astore 8
    //   265: aload 13
    //   267: astore 9
    //   269: aload 16
    //   271: aload 16
    //   273: invokeinterface 379 1 0
    //   278: anewarray 21	java/lang/String
    //   281: invokeinterface 1382 2 0
    //   286: checkcast 1333	[Ljava/lang/String;
    //   289: astore 11
    //   291: aload 12
    //   293: astore 10
    //   295: aload_2
    //   296: astore 8
    //   298: aload 13
    //   300: astore 9
    //   302: aload_0
    //   303: invokevirtual 297	com/google/android/gms/measurement/internal/zzam:zzh	()Landroid/database/sqlite/SQLiteDatabase;
    //   306: astore 16
    //   308: aload 12
    //   310: astore 10
    //   312: aload_2
    //   313: astore 8
    //   315: aload 13
    //   317: astore 9
    //   319: aload 15
    //   321: invokevirtual 657	java/lang/StringBuilder:toString	()Ljava/lang/String;
    //   324: astore 15
    //   326: aload 12
    //   328: astore 10
    //   330: aload_2
    //   331: astore 8
    //   333: aload 13
    //   335: astore 9
    //   337: aload_0
    //   338: getfield 216	com/google/android/gms/measurement/internal/zzgr:zzs	Lcom/google/android/gms/measurement/internal/zzfy;
    //   341: invokevirtual 231	com/google/android/gms/measurement/internal/zzfy:zzf	()Lcom/google/android/gms/measurement/internal/zzag;
    //   344: pop
    //   345: aload 12
    //   347: astore 10
    //   349: aload_2
    //   350: astore 8
    //   352: aload 13
    //   354: astore 9
    //   356: aload 16
    //   358: ldc_w 347
    //   361: iconst_4
    //   362: anewarray 21	java/lang/String
    //   365: dup
    //   366: iconst_0
    //   367: ldc_w 794
    //   370: aastore
    //   371: dup
    //   372: iconst_1
    //   373: ldc_w 977
    //   376: aastore
    //   377: dup
    //   378: iconst_2
    //   379: ldc_w 257
    //   382: aastore
    //   383: dup
    //   384: iconst_3
    //   385: ldc 49
    //   387: aastore
    //   388: aload 15
    //   390: aload 11
    //   392: aconst_null
    //   393: aconst_null
    //   394: ldc_w 1020
    //   397: ldc_w 1387
    //   400: invokevirtual 1026	android/database/sqlite/SQLiteDatabase:query	(Ljava/lang/String;[Ljava/lang/String;Ljava/lang/String;[Ljava/lang/String;Ljava/lang/String;Ljava/lang/String;Ljava/lang/String;Ljava/lang/String;)Landroid/database/Cursor;
    //   403: astore 11
    //   405: aload 11
    //   407: astore 10
    //   409: aload_2
    //   410: astore 8
    //   412: aload 11
    //   414: astore 9
    //   416: aload 11
    //   418: invokeinterface 309 1 0
    //   423: istore 5
    //   425: iload 5
    //   427: ifne +13 -> 440
    //   430: aload 11
    //   432: invokeinterface 316 1 0
    //   437: aload 14
    //   439: areturn
    //   440: aload 11
    //   442: astore 10
    //   444: aload_2
    //   445: astore 8
    //   447: aload 11
    //   449: astore 9
    //   451: aload 14
    //   453: invokeinterface 379 1 0
    //   458: istore 4
    //   460: aload 11
    //   462: astore 10
    //   464: aload_2
    //   465: astore 8
    //   467: aload 11
    //   469: astore 9
    //   471: aload_0
    //   472: getfield 216	com/google/android/gms/measurement/internal/zzgr:zzs	Lcom/google/android/gms/measurement/internal/zzfy;
    //   475: invokevirtual 231	com/google/android/gms/measurement/internal/zzfy:zzf	()Lcom/google/android/gms/measurement/internal/zzag;
    //   478: pop
    //   479: iload 4
    //   481: sipush 1000
    //   484: if_icmplt +71 -> 555
    //   487: aload 11
    //   489: astore 10
    //   491: aload_2
    //   492: astore 8
    //   494: aload 11
    //   496: astore 9
    //   498: aload_0
    //   499: getfield 216	com/google/android/gms/measurement/internal/zzgr:zzs	Lcom/google/android/gms/measurement/internal/zzfy;
    //   502: invokevirtual 323	com/google/android/gms/measurement/internal/zzfy:zzay	()Lcom/google/android/gms/measurement/internal/zzeo;
    //   505: invokevirtual 328	com/google/android/gms/measurement/internal/zzeo:zzd	()Lcom/google/android/gms/measurement/internal/zzem;
    //   508: astore_3
    //   509: aload 11
    //   511: astore 10
    //   513: aload_2
    //   514: astore 8
    //   516: aload 11
    //   518: astore 9
    //   520: aload_0
    //   521: getfield 216	com/google/android/gms/measurement/internal/zzgr:zzs	Lcom/google/android/gms/measurement/internal/zzfy;
    //   524: invokevirtual 231	com/google/android/gms/measurement/internal/zzfy:zzf	()Lcom/google/android/gms/measurement/internal/zzag;
    //   527: pop
    //   528: aload 11
    //   530: astore 10
    //   532: aload_2
    //   533: astore 8
    //   535: aload 11
    //   537: astore 9
    //   539: aload_3
    //   540: ldc_w 1405
    //   543: sipush 1000
    //   546: invokestatic 518	java/lang/Integer:valueOf	(I)Ljava/lang/Integer;
    //   549: invokevirtual 501	com/google/android/gms/measurement/internal/zzem:zzb	(Ljava/lang/String;Ljava/lang/Object;)V
    //   552: goto +188 -> 740
    //   555: aload 11
    //   557: astore 10
    //   559: aload_2
    //   560: astore 8
    //   562: aload 11
    //   564: astore 9
    //   566: aload 11
    //   568: iconst_0
    //   569: invokeinterface 1006 2 0
    //   574: astore 12
    //   576: aload 11
    //   578: astore 10
    //   580: aload_2
    //   581: astore 8
    //   583: aload 11
    //   585: astore 9
    //   587: aload 11
    //   589: iconst_1
    //   590: invokeinterface 313 2 0
    //   595: lstore 6
    //   597: aload 11
    //   599: astore 10
    //   601: aload_2
    //   602: astore 8
    //   604: aload 11
    //   606: astore 9
    //   608: aload_0
    //   609: aload 11
    //   611: iconst_2
    //   612: invokevirtual 1287	com/google/android/gms/measurement/internal/zzam:zzq	(Landroid/database/Cursor;I)Ljava/lang/Object;
    //   615: astore 13
    //   617: aload 11
    //   619: astore 10
    //   621: aload_2
    //   622: astore 8
    //   624: aload 11
    //   626: astore 9
    //   628: aload 11
    //   630: iconst_3
    //   631: invokeinterface 1006 2 0
    //   636: astore_2
    //   637: aload 13
    //   639: ifnonnull +39 -> 678
    //   642: aload 11
    //   644: astore 10
    //   646: aload_2
    //   647: astore 8
    //   649: aload 11
    //   651: astore 9
    //   653: aload_0
    //   654: getfield 216	com/google/android/gms/measurement/internal/zzgr:zzs	Lcom/google/android/gms/measurement/internal/zzfy;
    //   657: invokevirtual 323	com/google/android/gms/measurement/internal/zzfy:zzay	()Lcom/google/android/gms/measurement/internal/zzeo;
    //   660: invokevirtual 328	com/google/android/gms/measurement/internal/zzeo:zzd	()Lcom/google/android/gms/measurement/internal/zzem;
    //   663: ldc_w 1407
    //   666: aload_1
    //   667: invokestatic 359	com/google/android/gms/measurement/internal/zzeo:zzn	(Ljava/lang/String;)Ljava/lang/Object;
    //   670: aload_2
    //   671: aload_3
    //   672: invokevirtual 369	com/google/android/gms/measurement/internal/zzem:zzd	(Ljava/lang/String;Ljava/lang/Object;Ljava/lang/Object;Ljava/lang/Object;)V
    //   675: goto +37 -> 712
    //   678: aload 11
    //   680: astore 10
    //   682: aload_2
    //   683: astore 8
    //   685: aload 11
    //   687: astore 9
    //   689: aload 14
    //   691: new 953	com/google/android/gms/measurement/internal/zzle
    //   694: dup
    //   695: aload_1
    //   696: aload_2
    //   697: aload 12
    //   699: lload 6
    //   701: aload 13
    //   703: invokespecial 1343	com/google/android/gms/measurement/internal/zzle:<init>	(Ljava/lang/String;Ljava/lang/String;Ljava/lang/String;JLjava/lang/Object;)V
    //   706: invokeinterface 604 2 0
    //   711: pop
    //   712: aload 11
    //   714: astore 10
    //   716: aload_2
    //   717: astore 8
    //   719: aload 11
    //   721: astore 9
    //   723: aload 11
    //   725: invokeinterface 1047 1 0
    //   730: istore 5
    //   732: iload 5
    //   734: ifeq +6 -> 740
    //   737: goto -297 -> 440
    //   740: aload 11
    //   742: invokeinterface 316 1 0
    //   747: aload 14
    //   749: areturn
    //   750: astore_3
    //   751: goto +15 -> 766
    //   754: astore_1
    //   755: goto +60 -> 815
    //   758: astore_3
    //   759: goto +4 -> 763
    //   762: astore_3
    //   763: aload_2
    //   764: astore 8
    //   766: aload 10
    //   768: astore 9
    //   770: aload_0
    //   771: getfield 216	com/google/android/gms/measurement/internal/zzgr:zzs	Lcom/google/android/gms/measurement/internal/zzfy;
    //   774: invokevirtual 323	com/google/android/gms/measurement/internal/zzfy:zzay	()Lcom/google/android/gms/measurement/internal/zzeo;
    //   777: invokevirtual 328	com/google/android/gms/measurement/internal/zzeo:zzd	()Lcom/google/android/gms/measurement/internal/zzem;
    //   780: ldc_w 1409
    //   783: aload_1
    //   784: invokestatic 359	com/google/android/gms/measurement/internal/zzeo:zzn	(Ljava/lang/String;)Ljava/lang/Object;
    //   787: aload 8
    //   789: aload_3
    //   790: invokevirtual 369	com/google/android/gms/measurement/internal/zzem:zzd	(Ljava/lang/String;Ljava/lang/Object;Ljava/lang/Object;Ljava/lang/Object;)V
    //   793: aload 10
    //   795: astore 9
    //   797: invokestatic 1396	java/util/Collections:emptyList	()Ljava/util/List;
    //   800: astore_1
    //   801: aload 10
    //   803: ifnull +10 -> 813
    //   806: aload 10
    //   808: invokeinterface 316 1 0
    //   813: aload_1
    //   814: areturn
    //   815: aload 9
    //   817: ifnull +10 -> 827
    //   820: aload 9
    //   822: invokeinterface 316 1 0
    //   827: aload_1
    //   828: athrow
    //   829: goto -691 -> 138
    // Local variable table:
    //   start	length	slot	name	signature
    //   0	832	0	this	zzam
    //   0	832	1	paramString1	String
    //   0	832	2	paramString2	String
    //   0	832	3	paramString3	String
    //   458	27	4	i	int
    //   82	651	5	bool	boolean
    //   595	105	6	l	long
    //   98	690	8	localObject1	Object
    //   33	788	9	localObject2	Object
    //   26	781	10	localObject3	Object
    //   90	651	11	localObject4	Object
    //   29	669	12	str	String
    //   23	679	13	localObject5	Object
    //   20	728	14	localArrayList	ArrayList
    //   72	317	15	localObject6	Object
    //   43	314	16	localObject7	Object
    // Exception table:
    //   from	to	target	type
    //   104	114	750	android/database/sqlite/SQLiteException
    //   126	135	750	android/database/sqlite/SQLiteException
    //   149	156	750	android/database/sqlite/SQLiteException
    //   167	176	750	android/database/sqlite/SQLiteException
    //   187	194	750	android/database/sqlite/SQLiteException
    //   205	214	750	android/database/sqlite/SQLiteException
    //   225	238	750	android/database/sqlite/SQLiteException
    //   249	258	750	android/database/sqlite/SQLiteException
    //   269	291	750	android/database/sqlite/SQLiteException
    //   302	308	750	android/database/sqlite/SQLiteException
    //   319	326	750	android/database/sqlite/SQLiteException
    //   337	345	750	android/database/sqlite/SQLiteException
    //   356	405	750	android/database/sqlite/SQLiteException
    //   416	425	750	android/database/sqlite/SQLiteException
    //   451	460	750	android/database/sqlite/SQLiteException
    //   471	479	750	android/database/sqlite/SQLiteException
    //   498	509	750	android/database/sqlite/SQLiteException
    //   520	528	750	android/database/sqlite/SQLiteException
    //   539	552	750	android/database/sqlite/SQLiteException
    //   566	576	750	android/database/sqlite/SQLiteException
    //   587	597	750	android/database/sqlite/SQLiteException
    //   608	617	750	android/database/sqlite/SQLiteException
    //   628	637	750	android/database/sqlite/SQLiteException
    //   653	675	750	android/database/sqlite/SQLiteException
    //   689	712	750	android/database/sqlite/SQLiteException
    //   723	732	750	android/database/sqlite/SQLiteException
    //   35	45	754	finally
    //   49	58	754	finally
    //   62	74	754	finally
    //   78	84	754	finally
    //   104	114	754	finally
    //   126	135	754	finally
    //   149	156	754	finally
    //   167	176	754	finally
    //   187	194	754	finally
    //   205	214	754	finally
    //   225	238	754	finally
    //   249	258	754	finally
    //   269	291	754	finally
    //   302	308	754	finally
    //   319	326	754	finally
    //   337	345	754	finally
    //   356	405	754	finally
    //   416	425	754	finally
    //   451	460	754	finally
    //   471	479	754	finally
    //   498	509	754	finally
    //   520	528	754	finally
    //   539	552	754	finally
    //   566	576	754	finally
    //   587	597	754	finally
    //   608	617	754	finally
    //   628	637	754	finally
    //   653	675	754	finally
    //   689	712	754	finally
    //   723	732	754	finally
    //   770	793	754	finally
    //   797	801	754	finally
    //   49	58	758	android/database/sqlite/SQLiteException
    //   62	74	758	android/database/sqlite/SQLiteException
    //   78	84	758	android/database/sqlite/SQLiteException
    //   35	45	762	android/database/sqlite/SQLiteException
  }
  
  public final void zzw()
  {
    zzW();
    zzh().beginTransaction();
  }
  
  public final void zzx()
  {
    zzW();
    zzh().endTransaction();
  }
  
  @VisibleForTesting
  final void zzy(List paramList)
  {
    zzg();
    zzW();
    Preconditions.checkNotNull(paramList);
    Preconditions.checkNotZero(paramList.size());
    if (!zzI()) {
      return;
    }
    paramList = TextUtils.join(",", paramList);
    Object localObject = new StringBuilder();
    ((StringBuilder)localObject).append("(");
    ((StringBuilder)localObject).append(paramList);
    ((StringBuilder)localObject).append(")");
    paramList = ((StringBuilder)localObject).toString();
    localObject = new StringBuilder();
    ((StringBuilder)localObject).append("SELECT COUNT(1) FROM queue WHERE rowid IN ");
    ((StringBuilder)localObject).append(paramList);
    ((StringBuilder)localObject).append(" AND retry_count =  2147483647 LIMIT 1");
    if (zzZ(((StringBuilder)localObject).toString(), null) > 0L) {
      zzs.zzay().zzk().zza("The number of upload retries exceeds the limit. Will remain unchanged.");
    }
    try
    {
      localObject = zzh();
      StringBuilder localStringBuilder = new StringBuilder();
      localStringBuilder.append("UPDATE queue SET retry_count = IFNULL(retry_count, 0) + 1 WHERE rowid IN ");
      localStringBuilder.append(paramList);
      localStringBuilder.append(" AND (retry_count IS NULL OR retry_count < 2147483647)");
      ((SQLiteDatabase)localObject).execSQL(localStringBuilder.toString());
      return;
    }
    catch (SQLiteException paramList)
    {
      zzs.zzay().zzd().zzb("Error incrementing retry count. error", paramList);
    }
  }
  
  final void zzz()
  {
    zzg();
    zzW();
    if (zzI())
    {
      long l2 = zzf.zzs().zza.zza();
      long l1 = zzs.zzav().elapsedRealtime();
      l2 = Math.abs(l1 - l2);
      zzs.zzf();
      if (l2 > ((Long)zzeb.zzx.zza(null)).longValue())
      {
        zzf.zzs().zza.zzb(l1);
        zzg();
        zzW();
        if (!zzI()) {
          return;
        }
        SQLiteDatabase localSQLiteDatabase = zzh();
        l1 = zzs.zzav().currentTimeMillis();
        zzs.zzf();
        int i = localSQLiteDatabase.delete("queue", "abs(bundle_end_timestamp - ?) > cast(? as integer)", new String[] { String.valueOf(l1), String.valueOf(zzag.zzA()) });
        if (i > 0) {
          zzs.zzay().zzj().zzb("Deleted stale rows. rowsDeleted", Integer.valueOf(i));
        }
      }
    }
  }
}
