package com.google.android.gms.measurement.internal;

import java.util.concurrent.atomic.AtomicReference;

final class zzht
  implements Runnable
{
  zzht(zzid paramZzid, AtomicReference paramAtomicReference) {}
  
  /* Error */
  public final void run()
  {
    // Byte code:
    //   0: aload_0
    //   1: getfield 16	com/google/android/gms/measurement/internal/zzht:zza	Ljava/util/concurrent/atomic/AtomicReference;
    //   4: astore_1
    //   5: aload_1
    //   6: monitorenter
    //   7: aload_0
    //   8: getfield 16	com/google/android/gms/measurement/internal/zzht:zza	Ljava/util/concurrent/atomic/AtomicReference;
    //   11: aload_0
    //   12: getfield 14	com/google/android/gms/measurement/internal/zzht:zzb	Lcom/google/android/gms/measurement/internal/zzid;
    //   15: getfield 27	com/google/android/gms/measurement/internal/zzgr:zzs	Lcom/google/android/gms/measurement/internal/zzfy;
    //   18: invokevirtual 33	com/google/android/gms/measurement/internal/zzfy:zzf	()Lcom/google/android/gms/measurement/internal/zzag;
    //   21: aload_0
    //   22: getfield 14	com/google/android/gms/measurement/internal/zzht:zzb	Lcom/google/android/gms/measurement/internal/zzid;
    //   25: getfield 27	com/google/android/gms/measurement/internal/zzgr:zzs	Lcom/google/android/gms/measurement/internal/zzfy;
    //   28: invokevirtual 37	com/google/android/gms/measurement/internal/zzfy:zzh	()Lcom/google/android/gms/measurement/internal/zzef;
    //   31: invokevirtual 43	com/google/android/gms/measurement/internal/zzef:zzl	()Ljava/lang/String;
    //   34: getstatic 49	com/google/android/gms/measurement/internal/zzeb:zzL	Lcom/google/android/gms/measurement/internal/zzea;
    //   37: invokevirtual 55	com/google/android/gms/measurement/internal/zzag:zzi	(Ljava/lang/String;Lcom/google/android/gms/measurement/internal/zzea;)J
    //   40: invokestatic 61	java/lang/Long:valueOf	(J)Ljava/lang/Long;
    //   43: invokevirtual 67	java/util/concurrent/atomic/AtomicReference:set	(Ljava/lang/Object;)V
    //   46: aload_0
    //   47: getfield 16	com/google/android/gms/measurement/internal/zzht:zza	Ljava/util/concurrent/atomic/AtomicReference;
    //   50: invokevirtual 70	java/lang/Object:notify	()V
    //   53: aload_1
    //   54: monitorexit
    //   55: return
    //   56: astore_2
    //   57: aload_0
    //   58: getfield 16	com/google/android/gms/measurement/internal/zzht:zza	Ljava/util/concurrent/atomic/AtomicReference;
    //   61: invokevirtual 70	java/lang/Object:notify	()V
    //   64: aload_2
    //   65: athrow
    //   66: astore_2
    //   67: aload_1
    //   68: monitorexit
    //   69: aload_2
    //   70: athrow
    // Local variable table:
    //   start	length	slot	name	signature
    //   0	71	0	this	zzht
    //   4	64	1	localAtomicReference	AtomicReference
    //   56	9	2	localObject1	Object
    //   66	4	2	localObject2	Object
    // Exception table:
    //   from	to	target	type
    //   7	46	56	finally
    //   46	55	66	finally
    //   57	66	66	finally
    //   67	69	66	finally
  }
}
