package com.google.android.gms.measurement.internal;

import android.app.Activity;
import android.app.Application.ActivityLifecycleCallbacks;
import android.os.Bundle;
import com.google.android.gms.common.util.Clock;

final class zzic
  implements Application.ActivityLifecycleCallbacks
{
  /* Error */
  public final void onActivityCreated(Activity paramActivity, Bundle paramBundle)
  {
    // Byte code:
    //   0: aload_0
    //   1: getfield 12	com/google/android/gms/measurement/internal/zzic:zza	Lcom/google/android/gms/measurement/internal/zzid;
    //   4: getfield 26	com/google/android/gms/measurement/internal/zzgr:zzs	Lcom/google/android/gms/measurement/internal/zzfy;
    //   7: invokevirtual 32	com/google/android/gms/measurement/internal/zzfy:zzay	()Lcom/google/android/gms/measurement/internal/zzeo;
    //   10: invokevirtual 38	com/google/android/gms/measurement/internal/zzeo:zzj	()Lcom/google/android/gms/measurement/internal/zzem;
    //   13: ldc 39
    //   15: invokevirtual 44	com/google/android/gms/measurement/internal/zzem:zza	(Ljava/lang/String;)V
    //   18: aload_1
    //   19: invokevirtual 50	android/app/Activity:getIntent	()Landroid/content/Intent;
    //   22: astore 6
    //   24: aload 6
    //   26: ifnonnull +23 -> 49
    //   29: aload_0
    //   30: getfield 12	com/google/android/gms/measurement/internal/zzic:zza	Lcom/google/android/gms/measurement/internal/zzid;
    //   33: getfield 26	com/google/android/gms/measurement/internal/zzgr:zzs	Lcom/google/android/gms/measurement/internal/zzfy;
    //   36: astore 6
    //   38: aload 6
    //   40: invokevirtual 53	com/google/android/gms/measurement/internal/zzfy:zzs	()Lcom/google/android/gms/measurement/internal/zzis;
    //   43: aload_1
    //   44: aload_2
    //   45: invokevirtual 58	com/google/android/gms/measurement/internal/zzis:zzr	(Landroid/app/Activity;Landroid/os/Bundle;)V
    //   48: return
    //   49: aload 6
    //   51: invokevirtual 64	android/content/Intent:getData	()Landroid/net/Uri;
    //   54: astore 7
    //   56: aload 7
    //   58: ifnull +158 -> 216
    //   61: aload 7
    //   63: invokevirtual 70	android/net/Uri:isHierarchical	()Z
    //   66: ifne +6 -> 72
    //   69: goto +147 -> 216
    //   72: aload_0
    //   73: getfield 12	com/google/android/gms/measurement/internal/zzic:zza	Lcom/google/android/gms/measurement/internal/zzid;
    //   76: getfield 26	com/google/android/gms/measurement/internal/zzgr:zzs	Lcom/google/android/gms/measurement/internal/zzfy;
    //   79: invokevirtual 74	com/google/android/gms/measurement/internal/zzfy:zzv	()Lcom/google/android/gms/measurement/internal/zzlh;
    //   82: pop
    //   83: aload 6
    //   85: ldc 76
    //   87: invokevirtual 80	android/content/Intent:getStringExtra	(Ljava/lang/String;)Ljava/lang/String;
    //   90: astore 6
    //   92: ldc 82
    //   94: aload 6
    //   96: invokevirtual 88	java/lang/String:equals	(Ljava/lang/Object;)Z
    //   99: istore 5
    //   101: iconst_1
    //   102: istore 4
    //   104: iload 5
    //   106: ifne +35 -> 141
    //   109: ldc 90
    //   111: aload 6
    //   113: invokevirtual 88	java/lang/String:equals	(Ljava/lang/Object;)Z
    //   116: ifne +25 -> 141
    //   119: ldc 92
    //   121: aload 6
    //   123: invokevirtual 88	java/lang/String:equals	(Ljava/lang/Object;)Z
    //   126: istore 5
    //   128: iload 5
    //   130: ifeq +6 -> 136
    //   133: goto +8 -> 141
    //   136: iconst_0
    //   137: istore_3
    //   138: goto +5 -> 143
    //   141: iconst_1
    //   142: istore_3
    //   143: iconst_1
    //   144: iload_3
    //   145: if_icmpeq +10 -> 155
    //   148: ldc 94
    //   150: astore 6
    //   152: goto +7 -> 159
    //   155: ldc 96
    //   157: astore 6
    //   159: aload 7
    //   161: ldc 98
    //   163: invokevirtual 101	android/net/Uri:getQueryParameter	(Ljava/lang/String;)Ljava/lang/String;
    //   166: astore 8
    //   168: aload_2
    //   169: ifnonnull +116 -> 285
    //   172: goto +3 -> 175
    //   175: aload_0
    //   176: getfield 12	com/google/android/gms/measurement/internal/zzic:zza	Lcom/google/android/gms/measurement/internal/zzid;
    //   179: getfield 26	com/google/android/gms/measurement/internal/zzgr:zzs	Lcom/google/android/gms/measurement/internal/zzfy;
    //   182: invokevirtual 105	com/google/android/gms/measurement/internal/zzfy:zzaz	()Lcom/google/android/gms/measurement/internal/zzfv;
    //   185: new 107	com/google/android/gms/measurement/internal/zzia
    //   188: dup
    //   189: aload_0
    //   190: iload 4
    //   192: aload 7
    //   194: aload 6
    //   196: aload 8
    //   198: invokespecial 110	com/google/android/gms/measurement/internal/zzia:<init>	(Lcom/google/android/gms/measurement/internal/zzic;ZLandroid/net/Uri;Ljava/lang/String;Ljava/lang/String;)V
    //   201: invokevirtual 116	com/google/android/gms/measurement/internal/zzfv:zzp	(Ljava/lang/Runnable;)V
    //   204: aload_0
    //   205: getfield 12	com/google/android/gms/measurement/internal/zzic:zza	Lcom/google/android/gms/measurement/internal/zzid;
    //   208: getfield 26	com/google/android/gms/measurement/internal/zzgr:zzs	Lcom/google/android/gms/measurement/internal/zzfy;
    //   211: astore 6
    //   213: goto -175 -> 38
    //   216: aload_0
    //   217: getfield 12	com/google/android/gms/measurement/internal/zzic:zza	Lcom/google/android/gms/measurement/internal/zzid;
    //   220: getfield 26	com/google/android/gms/measurement/internal/zzgr:zzs	Lcom/google/android/gms/measurement/internal/zzfy;
    //   223: astore 6
    //   225: goto -187 -> 38
    //   228: astore 6
    //   230: goto +37 -> 267
    //   233: astore 6
    //   235: aload_0
    //   236: getfield 12	com/google/android/gms/measurement/internal/zzic:zza	Lcom/google/android/gms/measurement/internal/zzid;
    //   239: getfield 26	com/google/android/gms/measurement/internal/zzgr:zzs	Lcom/google/android/gms/measurement/internal/zzfy;
    //   242: invokevirtual 32	com/google/android/gms/measurement/internal/zzfy:zzay	()Lcom/google/android/gms/measurement/internal/zzeo;
    //   245: invokevirtual 119	com/google/android/gms/measurement/internal/zzeo:zzd	()Lcom/google/android/gms/measurement/internal/zzem;
    //   248: ldc 121
    //   250: aload 6
    //   252: invokevirtual 125	com/google/android/gms/measurement/internal/zzem:zzb	(Ljava/lang/String;Ljava/lang/Object;)V
    //   255: aload_0
    //   256: getfield 12	com/google/android/gms/measurement/internal/zzic:zza	Lcom/google/android/gms/measurement/internal/zzid;
    //   259: getfield 26	com/google/android/gms/measurement/internal/zzgr:zzs	Lcom/google/android/gms/measurement/internal/zzfy;
    //   262: astore 6
    //   264: goto -226 -> 38
    //   267: aload_0
    //   268: getfield 12	com/google/android/gms/measurement/internal/zzic:zza	Lcom/google/android/gms/measurement/internal/zzid;
    //   271: getfield 26	com/google/android/gms/measurement/internal/zzgr:zzs	Lcom/google/android/gms/measurement/internal/zzfy;
    //   274: invokevirtual 53	com/google/android/gms/measurement/internal/zzfy:zzs	()Lcom/google/android/gms/measurement/internal/zzis;
    //   277: aload_1
    //   278: aload_2
    //   279: invokevirtual 58	com/google/android/gms/measurement/internal/zzis:zzr	(Landroid/app/Activity;Landroid/os/Bundle;)V
    //   282: aload 6
    //   284: athrow
    //   285: iconst_0
    //   286: istore 4
    //   288: goto -113 -> 175
    // Local variable table:
    //   start	length	slot	name	signature
    //   0	291	0	this	zzic
    //   0	291	1	paramActivity	Activity
    //   0	291	2	paramBundle	Bundle
    //   137	9	3	i	int
    //   102	185	4	bool1	boolean
    //   99	30	5	bool2	boolean
    //   22	202	6	localObject1	Object
    //   228	1	6	localObject2	Object
    //   233	18	6	localRuntimeException	RuntimeException
    //   262	21	6	localZzfy	zzfy
    //   54	139	7	localUri	android.net.Uri
    //   166	31	8	str	String
    // Exception table:
    //   from	to	target	type
    //   0	24	228	finally
    //   49	56	228	finally
    //   61	69	228	finally
    //   72	101	228	finally
    //   109	128	228	finally
    //   159	168	228	finally
    //   175	204	228	finally
    //   235	255	228	finally
    //   0	24	233	java/lang/RuntimeException
    //   49	56	233	java/lang/RuntimeException
    //   61	69	233	java/lang/RuntimeException
    //   72	101	233	java/lang/RuntimeException
    //   109	128	233	java/lang/RuntimeException
    //   159	168	233	java/lang/RuntimeException
    //   175	204	233	java/lang/RuntimeException
  }
  
  public final void onActivityDestroyed(Activity paramActivity)
  {
    zza.zzs.zzs().zzs(paramActivity);
  }
  
  public final void onActivityPaused(Activity paramActivity)
  {
    zza.zzs.zzs().zzt(paramActivity);
    paramActivity = zza.zzs.zzu();
    long l = zzs.zzav().elapsedRealtime();
    zzs.zzaz().zzp(new zzkb(paramActivity, l));
  }
  
  public final void onActivityResumed(Activity paramActivity)
  {
    zzki localZzki = zza.zzs.zzu();
    long l = zzs.zzav().elapsedRealtime();
    zzs.zzaz().zzp(new zzka(localZzki, l));
    zza.zzs.zzs().zzu(paramActivity);
  }
  
  public final void onActivitySaveInstanceState(Activity paramActivity, Bundle paramBundle)
  {
    zza.zzs.zzs().zzv(paramActivity, paramBundle);
  }
  
  public final void onActivityStarted(Activity paramActivity) {}
  
  public final void onActivityStopped(Activity paramActivity) {}
}
