package com.google.android.gms.measurement.internal;

import com.google.android.gms.internal.measurement.zzcf;

final class zzit
  implements Runnable
{
  zzit(zzjs paramZzjs, String paramString1, String paramString2, Item paramItem, boolean paramBoolean, zzcf paramZzcf) {}
  
  /* Error */
  public final void run()
  {
    // Byte code:
    //   0: new 42	android/os/Bundle
    //   3: dup
    //   4: invokespecial 43	android/os/Bundle:<init>	()V
    //   7: astore_2
    //   8: aload_0
    //   9: getfield 21	com/google/android/gms/measurement/internal/zzit:this$0	Lcom/google/android/gms/measurement/internal/zzjs;
    //   12: astore 4
    //   14: aload 4
    //   16: invokestatic 49	com/google/android/gms/measurement/internal/zzjs:getInstance	(Lcom/google/android/gms/measurement/internal/zzjs;)Lcom/google/android/gms/measurement/internal/zzee;
    //   19: astore_3
    //   20: aload_3
    //   21: ifnonnull +58 -> 79
    //   24: aload 4
    //   26: getfield 54	com/google/android/gms/measurement/internal/zzgr:this$0	Lcom/google/android/gms/measurement/internal/zzfy;
    //   29: astore_3
    //   30: aload_3
    //   31: invokevirtual 60	com/google/android/gms/measurement/internal/zzfy:zzay	()Lcom/google/android/gms/measurement/internal/zzeo;
    //   34: invokevirtual 66	com/google/android/gms/measurement/internal/zzeo:iterator	()Lcom/google/android/gms/measurement/internal/zzem;
    //   37: astore_3
    //   38: aload_0
    //   39: getfield 23	com/google/android/gms/measurement/internal/zzit:id	Ljava/lang/String;
    //   42: astore 4
    //   44: aload_0
    //   45: getfield 25	com/google/android/gms/measurement/internal/zzit:url	Ljava/lang/String;
    //   48: astore 5
    //   50: aload_3
    //   51: ldc 68
    //   53: aload 4
    //   55: aload 5
    //   57: invokevirtual 74	com/google/android/gms/measurement/internal/zzem:append	(Ljava/lang/String;Ljava/lang/Object;Ljava/lang/Object;)V
    //   60: aload_0
    //   61: getfield 21	com/google/android/gms/measurement/internal/zzit:this$0	Lcom/google/android/gms/measurement/internal/zzjs;
    //   64: getfield 54	com/google/android/gms/measurement/internal/zzgr:this$0	Lcom/google/android/gms/measurement/internal/zzfy;
    //   67: invokevirtual 78	com/google/android/gms/measurement/internal/zzfy:get	()Lcom/google/android/gms/measurement/internal/zzlh;
    //   70: aload_0
    //   71: getfield 31	com/google/android/gms/measurement/internal/zzit:username	Lcom/google/android/gms/internal/measurement/zzcf;
    //   74: aload_2
    //   75: invokevirtual 84	com/google/android/gms/measurement/internal/zzlh:removeAccount	(Lcom/google/android/gms/internal/measurement/zzcf;Landroid/os/Bundle;)V
    //   78: return
    //   79: aload_0
    //   80: getfield 27	com/google/android/gms/measurement/internal/zzit:name	Lcom/google/android/gms/measurement/internal/Item;
    //   83: astore 4
    //   85: aload 4
    //   87: invokestatic 90	com/google/android/gms/common/internal/Preconditions:checkNotNull	(Ljava/lang/Object;)Ljava/lang/Object;
    //   90: pop
    //   91: aload_0
    //   92: getfield 23	com/google/android/gms/measurement/internal/zzit:id	Ljava/lang/String;
    //   95: astore 4
    //   97: aload_0
    //   98: getfield 25	com/google/android/gms/measurement/internal/zzit:url	Ljava/lang/String;
    //   101: astore 5
    //   103: aload_0
    //   104: getfield 29	com/google/android/gms/measurement/internal/zzit:client	Z
    //   107: istore_1
    //   108: aload_0
    //   109: getfield 27	com/google/android/gms/measurement/internal/zzit:name	Lcom/google/android/gms/measurement/internal/Item;
    //   112: astore 6
    //   114: aload_3
    //   115: aload 4
    //   117: aload 5
    //   119: iload_1
    //   120: aload 6
    //   122: invokeinterface 95 5 0
    //   127: astore 4
    //   129: new 42	android/os/Bundle
    //   132: dup
    //   133: invokespecial 43	android/os/Bundle:<init>	()V
    //   136: astore_3
    //   137: aload 4
    //   139: ifnonnull +6 -> 145
    //   142: goto +136 -> 278
    //   145: aload 4
    //   147: invokeinterface 100 1 0
    //   152: astore 4
    //   154: aload 4
    //   156: invokeinterface 106 1 0
    //   161: istore_1
    //   162: iload_1
    //   163: ifeq +115 -> 278
    //   166: aload 4
    //   168: invokeinterface 110 1 0
    //   173: astore 5
    //   175: aload 5
    //   177: checkcast 112	com/google/android/gms/measurement/internal/zzlc
    //   180: astore 5
    //   182: aload 5
    //   184: getfield 115	com/google/android/gms/measurement/internal/zzlc:key	Ljava/lang/String;
    //   187: astore 6
    //   189: aload 6
    //   191: ifnull +21 -> 212
    //   194: aload 5
    //   196: getfield 118	com/google/android/gms/measurement/internal/zzlc:type	Ljava/lang/String;
    //   199: astore 5
    //   201: aload_3
    //   202: aload 5
    //   204: aload 6
    //   206: invokevirtual 124	android/os/BaseBundle:putString	(Ljava/lang/String;Ljava/lang/String;)V
    //   209: goto -55 -> 154
    //   212: aload 5
    //   214: getfield 128	com/google/android/gms/measurement/internal/zzlc:data	Ljava/lang/Long;
    //   217: astore 6
    //   219: aload 6
    //   221: ifnull +24 -> 245
    //   224: aload 5
    //   226: getfield 118	com/google/android/gms/measurement/internal/zzlc:type	Ljava/lang/String;
    //   229: astore 5
    //   231: aload_3
    //   232: aload 5
    //   234: aload 6
    //   236: invokevirtual 134	java/lang/Long:longValue	()J
    //   239: invokevirtual 138	android/os/BaseBundle:putLong	(Ljava/lang/String;J)V
    //   242: goto -88 -> 154
    //   245: aload 5
    //   247: getfield 142	com/google/android/gms/measurement/internal/zzlc:value	Ljava/lang/Double;
    //   250: astore 6
    //   252: aload 6
    //   254: ifnull -100 -> 154
    //   257: aload 5
    //   259: getfield 118	com/google/android/gms/measurement/internal/zzlc:type	Ljava/lang/String;
    //   262: astore 5
    //   264: aload_3
    //   265: aload 5
    //   267: aload 6
    //   269: invokevirtual 148	java/lang/Double:doubleValue	()D
    //   272: invokevirtual 152	android/os/BaseBundle:putDouble	(Ljava/lang/String;D)V
    //   275: goto -121 -> 154
    //   278: aload_0
    //   279: getfield 21	com/google/android/gms/measurement/internal/zzit:this$0	Lcom/google/android/gms/measurement/internal/zzjs;
    //   282: astore 4
    //   284: aload_3
    //   285: astore_2
    //   286: aload 4
    //   288: invokestatic 156	com/google/android/gms/measurement/internal/zzjs:access$getCleanup	(Lcom/google/android/gms/measurement/internal/zzjs;)V
    //   291: aload_0
    //   292: getfield 21	com/google/android/gms/measurement/internal/zzit:this$0	Lcom/google/android/gms/measurement/internal/zzjs;
    //   295: getfield 54	com/google/android/gms/measurement/internal/zzgr:this$0	Lcom/google/android/gms/measurement/internal/zzfy;
    //   298: invokevirtual 78	com/google/android/gms/measurement/internal/zzfy:get	()Lcom/google/android/gms/measurement/internal/zzlh;
    //   301: aload_0
    //   302: getfield 31	com/google/android/gms/measurement/internal/zzit:username	Lcom/google/android/gms/internal/measurement/zzcf;
    //   305: aload_3
    //   306: invokevirtual 84	com/google/android/gms/measurement/internal/zzlh:removeAccount	(Lcom/google/android/gms/internal/measurement/zzcf;Landroid/os/Bundle;)V
    //   309: return
    //   310: astore 4
    //   312: goto +11 -> 323
    //   315: astore_3
    //   316: goto +53 -> 369
    //   319: astore 4
    //   321: aload_2
    //   322: astore_3
    //   323: aload_3
    //   324: astore_2
    //   325: aload_0
    //   326: getfield 21	com/google/android/gms/measurement/internal/zzit:this$0	Lcom/google/android/gms/measurement/internal/zzjs;
    //   329: getfield 54	com/google/android/gms/measurement/internal/zzgr:this$0	Lcom/google/android/gms/measurement/internal/zzfy;
    //   332: invokevirtual 60	com/google/android/gms/measurement/internal/zzfy:zzay	()Lcom/google/android/gms/measurement/internal/zzeo;
    //   335: invokevirtual 66	com/google/android/gms/measurement/internal/zzeo:iterator	()Lcom/google/android/gms/measurement/internal/zzem;
    //   338: ldc -98
    //   340: aload_0
    //   341: getfield 23	com/google/android/gms/measurement/internal/zzit:id	Ljava/lang/String;
    //   344: aload 4
    //   346: invokevirtual 74	com/google/android/gms/measurement/internal/zzem:append	(Ljava/lang/String;Ljava/lang/Object;Ljava/lang/Object;)V
    //   349: aload_0
    //   350: getfield 21	com/google/android/gms/measurement/internal/zzit:this$0	Lcom/google/android/gms/measurement/internal/zzjs;
    //   353: getfield 54	com/google/android/gms/measurement/internal/zzgr:this$0	Lcom/google/android/gms/measurement/internal/zzfy;
    //   356: invokevirtual 78	com/google/android/gms/measurement/internal/zzfy:get	()Lcom/google/android/gms/measurement/internal/zzlh;
    //   359: aload_0
    //   360: getfield 31	com/google/android/gms/measurement/internal/zzit:username	Lcom/google/android/gms/internal/measurement/zzcf;
    //   363: aload_3
    //   364: invokevirtual 84	com/google/android/gms/measurement/internal/zzlh:removeAccount	(Lcom/google/android/gms/internal/measurement/zzcf;Landroid/os/Bundle;)V
    //   367: return
    //   368: astore_3
    //   369: aload_0
    //   370: getfield 21	com/google/android/gms/measurement/internal/zzit:this$0	Lcom/google/android/gms/measurement/internal/zzjs;
    //   373: getfield 54	com/google/android/gms/measurement/internal/zzgr:this$0	Lcom/google/android/gms/measurement/internal/zzfy;
    //   376: invokevirtual 78	com/google/android/gms/measurement/internal/zzfy:get	()Lcom/google/android/gms/measurement/internal/zzlh;
    //   379: aload_0
    //   380: getfield 31	com/google/android/gms/measurement/internal/zzit:username	Lcom/google/android/gms/internal/measurement/zzcf;
    //   383: aload_2
    //   384: invokevirtual 84	com/google/android/gms/measurement/internal/zzlh:removeAccount	(Lcom/google/android/gms/internal/measurement/zzcf;Landroid/os/Bundle;)V
    //   387: aload_3
    //   388: athrow
    // Local variable table:
    //   start	length	slot	name	signature
    //   0	389	0	this	zzit
    //   107	56	1	bool	boolean
    //   7	377	2	localObject1	Object
    //   19	287	3	localObject2	Object
    //   315	1	3	localThrowable1	Throwable
    //   322	42	3	localObject3	Object
    //   368	20	3	localThrowable2	Throwable
    //   12	275	4	localObject4	Object
    //   310	1	4	localRemoteException1	android.os.RemoteException
    //   319	26	4	localRemoteException2	android.os.RemoteException
    //   48	218	5	localObject5	Object
    //   112	156	6	localObject6	Object
    // Exception table:
    //   from	to	target	type
    //   286	291	310	android/os/RemoteException
    //   14	20	315	java/lang/Throwable
    //   24	30	315	java/lang/Throwable
    //   30	38	315	java/lang/Throwable
    //   50	60	315	java/lang/Throwable
    //   79	85	315	java/lang/Throwable
    //   85	91	315	java/lang/Throwable
    //   91	114	315	java/lang/Throwable
    //   114	129	315	java/lang/Throwable
    //   129	137	315	java/lang/Throwable
    //   145	154	315	java/lang/Throwable
    //   154	162	315	java/lang/Throwable
    //   166	175	315	java/lang/Throwable
    //   175	189	315	java/lang/Throwable
    //   201	209	315	java/lang/Throwable
    //   212	219	315	java/lang/Throwable
    //   231	242	315	java/lang/Throwable
    //   245	252	315	java/lang/Throwable
    //   264	275	315	java/lang/Throwable
    //   14	20	319	android/os/RemoteException
    //   30	38	319	android/os/RemoteException
    //   50	60	319	android/os/RemoteException
    //   85	91	319	android/os/RemoteException
    //   114	129	319	android/os/RemoteException
    //   129	137	319	android/os/RemoteException
    //   145	154	319	android/os/RemoteException
    //   154	162	319	android/os/RemoteException
    //   166	175	319	android/os/RemoteException
    //   201	209	319	android/os/RemoteException
    //   231	242	319	android/os/RemoteException
    //   264	275	319	android/os/RemoteException
    //   286	291	368	java/lang/Throwable
    //   325	349	368	java/lang/Throwable
  }
}
