package com.google.android.gms.measurement.internal;

import com.google.android.gms.internal.measurement.zzcf;

final class zziy
  implements Runnable
{
  zziy(zzjs paramZzjs, zzq paramZzq, zzcf paramZzcf) {}
  
  /* Error */
  public final void run()
  {
    // Byte code:
    //   0: aconst_null
    //   1: astore 4
    //   3: aconst_null
    //   4: astore 5
    //   6: aconst_null
    //   7: astore_3
    //   8: aload 4
    //   10: astore_2
    //   11: aload 5
    //   13: astore_1
    //   14: aload_0
    //   15: getfield 16	com/google/android/gms/measurement/internal/zziy:zzc	Lcom/google/android/gms/measurement/internal/zzjs;
    //   18: getfield 33	com/google/android/gms/measurement/internal/zzgr:zzs	Lcom/google/android/gms/measurement/internal/zzfy;
    //   21: invokevirtual 39	com/google/android/gms/measurement/internal/zzfy:zzm	()Lcom/google/android/gms/measurement/internal/zzfd;
    //   24: invokevirtual 44	com/google/android/gms/measurement/internal/zzfd:zzc	()Lcom/google/android/gms/measurement/internal/zzai;
    //   27: getstatic 49	com/google/android/gms/measurement/internal/zzah:zzb	Lcom/google/android/gms/measurement/internal/zzah;
    //   30: invokevirtual 55	com/google/android/gms/measurement/internal/zzai:zzi	(Lcom/google/android/gms/measurement/internal/zzah;)Z
    //   33: ifne +93 -> 126
    //   36: aload 4
    //   38: astore_2
    //   39: aload 5
    //   41: astore_1
    //   42: aload_0
    //   43: getfield 16	com/google/android/gms/measurement/internal/zziy:zzc	Lcom/google/android/gms/measurement/internal/zzjs;
    //   46: getfield 33	com/google/android/gms/measurement/internal/zzgr:zzs	Lcom/google/android/gms/measurement/internal/zzfy;
    //   49: invokevirtual 59	com/google/android/gms/measurement/internal/zzfy:zzay	()Lcom/google/android/gms/measurement/internal/zzeo;
    //   52: invokevirtual 65	com/google/android/gms/measurement/internal/zzeo:zzl	()Lcom/google/android/gms/measurement/internal/zzem;
    //   55: ldc 67
    //   57: invokevirtual 72	com/google/android/gms/measurement/internal/zzem:zza	(Ljava/lang/String;)V
    //   60: aload 4
    //   62: astore_2
    //   63: aload 5
    //   65: astore_1
    //   66: aload_0
    //   67: getfield 16	com/google/android/gms/measurement/internal/zziy:zzc	Lcom/google/android/gms/measurement/internal/zzjs;
    //   70: getfield 33	com/google/android/gms/measurement/internal/zzgr:zzs	Lcom/google/android/gms/measurement/internal/zzfy;
    //   73: invokevirtual 76	com/google/android/gms/measurement/internal/zzfy:zzq	()Lcom/google/android/gms/measurement/internal/zzid;
    //   76: aconst_null
    //   77: invokevirtual 81	com/google/android/gms/measurement/internal/zzid:zzO	(Ljava/lang/String;)V
    //   80: aload 4
    //   82: astore_2
    //   83: aload 5
    //   85: astore_1
    //   86: aload_0
    //   87: getfield 16	com/google/android/gms/measurement/internal/zziy:zzc	Lcom/google/android/gms/measurement/internal/zzjs;
    //   90: getfield 33	com/google/android/gms/measurement/internal/zzgr:zzs	Lcom/google/android/gms/measurement/internal/zzfy;
    //   93: invokevirtual 39	com/google/android/gms/measurement/internal/zzfy:zzm	()Lcom/google/android/gms/measurement/internal/zzfd;
    //   96: getfield 85	com/google/android/gms/measurement/internal/zzfd:zze	Lcom/google/android/gms/measurement/internal/zzfc;
    //   99: aconst_null
    //   100: invokevirtual 89	com/google/android/gms/measurement/internal/zzfc:zzb	(Ljava/lang/String;)V
    //   103: aload_0
    //   104: getfield 16	com/google/android/gms/measurement/internal/zziy:zzc	Lcom/google/android/gms/measurement/internal/zzjs;
    //   107: getfield 33	com/google/android/gms/measurement/internal/zzgr:zzs	Lcom/google/android/gms/measurement/internal/zzfy;
    //   110: astore_2
    //   111: aload_3
    //   112: astore_1
    //   113: aload_2
    //   114: invokevirtual 93	com/google/android/gms/measurement/internal/zzfy:zzv	()Lcom/google/android/gms/measurement/internal/zzlh;
    //   117: aload_0
    //   118: getfield 20	com/google/android/gms/measurement/internal/zziy:zzb	Lcom/google/android/gms/internal/measurement/zzcf;
    //   121: aload_1
    //   122: invokevirtual 99	com/google/android/gms/measurement/internal/zzlh:zzV	(Lcom/google/android/gms/internal/measurement/zzcf;Ljava/lang/String;)V
    //   125: return
    //   126: aload 4
    //   128: astore_2
    //   129: aload 5
    //   131: astore_1
    //   132: aload_0
    //   133: getfield 16	com/google/android/gms/measurement/internal/zziy:zzc	Lcom/google/android/gms/measurement/internal/zzjs;
    //   136: astore 6
    //   138: aload 4
    //   140: astore_2
    //   141: aload 5
    //   143: astore_1
    //   144: aload 6
    //   146: invokestatic 105	com/google/android/gms/measurement/internal/zzjs:zzh	(Lcom/google/android/gms/measurement/internal/zzjs;)Lcom/google/android/gms/measurement/internal/zzee;
    //   149: astore 7
    //   151: aload 7
    //   153: ifnonnull +38 -> 191
    //   156: aload 4
    //   158: astore_2
    //   159: aload 5
    //   161: astore_1
    //   162: aload 6
    //   164: getfield 33	com/google/android/gms/measurement/internal/zzgr:zzs	Lcom/google/android/gms/measurement/internal/zzfy;
    //   167: invokevirtual 59	com/google/android/gms/measurement/internal/zzfy:zzay	()Lcom/google/android/gms/measurement/internal/zzeo;
    //   170: invokevirtual 108	com/google/android/gms/measurement/internal/zzeo:zzd	()Lcom/google/android/gms/measurement/internal/zzem;
    //   173: ldc 110
    //   175: invokevirtual 72	com/google/android/gms/measurement/internal/zzem:zza	(Ljava/lang/String;)V
    //   178: aload_0
    //   179: getfield 16	com/google/android/gms/measurement/internal/zziy:zzc	Lcom/google/android/gms/measurement/internal/zzjs;
    //   182: getfield 33	com/google/android/gms/measurement/internal/zzgr:zzs	Lcom/google/android/gms/measurement/internal/zzfy;
    //   185: astore_2
    //   186: aload_3
    //   187: astore_1
    //   188: goto -75 -> 113
    //   191: aload 4
    //   193: astore_2
    //   194: aload 5
    //   196: astore_1
    //   197: aload_0
    //   198: getfield 18	com/google/android/gms/measurement/internal/zziy:zza	Lcom/google/android/gms/measurement/internal/zzq;
    //   201: invokestatic 116	com/google/android/gms/common/internal/Preconditions:checkNotNull	(Ljava/lang/Object;)Ljava/lang/Object;
    //   204: pop
    //   205: aload 4
    //   207: astore_2
    //   208: aload 5
    //   210: astore_1
    //   211: aload 7
    //   213: aload_0
    //   214: getfield 18	com/google/android/gms/measurement/internal/zziy:zza	Lcom/google/android/gms/measurement/internal/zzq;
    //   217: invokeinterface 121 2 0
    //   222: astore_3
    //   223: aload_3
    //   224: ifnull +42 -> 266
    //   227: aload_3
    //   228: astore_2
    //   229: aload_3
    //   230: astore_1
    //   231: aload_0
    //   232: getfield 16	com/google/android/gms/measurement/internal/zziy:zzc	Lcom/google/android/gms/measurement/internal/zzjs;
    //   235: getfield 33	com/google/android/gms/measurement/internal/zzgr:zzs	Lcom/google/android/gms/measurement/internal/zzfy;
    //   238: invokevirtual 76	com/google/android/gms/measurement/internal/zzfy:zzq	()Lcom/google/android/gms/measurement/internal/zzid;
    //   241: aload_3
    //   242: invokevirtual 81	com/google/android/gms/measurement/internal/zzid:zzO	(Ljava/lang/String;)V
    //   245: aload_3
    //   246: astore_2
    //   247: aload_3
    //   248: astore_1
    //   249: aload_0
    //   250: getfield 16	com/google/android/gms/measurement/internal/zziy:zzc	Lcom/google/android/gms/measurement/internal/zzjs;
    //   253: getfield 33	com/google/android/gms/measurement/internal/zzgr:zzs	Lcom/google/android/gms/measurement/internal/zzfy;
    //   256: invokevirtual 39	com/google/android/gms/measurement/internal/zzfy:zzm	()Lcom/google/android/gms/measurement/internal/zzfd;
    //   259: getfield 85	com/google/android/gms/measurement/internal/zzfd:zze	Lcom/google/android/gms/measurement/internal/zzfc;
    //   262: aload_3
    //   263: invokevirtual 89	com/google/android/gms/measurement/internal/zzfc:zzb	(Ljava/lang/String;)V
    //   266: aload_3
    //   267: astore_2
    //   268: aload_3
    //   269: astore_1
    //   270: aload_0
    //   271: getfield 16	com/google/android/gms/measurement/internal/zziy:zzc	Lcom/google/android/gms/measurement/internal/zzjs;
    //   274: invokestatic 125	com/google/android/gms/measurement/internal/zzjs:zzp	(Lcom/google/android/gms/measurement/internal/zzjs;)V
    //   277: aload_0
    //   278: getfield 16	com/google/android/gms/measurement/internal/zziy:zzc	Lcom/google/android/gms/measurement/internal/zzjs;
    //   281: getfield 33	com/google/android/gms/measurement/internal/zzgr:zzs	Lcom/google/android/gms/measurement/internal/zzfy;
    //   284: astore_2
    //   285: aload_3
    //   286: astore_1
    //   287: goto -174 -> 113
    //   290: astore_1
    //   291: goto +36 -> 327
    //   294: astore_3
    //   295: aload_1
    //   296: astore_2
    //   297: aload_0
    //   298: getfield 16	com/google/android/gms/measurement/internal/zziy:zzc	Lcom/google/android/gms/measurement/internal/zzjs;
    //   301: getfield 33	com/google/android/gms/measurement/internal/zzgr:zzs	Lcom/google/android/gms/measurement/internal/zzfy;
    //   304: invokevirtual 59	com/google/android/gms/measurement/internal/zzfy:zzay	()Lcom/google/android/gms/measurement/internal/zzeo;
    //   307: invokevirtual 108	com/google/android/gms/measurement/internal/zzeo:zzd	()Lcom/google/android/gms/measurement/internal/zzem;
    //   310: ldc 110
    //   312: aload_3
    //   313: invokevirtual 128	com/google/android/gms/measurement/internal/zzem:zzb	(Ljava/lang/String;Ljava/lang/Object;)V
    //   316: aload_0
    //   317: getfield 16	com/google/android/gms/measurement/internal/zziy:zzc	Lcom/google/android/gms/measurement/internal/zzjs;
    //   320: getfield 33	com/google/android/gms/measurement/internal/zzgr:zzs	Lcom/google/android/gms/measurement/internal/zzfy;
    //   323: astore_2
    //   324: goto -211 -> 113
    //   327: aload_0
    //   328: getfield 16	com/google/android/gms/measurement/internal/zziy:zzc	Lcom/google/android/gms/measurement/internal/zzjs;
    //   331: getfield 33	com/google/android/gms/measurement/internal/zzgr:zzs	Lcom/google/android/gms/measurement/internal/zzfy;
    //   334: invokevirtual 93	com/google/android/gms/measurement/internal/zzfy:zzv	()Lcom/google/android/gms/measurement/internal/zzlh;
    //   337: aload_0
    //   338: getfield 20	com/google/android/gms/measurement/internal/zziy:zzb	Lcom/google/android/gms/internal/measurement/zzcf;
    //   341: aload_2
    //   342: invokevirtual 99	com/google/android/gms/measurement/internal/zzlh:zzV	(Lcom/google/android/gms/internal/measurement/zzcf;Ljava/lang/String;)V
    //   345: aload_1
    //   346: athrow
    // Local variable table:
    //   start	length	slot	name	signature
    //   0	347	0	this	zziy
    //   13	274	1	localObject1	Object
    //   290	56	1	localObject2	Object
    //   10	332	2	localObject3	Object
    //   7	279	3	str	String
    //   294	19	3	localRemoteException	android.os.RemoteException
    //   1	205	4	localObject4	Object
    //   4	205	5	localObject5	Object
    //   136	27	6	localZzjs	zzjs
    //   149	63	7	localZzee	zzee
    // Exception table:
    //   from	to	target	type
    //   14	36	290	finally
    //   42	60	290	finally
    //   66	80	290	finally
    //   86	103	290	finally
    //   132	138	290	finally
    //   144	151	290	finally
    //   162	178	290	finally
    //   197	205	290	finally
    //   211	223	290	finally
    //   231	245	290	finally
    //   249	266	290	finally
    //   270	277	290	finally
    //   297	316	290	finally
    //   14	36	294	android/os/RemoteException
    //   42	60	294	android/os/RemoteException
    //   66	80	294	android/os/RemoteException
    //   86	103	294	android/os/RemoteException
    //   132	138	294	android/os/RemoteException
    //   144	151	294	android/os/RemoteException
    //   162	178	294	android/os/RemoteException
    //   197	205	294	android/os/RemoteException
    //   211	223	294	android/os/RemoteException
    //   231	245	294	android/os/RemoteException
    //   249	266	294	android/os/RemoteException
    //   270	277	294	android/os/RemoteException
  }
}
