package com.google.android.gms.measurement.internal;

import com.google.android.gms.internal.measurement.zzcf;

final class zzjk
  implements Runnable
{
  zzjk(zzjs paramZzjs, String paramString1, String paramString2, zzq paramZzq, zzcf paramZzcf) {}
  
  /* Error */
  public final void run()
  {
    // Byte code:
    //   0: new 36	java/util/ArrayList
    //   3: dup
    //   4: invokespecial 37	java/util/ArrayList:<init>	()V
    //   7: astore_3
    //   8: aload_3
    //   9: astore_2
    //   10: aload_3
    //   11: astore_1
    //   12: aload_0
    //   13: getfield 19	com/google/android/gms/measurement/internal/zzjk:zze	Lcom/google/android/gms/measurement/internal/zzjs;
    //   16: astore 4
    //   18: aload_3
    //   19: astore_2
    //   20: aload_3
    //   21: astore_1
    //   22: aload 4
    //   24: invokestatic 43	com/google/android/gms/measurement/internal/zzjs:zzh	(Lcom/google/android/gms/measurement/internal/zzjs;)Lcom/google/android/gms/measurement/internal/zzee;
    //   27: astore 5
    //   29: aload 5
    //   31: ifnonnull +54 -> 85
    //   34: aload_3
    //   35: astore_2
    //   36: aload_3
    //   37: astore_1
    //   38: aload 4
    //   40: getfield 49	com/google/android/gms/measurement/internal/zzgr:zzs	Lcom/google/android/gms/measurement/internal/zzfy;
    //   43: invokevirtual 55	com/google/android/gms/measurement/internal/zzfy:zzay	()Lcom/google/android/gms/measurement/internal/zzeo;
    //   46: invokevirtual 60	com/google/android/gms/measurement/internal/zzeo:zzd	()Lcom/google/android/gms/measurement/internal/zzem;
    //   49: ldc 62
    //   51: aload_0
    //   52: getfield 21	com/google/android/gms/measurement/internal/zzjk:zza	Ljava/lang/String;
    //   55: aload_0
    //   56: getfield 23	com/google/android/gms/measurement/internal/zzjk:zzb	Ljava/lang/String;
    //   59: invokevirtual 67	com/google/android/gms/measurement/internal/zzem:zzc	(Ljava/lang/String;Ljava/lang/Object;Ljava/lang/Object;)V
    //   62: aload_0
    //   63: getfield 19	com/google/android/gms/measurement/internal/zzjk:zze	Lcom/google/android/gms/measurement/internal/zzjs;
    //   66: getfield 49	com/google/android/gms/measurement/internal/zzgr:zzs	Lcom/google/android/gms/measurement/internal/zzfy;
    //   69: astore_2
    //   70: aload_3
    //   71: astore_1
    //   72: aload_2
    //   73: invokevirtual 71	com/google/android/gms/measurement/internal/zzfy:zzv	()Lcom/google/android/gms/measurement/internal/zzlh;
    //   76: aload_0
    //   77: getfield 27	com/google/android/gms/measurement/internal/zzjk:zzd	Lcom/google/android/gms/internal/measurement/zzcf;
    //   80: aload_1
    //   81: invokevirtual 77	com/google/android/gms/measurement/internal/zzlh:zzQ	(Lcom/google/android/gms/internal/measurement/zzcf;Ljava/util/ArrayList;)V
    //   84: return
    //   85: aload_3
    //   86: astore_2
    //   87: aload_3
    //   88: astore_1
    //   89: aload_0
    //   90: getfield 25	com/google/android/gms/measurement/internal/zzjk:zzc	Lcom/google/android/gms/measurement/internal/zzq;
    //   93: invokestatic 83	com/google/android/gms/common/internal/Preconditions:checkNotNull	(Ljava/lang/Object;)Ljava/lang/Object;
    //   96: pop
    //   97: aload_3
    //   98: astore_2
    //   99: aload_3
    //   100: astore_1
    //   101: aload 5
    //   103: aload_0
    //   104: getfield 21	com/google/android/gms/measurement/internal/zzjk:zza	Ljava/lang/String;
    //   107: aload_0
    //   108: getfield 23	com/google/android/gms/measurement/internal/zzjk:zzb	Ljava/lang/String;
    //   111: aload_0
    //   112: getfield 25	com/google/android/gms/measurement/internal/zzjk:zzc	Lcom/google/android/gms/measurement/internal/zzq;
    //   115: invokeinterface 89 4 0
    //   120: invokestatic 93	com/google/android/gms/measurement/internal/zzlh:zzH	(Ljava/util/List;)Ljava/util/ArrayList;
    //   123: astore_3
    //   124: aload_3
    //   125: astore_2
    //   126: aload_3
    //   127: astore_1
    //   128: aload_0
    //   129: getfield 19	com/google/android/gms/measurement/internal/zzjk:zze	Lcom/google/android/gms/measurement/internal/zzjs;
    //   132: invokestatic 97	com/google/android/gms/measurement/internal/zzjs:zzp	(Lcom/google/android/gms/measurement/internal/zzjs;)V
    //   135: aload_0
    //   136: getfield 19	com/google/android/gms/measurement/internal/zzjk:zze	Lcom/google/android/gms/measurement/internal/zzjs;
    //   139: getfield 49	com/google/android/gms/measurement/internal/zzgr:zzs	Lcom/google/android/gms/measurement/internal/zzfy;
    //   142: astore_2
    //   143: aload_3
    //   144: astore_1
    //   145: goto -73 -> 72
    //   148: astore_1
    //   149: goto +44 -> 193
    //   152: astore_3
    //   153: aload_1
    //   154: astore_2
    //   155: aload_0
    //   156: getfield 19	com/google/android/gms/measurement/internal/zzjk:zze	Lcom/google/android/gms/measurement/internal/zzjs;
    //   159: getfield 49	com/google/android/gms/measurement/internal/zzgr:zzs	Lcom/google/android/gms/measurement/internal/zzfy;
    //   162: invokevirtual 55	com/google/android/gms/measurement/internal/zzfy:zzay	()Lcom/google/android/gms/measurement/internal/zzeo;
    //   165: invokevirtual 60	com/google/android/gms/measurement/internal/zzeo:zzd	()Lcom/google/android/gms/measurement/internal/zzem;
    //   168: ldc 99
    //   170: aload_0
    //   171: getfield 21	com/google/android/gms/measurement/internal/zzjk:zza	Ljava/lang/String;
    //   174: aload_0
    //   175: getfield 23	com/google/android/gms/measurement/internal/zzjk:zzb	Ljava/lang/String;
    //   178: aload_3
    //   179: invokevirtual 102	com/google/android/gms/measurement/internal/zzem:zzd	(Ljava/lang/String;Ljava/lang/Object;Ljava/lang/Object;Ljava/lang/Object;)V
    //   182: aload_0
    //   183: getfield 19	com/google/android/gms/measurement/internal/zzjk:zze	Lcom/google/android/gms/measurement/internal/zzjs;
    //   186: getfield 49	com/google/android/gms/measurement/internal/zzgr:zzs	Lcom/google/android/gms/measurement/internal/zzfy;
    //   189: astore_2
    //   190: goto -118 -> 72
    //   193: aload_0
    //   194: getfield 19	com/google/android/gms/measurement/internal/zzjk:zze	Lcom/google/android/gms/measurement/internal/zzjs;
    //   197: getfield 49	com/google/android/gms/measurement/internal/zzgr:zzs	Lcom/google/android/gms/measurement/internal/zzfy;
    //   200: invokevirtual 71	com/google/android/gms/measurement/internal/zzfy:zzv	()Lcom/google/android/gms/measurement/internal/zzlh;
    //   203: aload_0
    //   204: getfield 27	com/google/android/gms/measurement/internal/zzjk:zzd	Lcom/google/android/gms/internal/measurement/zzcf;
    //   207: aload_2
    //   208: invokevirtual 77	com/google/android/gms/measurement/internal/zzlh:zzQ	(Lcom/google/android/gms/internal/measurement/zzcf;Ljava/util/ArrayList;)V
    //   211: aload_1
    //   212: athrow
    // Local variable table:
    //   start	length	slot	name	signature
    //   0	213	0	this	zzjk
    //   11	134	1	localArrayList1	java.util.ArrayList
    //   148	64	1	localObject1	Object
    //   9	199	2	localObject2	Object
    //   7	137	3	localArrayList2	java.util.ArrayList
    //   152	27	3	localRemoteException	android.os.RemoteException
    //   16	23	4	localZzjs	zzjs
    //   27	75	5	localZzee	zzee
    // Exception table:
    //   from	to	target	type
    //   12	18	148	finally
    //   22	29	148	finally
    //   38	62	148	finally
    //   89	97	148	finally
    //   101	124	148	finally
    //   128	135	148	finally
    //   155	182	148	finally
    //   12	18	152	android/os/RemoteException
    //   22	29	152	android/os/RemoteException
    //   38	62	152	android/os/RemoteException
    //   89	97	152	android/os/RemoteException
    //   101	124	152	android/os/RemoteException
    //   128	135	152	android/os/RemoteException
  }
}
