package com.google.android.gms.internal.fitness;

import java.io.IOException;
import java.lang.reflect.Field;
import java.util.AbstractMap;
import java.util.Arrays;
import java.util.Collection;
import java.util.Iterator;
import java.util.List;
import java.util.Map;
import java.util.Map.Entry;
import java.util.Objects;
import sun.misc.Unsafe;

final class zzio<T>
  implements zzja<T>
{
  private static final int[] zzaac = new int[0];
  private static final Unsafe zzaad = zzjy.zzdt();
  private final boolean zzaaa;
  private final zzgo<?> zzaab;
  private final int[] zzaae;
  private final Object[] zzaaf;
  private final int zzaag;
  private final int zzaah;
  private final boolean zzaai;
  private final boolean zzaaj;
  private final boolean zzaak;
  private final int[] zzaal;
  private final int zzaam;
  private final int zzaan;
  private final zzip zzaao;
  private final zzhu zzaap;
  private final zzid zzaaq;
  private final zzik zzzy;
  private final zzjs<?, ?> zzzz;
  
  private zzio(int[] paramArrayOfInt1, Object[] paramArrayOfObject, int paramInt1, int paramInt2, zzik paramZzik, boolean paramBoolean1, boolean paramBoolean2, int[] paramArrayOfInt2, int paramInt3, int paramInt4, zzip paramZzip, zzhu paramZzhu, zzjs<?, ?> paramZzjs, zzgo<?> paramZzgo, zzid paramZzid)
  {
    zzaae = paramArrayOfInt1;
    zzaaf = paramArrayOfObject;
    zzaag = paramInt1;
    zzaah = paramInt2;
    zzaai = (paramZzik instanceof zzgy);
    zzaaj = paramBoolean1;
    if ((paramZzgo != null) && (paramZzgo.zze(paramZzik))) {
      paramBoolean1 = true;
    } else {
      paramBoolean1 = false;
    }
    zzaaa = paramBoolean1;
    zzaak = false;
    zzaal = paramArrayOfInt2;
    zzaam = paramInt3;
    zzaan = paramInt4;
    zzaao = paramZzip;
    zzaap = paramZzhu;
    zzzz = paramZzjs;
    zzaab = paramZzgo;
    zzzy = paramZzik;
    zzaaq = paramZzid;
  }
  
  private static <UT, UB> int zza(zzjs<UT, UB> paramZzjs, T paramT)
  {
    return paramZzjs.zzm(paramZzjs.zzo(paramT));
  }
  
  static <T> zzio<T> zza(Class<T> paramClass, zzii paramZzii, zzip paramZzip, zzhu paramZzhu, zzjs<?, ?> paramZzjs, zzgo<?> paramZzgo, zzid paramZzid)
  {
    if ((paramZzii instanceof zzix))
    {
      zzix localZzix = (zzix)paramZzii;
      i = localZzix.zzcs();
      int j = zziw.zzaax;
      int i4 = 0;
      boolean bool;
      if (i == j) {
        bool = true;
      } else {
        bool = false;
      }
      paramZzii = localZzix.zzcz();
      int i9 = paramZzii.length();
      if (paramZzii.charAt(0) >= 55296) {
        for (j = 1;; j = k)
        {
          k = j + 1;
          i = k;
          if (paramZzii.charAt(j) < 55296) {
            break;
          }
        }
      }
      i = 1;
      j = i + 1;
      int m = paramZzii.charAt(i);
      i = j;
      int k = m;
      if (m >= 55296)
      {
        k = m & 0x1FFF;
        i = 13;
        for (m = j;; m = j)
        {
          j = m + 1;
          m = paramZzii.charAt(m);
          if (m < 55296) {
            break;
          }
          k |= (m & 0x1FFF) << i;
          i += 13;
        }
        k |= m << i;
        i = j;
      }
      int i2;
      if (k == 0)
      {
        paramClass = zzaac;
        n = 0;
        i2 = n;
        i3 = i2;
        i1 = i3;
        j = i1;
        m = j;
        k = i4;
        i4 = i3;
      }
      else
      {
        j = i + 1;
        m = paramZzii.charAt(i);
        i = m;
        k = j;
        if (m >= 55296)
        {
          k = m & 0x1FFF;
          i = 13;
          for (m = j;; m = j)
          {
            j = m + 1;
            m = paramZzii.charAt(m);
            if (m < 55296) {
              break;
            }
            k |= (m & 0x1FFF) << i;
            i += 13;
          }
          i = k | m << i;
          k = j;
        }
        j = k + 1;
        m = paramZzii.charAt(k);
        i3 = m;
        k = j;
        if (m >= 55296)
        {
          m &= 0x1FFF;
          k = 13;
          for (n = j;; n = j)
          {
            j = n + 1;
            n = paramZzii.charAt(n);
            if (n < 55296) {
              break;
            }
            m |= (n & 0x1FFF) << k;
            k += 13;
          }
          i3 = m | n << k;
          k = j;
        }
        j = k + 1;
        n = paramZzii.charAt(k);
        k = n;
        m = j;
        if (n >= 55296)
        {
          m = n & 0x1FFF;
          k = 13;
          for (n = j;; n = j)
          {
            j = n + 1;
            n = paramZzii.charAt(n);
            if (n < 55296) {
              break;
            }
            m |= (n & 0x1FFF) << k;
            k += 13;
          }
          k = m | n << k;
          m = j;
        }
        j = m + 1;
        i1 = paramZzii.charAt(m);
        m = i1;
        n = j;
        if (i1 >= 55296)
        {
          n = i1 & 0x1FFF;
          m = 13;
          for (i1 = j;; i1 = j)
          {
            j = i1 + 1;
            i1 = paramZzii.charAt(i1);
            if (i1 < 55296) {
              break;
            }
            n |= (i1 & 0x1FFF) << m;
            m += 13;
          }
          m = n | i1 << m;
          n = j;
        }
        j = n + 1;
        i2 = paramZzii.charAt(n);
        n = i2;
        i1 = j;
        if (i2 >= 55296)
        {
          i1 = i2 & 0x1FFF;
          n = 13;
          for (i2 = j;; i2 = j)
          {
            j = i2 + 1;
            i2 = paramZzii.charAt(i2);
            if (i2 < 55296) {
              break;
            }
            i1 |= (i2 & 0x1FFF) << n;
            n += 13;
          }
          n = i1 | i2 << n;
          i1 = j;
        }
        j = i1 + 1;
        i4 = paramZzii.charAt(i1);
        i1 = i4;
        i2 = j;
        if (i4 >= 55296)
        {
          i2 = i4 & 0x1FFF;
          i1 = 13;
          for (i4 = j;; i4 = j)
          {
            j = i4 + 1;
            i4 = paramZzii.charAt(i4);
            if (i4 < 55296) {
              break;
            }
            i2 |= (i4 & 0x1FFF) << i1;
            i1 += 13;
          }
          i1 = i2 | i4 << i1;
          i2 = j;
        }
        j = i2 + 1;
        i5 = paramZzii.charAt(i2);
        i4 = i5;
        i2 = j;
        if (i5 >= 55296)
        {
          i4 = i5 & 0x1FFF;
          i2 = 13;
          for (i5 = j;; i5 = j)
          {
            j = i5 + 1;
            i5 = paramZzii.charAt(i5);
            if (i5 < 55296) {
              break;
            }
            i4 |= (i5 & 0x1FFF) << i2;
            i2 += 13;
          }
          i4 |= i5 << i2;
          i2 = j;
        }
        i5 = i2 + 1;
        i6 = paramZzii.charAt(i2);
        j = i6;
        i2 = i5;
        if (i6 >= 55296)
        {
          i2 = i6 & 0x1FFF;
          i6 = i5;
          j = 13;
          i5 = i2;
          for (;;)
          {
            i2 = i6 + 1;
            i6 = paramZzii.charAt(i6);
            if (i6 < 55296) {
              break;
            }
            i5 |= (i6 & 0x1FFF) << j;
            j += 13;
            i6 = i2;
          }
          j = i5 | i6 << j;
        }
        paramClass = new int[j + i1 + i4];
        i5 = (i << 1) + i3;
        i3 = i;
        i = i2;
        i4 = n;
        i2 = m;
        n = k;
        m = i5;
        k = i3;
      }
      Unsafe localUnsafe = zzaad;
      Object[] arrayOfObject1 = localZzix.zzda();
      Class localClass = localZzix.zzcu().getClass();
      int[] arrayOfInt = new int[i4 * 3];
      Object[] arrayOfObject2 = new Object[i4 << 1];
      int i13 = j + i1;
      int i1 = m;
      int i3 = j;
      i4 = i;
      m = i13;
      int i5 = 0;
      int i8 = 0;
      i = i3;
      i3 = i5;
      int i6 = i2;
      i5 = n;
      int n = i4;
      int i7 = k;
      k = i9;
      while (n < k)
      {
        i2 = n + 1;
        i9 = paramZzii.charAt(n);
        if (i9 >= 55296)
        {
          i4 = i9 & 0x1FFF;
          i9 = i2;
          n = 13;
          i2 = i4;
          for (;;)
          {
            i4 = i9 + 1;
            i9 = paramZzii.charAt(i9);
            if (i9 < 55296) {
              break;
            }
            i2 |= (i9 & 0x1FFF) << n;
            n += 13;
            i9 = i4;
          }
          i9 = i2 | i9 << n;
          i2 = i4;
        }
        n = i2 + 1;
        int i11 = paramZzii.charAt(i2);
        if (i11 >= 55296)
        {
          i4 = i11 & 0x1FFF;
          i2 = 13;
          for (;;)
          {
            i10 = n + 1;
            i11 = paramZzii.charAt(n);
            n = j;
            if (i11 < 55296) {
              break;
            }
            i4 |= (i11 & 0x1FFF) << i2;
            i2 += 13;
            j = n;
            n = i10;
          }
          i11 = i4 | i11 << i2;
          i2 = i10;
        }
        else
        {
          i2 = n;
          n = j;
        }
        int i15 = i11 & 0xFF;
        int i10 = i3;
        if ((i11 & 0x400) != 0)
        {
          paramClass[i3] = i8;
          i10 = i3 + 1;
        }
        Object localObject;
        if (i15 >= 51)
        {
          i4 = i2 + 1;
          i2 = paramZzii.charAt(i2);
          i3 = i2;
          j = i4;
          if (i2 >= 55296)
          {
            i3 = i2 & 0x1FFF;
            j = 13;
            for (;;)
            {
              i2 = i4 + 1;
              i4 = paramZzii.charAt(i4);
              if (i4 < 55296) {
                break;
              }
              i3 |= (i4 & 0x1FFF) << j;
              j += 13;
              i4 = i2;
            }
            i3 |= i4 << j;
            j = i2;
          }
          i4 = i15 - 51;
          if ((i4 != 9) && (i4 != 17))
          {
            i2 = i1;
            if (i4 == 12)
            {
              i2 = i1;
              if (!bool)
              {
                arrayOfObject2[((i8 / 3 << 1) + 1)] = arrayOfObject1[i1];
                i2 = i1 + 1;
              }
            }
            i1 = i2;
          }
          else
          {
            arrayOfObject2[((i8 / 3 << 1) + 1)] = arrayOfObject1[i1];
            i1 += 1;
          }
          i2 = i3 << 1;
          localObject = arrayOfObject1[i2];
          if ((localObject instanceof Field))
          {
            localObject = (Field)localObject;
          }
          else
          {
            localObject = zza(localClass, (String)localObject);
            arrayOfObject1[i2] = localObject;
          }
          i3 = (int)localUnsafe.objectFieldOffset((Field)localObject);
          i2 += 1;
          localObject = arrayOfObject1[i2];
          if ((localObject instanceof Field))
          {
            localObject = (Field)localObject;
          }
          else
          {
            localObject = zza(localClass, (String)localObject);
            arrayOfObject1[i2] = localObject;
          }
          i4 = (int)localUnsafe.objectFieldOffset((Field)localObject);
          i2 = 0;
        }
        else
        {
          i3 = i1 + 1;
          localObject = zza(localClass, (String)arrayOfObject1[i1]);
          if ((i15 != 9) && (i15 != 17))
          {
            if ((i15 != 27) && (i15 != 49))
            {
              if ((i15 != 12) && (i15 != 30) && (i15 != 44))
              {
                j = i3;
                i1 = i;
                if (i15 != 50) {
                  break label2130;
                }
                j = i + 1;
                paramClass[i] = i8;
                i4 = i8 / 3 << 1;
                i1 = i3 + 1;
                arrayOfObject2[i4] = arrayOfObject1[i3];
                if ((i11 & 0x800) != 0)
                {
                  i = i1 + 1;
                  arrayOfObject2[(i4 + 1)] = arrayOfObject1[i1];
                  i1 = j;
                  j = i;
                  break label2130;
                }
                i = j;
                j = i1;
              }
              else if (!bool)
              {
                i1 = i8 / 3;
                j = i3 + 1;
                arrayOfObject2[((i1 << 1) + 1)] = arrayOfObject1[i3];
              }
              else
              {
                j = i3;
                i1 = i;
                break label2130;
              }
            }
            else
            {
              i1 = i8 / 3;
              j = i3 + 1;
              arrayOfObject2[((i1 << 1) + 1)] = arrayOfObject1[i3];
            }
            break label2134;
          }
          else
          {
            arrayOfObject2[((i8 / 3 << 1) + 1)] = ((Field)localObject).getType();
            i1 = i;
            j = i3;
          }
          label2130:
          i = i1;
          label2134:
          i14 = (int)localUnsafe.objectFieldOffset((Field)localObject);
          if (((i11 & 0x1000) == 4096) && (i15 <= 17))
          {
            i3 = i2 + 1;
            i4 = paramZzii.charAt(i2);
            i2 = i4;
            i1 = i3;
            if (i4 >= 55296)
            {
              i2 = i4 & 0x1FFF;
              i1 = 13;
              i4 = i3;
              i3 = i2;
              for (;;)
              {
                i2 = i4 + 1;
                i4 = paramZzii.charAt(i4);
                if (i4 < 55296) {
                  break;
                }
                i3 |= (i4 & 0x1FFF) << i1;
                i1 += 13;
                i4 = i2;
              }
              i3 |= i4 << i1;
              i1 = i2;
              i2 = i3;
            }
            i3 = (i7 << 1) + i2 / 32;
            localObject = arrayOfObject1[i3];
            if ((localObject instanceof Field))
            {
              localObject = (Field)localObject;
            }
            else
            {
              localObject = zza(localClass, (String)localObject);
              arrayOfObject1[i3] = localObject;
            }
            i3 = (int)localUnsafe.objectFieldOffset((Field)localObject);
            i2 %= 32;
          }
          else
          {
            i3 = 1048575;
            i1 = i2;
            i2 = 0;
          }
          i4 = m;
          if (i15 >= 18)
          {
            i4 = m;
            if (i15 <= 49)
            {
              paramClass[m] = i14;
              i4 = m + 1;
            }
          }
          i12 = j;
          j = i1;
          m = i4;
          i1 = i12;
          i4 = i3;
          i3 = i14;
        }
        int i14 = i8 + 1;
        arrayOfInt[i8] = i9;
        int i12 = i14 + 1;
        if ((i11 & 0x200) != 0) {
          i8 = 536870912;
        } else {
          i8 = 0;
        }
        if ((i11 & 0x100) != 0) {
          i9 = 268435456;
        } else {
          i9 = 0;
        }
        arrayOfInt[i14] = (i9 | i8 | i15 << 20 | i3);
        arrayOfInt[i12] = (i2 << 20 | i4);
        i2 = j;
        j = n;
        i8 = i12 + 1;
        n = i2;
        i3 = i10;
      }
      return new zzio(arrayOfInt, arrayOfObject2, i5, i6, localZzix.zzcu(), bool, false, paramClass, j, i13, paramZzip, paramZzhu, paramZzjs, paramZzgo, paramZzid);
    }
    ((zzjl)paramZzii).zzcs();
    int i = zziw.zzaax;
    throw new NoSuchMethodError();
  }
  
  private static Field zza(Class<?> paramClass, String paramString)
  {
    try
    {
      localObject1 = paramClass.getDeclaredField(paramString);
      return localObject1;
    }
    catch (NoSuchFieldException localNoSuchFieldException)
    {
      Object localObject1;
      int j;
      int i;
      Object localObject2;
      for (;;) {}
    }
    localObject1 = paramClass.getDeclaredFields();
    j = localObject1.length;
    i = 0;
    while (i < j)
    {
      localObject2 = localObject1[i];
      if (paramString.equals(((Field)localObject2).getName())) {
        return localObject2;
      }
      i += 1;
    }
    paramClass = paramClass.getName();
    localObject1 = Arrays.toString((Object[])localObject1);
    localObject2 = new StringBuilder(String.valueOf(paramString).length() + 40 + paramClass.length() + String.valueOf(localObject1).length());
    ((StringBuilder)localObject2).append("Field ");
    ((StringBuilder)localObject2).append(paramString);
    ((StringBuilder)localObject2).append(" for ");
    ((StringBuilder)localObject2).append(paramClass);
    ((StringBuilder)localObject2).append(" not found. Known fields are ");
    ((StringBuilder)localObject2).append((String)localObject1);
    throw new RuntimeException(((StringBuilder)localObject2).toString());
  }
  
  private static void zza(int paramInt, Object paramObject, zzkm paramZzkm)
    throws IOException
  {
    if ((paramObject instanceof String))
    {
      paramZzkm.zza(paramInt, (String)paramObject);
      return;
    }
    paramZzkm.zza(paramInt, (zzfx)paramObject);
  }
  
  private static <UT, UB> void zza(zzjs<UT, UB> paramZzjs, T paramT, zzkm paramZzkm)
    throws IOException
  {
    paramZzjs.zza(paramZzjs.zzo(paramT), paramZzkm);
  }
  
  private final <K, V> void zza(zzkm paramZzkm, int paramInt1, Object paramObject, int paramInt2)
    throws IOException
  {
    if (paramObject != null) {
      paramZzkm.zza(paramInt1, zzaaq.zzj(zzah(paramInt2)), zzaaq.zzh(paramObject));
    }
  }
  
  private final void zza(T paramT1, T paramT2, int paramInt)
  {
    long l = zzai(paramInt) & 0xFFFFF;
    if (!zzb(paramT2, paramInt)) {
      return;
    }
    Object localObject = zzjy.zzo(paramT1, l);
    paramT2 = zzjy.zzo(paramT2, l);
    if ((localObject != null) && (paramT2 != null))
    {
      zzjy.zza(paramT1, l, zzhc.zzb(localObject, paramT2));
      zzc(paramT1, paramInt);
      return;
    }
    if (paramT2 != null)
    {
      zzjy.zza(paramT1, l, paramT2);
      zzc(paramT1, paramInt);
    }
  }
  
  private final boolean zza(T paramT, int paramInt1, int paramInt2)
  {
    return zzjy.zzj(paramT, zzaj(paramInt2) & 0xFFFFF) == paramInt1;
  }
  
  private final boolean zza(T paramT, int paramInt1, int paramInt2, int paramInt3, int paramInt4)
  {
    if (paramInt2 == 1048575) {
      return zzb(paramT, paramInt1);
    }
    return (paramInt3 & paramInt4) != 0;
  }
  
  private static boolean zza(Object paramObject, int paramInt, zzja paramZzja)
  {
    return paramZzja.zzl(zzjy.zzo(paramObject, paramInt & 0xFFFFF));
  }
  
  private final zzja zzag(int paramInt)
  {
    paramInt = paramInt / 3 << 1;
    zzja localZzja = (zzja)zzaaf[paramInt];
    if (localZzja != null) {
      return localZzja;
    }
    localZzja = zziv.zzcy().zze((Class)zzaaf[(paramInt + 1)]);
    zzaaf[paramInt] = localZzja;
    return localZzja;
  }
  
  private final Object zzah(int paramInt)
  {
    return zzaaf[(paramInt / 3 << 1)];
  }
  
  private final int zzai(int paramInt)
  {
    return zzaae[(paramInt + 1)];
  }
  
  private final int zzaj(int paramInt)
  {
    return zzaae[(paramInt + 2)];
  }
  
  private final void zzb(T paramT, int paramInt1, int paramInt2)
  {
    zzjy.zza(paramT, zzaj(paramInt2) & 0xFFFFF, paramInt1);
  }
  
  private final void zzb(T paramT, zzkm paramZzkm)
    throws IOException
  {
    if (zzaaa)
    {
      localObject1 = zzaab.zzc(paramT);
      if (!zzvb.isEmpty())
      {
        localIterator = ((zzgt)localObject1).iterator();
        localObject1 = (Map.Entry)localIterator.next();
        break label56;
      }
    }
    Iterator localIterator = null;
    Object localObject1 = null;
    label56:
    int i1 = zzaae.length;
    Unsafe localUnsafe = zzaad;
    int m = 0;
    int i = 1048575;
    int j = 0;
    Object localObject2;
    for (;;)
    {
      localObject2 = localObject1;
      if (m >= i1) {
        break;
      }
      int i2 = zzai(m);
      localObject2 = zzaae;
      int i3 = localObject2[m];
      int i4 = (i2 & 0xFF00000) >>> 20;
      int n;
      if (i4 <= 17)
      {
        int i5 = localObject2[(m + 2)];
        n = i5 & 0xFFFFF;
        int k = i;
        if (n != i)
        {
          j = localUnsafe.getInt(paramT, n);
          k = n;
        }
        n = 1 << (i5 >>> 20);
        i = k;
      }
      else
      {
        n = 0;
      }
      while ((localObject1 != null) && (zzaab.zza((Map.Entry)localObject1) <= i3))
      {
        zzaab.zza(paramZzkm, (Map.Entry)localObject1);
        if (localIterator.hasNext()) {
          localObject1 = (Map.Entry)localIterator.next();
        } else {
          localObject1 = null;
        }
      }
      long l = i2 & 0xFFFFF;
      switch (i4)
      {
      }
      for (;;)
      {
        break;
        if (zza(paramT, i3, m))
        {
          paramZzkm.zzb(i3, localUnsafe.getObject(paramT, l), zzag(m));
          continue;
          if (zza(paramT, i3, m))
          {
            paramZzkm.zzb(i3, zzh(paramT, l));
            continue;
            if (zza(paramT, i3, m))
            {
              paramZzkm.zzg(i3, zzg(paramT, l));
              continue;
              if (zza(paramT, i3, m))
              {
                paramZzkm.zzj(i3, zzh(paramT, l));
                continue;
                if (zza(paramT, i3, m))
                {
                  paramZzkm.zzo(i3, zzg(paramT, l));
                  continue;
                  if (zza(paramT, i3, m))
                  {
                    paramZzkm.zzp(i3, zzg(paramT, l));
                    continue;
                    if (zza(paramT, i3, m))
                    {
                      paramZzkm.zzf(i3, zzg(paramT, l));
                      continue;
                      if (zza(paramT, i3, m))
                      {
                        paramZzkm.zza(i3, (zzfx)localUnsafe.getObject(paramT, l));
                        continue;
                        if (zza(paramT, i3, m))
                        {
                          paramZzkm.zza(i3, localUnsafe.getObject(paramT, l), zzag(m));
                          continue;
                          if (zza(paramT, i3, m))
                          {
                            zza(i3, localUnsafe.getObject(paramT, l), paramZzkm);
                            continue;
                            if (zza(paramT, i3, m))
                            {
                              paramZzkm.zza(i3, zzi(paramT, l));
                              continue;
                              if (zza(paramT, i3, m))
                              {
                                paramZzkm.zzh(i3, zzg(paramT, l));
                                continue;
                                if (zza(paramT, i3, m))
                                {
                                  paramZzkm.zzc(i3, zzh(paramT, l));
                                  continue;
                                  if (zza(paramT, i3, m))
                                  {
                                    paramZzkm.zze(i3, zzg(paramT, l));
                                    continue;
                                    if (zza(paramT, i3, m))
                                    {
                                      paramZzkm.zza(i3, zzh(paramT, l));
                                      continue;
                                      if (zza(paramT, i3, m))
                                      {
                                        paramZzkm.zzi(i3, zzh(paramT, l));
                                        continue;
                                        if (zza(paramT, i3, m))
                                        {
                                          paramZzkm.zza(i3, zzf(paramT, l));
                                          continue;
                                          if (zza(paramT, i3, m))
                                          {
                                            paramZzkm.zza(i3, zze(paramT, l));
                                            continue;
                                            zza(paramZzkm, i3, localUnsafe.getObject(paramT, l), m);
                                            continue;
                                            zzjc.zzb(zzaae[m], (List)localUnsafe.getObject(paramT, l), paramZzkm, zzag(m));
                                            continue;
                                            zzjc.zze(zzaae[m], (List)localUnsafe.getObject(paramT, l), paramZzkm, true);
                                            continue;
                                            zzjc.zzj(zzaae[m], (List)localUnsafe.getObject(paramT, l), paramZzkm, true);
                                            continue;
                                            zzjc.zzg(zzaae[m], (List)localUnsafe.getObject(paramT, l), paramZzkm, true);
                                            continue;
                                            zzjc.zzl(zzaae[m], (List)localUnsafe.getObject(paramT, l), paramZzkm, true);
                                            continue;
                                            zzjc.zzm(zzaae[m], (List)localUnsafe.getObject(paramT, l), paramZzkm, true);
                                            continue;
                                            zzjc.zzi(zzaae[m], (List)localUnsafe.getObject(paramT, l), paramZzkm, true);
                                            continue;
                                            zzjc.zzn(zzaae[m], (List)localUnsafe.getObject(paramT, l), paramZzkm, true);
                                            continue;
                                            zzjc.zzk(zzaae[m], (List)localUnsafe.getObject(paramT, l), paramZzkm, true);
                                            continue;
                                            zzjc.zzf(zzaae[m], (List)localUnsafe.getObject(paramT, l), paramZzkm, true);
                                            continue;
                                            zzjc.zzh(zzaae[m], (List)localUnsafe.getObject(paramT, l), paramZzkm, true);
                                            continue;
                                            zzjc.zzd(zzaae[m], (List)localUnsafe.getObject(paramT, l), paramZzkm, true);
                                            continue;
                                            zzjc.zzc(zzaae[m], (List)localUnsafe.getObject(paramT, l), paramZzkm, true);
                                            continue;
                                            zzjc.zzb(zzaae[m], (List)localUnsafe.getObject(paramT, l), paramZzkm, true);
                                            continue;
                                            zzjc.zza(zzaae[m], (List)localUnsafe.getObject(paramT, l), paramZzkm, true);
                                            continue;
                                            zzjc.zze(zzaae[m], (List)localUnsafe.getObject(paramT, l), paramZzkm, false);
                                            break label1947;
                                            zzjc.zzj(zzaae[m], (List)localUnsafe.getObject(paramT, l), paramZzkm, false);
                                            break label1947;
                                            zzjc.zzg(zzaae[m], (List)localUnsafe.getObject(paramT, l), paramZzkm, false);
                                            break label1947;
                                            zzjc.zzl(zzaae[m], (List)localUnsafe.getObject(paramT, l), paramZzkm, false);
                                            break label1947;
                                            zzjc.zzm(zzaae[m], (List)localUnsafe.getObject(paramT, l), paramZzkm, false);
                                            break label1947;
                                            zzjc.zzi(zzaae[m], (List)localUnsafe.getObject(paramT, l), paramZzkm, false);
                                            break label1947;
                                            zzjc.zzb(zzaae[m], (List)localUnsafe.getObject(paramT, l), paramZzkm);
                                            continue;
                                            zzjc.zza(zzaae[m], (List)localUnsafe.getObject(paramT, l), paramZzkm, zzag(m));
                                            continue;
                                            zzjc.zza(zzaae[m], (List)localUnsafe.getObject(paramT, l), paramZzkm);
                                            continue;
                                            zzjc.zzn(zzaae[m], (List)localUnsafe.getObject(paramT, l), paramZzkm, false);
                                            break label1947;
                                            zzjc.zzk(zzaae[m], (List)localUnsafe.getObject(paramT, l), paramZzkm, false);
                                            break label1947;
                                            zzjc.zzf(zzaae[m], (List)localUnsafe.getObject(paramT, l), paramZzkm, false);
                                            break label1947;
                                            zzjc.zzh(zzaae[m], (List)localUnsafe.getObject(paramT, l), paramZzkm, false);
                                            break label1947;
                                            zzjc.zzd(zzaae[m], (List)localUnsafe.getObject(paramT, l), paramZzkm, false);
                                            break label1947;
                                            zzjc.zzc(zzaae[m], (List)localUnsafe.getObject(paramT, l), paramZzkm, false);
                                            break label1947;
                                            zzjc.zzb(zzaae[m], (List)localUnsafe.getObject(paramT, l), paramZzkm, false);
                                            break label1947;
                                            zzjc.zza(zzaae[m], (List)localUnsafe.getObject(paramT, l), paramZzkm, false);
                                            label1947:
                                            break;
                                            if ((n & j) != 0)
                                            {
                                              paramZzkm.zzb(i3, localUnsafe.getObject(paramT, l), zzag(m));
                                              break;
                                              if ((n & j) != 0)
                                              {
                                                paramZzkm.zzb(i3, localUnsafe.getLong(paramT, l));
                                                break;
                                                if ((n & j) != 0)
                                                {
                                                  paramZzkm.zzg(i3, localUnsafe.getInt(paramT, l));
                                                  break;
                                                  if ((n & j) != 0)
                                                  {
                                                    paramZzkm.zzj(i3, localUnsafe.getLong(paramT, l));
                                                    break;
                                                    if ((n & j) != 0)
                                                    {
                                                      paramZzkm.zzo(i3, localUnsafe.getInt(paramT, l));
                                                      break;
                                                      if ((n & j) != 0)
                                                      {
                                                        paramZzkm.zzp(i3, localUnsafe.getInt(paramT, l));
                                                        break;
                                                        if ((n & j) != 0)
                                                        {
                                                          paramZzkm.zzf(i3, localUnsafe.getInt(paramT, l));
                                                          break;
                                                          if ((n & j) != 0)
                                                          {
                                                            paramZzkm.zza(i3, (zzfx)localUnsafe.getObject(paramT, l));
                                                            break;
                                                            if ((n & j) != 0)
                                                            {
                                                              paramZzkm.zza(i3, localUnsafe.getObject(paramT, l), zzag(m));
                                                              break;
                                                              if ((n & j) != 0)
                                                              {
                                                                zza(i3, localUnsafe.getObject(paramT, l), paramZzkm);
                                                                break;
                                                                if ((n & j) != 0)
                                                                {
                                                                  paramZzkm.zza(i3, zzjy.zzl(paramT, l));
                                                                  break;
                                                                  if ((n & j) != 0)
                                                                  {
                                                                    paramZzkm.zzh(i3, localUnsafe.getInt(paramT, l));
                                                                    break;
                                                                    if ((n & j) != 0)
                                                                    {
                                                                      paramZzkm.zzc(i3, localUnsafe.getLong(paramT, l));
                                                                      break;
                                                                      if ((n & j) != 0)
                                                                      {
                                                                        paramZzkm.zze(i3, localUnsafe.getInt(paramT, l));
                                                                        break;
                                                                        if ((n & j) != 0)
                                                                        {
                                                                          paramZzkm.zza(i3, localUnsafe.getLong(paramT, l));
                                                                          break;
                                                                          if ((n & j) != 0)
                                                                          {
                                                                            paramZzkm.zzi(i3, localUnsafe.getLong(paramT, l));
                                                                            break;
                                                                            if ((n & j) != 0)
                                                                            {
                                                                              paramZzkm.zza(i3, zzjy.zzm(paramT, l));
                                                                              break;
                                                                              if ((n & j) != 0) {
                                                                                paramZzkm.zza(i3, zzjy.zzn(paramT, l));
                                                                              }
                                                                            }
                                                                          }
                                                                        }
                                                                      }
                                                                    }
                                                                  }
                                                                }
                                                              }
                                                            }
                                                          }
                                                        }
                                                      }
                                                    }
                                                  }
                                                }
                                              }
                                            }
                                          }
                                        }
                                      }
                                    }
                                  }
                                }
                              }
                            }
                          }
                        }
                      }
                    }
                  }
                }
              }
            }
          }
        }
      }
      m += 3;
    }
    while (localObject2 != null)
    {
      zzaab.zza(paramZzkm, (Map.Entry)localObject2);
      if (localIterator.hasNext()) {
        localObject2 = (Map.Entry)localIterator.next();
      } else {
        localObject2 = null;
      }
    }
    zza(zzzz, paramT, paramZzkm);
  }
  
  private final void zzb(T paramT1, T paramT2, int paramInt)
  {
    int i = zzai(paramInt);
    int j = zzaae[paramInt];
    long l = i & 0xFFFFF;
    if (!zza(paramT2, j, paramInt)) {
      return;
    }
    Object localObject = null;
    if (zza(paramT1, j, paramInt)) {
      localObject = zzjy.zzo(paramT1, l);
    }
    paramT2 = zzjy.zzo(paramT2, l);
    if ((localObject != null) && (paramT2 != null))
    {
      zzjy.zza(paramT1, l, zzhc.zzb(localObject, paramT2));
      zzb(paramT1, j, paramInt);
      return;
    }
    if (paramT2 != null)
    {
      zzjy.zza(paramT1, l, paramT2);
      zzb(paramT1, j, paramInt);
    }
  }
  
  private final boolean zzb(T paramT, int paramInt)
  {
    int i = zzaj(paramInt);
    long l = i & 0xFFFFF;
    if (l == 1048575L)
    {
      paramInt = zzai(paramInt);
      l = paramInt & 0xFFFFF;
      switch ((paramInt & 0xFF00000) >>> 20)
      {
      default: 
        throw new IllegalArgumentException();
      case 17: 
        return zzjy.zzo(paramT, l) != null;
      case 16: 
        return zzjy.zzk(paramT, l) != 0L;
      case 15: 
        return zzjy.zzj(paramT, l) != 0;
      case 14: 
        return zzjy.zzk(paramT, l) != 0L;
      case 13: 
        return zzjy.zzj(paramT, l) != 0;
      case 12: 
        return zzjy.zzj(paramT, l) != 0;
      case 11: 
        return zzjy.zzj(paramT, l) != 0;
      case 10: 
        return !zzfx.zzub.equals(zzjy.zzo(paramT, l));
      case 9: 
        return zzjy.zzo(paramT, l) != null;
      case 8: 
        paramT = zzjy.zzo(paramT, l);
        if ((paramT instanceof String)) {
          return !((String)paramT).isEmpty();
        }
        if ((paramT instanceof zzfx)) {
          return !zzfx.zzub.equals(paramT);
        }
        throw new IllegalArgumentException();
      case 7: 
        return zzjy.zzl(paramT, l);
      case 6: 
        return zzjy.zzj(paramT, l) != 0;
      case 5: 
        return zzjy.zzk(paramT, l) != 0L;
      case 4: 
        return zzjy.zzj(paramT, l) != 0;
      case 3: 
        return zzjy.zzk(paramT, l) != 0L;
      case 2: 
        return zzjy.zzk(paramT, l) != 0L;
      case 1: 
        return zzjy.zzm(paramT, l) != 0.0F;
      }
      return zzjy.zzn(paramT, l) != 0.0D;
    }
    return (zzjy.zzj(paramT, l) & 1 << (i >>> 20)) != 0;
  }
  
  private final void zzc(T paramT, int paramInt)
  {
    paramInt = zzaj(paramInt);
    long l = 0xFFFFF & paramInt;
    if (l == 1048575L) {
      return;
    }
    zzjy.zza(paramT, l, 1 << (paramInt >>> 20) | zzjy.zzj(paramT, l));
  }
  
  private final boolean zzc(T paramT1, T paramT2, int paramInt)
  {
    return zzb(paramT1, paramInt) == zzb(paramT2, paramInt);
  }
  
  private static List<?> zzd(Object paramObject, long paramLong)
  {
    return (List)zzjy.zzo(paramObject, paramLong);
  }
  
  private static <T> double zze(T paramT, long paramLong)
  {
    return ((Double)zzjy.zzo(paramT, paramLong)).doubleValue();
  }
  
  private static <T> float zzf(T paramT, long paramLong)
  {
    return ((Float)zzjy.zzo(paramT, paramLong)).floatValue();
  }
  
  private static <T> int zzg(T paramT, long paramLong)
  {
    return ((Integer)zzjy.zzo(paramT, paramLong)).intValue();
  }
  
  private static <T> long zzh(T paramT, long paramLong)
  {
    return ((Long)zzjy.zzo(paramT, paramLong)).longValue();
  }
  
  private static <T> boolean zzi(T paramT, long paramLong)
  {
    return ((Boolean)zzjy.zzo(paramT, paramLong)).booleanValue();
  }
  
  /* Error */
  public final boolean equals(T paramT1, T paramT2)
  {
    // Byte code:
    //   0: aload_0
    //   1: getfield 58	com/google/android/gms/internal/fitness/zzio:zzaae	[I
    //   4: arraylength
    //   5: istore 4
    //   7: iconst_0
    //   8: istore_3
    //   9: iconst_1
    //   10: istore 6
    //   12: iload_3
    //   13: iload 4
    //   15: if_icmpge +955 -> 970
    //   18: aload_0
    //   19: iload_3
    //   20: invokespecial 273	com/google/android/gms/internal/fitness/zzio:zzai	(I)I
    //   23: istore 5
    //   25: iload 5
    //   27: ldc -90
    //   29: iand
    //   30: i2l
    //   31: lstore 7
    //   33: iload 5
    //   35: ldc_w 351
    //   38: iand
    //   39: bipush 20
    //   41: iushr
    //   42: tableswitch	default:+290->332, 0:+879->921, 1:+845->887, 2:+816->858, 3:+787->829, 4:+759->801, 5:+730->772, 6:+702->744, 7:+674->716, 8:+643->685, 9:+612->654, 10:+581->623, 11:+553->595, 12:+525->567, 13:+497->539, 14:+468->510, 15:+440->482, 16:+411->453, 17:+380->422, 18:+360->402, 19:+360->402, 20:+360->402, 21:+360->402, 22:+360->402, 23:+360->402, 24:+360->402, 25:+360->402, 26:+360->402, 27:+360->402, 28:+360->402, 29:+360->402, 30:+360->402, 31:+360->402, 32:+360->402, 33:+360->402, 34:+360->402, 35:+360->402, 36:+360->402, 37:+360->402, 38:+360->402, 39:+360->402, 40:+360->402, 41:+360->402, 42:+360->402, 43:+360->402, 44:+360->402, 45:+360->402, 46:+360->402, 47:+360->402, 48:+360->402, 49:+360->402, 50:+340->382, 51:+293->335, 52:+293->335, 53:+293->335, 54:+293->335, 55:+293->335, 56:+293->335, 57:+293->335, 58:+293->335, 59:+293->335, 60:+293->335, 61:+293->335, 62:+293->335, 63:+293->335, 64:+293->335, 65:+293->335, 66:+293->335, 67:+293->335, 68:+293->335
    //   332: goto +624 -> 956
    //   335: aload_0
    //   336: iload_3
    //   337: invokespecial 297	com/google/android/gms/internal/fitness/zzio:zzaj	(I)I
    //   340: ldc -90
    //   342: iand
    //   343: i2l
    //   344: lstore 9
    //   346: aload_1
    //   347: lload 9
    //   349: invokestatic 300	com/google/android/gms/internal/fitness/zzjy:zzj	(Ljava/lang/Object;J)I
    //   352: aload_2
    //   353: lload 9
    //   355: invokestatic 300	com/google/android/gms/internal/fitness/zzjy:zzj	(Ljava/lang/Object;J)I
    //   358: if_icmpne +595 -> 953
    //   361: aload_1
    //   362: lload 7
    //   364: invokestatic 280	com/google/android/gms/internal/fitness/zzjy:zzo	(Ljava/lang/Object;J)Ljava/lang/Object;
    //   367: aload_2
    //   368: lload 7
    //   370: invokestatic 280	com/google/android/gms/internal/fitness/zzjy:zzo	(Ljava/lang/Object;J)Ljava/lang/Object;
    //   373: invokestatic 545	com/google/android/gms/internal/fitness/zzjc:zze	(Ljava/lang/Object;Ljava/lang/Object;)Z
    //   376: ifne +580 -> 956
    //   379: goto +574 -> 953
    //   382: aload_1
    //   383: lload 7
    //   385: invokestatic 280	com/google/android/gms/internal/fitness/zzjy:zzo	(Ljava/lang/Object;J)Ljava/lang/Object;
    //   388: aload_2
    //   389: lload 7
    //   391: invokestatic 280	com/google/android/gms/internal/fitness/zzjy:zzo	(Ljava/lang/Object;J)Ljava/lang/Object;
    //   394: invokestatic 545	com/google/android/gms/internal/fitness/zzjc:zze	(Ljava/lang/Object;Ljava/lang/Object;)Z
    //   397: istore 6
    //   399: goto +557 -> 956
    //   402: aload_1
    //   403: lload 7
    //   405: invokestatic 280	com/google/android/gms/internal/fitness/zzjy:zzo	(Ljava/lang/Object;J)Ljava/lang/Object;
    //   408: aload_2
    //   409: lload 7
    //   411: invokestatic 280	com/google/android/gms/internal/fitness/zzjy:zzo	(Ljava/lang/Object;J)Ljava/lang/Object;
    //   414: invokestatic 545	com/google/android/gms/internal/fitness/zzjc:zze	(Ljava/lang/Object;Ljava/lang/Object;)Z
    //   417: istore 6
    //   419: goto +537 -> 956
    //   422: aload_0
    //   423: aload_1
    //   424: aload_2
    //   425: iload_3
    //   426: invokespecial 547	com/google/android/gms/internal/fitness/zzio:zzc	(Ljava/lang/Object;Ljava/lang/Object;I)Z
    //   429: ifeq +524 -> 953
    //   432: aload_1
    //   433: lload 7
    //   435: invokestatic 280	com/google/android/gms/internal/fitness/zzjy:zzo	(Ljava/lang/Object;J)Ljava/lang/Object;
    //   438: aload_2
    //   439: lload 7
    //   441: invokestatic 280	com/google/android/gms/internal/fitness/zzjy:zzo	(Ljava/lang/Object;J)Ljava/lang/Object;
    //   444: invokestatic 545	com/google/android/gms/internal/fitness/zzjc:zze	(Ljava/lang/Object;Ljava/lang/Object;)Z
    //   447: ifne +509 -> 956
    //   450: goto +503 -> 953
    //   453: aload_0
    //   454: aload_1
    //   455: aload_2
    //   456: iload_3
    //   457: invokespecial 547	com/google/android/gms/internal/fitness/zzio:zzc	(Ljava/lang/Object;Ljava/lang/Object;I)Z
    //   460: ifeq +493 -> 953
    //   463: aload_1
    //   464: lload 7
    //   466: invokestatic 497	com/google/android/gms/internal/fitness/zzjy:zzk	(Ljava/lang/Object;J)J
    //   469: aload_2
    //   470: lload 7
    //   472: invokestatic 497	com/google/android/gms/internal/fitness/zzjy:zzk	(Ljava/lang/Object;J)J
    //   475: lcmp
    //   476: ifeq +480 -> 956
    //   479: goto +474 -> 953
    //   482: aload_0
    //   483: aload_1
    //   484: aload_2
    //   485: iload_3
    //   486: invokespecial 547	com/google/android/gms/internal/fitness/zzio:zzc	(Ljava/lang/Object;Ljava/lang/Object;I)Z
    //   489: ifeq +464 -> 953
    //   492: aload_1
    //   493: lload 7
    //   495: invokestatic 300	com/google/android/gms/internal/fitness/zzjy:zzj	(Ljava/lang/Object;J)I
    //   498: aload_2
    //   499: lload 7
    //   501: invokestatic 300	com/google/android/gms/internal/fitness/zzjy:zzj	(Ljava/lang/Object;J)I
    //   504: if_icmpeq +452 -> 956
    //   507: goto +446 -> 953
    //   510: aload_0
    //   511: aload_1
    //   512: aload_2
    //   513: iload_3
    //   514: invokespecial 547	com/google/android/gms/internal/fitness/zzio:zzc	(Ljava/lang/Object;Ljava/lang/Object;I)Z
    //   517: ifeq +436 -> 953
    //   520: aload_1
    //   521: lload 7
    //   523: invokestatic 497	com/google/android/gms/internal/fitness/zzjy:zzk	(Ljava/lang/Object;J)J
    //   526: aload_2
    //   527: lload 7
    //   529: invokestatic 497	com/google/android/gms/internal/fitness/zzjy:zzk	(Ljava/lang/Object;J)J
    //   532: lcmp
    //   533: ifeq +423 -> 956
    //   536: goto +417 -> 953
    //   539: aload_0
    //   540: aload_1
    //   541: aload_2
    //   542: iload_3
    //   543: invokespecial 547	com/google/android/gms/internal/fitness/zzio:zzc	(Ljava/lang/Object;Ljava/lang/Object;I)Z
    //   546: ifeq +407 -> 953
    //   549: aload_1
    //   550: lload 7
    //   552: invokestatic 300	com/google/android/gms/internal/fitness/zzjy:zzj	(Ljava/lang/Object;J)I
    //   555: aload_2
    //   556: lload 7
    //   558: invokestatic 300	com/google/android/gms/internal/fitness/zzjy:zzj	(Ljava/lang/Object;J)I
    //   561: if_icmpeq +395 -> 956
    //   564: goto +389 -> 953
    //   567: aload_0
    //   568: aload_1
    //   569: aload_2
    //   570: iload_3
    //   571: invokespecial 547	com/google/android/gms/internal/fitness/zzio:zzc	(Ljava/lang/Object;Ljava/lang/Object;I)Z
    //   574: ifeq +379 -> 953
    //   577: aload_1
    //   578: lload 7
    //   580: invokestatic 300	com/google/android/gms/internal/fitness/zzjy:zzj	(Ljava/lang/Object;J)I
    //   583: aload_2
    //   584: lload 7
    //   586: invokestatic 300	com/google/android/gms/internal/fitness/zzjy:zzj	(Ljava/lang/Object;J)I
    //   589: if_icmpeq +367 -> 956
    //   592: goto +361 -> 953
    //   595: aload_0
    //   596: aload_1
    //   597: aload_2
    //   598: iload_3
    //   599: invokespecial 547	com/google/android/gms/internal/fitness/zzio:zzc	(Ljava/lang/Object;Ljava/lang/Object;I)Z
    //   602: ifeq +351 -> 953
    //   605: aload_1
    //   606: lload 7
    //   608: invokestatic 300	com/google/android/gms/internal/fitness/zzjy:zzj	(Ljava/lang/Object;J)I
    //   611: aload_2
    //   612: lload 7
    //   614: invokestatic 300	com/google/android/gms/internal/fitness/zzjy:zzj	(Ljava/lang/Object;J)I
    //   617: if_icmpeq +339 -> 956
    //   620: goto +333 -> 953
    //   623: aload_0
    //   624: aload_1
    //   625: aload_2
    //   626: iload_3
    //   627: invokespecial 547	com/google/android/gms/internal/fitness/zzio:zzc	(Ljava/lang/Object;Ljava/lang/Object;I)Z
    //   630: ifeq +323 -> 953
    //   633: aload_1
    //   634: lload 7
    //   636: invokestatic 280	com/google/android/gms/internal/fitness/zzjy:zzo	(Ljava/lang/Object;J)Ljava/lang/Object;
    //   639: aload_2
    //   640: lload 7
    //   642: invokestatic 280	com/google/android/gms/internal/fitness/zzjy:zzo	(Ljava/lang/Object;J)Ljava/lang/Object;
    //   645: invokestatic 545	com/google/android/gms/internal/fitness/zzjc:zze	(Ljava/lang/Object;Ljava/lang/Object;)Z
    //   648: ifne +308 -> 956
    //   651: goto +302 -> 953
    //   654: aload_0
    //   655: aload_1
    //   656: aload_2
    //   657: iload_3
    //   658: invokespecial 547	com/google/android/gms/internal/fitness/zzio:zzc	(Ljava/lang/Object;Ljava/lang/Object;I)Z
    //   661: ifeq +292 -> 953
    //   664: aload_1
    //   665: lload 7
    //   667: invokestatic 280	com/google/android/gms/internal/fitness/zzjy:zzo	(Ljava/lang/Object;J)Ljava/lang/Object;
    //   670: aload_2
    //   671: lload 7
    //   673: invokestatic 280	com/google/android/gms/internal/fitness/zzjy:zzo	(Ljava/lang/Object;J)Ljava/lang/Object;
    //   676: invokestatic 545	com/google/android/gms/internal/fitness/zzjc:zze	(Ljava/lang/Object;Ljava/lang/Object;)Z
    //   679: ifne +277 -> 956
    //   682: goto +271 -> 953
    //   685: aload_0
    //   686: aload_1
    //   687: aload_2
    //   688: iload_3
    //   689: invokespecial 547	com/google/android/gms/internal/fitness/zzio:zzc	(Ljava/lang/Object;Ljava/lang/Object;I)Z
    //   692: ifeq +261 -> 953
    //   695: aload_1
    //   696: lload 7
    //   698: invokestatic 280	com/google/android/gms/internal/fitness/zzjy:zzo	(Ljava/lang/Object;J)Ljava/lang/Object;
    //   701: aload_2
    //   702: lload 7
    //   704: invokestatic 280	com/google/android/gms/internal/fitness/zzjy:zzo	(Ljava/lang/Object;J)Ljava/lang/Object;
    //   707: invokestatic 545	com/google/android/gms/internal/fitness/zzjc:zze	(Ljava/lang/Object;Ljava/lang/Object;)Z
    //   710: ifne +246 -> 956
    //   713: goto +240 -> 953
    //   716: aload_0
    //   717: aload_1
    //   718: aload_2
    //   719: iload_3
    //   720: invokespecial 547	com/google/android/gms/internal/fitness/zzio:zzc	(Ljava/lang/Object;Ljava/lang/Object;I)Z
    //   723: ifeq +230 -> 953
    //   726: aload_1
    //   727: lload 7
    //   729: invokestatic 481	com/google/android/gms/internal/fitness/zzjy:zzl	(Ljava/lang/Object;J)Z
    //   732: aload_2
    //   733: lload 7
    //   735: invokestatic 481	com/google/android/gms/internal/fitness/zzjy:zzl	(Ljava/lang/Object;J)Z
    //   738: if_icmpeq +218 -> 956
    //   741: goto +212 -> 953
    //   744: aload_0
    //   745: aload_1
    //   746: aload_2
    //   747: iload_3
    //   748: invokespecial 547	com/google/android/gms/internal/fitness/zzio:zzc	(Ljava/lang/Object;Ljava/lang/Object;I)Z
    //   751: ifeq +202 -> 953
    //   754: aload_1
    //   755: lload 7
    //   757: invokestatic 300	com/google/android/gms/internal/fitness/zzjy:zzj	(Ljava/lang/Object;J)I
    //   760: aload_2
    //   761: lload 7
    //   763: invokestatic 300	com/google/android/gms/internal/fitness/zzjy:zzj	(Ljava/lang/Object;J)I
    //   766: if_icmpeq +190 -> 956
    //   769: goto +184 -> 953
    //   772: aload_0
    //   773: aload_1
    //   774: aload_2
    //   775: iload_3
    //   776: invokespecial 547	com/google/android/gms/internal/fitness/zzio:zzc	(Ljava/lang/Object;Ljava/lang/Object;I)Z
    //   779: ifeq +174 -> 953
    //   782: aload_1
    //   783: lload 7
    //   785: invokestatic 497	com/google/android/gms/internal/fitness/zzjy:zzk	(Ljava/lang/Object;J)J
    //   788: aload_2
    //   789: lload 7
    //   791: invokestatic 497	com/google/android/gms/internal/fitness/zzjy:zzk	(Ljava/lang/Object;J)J
    //   794: lcmp
    //   795: ifeq +161 -> 956
    //   798: goto +155 -> 953
    //   801: aload_0
    //   802: aload_1
    //   803: aload_2
    //   804: iload_3
    //   805: invokespecial 547	com/google/android/gms/internal/fitness/zzio:zzc	(Ljava/lang/Object;Ljava/lang/Object;I)Z
    //   808: ifeq +145 -> 953
    //   811: aload_1
    //   812: lload 7
    //   814: invokestatic 300	com/google/android/gms/internal/fitness/zzjy:zzj	(Ljava/lang/Object;J)I
    //   817: aload_2
    //   818: lload 7
    //   820: invokestatic 300	com/google/android/gms/internal/fitness/zzjy:zzj	(Ljava/lang/Object;J)I
    //   823: if_icmpeq +133 -> 956
    //   826: goto +127 -> 953
    //   829: aload_0
    //   830: aload_1
    //   831: aload_2
    //   832: iload_3
    //   833: invokespecial 547	com/google/android/gms/internal/fitness/zzio:zzc	(Ljava/lang/Object;Ljava/lang/Object;I)Z
    //   836: ifeq +117 -> 953
    //   839: aload_1
    //   840: lload 7
    //   842: invokestatic 497	com/google/android/gms/internal/fitness/zzjy:zzk	(Ljava/lang/Object;J)J
    //   845: aload_2
    //   846: lload 7
    //   848: invokestatic 497	com/google/android/gms/internal/fitness/zzjy:zzk	(Ljava/lang/Object;J)J
    //   851: lcmp
    //   852: ifeq +104 -> 956
    //   855: goto +98 -> 953
    //   858: aload_0
    //   859: aload_1
    //   860: aload_2
    //   861: iload_3
    //   862: invokespecial 547	com/google/android/gms/internal/fitness/zzio:zzc	(Ljava/lang/Object;Ljava/lang/Object;I)Z
    //   865: ifeq +88 -> 953
    //   868: aload_1
    //   869: lload 7
    //   871: invokestatic 497	com/google/android/gms/internal/fitness/zzjy:zzk	(Ljava/lang/Object;J)J
    //   874: aload_2
    //   875: lload 7
    //   877: invokestatic 497	com/google/android/gms/internal/fitness/zzjy:zzk	(Ljava/lang/Object;J)J
    //   880: lcmp
    //   881: ifeq +75 -> 956
    //   884: goto +69 -> 953
    //   887: aload_0
    //   888: aload_1
    //   889: aload_2
    //   890: iload_3
    //   891: invokespecial 547	com/google/android/gms/internal/fitness/zzio:zzc	(Ljava/lang/Object;Ljava/lang/Object;I)Z
    //   894: ifeq +59 -> 953
    //   897: aload_1
    //   898: lload 7
    //   900: invokestatic 483	com/google/android/gms/internal/fitness/zzjy:zzm	(Ljava/lang/Object;J)F
    //   903: invokestatic 551	java/lang/Float:floatToIntBits	(F)I
    //   906: aload_2
    //   907: lload 7
    //   909: invokestatic 483	com/google/android/gms/internal/fitness/zzjy:zzm	(Ljava/lang/Object;J)F
    //   912: invokestatic 551	java/lang/Float:floatToIntBits	(F)I
    //   915: if_icmpeq +41 -> 956
    //   918: goto +35 -> 953
    //   921: aload_0
    //   922: aload_1
    //   923: aload_2
    //   924: iload_3
    //   925: invokespecial 547	com/google/android/gms/internal/fitness/zzio:zzc	(Ljava/lang/Object;Ljava/lang/Object;I)Z
    //   928: ifeq +25 -> 953
    //   931: aload_1
    //   932: lload 7
    //   934: invokestatic 485	com/google/android/gms/internal/fitness/zzjy:zzn	(Ljava/lang/Object;J)D
    //   937: invokestatic 555	java/lang/Double:doubleToLongBits	(D)J
    //   940: aload_2
    //   941: lload 7
    //   943: invokestatic 485	com/google/android/gms/internal/fitness/zzjy:zzn	(Ljava/lang/Object;J)D
    //   946: invokestatic 555	java/lang/Double:doubleToLongBits	(D)J
    //   949: lcmp
    //   950: ifeq +6 -> 956
    //   953: iconst_0
    //   954: istore 6
    //   956: iload 6
    //   958: ifne +5 -> 963
    //   961: iconst_0
    //   962: ireturn
    //   963: iload_3
    //   964: iconst_3
    //   965: iadd
    //   966: istore_3
    //   967: goto -958 -> 9
    //   970: aload_0
    //   971: getfield 92	com/google/android/gms/internal/fitness/zzio:zzzz	Lcom/google/android/gms/internal/fitness/zzjs;
    //   974: aload_1
    //   975: invokevirtual 108	com/google/android/gms/internal/fitness/zzjs:zzo	(Ljava/lang/Object;)Ljava/lang/Object;
    //   978: aload_0
    //   979: getfield 92	com/google/android/gms/internal/fitness/zzio:zzzz	Lcom/google/android/gms/internal/fitness/zzjs;
    //   982: aload_2
    //   983: invokevirtual 108	com/google/android/gms/internal/fitness/zzjs:zzo	(Ljava/lang/Object;)Ljava/lang/Object;
    //   986: invokevirtual 556	java/lang/Object:equals	(Ljava/lang/Object;)Z
    //   989: ifne +5 -> 994
    //   992: iconst_0
    //   993: ireturn
    //   994: aload_0
    //   995: getfield 78	com/google/android/gms/internal/fitness/zzio:zzaaa	Z
    //   998: ifeq +23 -> 1021
    //   1001: aload_0
    //   1002: getfield 94	com/google/android/gms/internal/fitness/zzio:zzaab	Lcom/google/android/gms/internal/fitness/zzgo;
    //   1005: aload_1
    //   1006: invokevirtual 326	com/google/android/gms/internal/fitness/zzgo:zzc	(Ljava/lang/Object;)Lcom/google/android/gms/internal/fitness/zzgt;
    //   1009: aload_0
    //   1010: getfield 94	com/google/android/gms/internal/fitness/zzio:zzaab	Lcom/google/android/gms/internal/fitness/zzgo;
    //   1013: aload_2
    //   1014: invokevirtual 326	com/google/android/gms/internal/fitness/zzgo:zzc	(Ljava/lang/Object;)Lcom/google/android/gms/internal/fitness/zzgt;
    //   1017: invokevirtual 557	com/google/android/gms/internal/fitness/zzgt:equals	(Ljava/lang/Object;)Z
    //   1020: ireturn
    //   1021: iconst_1
    //   1022: ireturn
    // Local variable table:
    //   start	length	slot	name	signature
    //   0	1023	0	this	zzio
    //   0	1023	1	paramT1	T
    //   0	1023	2	paramT2	T
    //   8	959	3	i	int
    //   5	11	4	j	int
    //   23	16	5	k	int
    //   10	947	6	bool	boolean
    //   31	911	7	l1	long
    //   344	10	9	l2	long
  }
  
  public final int hashCode(T paramT)
  {
    int m = zzaae.length;
    int k = 0;
    for (int j = 0; k < m; j = i)
    {
      int i1 = zzai(k);
      int n = zzaae[k];
      long l = 0xFFFFF & i1;
      i = 37;
      Object localObject;
      switch ((i1 & 0xFF00000) >>> 20)
      {
      default: 
        i = j;
        break;
      case 68: 
        i = j;
        if (!zza(paramT, n, k)) {
          break label1289;
        }
        localObject = zzjy.zzo(paramT, l);
        i = j * 53;
        j = localObject.hashCode();
        break;
      case 67: 
        i = j;
        if (!zza(paramT, n, k)) {
          break label1289;
        }
        i = j * 53;
        j = zzhc.zzj(zzh(paramT, l));
        break;
      case 66: 
        i = j;
        if (!zza(paramT, n, k)) {
          break label1289;
        }
        i = j * 53;
        j = zzg(paramT, l);
        break;
      case 65: 
        i = j;
        if (!zza(paramT, n, k)) {
          break label1289;
        }
        i = j * 53;
        j = zzhc.zzj(zzh(paramT, l));
        break;
      case 64: 
        i = j;
        if (!zza(paramT, n, k)) {
          break label1289;
        }
        i = j * 53;
        j = zzg(paramT, l);
        break;
      case 63: 
        i = j;
        if (!zza(paramT, n, k)) {
          break label1289;
        }
        i = j * 53;
        j = zzg(paramT, l);
        break;
      case 62: 
        i = j;
        if (!zza(paramT, n, k)) {
          break label1289;
        }
        i = j * 53;
        j = zzg(paramT, l);
        break;
      case 61: 
        i = j;
        if (!zza(paramT, n, k)) {
          break label1289;
        }
        i = j * 53;
        j = zzjy.zzo(paramT, l).hashCode();
        break;
      case 60: 
        i = j;
        if (!zza(paramT, n, k)) {
          break label1289;
        }
        localObject = zzjy.zzo(paramT, l);
        i = j * 53;
        j = localObject.hashCode();
        break;
      case 59: 
        i = j;
        if (!zza(paramT, n, k)) {
          break label1289;
        }
        i = j * 53;
        j = ((String)zzjy.zzo(paramT, l)).hashCode();
        break;
      case 58: 
        i = j;
        if (!zza(paramT, n, k)) {
          break label1289;
        }
        i = j * 53;
        j = zzhc.zzc(zzi(paramT, l));
        break;
      case 57: 
        i = j;
        if (!zza(paramT, n, k)) {
          break label1289;
        }
        i = j * 53;
        j = zzg(paramT, l);
        break;
      case 56: 
        i = j;
        if (!zza(paramT, n, k)) {
          break label1289;
        }
        i = j * 53;
        j = zzhc.zzj(zzh(paramT, l));
        break;
      case 55: 
        i = j;
        if (!zza(paramT, n, k)) {
          break label1289;
        }
        i = j * 53;
        j = zzg(paramT, l);
        break;
      case 54: 
        i = j;
        if (!zza(paramT, n, k)) {
          break label1289;
        }
        i = j * 53;
        j = zzhc.zzj(zzh(paramT, l));
        break;
      case 53: 
        i = j;
        if (!zza(paramT, n, k)) {
          break label1289;
        }
        i = j * 53;
        j = zzhc.zzj(zzh(paramT, l));
        break;
      case 52: 
        i = j;
        if (!zza(paramT, n, k)) {
          break label1289;
        }
        i = j * 53;
        j = Float.floatToIntBits(zzf(paramT, l));
        break;
      case 51: 
        i = j;
        if (!zza(paramT, n, k)) {
          break label1289;
        }
        i = j * 53;
        j = zzhc.zzj(Double.doubleToLongBits(zze(paramT, l)));
        break;
      case 50: 
        i = j * 53;
        j = zzjy.zzo(paramT, l).hashCode();
        break;
      case 18: 
      case 19: 
      case 20: 
      case 21: 
      case 22: 
      case 23: 
      case 24: 
      case 25: 
      case 26: 
      case 27: 
      case 28: 
      case 29: 
      case 30: 
      case 31: 
      case 32: 
      case 33: 
      case 34: 
      case 35: 
      case 36: 
      case 37: 
      case 38: 
      case 39: 
      case 40: 
      case 41: 
      case 42: 
      case 43: 
      case 44: 
      case 45: 
      case 46: 
      case 47: 
      case 48: 
      case 49: 
        i = j * 53;
        j = zzjy.zzo(paramT, l).hashCode();
        break;
      case 17: 
        localObject = zzjy.zzo(paramT, l);
        if (localObject != null) {
          i = localObject.hashCode();
        }
        break;
      case 16: 
        i = j * 53;
        j = zzhc.zzj(zzjy.zzk(paramT, l));
        break;
      case 15: 
        i = j * 53;
        j = zzjy.zzj(paramT, l);
        break;
      case 14: 
        i = j * 53;
        j = zzhc.zzj(zzjy.zzk(paramT, l));
        break;
      case 13: 
        i = j * 53;
        j = zzjy.zzj(paramT, l);
        break;
      case 12: 
        i = j * 53;
        j = zzjy.zzj(paramT, l);
        break;
      case 11: 
        i = j * 53;
        j = zzjy.zzj(paramT, l);
        break;
      case 10: 
        i = j * 53;
        j = zzjy.zzo(paramT, l).hashCode();
        break;
      case 9: 
        localObject = zzjy.zzo(paramT, l);
        if (localObject != null) {
          i = localObject.hashCode();
        }
        i = j * 53 + i;
        break;
      case 8: 
        i = j * 53;
        j = ((String)zzjy.zzo(paramT, l)).hashCode();
        break;
      case 7: 
        i = j * 53;
        j = zzhc.zzc(zzjy.zzl(paramT, l));
        break;
      case 6: 
        i = j * 53;
        j = zzjy.zzj(paramT, l);
        break;
      case 5: 
        i = j * 53;
        j = zzhc.zzj(zzjy.zzk(paramT, l));
        break;
      case 4: 
        i = j * 53;
        j = zzjy.zzj(paramT, l);
        break;
      case 3: 
        i = j * 53;
        j = zzhc.zzj(zzjy.zzk(paramT, l));
        break;
      case 2: 
        i = j * 53;
        j = zzhc.zzj(zzjy.zzk(paramT, l));
        break;
      case 1: 
        i = j * 53;
        j = Float.floatToIntBits(zzjy.zzm(paramT, l));
        break;
      }
      i = j * 53;
      j = zzhc.zzj(Double.doubleToLongBits(zzjy.zzn(paramT, l)));
      i += j;
      label1289:
      k += 3;
    }
    j = j * 53 + zzzz.zzo(paramT).hashCode();
    int i = j;
    if (zzaaa) {
      i = j * 53 + zzaab.zzc(paramT).hashCode();
    }
    return i;
  }
  
  public final void zza(T paramT, zzkm paramZzkm)
    throws IOException
  {
    Object localObject1;
    Iterator localIterator;
    label78:
    int i;
    Object localObject2;
    int j;
    int k;
    if (paramZzkm.zzbe() == zzkl.zzaeb)
    {
      zza(zzzz, paramT, paramZzkm);
      if (zzaaa)
      {
        localObject1 = zzaab.zzc(paramT);
        if (!zzvb.isEmpty())
        {
          localIterator = ((zzgt)localObject1).descendingIterator();
          localObject1 = (Map.Entry)localIterator.next();
          break label78;
        }
      }
      localIterator = null;
      localObject1 = localIterator;
      i = zzaae.length - 3;
      for (;;)
      {
        localObject2 = localObject1;
        if (i < 0) {
          break;
        }
        j = zzai(i);
        k = zzaae[i];
        while ((localObject1 != null) && (zzaab.zza((Map.Entry)localObject1) > k))
        {
          zzaab.zza(paramZzkm, (Map.Entry)localObject1);
          if (localIterator.hasNext()) {
            localObject1 = (Map.Entry)localIterator.next();
          } else {
            localObject1 = null;
          }
        }
        switch ((j & 0xFF00000) >>> 20)
        {
        default: 
          break;
        case 68: 
          if (zza(paramT, k, i)) {
            paramZzkm.zzb(k, zzjy.zzo(paramT, j & 0xFFFFF), zzag(i));
          }
          break;
        case 67: 
          if (zza(paramT, k, i)) {
            paramZzkm.zzb(k, zzh(paramT, j & 0xFFFFF));
          }
          break;
        case 66: 
          if (zza(paramT, k, i)) {
            paramZzkm.zzg(k, zzg(paramT, j & 0xFFFFF));
          }
          break;
        case 65: 
          if (zza(paramT, k, i)) {
            paramZzkm.zzj(k, zzh(paramT, j & 0xFFFFF));
          }
          break;
        case 64: 
          if (zza(paramT, k, i)) {
            paramZzkm.zzo(k, zzg(paramT, j & 0xFFFFF));
          }
          break;
        case 63: 
          if (zza(paramT, k, i)) {
            paramZzkm.zzp(k, zzg(paramT, j & 0xFFFFF));
          }
          break;
        case 62: 
          if (zza(paramT, k, i)) {
            paramZzkm.zzf(k, zzg(paramT, j & 0xFFFFF));
          }
          break;
        case 61: 
          if (zza(paramT, k, i)) {
            paramZzkm.zza(k, (zzfx)zzjy.zzo(paramT, j & 0xFFFFF));
          }
          break;
        case 60: 
          if (zza(paramT, k, i)) {
            paramZzkm.zza(k, zzjy.zzo(paramT, j & 0xFFFFF), zzag(i));
          }
          break;
        case 59: 
          if (zza(paramT, k, i)) {
            zza(k, zzjy.zzo(paramT, j & 0xFFFFF), paramZzkm);
          }
          break;
        case 58: 
          if (zza(paramT, k, i)) {
            paramZzkm.zza(k, zzi(paramT, j & 0xFFFFF));
          }
          break;
        case 57: 
          if (zza(paramT, k, i)) {
            paramZzkm.zzh(k, zzg(paramT, j & 0xFFFFF));
          }
          break;
        case 56: 
          if (zza(paramT, k, i)) {
            paramZzkm.zzc(k, zzh(paramT, j & 0xFFFFF));
          }
          break;
        case 55: 
          if (zza(paramT, k, i)) {
            paramZzkm.zze(k, zzg(paramT, j & 0xFFFFF));
          }
          break;
        case 54: 
          if (zza(paramT, k, i)) {
            paramZzkm.zza(k, zzh(paramT, j & 0xFFFFF));
          }
          break;
        case 53: 
          if (zza(paramT, k, i)) {
            paramZzkm.zzi(k, zzh(paramT, j & 0xFFFFF));
          }
          break;
        case 52: 
          if (zza(paramT, k, i)) {
            paramZzkm.zza(k, zzf(paramT, j & 0xFFFFF));
          }
          break;
        case 51: 
          if (zza(paramT, k, i)) {
            paramZzkm.zza(k, zze(paramT, j & 0xFFFFF));
          }
          break;
        case 50: 
          zza(paramZzkm, k, zzjy.zzo(paramT, j & 0xFFFFF), i);
          break;
        case 49: 
          zzjc.zzb(zzaae[i], (List)zzjy.zzo(paramT, j & 0xFFFFF), paramZzkm, zzag(i));
          break;
        case 48: 
          zzjc.zze(zzaae[i], (List)zzjy.zzo(paramT, j & 0xFFFFF), paramZzkm, true);
          break;
        case 47: 
          zzjc.zzj(zzaae[i], (List)zzjy.zzo(paramT, j & 0xFFFFF), paramZzkm, true);
          break;
        case 46: 
          zzjc.zzg(zzaae[i], (List)zzjy.zzo(paramT, j & 0xFFFFF), paramZzkm, true);
          break;
        case 45: 
          zzjc.zzl(zzaae[i], (List)zzjy.zzo(paramT, j & 0xFFFFF), paramZzkm, true);
          break;
        case 44: 
          zzjc.zzm(zzaae[i], (List)zzjy.zzo(paramT, j & 0xFFFFF), paramZzkm, true);
          break;
        case 43: 
          zzjc.zzi(zzaae[i], (List)zzjy.zzo(paramT, j & 0xFFFFF), paramZzkm, true);
          break;
        case 42: 
          zzjc.zzn(zzaae[i], (List)zzjy.zzo(paramT, j & 0xFFFFF), paramZzkm, true);
          break;
        case 41: 
          zzjc.zzk(zzaae[i], (List)zzjy.zzo(paramT, j & 0xFFFFF), paramZzkm, true);
          break;
        case 40: 
          zzjc.zzf(zzaae[i], (List)zzjy.zzo(paramT, j & 0xFFFFF), paramZzkm, true);
          break;
        case 39: 
          zzjc.zzh(zzaae[i], (List)zzjy.zzo(paramT, j & 0xFFFFF), paramZzkm, true);
          break;
        case 38: 
          zzjc.zzd(zzaae[i], (List)zzjy.zzo(paramT, j & 0xFFFFF), paramZzkm, true);
          break;
        case 37: 
          zzjc.zzc(zzaae[i], (List)zzjy.zzo(paramT, j & 0xFFFFF), paramZzkm, true);
          break;
        case 36: 
          zzjc.zzb(zzaae[i], (List)zzjy.zzo(paramT, j & 0xFFFFF), paramZzkm, true);
          break;
        case 35: 
          zzjc.zza(zzaae[i], (List)zzjy.zzo(paramT, j & 0xFFFFF), paramZzkm, true);
          break;
        case 34: 
          zzjc.zze(zzaae[i], (List)zzjy.zzo(paramT, j & 0xFFFFF), paramZzkm, false);
          break;
        case 33: 
          zzjc.zzj(zzaae[i], (List)zzjy.zzo(paramT, j & 0xFFFFF), paramZzkm, false);
          break;
        case 32: 
          zzjc.zzg(zzaae[i], (List)zzjy.zzo(paramT, j & 0xFFFFF), paramZzkm, false);
          break;
        case 31: 
          zzjc.zzl(zzaae[i], (List)zzjy.zzo(paramT, j & 0xFFFFF), paramZzkm, false);
          break;
        case 30: 
          zzjc.zzm(zzaae[i], (List)zzjy.zzo(paramT, j & 0xFFFFF), paramZzkm, false);
          break;
        case 29: 
          zzjc.zzi(zzaae[i], (List)zzjy.zzo(paramT, j & 0xFFFFF), paramZzkm, false);
          break;
        case 28: 
          zzjc.zzb(zzaae[i], (List)zzjy.zzo(paramT, j & 0xFFFFF), paramZzkm);
          break;
        case 27: 
          zzjc.zza(zzaae[i], (List)zzjy.zzo(paramT, j & 0xFFFFF), paramZzkm, zzag(i));
          break;
        case 26: 
          zzjc.zza(zzaae[i], (List)zzjy.zzo(paramT, j & 0xFFFFF), paramZzkm);
          break;
        case 25: 
          zzjc.zzn(zzaae[i], (List)zzjy.zzo(paramT, j & 0xFFFFF), paramZzkm, false);
          break;
        case 24: 
          zzjc.zzk(zzaae[i], (List)zzjy.zzo(paramT, j & 0xFFFFF), paramZzkm, false);
          break;
        case 23: 
          zzjc.zzf(zzaae[i], (List)zzjy.zzo(paramT, j & 0xFFFFF), paramZzkm, false);
          break;
        case 22: 
          zzjc.zzh(zzaae[i], (List)zzjy.zzo(paramT, j & 0xFFFFF), paramZzkm, false);
          break;
        case 21: 
          zzjc.zzd(zzaae[i], (List)zzjy.zzo(paramT, j & 0xFFFFF), paramZzkm, false);
          break;
        case 20: 
          zzjc.zzc(zzaae[i], (List)zzjy.zzo(paramT, j & 0xFFFFF), paramZzkm, false);
          break;
        case 19: 
          zzjc.zzb(zzaae[i], (List)zzjy.zzo(paramT, j & 0xFFFFF), paramZzkm, false);
          break;
        case 18: 
          zzjc.zza(zzaae[i], (List)zzjy.zzo(paramT, j & 0xFFFFF), paramZzkm, false);
          break;
        case 17: 
          if (zzb(paramT, i)) {
            paramZzkm.zzb(k, zzjy.zzo(paramT, j & 0xFFFFF), zzag(i));
          }
          break;
        case 16: 
          if (zzb(paramT, i)) {
            paramZzkm.zzb(k, zzjy.zzk(paramT, j & 0xFFFFF));
          }
          break;
        case 15: 
          if (zzb(paramT, i)) {
            paramZzkm.zzg(k, zzjy.zzj(paramT, j & 0xFFFFF));
          }
          break;
        case 14: 
          if (zzb(paramT, i)) {
            paramZzkm.zzj(k, zzjy.zzk(paramT, j & 0xFFFFF));
          }
          break;
        case 13: 
          if (zzb(paramT, i)) {
            paramZzkm.zzo(k, zzjy.zzj(paramT, j & 0xFFFFF));
          }
          break;
        case 12: 
          if (zzb(paramT, i)) {
            paramZzkm.zzp(k, zzjy.zzj(paramT, j & 0xFFFFF));
          }
          break;
        case 11: 
          if (zzb(paramT, i)) {
            paramZzkm.zzf(k, zzjy.zzj(paramT, j & 0xFFFFF));
          }
          break;
        case 10: 
          if (zzb(paramT, i)) {
            paramZzkm.zza(k, (zzfx)zzjy.zzo(paramT, j & 0xFFFFF));
          }
          break;
        case 9: 
          if (zzb(paramT, i)) {
            paramZzkm.zza(k, zzjy.zzo(paramT, j & 0xFFFFF), zzag(i));
          }
          break;
        case 8: 
          if (zzb(paramT, i)) {
            zza(k, zzjy.zzo(paramT, j & 0xFFFFF), paramZzkm);
          }
          break;
        case 7: 
          if (zzb(paramT, i)) {
            paramZzkm.zza(k, zzjy.zzl(paramT, j & 0xFFFFF));
          }
          break;
        case 6: 
          if (zzb(paramT, i)) {
            paramZzkm.zzh(k, zzjy.zzj(paramT, j & 0xFFFFF));
          }
          break;
        case 5: 
          if (zzb(paramT, i)) {
            paramZzkm.zzc(k, zzjy.zzk(paramT, j & 0xFFFFF));
          }
          break;
        case 4: 
          if (zzb(paramT, i)) {
            paramZzkm.zze(k, zzjy.zzj(paramT, j & 0xFFFFF));
          }
          break;
        case 3: 
          if (zzb(paramT, i)) {
            paramZzkm.zza(k, zzjy.zzk(paramT, j & 0xFFFFF));
          }
          break;
        case 2: 
          if (zzb(paramT, i)) {
            paramZzkm.zzi(k, zzjy.zzk(paramT, j & 0xFFFFF));
          }
          break;
        case 1: 
          if (zzb(paramT, i)) {
            paramZzkm.zza(k, zzjy.zzm(paramT, j & 0xFFFFF));
          }
          break;
        case 0: 
          if (zzb(paramT, i)) {
            paramZzkm.zza(k, zzjy.zzn(paramT, j & 0xFFFFF));
          }
          break;
        }
        i -= 3;
      }
      while (localObject2 != null)
      {
        zzaab.zza(paramZzkm, (Map.Entry)localObject2);
        if (localIterator.hasNext()) {
          localObject2 = (Map.Entry)localIterator.next();
        } else {
          localObject2 = null;
        }
      }
      return;
    }
    if (zzaaj)
    {
      if (zzaaa)
      {
        localObject1 = zzaab.zzc(paramT);
        if (!zzvb.isEmpty())
        {
          localIterator = ((zzgt)localObject1).iterator();
          localObject1 = (Map.Entry)localIterator.next();
          break label2615;
        }
      }
      localIterator = null;
      localObject1 = localIterator;
      label2615:
      j = zzaae.length;
      i = 0;
      for (;;)
      {
        localObject2 = localObject1;
        if (i >= j) {
          break;
        }
        k = zzai(i);
        int m = zzaae[i];
        while ((localObject1 != null) && (zzaab.zza((Map.Entry)localObject1) <= m))
        {
          zzaab.zza(paramZzkm, (Map.Entry)localObject1);
          if (localIterator.hasNext()) {
            localObject1 = (Map.Entry)localIterator.next();
          } else {
            localObject1 = null;
          }
        }
        switch ((k & 0xFF00000) >>> 20)
        {
        default: 
          break;
        case 68: 
          if (zza(paramT, m, i)) {
            paramZzkm.zzb(m, zzjy.zzo(paramT, k & 0xFFFFF), zzag(i));
          }
          break;
        case 67: 
          if (zza(paramT, m, i)) {
            paramZzkm.zzb(m, zzh(paramT, k & 0xFFFFF));
          }
          break;
        case 66: 
          if (zza(paramT, m, i)) {
            paramZzkm.zzg(m, zzg(paramT, k & 0xFFFFF));
          }
          break;
        case 65: 
          if (zza(paramT, m, i)) {
            paramZzkm.zzj(m, zzh(paramT, k & 0xFFFFF));
          }
          break;
        case 64: 
          if (zza(paramT, m, i)) {
            paramZzkm.zzo(m, zzg(paramT, k & 0xFFFFF));
          }
          break;
        case 63: 
          if (zza(paramT, m, i)) {
            paramZzkm.zzp(m, zzg(paramT, k & 0xFFFFF));
          }
          break;
        case 62: 
          if (zza(paramT, m, i)) {
            paramZzkm.zzf(m, zzg(paramT, k & 0xFFFFF));
          }
          break;
        case 61: 
          if (zza(paramT, m, i)) {
            paramZzkm.zza(m, (zzfx)zzjy.zzo(paramT, k & 0xFFFFF));
          }
          break;
        case 60: 
          if (zza(paramT, m, i)) {
            paramZzkm.zza(m, zzjy.zzo(paramT, k & 0xFFFFF), zzag(i));
          }
          break;
        case 59: 
          if (zza(paramT, m, i)) {
            zza(m, zzjy.zzo(paramT, k & 0xFFFFF), paramZzkm);
          }
          break;
        case 58: 
          if (zza(paramT, m, i)) {
            paramZzkm.zza(m, zzi(paramT, k & 0xFFFFF));
          }
          break;
        case 57: 
          if (zza(paramT, m, i)) {
            paramZzkm.zzh(m, zzg(paramT, k & 0xFFFFF));
          }
          break;
        case 56: 
          if (zza(paramT, m, i)) {
            paramZzkm.zzc(m, zzh(paramT, k & 0xFFFFF));
          }
          break;
        case 55: 
          if (zza(paramT, m, i)) {
            paramZzkm.zze(m, zzg(paramT, k & 0xFFFFF));
          }
          break;
        case 54: 
          if (zza(paramT, m, i)) {
            paramZzkm.zza(m, zzh(paramT, k & 0xFFFFF));
          }
          break;
        case 53: 
          if (zza(paramT, m, i)) {
            paramZzkm.zzi(m, zzh(paramT, k & 0xFFFFF));
          }
          break;
        case 52: 
          if (zza(paramT, m, i)) {
            paramZzkm.zza(m, zzf(paramT, k & 0xFFFFF));
          }
          break;
        case 51: 
          if (zza(paramT, m, i)) {
            paramZzkm.zza(m, zze(paramT, k & 0xFFFFF));
          }
          break;
        case 50: 
          zza(paramZzkm, m, zzjy.zzo(paramT, k & 0xFFFFF), i);
          break;
        case 49: 
          zzjc.zzb(zzaae[i], (List)zzjy.zzo(paramT, k & 0xFFFFF), paramZzkm, zzag(i));
          break;
        case 48: 
          zzjc.zze(zzaae[i], (List)zzjy.zzo(paramT, k & 0xFFFFF), paramZzkm, true);
          break;
        case 47: 
          zzjc.zzj(zzaae[i], (List)zzjy.zzo(paramT, k & 0xFFFFF), paramZzkm, true);
          break;
        case 46: 
          zzjc.zzg(zzaae[i], (List)zzjy.zzo(paramT, k & 0xFFFFF), paramZzkm, true);
          break;
        case 45: 
          zzjc.zzl(zzaae[i], (List)zzjy.zzo(paramT, k & 0xFFFFF), paramZzkm, true);
          break;
        case 44: 
          zzjc.zzm(zzaae[i], (List)zzjy.zzo(paramT, k & 0xFFFFF), paramZzkm, true);
          break;
        case 43: 
          zzjc.zzi(zzaae[i], (List)zzjy.zzo(paramT, k & 0xFFFFF), paramZzkm, true);
          break;
        case 42: 
          zzjc.zzn(zzaae[i], (List)zzjy.zzo(paramT, k & 0xFFFFF), paramZzkm, true);
          break;
        case 41: 
          zzjc.zzk(zzaae[i], (List)zzjy.zzo(paramT, k & 0xFFFFF), paramZzkm, true);
          break;
        case 40: 
          zzjc.zzf(zzaae[i], (List)zzjy.zzo(paramT, k & 0xFFFFF), paramZzkm, true);
          break;
        case 39: 
          zzjc.zzh(zzaae[i], (List)zzjy.zzo(paramT, k & 0xFFFFF), paramZzkm, true);
          break;
        case 38: 
          zzjc.zzd(zzaae[i], (List)zzjy.zzo(paramT, k & 0xFFFFF), paramZzkm, true);
          break;
        case 37: 
          zzjc.zzc(zzaae[i], (List)zzjy.zzo(paramT, k & 0xFFFFF), paramZzkm, true);
          break;
        case 36: 
          zzjc.zzb(zzaae[i], (List)zzjy.zzo(paramT, k & 0xFFFFF), paramZzkm, true);
          break;
        case 35: 
          zzjc.zza(zzaae[i], (List)zzjy.zzo(paramT, k & 0xFFFFF), paramZzkm, true);
          break;
        case 34: 
          zzjc.zze(zzaae[i], (List)zzjy.zzo(paramT, k & 0xFFFFF), paramZzkm, false);
          break;
        case 33: 
          zzjc.zzj(zzaae[i], (List)zzjy.zzo(paramT, k & 0xFFFFF), paramZzkm, false);
          break;
        case 32: 
          zzjc.zzg(zzaae[i], (List)zzjy.zzo(paramT, k & 0xFFFFF), paramZzkm, false);
          break;
        case 31: 
          zzjc.zzl(zzaae[i], (List)zzjy.zzo(paramT, k & 0xFFFFF), paramZzkm, false);
          break;
        case 30: 
          zzjc.zzm(zzaae[i], (List)zzjy.zzo(paramT, k & 0xFFFFF), paramZzkm, false);
          break;
        case 29: 
          zzjc.zzi(zzaae[i], (List)zzjy.zzo(paramT, k & 0xFFFFF), paramZzkm, false);
          break;
        case 28: 
          zzjc.zzb(zzaae[i], (List)zzjy.zzo(paramT, k & 0xFFFFF), paramZzkm);
          break;
        case 27: 
          zzjc.zza(zzaae[i], (List)zzjy.zzo(paramT, k & 0xFFFFF), paramZzkm, zzag(i));
          break;
        case 26: 
          zzjc.zza(zzaae[i], (List)zzjy.zzo(paramT, k & 0xFFFFF), paramZzkm);
          break;
        case 25: 
          zzjc.zzn(zzaae[i], (List)zzjy.zzo(paramT, k & 0xFFFFF), paramZzkm, false);
          break;
        case 24: 
          zzjc.zzk(zzaae[i], (List)zzjy.zzo(paramT, k & 0xFFFFF), paramZzkm, false);
          break;
        case 23: 
          zzjc.zzf(zzaae[i], (List)zzjy.zzo(paramT, k & 0xFFFFF), paramZzkm, false);
          break;
        case 22: 
          zzjc.zzh(zzaae[i], (List)zzjy.zzo(paramT, k & 0xFFFFF), paramZzkm, false);
          break;
        case 21: 
          zzjc.zzd(zzaae[i], (List)zzjy.zzo(paramT, k & 0xFFFFF), paramZzkm, false);
          break;
        case 20: 
          zzjc.zzc(zzaae[i], (List)zzjy.zzo(paramT, k & 0xFFFFF), paramZzkm, false);
          break;
        case 19: 
          zzjc.zzb(zzaae[i], (List)zzjy.zzo(paramT, k & 0xFFFFF), paramZzkm, false);
          break;
        case 18: 
          zzjc.zza(zzaae[i], (List)zzjy.zzo(paramT, k & 0xFFFFF), paramZzkm, false);
          break;
        case 17: 
          if (zzb(paramT, i)) {
            paramZzkm.zzb(m, zzjy.zzo(paramT, k & 0xFFFFF), zzag(i));
          }
          break;
        case 16: 
          if (zzb(paramT, i)) {
            paramZzkm.zzb(m, zzjy.zzk(paramT, k & 0xFFFFF));
          }
          break;
        case 15: 
          if (zzb(paramT, i)) {
            paramZzkm.zzg(m, zzjy.zzj(paramT, k & 0xFFFFF));
          }
          break;
        case 14: 
          if (zzb(paramT, i)) {
            paramZzkm.zzj(m, zzjy.zzk(paramT, k & 0xFFFFF));
          }
          break;
        case 13: 
          if (zzb(paramT, i)) {
            paramZzkm.zzo(m, zzjy.zzj(paramT, k & 0xFFFFF));
          }
          break;
        case 12: 
          if (zzb(paramT, i)) {
            paramZzkm.zzp(m, zzjy.zzj(paramT, k & 0xFFFFF));
          }
          break;
        case 11: 
          if (zzb(paramT, i)) {
            paramZzkm.zzf(m, zzjy.zzj(paramT, k & 0xFFFFF));
          }
          break;
        case 10: 
          if (zzb(paramT, i)) {
            paramZzkm.zza(m, (zzfx)zzjy.zzo(paramT, k & 0xFFFFF));
          }
          break;
        case 9: 
          if (zzb(paramT, i)) {
            paramZzkm.zza(m, zzjy.zzo(paramT, k & 0xFFFFF), zzag(i));
          }
          break;
        case 8: 
          if (zzb(paramT, i)) {
            zza(m, zzjy.zzo(paramT, k & 0xFFFFF), paramZzkm);
          }
          break;
        case 7: 
          if (zzb(paramT, i)) {
            paramZzkm.zza(m, zzjy.zzl(paramT, k & 0xFFFFF));
          }
          break;
        case 6: 
          if (zzb(paramT, i)) {
            paramZzkm.zzh(m, zzjy.zzj(paramT, k & 0xFFFFF));
          }
          break;
        case 5: 
          if (zzb(paramT, i)) {
            paramZzkm.zzc(m, zzjy.zzk(paramT, k & 0xFFFFF));
          }
          break;
        case 4: 
          if (zzb(paramT, i)) {
            paramZzkm.zze(m, zzjy.zzj(paramT, k & 0xFFFFF));
          }
          break;
        case 3: 
          if (zzb(paramT, i)) {
            paramZzkm.zza(m, zzjy.zzk(paramT, k & 0xFFFFF));
          }
          break;
        case 2: 
          if (zzb(paramT, i)) {
            paramZzkm.zzi(m, zzjy.zzk(paramT, k & 0xFFFFF));
          }
          break;
        case 1: 
          if (zzb(paramT, i)) {
            paramZzkm.zza(m, zzjy.zzm(paramT, k & 0xFFFFF));
          }
          break;
        case 0: 
          if (zzb(paramT, i)) {
            paramZzkm.zza(m, zzjy.zzn(paramT, k & 0xFFFFF));
          }
          break;
        }
        i += 3;
      }
      while (localObject2 != null)
      {
        zzaab.zza(paramZzkm, (Map.Entry)localObject2);
        if (localIterator.hasNext()) {
          localObject2 = (Map.Entry)localIterator.next();
        } else {
          localObject2 = null;
        }
      }
      zza(zzzz, paramT, paramZzkm);
      return;
    }
    zzb(paramT, paramZzkm);
  }
  
  public final void zzd(T paramT1, T paramT2)
  {
    Objects.requireNonNull(paramT2);
    int i = 0;
    while (i < zzaae.length)
    {
      int j = zzai(i);
      long l = 0xFFFFF & j;
      int k = zzaae[i];
      switch ((j & 0xFF00000) >>> 20)
      {
      default: 
        break;
      case 68: 
        zzb(paramT1, paramT2, i);
        break;
      case 61: 
      case 62: 
      case 63: 
      case 64: 
      case 65: 
      case 66: 
      case 67: 
        if (zza(paramT2, k, i))
        {
          zzjy.zza(paramT1, l, zzjy.zzo(paramT2, l));
          zzb(paramT1, k, i);
        }
        break;
      case 60: 
        zzb(paramT1, paramT2, i);
        break;
      case 51: 
      case 52: 
      case 53: 
      case 54: 
      case 55: 
      case 56: 
      case 57: 
      case 58: 
      case 59: 
        if (zza(paramT2, k, i))
        {
          zzjy.zza(paramT1, l, zzjy.zzo(paramT2, l));
          zzb(paramT1, k, i);
        }
        break;
      case 50: 
        zzjc.zza(zzaaq, paramT1, paramT2, l);
        break;
      case 18: 
      case 19: 
      case 20: 
      case 21: 
      case 22: 
      case 23: 
      case 24: 
      case 25: 
      case 26: 
      case 27: 
      case 28: 
      case 29: 
      case 30: 
      case 31: 
      case 32: 
      case 33: 
      case 34: 
      case 35: 
      case 36: 
      case 37: 
      case 38: 
      case 39: 
      case 40: 
      case 41: 
      case 42: 
      case 43: 
      case 44: 
      case 45: 
      case 46: 
      case 47: 
      case 48: 
      case 49: 
        zzaap.zza(paramT1, paramT2, l);
        break;
      case 17: 
        zza(paramT1, paramT2, i);
        break;
      case 16: 
        if (zzb(paramT2, i))
        {
          zzjy.zza(paramT1, l, zzjy.zzk(paramT2, l));
          zzc(paramT1, i);
        }
        break;
      case 15: 
        if (zzb(paramT2, i))
        {
          zzjy.zza(paramT1, l, zzjy.zzj(paramT2, l));
          zzc(paramT1, i);
        }
        break;
      case 14: 
        if (zzb(paramT2, i))
        {
          zzjy.zza(paramT1, l, zzjy.zzk(paramT2, l));
          zzc(paramT1, i);
        }
        break;
      case 13: 
        if (zzb(paramT2, i))
        {
          zzjy.zza(paramT1, l, zzjy.zzj(paramT2, l));
          zzc(paramT1, i);
        }
        break;
      case 12: 
        if (zzb(paramT2, i))
        {
          zzjy.zza(paramT1, l, zzjy.zzj(paramT2, l));
          zzc(paramT1, i);
        }
        break;
      case 11: 
        if (zzb(paramT2, i))
        {
          zzjy.zza(paramT1, l, zzjy.zzj(paramT2, l));
          zzc(paramT1, i);
        }
        break;
      case 10: 
        if (zzb(paramT2, i))
        {
          zzjy.zza(paramT1, l, zzjy.zzo(paramT2, l));
          zzc(paramT1, i);
        }
        break;
      case 9: 
        zza(paramT1, paramT2, i);
        break;
      case 8: 
        if (zzb(paramT2, i))
        {
          zzjy.zza(paramT1, l, zzjy.zzo(paramT2, l));
          zzc(paramT1, i);
        }
        break;
      case 7: 
        if (zzb(paramT2, i))
        {
          zzjy.zza(paramT1, l, zzjy.zzl(paramT2, l));
          zzc(paramT1, i);
        }
        break;
      case 6: 
        if (zzb(paramT2, i))
        {
          zzjy.zza(paramT1, l, zzjy.zzj(paramT2, l));
          zzc(paramT1, i);
        }
        break;
      case 5: 
        if (zzb(paramT2, i))
        {
          zzjy.zza(paramT1, l, zzjy.zzk(paramT2, l));
          zzc(paramT1, i);
        }
        break;
      case 4: 
        if (zzb(paramT2, i))
        {
          zzjy.zza(paramT1, l, zzjy.zzj(paramT2, l));
          zzc(paramT1, i);
        }
        break;
      case 3: 
        if (zzb(paramT2, i))
        {
          zzjy.zza(paramT1, l, zzjy.zzk(paramT2, l));
          zzc(paramT1, i);
        }
        break;
      case 2: 
        if (zzb(paramT2, i))
        {
          zzjy.zza(paramT1, l, zzjy.zzk(paramT2, l));
          zzc(paramT1, i);
        }
        break;
      case 1: 
        if (zzb(paramT2, i))
        {
          zzjy.zza(paramT1, l, zzjy.zzm(paramT2, l));
          zzc(paramT1, i);
        }
        break;
      case 0: 
        if (zzb(paramT2, i))
        {
          zzjy.zza(paramT1, l, zzjy.zzn(paramT2, l));
          zzc(paramT1, i);
        }
        break;
      }
      i += 3;
    }
    zzjc.zza(zzzz, paramT1, paramT2);
    if (zzaaa) {
      zzjc.zza(zzaab, paramT1, paramT2);
    }
  }
  
  public final void zze(T paramT)
  {
    int i = zzaam;
    int j;
    for (;;)
    {
      j = zzaan;
      if (i >= j) {
        break;
      }
      long l = zzai(zzaal[i]) & 0xFFFFF;
      Object localObject = zzjy.zzo(paramT, l);
      if (localObject != null) {
        zzjy.zza(paramT, l, zzaaq.zzi(localObject));
      }
      i += 1;
    }
    int k = zzaal.length;
    i = j;
    while (i < k)
    {
      zzaap.zza(paramT, zzaal[i]);
      i += 1;
    }
    zzzz.zze(paramT);
    if (zzaaa) {
      zzaab.zze(paramT);
    }
  }
  
  public final boolean zzl(T paramT)
  {
    int j = 1048575;
    int i = 0;
    int k = i;
    for (;;)
    {
      int m = zzaam;
      int i1 = 1;
      int n = 1;
      if (k >= m) {
        break;
      }
      int i2 = zzaal[k];
      int i3 = zzaae[i2];
      int i4 = zzai(i2);
      int i5 = zzaae[(i2 + 2)];
      m = i5 & 0xFFFFF;
      i5 = 1 << (i5 >>> 20);
      if (m != j)
      {
        if (m != 1048575) {
          i = zzaad.getInt(paramT, m);
        }
        j = m;
      }
      if ((0x10000000 & i4) != 0) {
        m = 1;
      } else {
        m = 0;
      }
      if ((m != 0) && (!zza(paramT, i2, j, i, i5))) {
        return false;
      }
      m = (0xFF00000 & i4) >>> 20;
      if ((m != 9) && (m != 17))
      {
        Object localObject2;
        if (m != 27) {
          if ((m != 60) && (m != 68))
          {
            if (m != 49)
            {
              if (m != 50) {
                break label526;
              }
              localObject2 = zzaaq.zzh(zzjy.zzo(paramT, i4 & 0xFFFFF));
              m = n;
              if (!((Map)localObject2).isEmpty())
              {
                localObject1 = zzah(i2);
                m = n;
                if (zzaaq.zzj(localObject1).zzzu.zzdx() == zzkj.zzady)
                {
                  localObject1 = null;
                  Iterator localIterator = ((Map)localObject2).values().iterator();
                  Object localObject3;
                  do
                  {
                    m = n;
                    if (!localIterator.hasNext()) {
                      break;
                    }
                    localObject3 = localIterator.next();
                    localObject2 = localObject1;
                    if (localObject1 == null) {
                      localObject2 = zziv.zzcy().zze(localObject3.getClass());
                    }
                    localObject1 = localObject2;
                  } while (((zzja)localObject2).zzl(localObject3));
                  m = 0;
                }
              }
              if (m != 0) {
                break label526;
              }
              return false;
            }
          }
          else
          {
            if ((!zza(paramT, i3, i2)) || (zza(paramT, i4, zzag(i2)))) {
              break label526;
            }
            return false;
          }
        }
        Object localObject1 = (List)zzjy.zzo(paramT, i4 & 0xFFFFF);
        m = i1;
        if (!((List)localObject1).isEmpty())
        {
          localObject2 = zzag(i2);
          n = 0;
          for (;;)
          {
            m = i1;
            if (n >= ((List)localObject1).size()) {
              break;
            }
            if (!((zzja)localObject2).zzl(((List)localObject1).get(n)))
            {
              m = 0;
              break;
            }
            n += 1;
          }
        }
        if (m == 0) {
          return false;
        }
      }
      else if ((zza(paramT, i2, j, i, i5)) && (!zza(paramT, i4, zzag(i2))))
      {
        return false;
      }
      label526:
      k += 1;
    }
    return (!zzaaa) || (zzaab.zzc(paramT).isInitialized());
  }
  
  public final int zzm(T paramT)
  {
    boolean bool = zzaaj;
    int k = 1;
    int i = 0;
    long l;
    Object localObject2;
    if (bool)
    {
      localObject1 = zzaad;
      m = 0;
      for (n = m; m < zzaae.length; n = i)
      {
        j = zzai(m);
        i = (j & 0xFF00000) >>> 20;
        k = zzaae[m];
        l = j & 0xFFFFF;
        if ((i >= zzgu.zzwo.id()) && (i <= zzgu.zzxb.id())) {
          j = zzaae[(m + 2)];
        }
        switch (i)
        {
        default: 
          i = n;
          break;
        case 68: 
          i = n;
          if (!zza(paramT, k, m)) {
            break label2319;
          }
          i = zzgk.zzc(k, (zzik)zzjy.zzo(paramT, l), zzag(m));
          break;
        case 67: 
          i = n;
          if (!zza(paramT, k, m)) {
            break label2319;
          }
          i = zzgk.zzf(k, zzh(paramT, l));
          break;
        case 66: 
          i = n;
          if (!zza(paramT, k, m)) {
            break label2319;
          }
          i = zzgk.zzk(k, zzg(paramT, l));
          break;
        case 65: 
          i = n;
          if (!zza(paramT, k, m)) {
            break label2319;
          }
          i = zzgk.zzh(k, 0L);
          break;
        case 64: 
          i = n;
          if (!zza(paramT, k, m)) {
            break label2319;
          }
          i = zzgk.zzm(k, 0);
          break;
        case 63: 
          i = n;
          if (!zza(paramT, k, m)) {
            break label2319;
          }
          i = zzgk.zzn(k, zzg(paramT, l));
          break;
        case 62: 
          i = n;
          if (!zza(paramT, k, m)) {
            break label2319;
          }
          i = zzgk.zzj(k, zzg(paramT, l));
          break;
        case 61: 
          i = n;
          if (!zza(paramT, k, m)) {
            break label2319;
          }
          i = zzgk.zzc(k, (zzfx)zzjy.zzo(paramT, l));
          break;
        case 60: 
          i = n;
          if (!zza(paramT, k, m)) {
            break label2319;
          }
          i = zzjc.zzc(k, zzjy.zzo(paramT, l), zzag(m));
          break;
        case 59: 
          i = n;
          if (!zza(paramT, k, m)) {
            break label2319;
          }
          localObject2 = zzjy.zzo(paramT, l);
          if ((localObject2 instanceof zzfx)) {
            i = zzgk.zzc(k, (zzfx)localObject2);
          } else {
            i = zzgk.zzb(k, (String)localObject2);
          }
          break;
        case 58: 
          i = n;
          if (!zza(paramT, k, m)) {
            break label2319;
          }
          i = zzgk.zzb(k, true);
          break;
        case 57: 
          i = n;
          if (!zza(paramT, k, m)) {
            break label2319;
          }
          i = zzgk.zzl(k, 0);
          break;
        case 56: 
          i = n;
          if (!zza(paramT, k, m)) {
            break label2319;
          }
          i = zzgk.zzg(k, 0L);
          break;
        case 55: 
          i = n;
          if (!zza(paramT, k, m)) {
            break label2319;
          }
          i = zzgk.zzi(k, zzg(paramT, l));
          break;
        case 54: 
          i = n;
          if (!zza(paramT, k, m)) {
            break label2319;
          }
          i = zzgk.zze(k, zzh(paramT, l));
          break;
        case 53: 
          i = n;
          if (!zza(paramT, k, m)) {
            break label2319;
          }
          i = zzgk.zzd(k, zzh(paramT, l));
          break;
        case 52: 
          i = n;
          if (!zza(paramT, k, m)) {
            break label2319;
          }
          i = zzgk.zzb(k, 0.0F);
          break;
        case 51: 
          i = n;
          if (!zza(paramT, k, m)) {
            break label2319;
          }
          i = zzgk.zzb(k, 0.0D);
          break;
        case 50: 
          i = zzaaq.zzb(k, zzjy.zzo(paramT, l), zzah(m));
          break;
        case 49: 
          i = zzjc.zzd(k, zzd(paramT, l), zzag(m));
          break;
        case 48: 
          j = zzjc.zzd((List)((Unsafe)localObject1).getObject(paramT, l));
          i = n;
          if (j <= 0) {
            break label2319;
          }
          i = zzgk.zzr(k);
          k = zzgk.zzt(j);
          break;
        case 47: 
          j = zzjc.zzh((List)((Unsafe)localObject1).getObject(paramT, l));
          i = n;
          if (j <= 0) {
            break label2319;
          }
          i = zzgk.zzr(k);
          k = zzgk.zzt(j);
          break;
        case 46: 
          j = zzjc.zzj((List)((Unsafe)localObject1).getObject(paramT, l));
          i = n;
          if (j <= 0) {
            break label2319;
          }
          i = zzgk.zzr(k);
          k = zzgk.zzt(j);
          break;
        case 45: 
          j = zzjc.zzi((List)((Unsafe)localObject1).getObject(paramT, l));
          i = n;
          if (j <= 0) {
            break label2319;
          }
          i = zzgk.zzr(k);
          k = zzgk.zzt(j);
          break;
        case 44: 
          j = zzjc.zze((List)((Unsafe)localObject1).getObject(paramT, l));
          i = n;
          if (j <= 0) {
            break label2319;
          }
          i = zzgk.zzr(k);
          k = zzgk.zzt(j);
          break;
        case 43: 
          j = zzjc.zzg((List)((Unsafe)localObject1).getObject(paramT, l));
          i = n;
          if (j <= 0) {
            break label2319;
          }
          i = zzgk.zzr(k);
          k = zzgk.zzt(j);
          break;
        case 42: 
          j = zzjc.zzk((List)((Unsafe)localObject1).getObject(paramT, l));
          i = n;
          if (j <= 0) {
            break label2319;
          }
          i = zzgk.zzr(k);
          k = zzgk.zzt(j);
          break;
        case 41: 
          j = zzjc.zzi((List)((Unsafe)localObject1).getObject(paramT, l));
          i = n;
          if (j <= 0) {
            break label2319;
          }
          i = zzgk.zzr(k);
          k = zzgk.zzt(j);
          break;
        case 40: 
          j = zzjc.zzj((List)((Unsafe)localObject1).getObject(paramT, l));
          i = n;
          if (j <= 0) {
            break label2319;
          }
          i = zzgk.zzr(k);
          k = zzgk.zzt(j);
          break;
        case 39: 
          j = zzjc.zzf((List)((Unsafe)localObject1).getObject(paramT, l));
          i = n;
          if (j <= 0) {
            break label2319;
          }
          i = zzgk.zzr(k);
          k = zzgk.zzt(j);
          break;
        case 38: 
          j = zzjc.zzc((List)((Unsafe)localObject1).getObject(paramT, l));
          i = n;
          if (j <= 0) {
            break label2319;
          }
          i = zzgk.zzr(k);
          k = zzgk.zzt(j);
          break;
        case 37: 
          j = zzjc.zzb((List)((Unsafe)localObject1).getObject(paramT, l));
          i = n;
          if (j <= 0) {
            break label2319;
          }
          i = zzgk.zzr(k);
          k = zzgk.zzt(j);
          break;
        case 36: 
          j = zzjc.zzi((List)((Unsafe)localObject1).getObject(paramT, l));
          i = n;
          if (j <= 0) {
            break label2319;
          }
          i = zzgk.zzr(k);
          k = zzgk.zzt(j);
          break;
        case 35: 
          j = zzjc.zzj((List)((Unsafe)localObject1).getObject(paramT, l));
          i = n;
          if (j <= 0) {
            break label2319;
          }
          i = zzgk.zzr(k);
          k = zzgk.zzt(j);
          i = i + k + j;
          break;
        case 34: 
          i = zzjc.zzq(k, zzd(paramT, l), false);
          break;
        case 33: 
          i = zzjc.zzu(k, zzd(paramT, l), false);
          break;
        case 32: 
          i = zzjc.zzw(k, zzd(paramT, l), false);
          break;
        case 31: 
          i = zzjc.zzv(k, zzd(paramT, l), false);
          break;
        case 30: 
          i = zzjc.zzr(k, zzd(paramT, l), false);
          break;
        case 29: 
          i = zzjc.zzt(k, zzd(paramT, l), false);
          break;
        case 28: 
          i = zzjc.zzd(k, zzd(paramT, l));
          break;
        case 27: 
          i = zzjc.zzc(k, zzd(paramT, l), zzag(m));
          break;
        case 26: 
          i = zzjc.zzc(k, zzd(paramT, l));
          break;
        case 25: 
          i = zzjc.zzx(k, zzd(paramT, l), false);
          break;
        case 24: 
          i = zzjc.zzv(k, zzd(paramT, l), false);
          break;
        case 23: 
          i = zzjc.zzw(k, zzd(paramT, l), false);
          break;
        case 22: 
          i = zzjc.zzs(k, zzd(paramT, l), false);
          break;
        case 21: 
          i = zzjc.zzp(k, zzd(paramT, l), false);
          break;
        case 20: 
          i = zzjc.zzo(k, zzd(paramT, l), false);
          break;
        case 19: 
          i = zzjc.zzv(k, zzd(paramT, l), false);
          break;
        case 18: 
          i = zzjc.zzw(k, zzd(paramT, l), false);
        }
        for (;;)
        {
          i = n + i;
          break;
          i = n;
          if (!zzb(paramT, m)) {
            break;
          }
          i = zzgk.zzc(k, (zzik)zzjy.zzo(paramT, l), zzag(m));
          continue;
          i = n;
          if (!zzb(paramT, m)) {
            break;
          }
          i = zzgk.zzf(k, zzjy.zzk(paramT, l));
          continue;
          i = n;
          if (!zzb(paramT, m)) {
            break;
          }
          i = zzgk.zzk(k, zzjy.zzj(paramT, l));
          continue;
          i = n;
          if (!zzb(paramT, m)) {
            break;
          }
          i = zzgk.zzh(k, 0L);
          continue;
          i = n;
          if (!zzb(paramT, m)) {
            break;
          }
          i = zzgk.zzm(k, 0);
          continue;
          i = n;
          if (!zzb(paramT, m)) {
            break;
          }
          i = zzgk.zzn(k, zzjy.zzj(paramT, l));
          continue;
          i = n;
          if (!zzb(paramT, m)) {
            break;
          }
          i = zzgk.zzj(k, zzjy.zzj(paramT, l));
          continue;
          i = n;
          if (!zzb(paramT, m)) {
            break;
          }
          i = zzgk.zzc(k, (zzfx)zzjy.zzo(paramT, l));
          continue;
          i = n;
          if (!zzb(paramT, m)) {
            break;
          }
          i = zzjc.zzc(k, zzjy.zzo(paramT, l), zzag(m));
          continue;
          i = n;
          if (!zzb(paramT, m)) {
            break;
          }
          localObject2 = zzjy.zzo(paramT, l);
          if ((localObject2 instanceof zzfx))
          {
            i = zzgk.zzc(k, (zzfx)localObject2);
          }
          else
          {
            i = zzgk.zzb(k, (String)localObject2);
            continue;
            i = n;
            if (!zzb(paramT, m)) {
              break;
            }
            i = zzgk.zzb(k, true);
            continue;
            i = n;
            if (!zzb(paramT, m)) {
              break;
            }
            i = zzgk.zzl(k, 0);
            continue;
            i = n;
            if (!zzb(paramT, m)) {
              break;
            }
            i = zzgk.zzg(k, 0L);
            continue;
            i = n;
            if (!zzb(paramT, m)) {
              break;
            }
            i = zzgk.zzi(k, zzjy.zzj(paramT, l));
            continue;
            i = n;
            if (!zzb(paramT, m)) {
              break;
            }
            i = zzgk.zze(k, zzjy.zzk(paramT, l));
            continue;
            i = n;
            if (!zzb(paramT, m)) {
              break;
            }
            i = zzgk.zzd(k, zzjy.zzk(paramT, l));
            continue;
            i = n;
            if (!zzb(paramT, m)) {
              break;
            }
            i = zzgk.zzb(k, 0.0F);
            continue;
            i = n;
            if (!zzb(paramT, m)) {
              break;
            }
            i = zzgk.zzb(k, 0.0D);
          }
        }
        label2319:
        m += 3;
      }
      return n + zza(zzzz, paramT);
    }
    Object localObject1 = zzaad;
    int j = 1048575;
    int n = 0;
    int m = n;
    int i1 = m;
    while (n < zzaae.length)
    {
      int i5 = zzai(n);
      localObject2 = zzaae;
      int i4 = localObject2[n];
      int i6 = (i5 & 0xFF00000) >>> 20;
      int i2;
      if (i6 <= 17)
      {
        i2 = localObject2[(n + 2)];
        i = i2 & 0xFFFFF;
        i3 = k << (i2 >>> 20);
        i2 = j;
        k = i3;
        if (i != j)
        {
          i1 = ((Unsafe)localObject1).getInt(paramT, i);
          i2 = i;
          k = i3;
        }
      }
      else
      {
        k = 0;
        i2 = j;
      }
      l = i5 & 0xFFFFF;
      switch (i6)
      {
      default: 
        i = m;
        break;
      case 68: 
        i = m;
        if (zza(paramT, i4, n)) {
          i = zzgk.zzc(i4, (zzik)((Unsafe)localObject1).getObject(paramT, l), zzag(n));
        }
        break;
      case 67: 
        i = m;
        if (zza(paramT, i4, n)) {
          i = zzgk.zzf(i4, zzh(paramT, l));
        }
        break;
      case 66: 
        i = m;
        if (zza(paramT, i4, n)) {
          i = zzgk.zzk(i4, zzg(paramT, l));
        }
        break;
      case 65: 
        i = m;
        if (zza(paramT, i4, n)) {
          i = zzgk.zzh(i4, 0L);
        }
        break;
      case 64: 
        i = m;
        if (zza(paramT, i4, n)) {
          i = zzgk.zzm(i4, 0);
        }
        break;
      case 63: 
        i = m;
        if (zza(paramT, i4, n)) {
          i = zzgk.zzn(i4, zzg(paramT, l));
        }
        break;
      case 62: 
        i = m;
        if (zza(paramT, i4, n)) {
          i = zzgk.zzj(i4, zzg(paramT, l));
        }
        break;
      case 61: 
        i = m;
        if (zza(paramT, i4, n)) {
          i = zzgk.zzc(i4, (zzfx)((Unsafe)localObject1).getObject(paramT, l));
        }
        break;
      case 60: 
        i = m;
        if (zza(paramT, i4, n)) {
          i = zzjc.zzc(i4, ((Unsafe)localObject1).getObject(paramT, l), zzag(n));
        }
        break;
      case 59: 
        i = m;
        if (zza(paramT, i4, n))
        {
          localObject2 = ((Unsafe)localObject1).getObject(paramT, l);
          if ((localObject2 instanceof zzfx)) {
            i = zzgk.zzc(i4, (zzfx)localObject2);
          } else {
            i = zzgk.zzb(i4, (String)localObject2);
          }
        }
        break;
      case 58: 
        i = m;
        if (zza(paramT, i4, n)) {
          i = zzgk.zzb(i4, true);
        }
        break;
      case 57: 
        i = m;
        if (zza(paramT, i4, n)) {
          i = zzgk.zzl(i4, 0);
        }
        break;
      case 56: 
        i = m;
        if (zza(paramT, i4, n)) {
          i = zzgk.zzg(i4, 0L);
        }
        break;
      case 55: 
        i = m;
        if (zza(paramT, i4, n)) {
          i = zzgk.zzi(i4, zzg(paramT, l));
        }
        break;
      case 54: 
        i = m;
        if (zza(paramT, i4, n)) {
          i = zzgk.zze(i4, zzh(paramT, l));
        }
        break;
      case 53: 
        i = m;
        if (zza(paramT, i4, n)) {
          i = zzgk.zzd(i4, zzh(paramT, l));
        }
        break;
      case 52: 
        i = m;
        if (zza(paramT, i4, n)) {
          i = zzgk.zzb(i4, 0.0F);
        }
        break;
      case 51: 
        i = m;
        if (zza(paramT, i4, n)) {
          i = zzgk.zzb(i4, 0.0D);
        }
        break;
      case 50: 
        i = zzaaq.zzb(i4, ((Unsafe)localObject1).getObject(paramT, l), zzah(n));
        break;
      case 49: 
        i = zzjc.zzd(i4, (List)((Unsafe)localObject1).getObject(paramT, l), zzag(n));
        break;
      case 48: 
        j = zzjc.zzd((List)((Unsafe)localObject1).getObject(paramT, l));
        i = m;
        if (j > 0)
        {
          i3 = zzgk.zzr(i4);
          k = zzgk.zzt(j);
          i = j;
          j = i3;
        }
        break;
      case 47: 
        j = zzjc.zzh((List)((Unsafe)localObject1).getObject(paramT, l));
        i = m;
        if (j > 0)
        {
          i3 = zzgk.zzr(i4);
          k = zzgk.zzt(j);
          i = j;
          j = i3;
        }
        break;
      case 46: 
        j = zzjc.zzj((List)((Unsafe)localObject1).getObject(paramT, l));
        i = m;
        if (j > 0)
        {
          i3 = zzgk.zzr(i4);
          k = zzgk.zzt(j);
          i = j;
          j = i3;
        }
        break;
      case 45: 
        j = zzjc.zzi((List)((Unsafe)localObject1).getObject(paramT, l));
        i = m;
        if (j > 0)
        {
          i3 = zzgk.zzr(i4);
          k = zzgk.zzt(j);
          i = j;
          j = i3;
        }
        break;
      case 44: 
        j = zzjc.zze((List)((Unsafe)localObject1).getObject(paramT, l));
        i = m;
        if (j > 0)
        {
          i3 = zzgk.zzr(i4);
          k = zzgk.zzt(j);
          i = j;
          j = i3;
        }
        break;
      case 43: 
        j = zzjc.zzg((List)((Unsafe)localObject1).getObject(paramT, l));
        i = m;
        if (j > 0)
        {
          i3 = zzgk.zzr(i4);
          k = zzgk.zzt(j);
          i = j;
          j = i3;
        }
        break;
      case 42: 
        j = zzjc.zzk((List)((Unsafe)localObject1).getObject(paramT, l));
        i = m;
        if (j > 0)
        {
          i3 = zzgk.zzr(i4);
          k = zzgk.zzt(j);
          i = j;
          j = i3;
        }
        break;
      case 41: 
        j = zzjc.zzi((List)((Unsafe)localObject1).getObject(paramT, l));
        i = m;
        if (j > 0)
        {
          i3 = zzgk.zzr(i4);
          k = zzgk.zzt(j);
          i = j;
          j = i3;
        }
        break;
      case 40: 
        j = zzjc.zzj((List)((Unsafe)localObject1).getObject(paramT, l));
        i = m;
        if (j > 0)
        {
          i3 = zzgk.zzr(i4);
          k = zzgk.zzt(j);
          i = j;
          j = i3;
        }
        break;
      case 39: 
        j = zzjc.zzf((List)((Unsafe)localObject1).getObject(paramT, l));
        i = m;
        if (j > 0)
        {
          i3 = zzgk.zzr(i4);
          k = zzgk.zzt(j);
          i = j;
          j = i3;
        }
        break;
      case 38: 
        j = zzjc.zzc((List)((Unsafe)localObject1).getObject(paramT, l));
        i = m;
        if (j > 0)
        {
          i3 = zzgk.zzr(i4);
          k = zzgk.zzt(j);
          i = j;
          j = i3;
        }
        break;
      case 37: 
        j = zzjc.zzb((List)((Unsafe)localObject1).getObject(paramT, l));
        i = m;
        if (j > 0)
        {
          i3 = zzgk.zzr(i4);
          k = zzgk.zzt(j);
          i = j;
          j = i3;
        }
        break;
      case 36: 
        j = zzjc.zzi((List)((Unsafe)localObject1).getObject(paramT, l));
        i = m;
        if (j > 0)
        {
          i3 = zzgk.zzr(i4);
          k = zzgk.zzt(j);
          i = j;
          j = i3;
        }
        break;
      case 35: 
        i3 = zzjc.zzj((List)((Unsafe)localObject1).getObject(paramT, l));
        i = m;
        if (i3 > 0)
        {
          j = zzgk.zzr(i4);
          k = zzgk.zzt(i3);
          i = i3;
          i = j + k + i;
        }
        break;
      case 34: 
        i = zzjc.zzq(i4, (List)((Unsafe)localObject1).getObject(paramT, l), false);
        break;
      case 33: 
        i = zzjc.zzu(i4, (List)((Unsafe)localObject1).getObject(paramT, l), false);
        break;
      case 32: 
        i = zzjc.zzw(i4, (List)((Unsafe)localObject1).getObject(paramT, l), false);
        break;
      case 31: 
        i = zzjc.zzv(i4, (List)((Unsafe)localObject1).getObject(paramT, l), false);
        break;
      case 30: 
        i = zzjc.zzr(i4, (List)((Unsafe)localObject1).getObject(paramT, l), false);
        break;
      case 29: 
        i = zzjc.zzt(i4, (List)((Unsafe)localObject1).getObject(paramT, l), false);
        break;
      case 28: 
        i = zzjc.zzd(i4, (List)((Unsafe)localObject1).getObject(paramT, l));
        break;
      case 27: 
        i = zzjc.zzc(i4, (List)((Unsafe)localObject1).getObject(paramT, l), zzag(n));
        break;
      case 26: 
        i = zzjc.zzc(i4, (List)((Unsafe)localObject1).getObject(paramT, l));
        break;
      case 25: 
        i = zzjc.zzx(i4, (List)((Unsafe)localObject1).getObject(paramT, l), false);
        break;
      case 24: 
        i = zzjc.zzv(i4, (List)((Unsafe)localObject1).getObject(paramT, l), false);
        break;
      case 23: 
        i = zzjc.zzw(i4, (List)((Unsafe)localObject1).getObject(paramT, l), false);
        break;
      case 22: 
        i = zzjc.zzs(i4, (List)((Unsafe)localObject1).getObject(paramT, l), false);
        break;
      case 21: 
        i = zzjc.zzp(i4, (List)((Unsafe)localObject1).getObject(paramT, l), false);
        break;
      case 20: 
        i = zzjc.zzo(i4, (List)((Unsafe)localObject1).getObject(paramT, l), false);
        break;
      case 19: 
        i = zzjc.zzv(i4, (List)((Unsafe)localObject1).getObject(paramT, l), false);
        i = m + i;
      case 18: 
      case 17: 
      case 16: 
      case 15: 
      case 14: 
      case 13: 
      case 12: 
      case 11: 
      case 10: 
      case 9: 
      case 8: 
      case 7: 
      case 6: 
        for (;;)
        {
          break label4373;
          i = zzjc.zzw(i4, (List)((Unsafe)localObject1).getObject(paramT, l), false);
          i = m + i;
          for (;;)
          {
            break label4897;
            i = m;
            if ((i1 & k) != 0)
            {
              i = zzgk.zzc(i4, (zzik)((Unsafe)localObject1).getObject(paramT, l), zzag(n));
              break;
              i = m;
              if ((i1 & k) != 0)
              {
                i = zzgk.zzf(i4, ((Unsafe)localObject1).getLong(paramT, l));
                break;
                i = m;
                if ((i1 & k) != 0)
                {
                  i = zzgk.zzk(i4, ((Unsafe)localObject1).getInt(paramT, l));
                  break;
                  i = m;
                  if ((i1 & k) != 0)
                  {
                    i = zzgk.zzh(i4, 0L);
                    break;
                    i = m;
                    if ((i1 & k) != 0)
                    {
                      i = zzgk.zzm(i4, 0);
                      i = m + i;
                      continue;
                      i = m;
                      if ((i1 & k) != 0)
                      {
                        i = zzgk.zzn(i4, ((Unsafe)localObject1).getInt(paramT, l));
                        break;
                        i = m;
                        if ((i1 & k) != 0)
                        {
                          i = zzgk.zzj(i4, ((Unsafe)localObject1).getInt(paramT, l));
                          break;
                          i = m;
                          if ((i1 & k) != 0)
                          {
                            i = zzgk.zzc(i4, (zzfx)((Unsafe)localObject1).getObject(paramT, l));
                            break;
                            i = m;
                            if ((i1 & k) != 0)
                            {
                              i = zzjc.zzc(i4, ((Unsafe)localObject1).getObject(paramT, l), zzag(n));
                              break;
                              i = m;
                              if ((i1 & k) != 0)
                              {
                                localObject2 = ((Unsafe)localObject1).getObject(paramT, l);
                                if ((localObject2 instanceof zzfx))
                                {
                                  i = zzgk.zzc(i4, (zzfx)localObject2);
                                  break;
                                }
                                i = zzgk.zzb(i4, (String)localObject2);
                                break;
                                i = m;
                                if ((i1 & k) != 0) {
                                  i = m + zzgk.zzb(i4, true);
                                }
                              }
                            }
                          }
                        }
                      }
                    }
                  }
                }
              }
            }
          }
          i = m;
          if ((i1 & k) != 0) {
            i = m + zzgk.zzl(i4, 0);
          }
        }
      case 5: 
        i = m;
        if ((i1 & k) != 0) {
          i = zzgk.zzg(i4, 0L);
        }
        break;
      case 4: 
        i = m;
        if ((k & i1) != 0) {
          i = zzgk.zzi(i4, ((Unsafe)localObject1).getInt(paramT, l));
        }
        break;
      case 3: 
        i = m;
        if ((k & i1) != 0) {
          i = zzgk.zze(i4, ((Unsafe)localObject1).getLong(paramT, l));
        }
        break;
      case 2: 
        i = m;
        if ((k & i1) != 0)
        {
          i = zzgk.zzd(i4, ((Unsafe)localObject1).getLong(paramT, l));
          i = m + i;
        }
        break;
      case 1: 
        label4373:
        i = m;
        if ((i1 & k) != 0) {
          i = m + zzgk.zzb(i4, 0.0F);
        }
        break;
      }
      for (;;)
      {
        break;
        i = m;
        if ((i1 & k) != 0) {
          i = m + zzgk.zzb(i4, 0.0D);
        }
      }
      label4897:
      n += 3;
      k = 1;
      int i3 = 0;
      m = i;
      j = i2;
      i = i3;
    }
    k = m + zza(zzzz, paramT);
    j = k;
    if (zzaaa)
    {
      paramT = zzaab.zzc(paramT);
      j = i;
      while (j < zzvb.zzdc())
      {
        localObject1 = zzvb.zzal(j);
        i += zzgt.zzb((zzgv)((Map.Entry)localObject1).getKey(), ((Map.Entry)localObject1).getValue());
        j += 1;
      }
      paramT = zzvb.zzdd().iterator();
      while (paramT.hasNext())
      {
        localObject1 = (Map.Entry)paramT.next();
        i += zzgt.zzb((zzgv)((Map.Entry)localObject1).getKey(), ((Map.Entry)localObject1).getValue());
      }
      j = k + i;
    }
    return j;
  }
}
